Workbook
Name ENMO: 'Data Validation'!$C$14:$C$36
Name ESWM_FOCAL: 'Data Validation'!$E$14:$E$19
Name ESWM_STAFF: 'Data Validation'!$D$14

Sheet ENMO TARGET
A1: No. | B1: PROVINCE | C1: ENMO | D1: 10 Year Plan | E1: MRF | F1: Equipment | G1: ODS | H1: SLF | I1: Transfer Station | J1: RCA | K1: Trash Trap | L1: Preliminary Disinpection Facility
A2: 1 | B2: AURORA | C2: Zaila Mae R. Leander | D2: 4 | E2: 12 | F2: 3 | G2: 1 | H2: 1 | J2: 2 | L2: 1
A3: 2 | B3: AURORA | C3: Nikko Jay M. Valenzuela | D3: 2 | E3: 4 | F3: 2 | H3: 2 | L3: 1
A4: 3 | B4: AURORA | C4: Queenyvel R. Laguisma | D4: 3 | E4: 3 | F4: 3 | J4: 3 | L4: 1
A5: 4 | B5: BATAAN | C5: Dennis G. Tolentino | D5: 6 | E5: 10 | F5: 6 | G5: 2 | H5: 3 | L5: 1
A6: 5 | B6: BATAAN | C6: John-lester C. Signio | D6: 4 | E6: 4 | F6: 4 | G6: 3 | L6: 1
A7: 6 | B7: BATAAN | C7: Laurence Radasa | D7: 3 | E7: 12 | F7: 3 | G7: 2 | I7: 1 | J7: 2
A8: 7 | B8: BULACAN | C8: Jasmine Marie J. Nicolas | D8: 5 | E8: 7 | F8: 6 | I8: 3 | K8: 21
A9: 8 | B9: BULACAN | C9: Ronaldo P. Roque Jr. | D9: 5 | E9: 5 | F9: 5 | G9: 2 | I9: 2 | K9: 8
A10: 9 | B10: BULACAN | C10: Vacant
A11: 10 | B11: BULACAN | C11: James Wilson T. Peña | D11: 6 | E11: 8 | F11: 6 | G11: 2 | K11: 7 | L11: 2
A12: 11 | B12: NUEVA ECIJA | C12: Hosannah R. Sabio | D12: 6 | E12: 6 | F12: 7 | G12: 4 | I12: 6 | L12: 2
A13: 12 | B13: NUEVA ECIJA | C13: Gem C. Vicencio | D13: 6 | E13: 6 | F13: 6 | G13: 5 | I13: 6
A14: 13 | B14: NUEVA ECIJA | C14: Jan Emerson C. Gonzales | D14: 7 | E14: 9 | F14: 7 | H14: 2 | I14: 4 | J14: 1
A15: 14 | B15: NUEVA ECIJA | C15: Aser A. Inocencio, Jr. | D15: 7 | E15: 10 | F15: 8 | G15: 1 | H15: 1 | I15: 3 | J15: 3 | L15: 1
A16: 15 | B16: NUEVA ECIJA | C16: Christine Ann V. Ramos | D16: 6 | E16: 7 | F16: 7 | G16: 4 | I16: 6 | K16: 11 | L16: 1
A17: 16 | B17: PAMPANGA | C17: Roger T. Encarnacion II | D17: 6 | E17: 7 | F17: 6 | G17: 6 | K17: 8
A18: 17 | B18: PAMPANGA | C18: Elyza A. Evilla | D18: 5 | E18: 6 | F18: 5 | H18: 3 | I18: 2 | K18: 31 | L18: 4
A19: 18 | B19: PAMPANGA | C19: Glaiza S.Gaza | D19: 5 | E19: 6 | F19: 5 | G19: 4 | I19: 2 | K19: 14
A20: 19 | B20: PAMPANGA | C20: Ivy M. Castro | D20: 5 | E20: 4 | F20: 5 | G20: 2 | I20: 2 | K20: 13
A21: 20 | B21: TARLAC | C21: Joshua A. Capones | D21: 7 | E21: 6 | F21: 6 | G21: 1 | I21: 1 | L21: 2
A22: 21 | B22: TARLAC | C22: Jasper Kieht B. Pili | D22: 6 | E22: 5 | F22: 6 | G22: 1
A23: 22 | B23: TARLAC | C23: Gretzhen M. Apolonio | D23: 6 | E23: 7 | F23: 7 | H23: 1
A24: 23 | B24: ZAMBALES | C24: Larizze A. Santos | D24: 5 | E24: 5 | F24: 5 | G24: 2 | H24: 1 | I24: 2 | J24: 2 | L24: 2
A25: 24 | B25: ZAMBALES | C25: Vacant
A26: 25 | B26: ZAMBALES | C26: Ryan Ace R. Angel | D26: 3 | E26: 12 | F26: 3 | G26: 1 | H26: 2

Sheet Summary of Target
A3: 10 Year Plan | B3: Target Month
A4: Province | B4: 3.March | C4: Grand Total
A5: Aurora | B5: 1 | C5: 1
A6: Bataan | B6: 1 | C6: 1
A7: Bulacan | B7: 2 | C7: 2
A8: Nueva Ecija | B8: 3 | C8: 3
A9: Pampanga | B9: 3 | C9: 3
A10: Tarlac | B10: 2 | C10: 2
A11: Zambales | B11: 1 | C11: 1
A12: Grand Total | B12: 13 | C12: 13
A17: FUNDED MRF | B17: Target Month
A18: Province | B18: 3.March | C18: Grand Total
A19: Bataan | B19: 2 | C19: 2
A20: Bulacan | B20: 3 | C20: 3
A21: Nueva Ecija | B21: 3 | C21: 3
A22: Pampanga | B22: 1 | C22: 1
A23: Tarlac | B23: 1 | C23: 1
A24: Zambales | B24: 1 | C24: 1
A25: Grand Total | B25: 11 | C25: 11
A30: Sanitary landfill | B30: Target Month
A31: Province | B31: 3.March | C31: Grand Total
A32: Aurora | B32: 1 | C32: 1
A33: Pampanga | B33: 1 | C33: 1
A34: Grand Total | B34: 2 | C34: 2
A41: Open Dumpsite | B41: Target Month
A42: Province | B42: 4.April | C42: (blank) | D42: Grand Total
A43: Bulacan | B43: 1 | D43: 1
A44: Zambales
A45: Grand Total | B45: 1 | D45: 1
A48: Funded Equipment | B48: Target Month
A49: Province | B49: 3.March | C49: Grand Total
A50: Bataan | B50: 2 | C50: 2
A51: Bulacan | B51: 3 | C51: 3
A52: Nueva Ecija | B52: 4 | C52: 4
A53: Pampanga | B53: 2 | C53: 2
A54: Tarlac | B54: 2 | C54: 2
A55: Zambales | B55: 1 | C55: 1
A56: Grand Total | B56: 14 | C56: 14
A67: LGU Intiated MRF | B67: Target Month
A68: Province | B68: 3.March | C68: Grand Total
A69: Bulacan | B69: 1 | C69: 1
A70: Nueva Ecija | B70: 3 | C70: 3
A71: Pampanga | B71: 1 | C71: 1
A72: Tarlac | B72: 2 | C72: 2
A73: Grand Total | B73: 7 | C73: 7
A80: Transfer Stations | B80: Target Month
A81: Province | B81: 2.February | C81: 3.March | D81: 4.April | E81: 5.May | F81: 6.June | G81: (blank) | H81: Grand Total
A82: Bataan | C82: 1 | H82: 1
A83: Bulacan | B83: 1 | H83: 1
A84: Nueva_Ecija | B84: 1 | D84: 1 | E84: 1 | H84: 3
A85: Pampanga | D85: 1 | F85: 1 | H85: 2
A86: Tarlac
A87: Zambales | D87: 1 | E87: 1 | H87: 2
A88: Grand Total | B88: 2 | C88: 1 | D88: 3 | E88: 2 | F88: 1 | H88: 9
A91: RCA | B91: Target Month
A92: Province | B92: 2.February | C92: 3.March | D92: 4.April | E92: 5.May | F92: 6.June | G92: (blank) | H92: Grand Total
A93: Aurora | B93: 1 | F93: 1 | H93: 2
A94: Bataan | C94: 1 | H94: 1
A95: Nueva_Ecija | D95: 1 | H95: 1
A96: Zambales | E96: 1 | H96: 1
A97: Grand Total | B97: 1 | C97: 1 | D97: 1 | E97: 1 | F97: 1 | H97: 5
A101: PDSF | B101: Target Month
A102: Province | B102: 3.March | C102: Grand Total
A103: Pampanga | B103: 1 | C103: 1
A104: Zambales | B104: 1 | C104: 1
A105: Grand Total | B105: 2 | C105: 2
A114: Trashtrap | B114: Target Month
A115: Province | B115: 2.February | C115: 5.May | D115: 3.March | E115: 4.April | F115: 6.June | G115: 7.July | H115: 8.August | I115: 9.September | J115: 10.October | K115: Grand Total
A116: Bulacan | B116: 9 | C116: 7 | D116: 6 | E116: 8 | F116: 7 | G116: 8 | H116: 8 | I116: 5 | J116: 8 | K116: 66
A117: Nueva_Ecija | C117: 3 | D117: 2 | H117: 4 | J117: 2 | K117: 11
A118: Pampanga | B118: 6 | C118: 7 | D118: 9 | E118: 7 | F118: 8 | G118: 7 | H118: 5 | I118: 10 | J118: 7 | K118: 66
A119: Grand Total | B119: 15 | C119: 17 | D119: 17 | E119: 15 | F119: 15 | G119: 15 | H119: 17 | I119: 15 | J119: 17 | K119: 143
A121: Barangay Technical Assistance
B122: January | C122: February | D122: March | E122: April | F122: May | G122: June | H122: July | I122: August | J122: September | K122: October | L122: November | M122: December | N122: TOTAL
A123: Target | B123: 31 | C123: 140 | D123: 140 | E123: 124 | F123: 124 | G123: 127 | H123: 103 | I123: 103 | J123: 106 | K123: 125 | L123: 66 | N123: =SUM(B123:L123) -> 1189
A124: MBA | B124: 30 | C124: 115 | D124: 120 | E124: 115 | F124: 120 | G124: 110 | H124: 90 | I124: 90 | J124: 90 | K124: 90 | L124: 32 | N124: =SUM(B124:L124) -> 1002
A125: OUTSIDE MBA | B125: =B123-B124 -> 1 | C125: =C123-C124 -> 25 | D125: =D123-D124 -> 20 | E125: =E123-E124 -> 9 | F125: =F123-F124 -> 4 | G125: =G123-G124 -> 17 | H125: =H123-H124 -> 13 | I125: =I123-I124 -> 13 | ... M125: =M123-M124 -> 0 | N125: =SUM(B125:M125) -> 187
A126: Bulacan | B126: 6 | C126: 28 | D126: 28 | E126: 25 | F126: 25 | G126: 25 | H126: 21 | I126: 21 | J126: 21 | K126: 25 | L126: 13 | M126: 0 | N126: =SUM(B126:M126) -> 238
A127: Nueva Ecija | B127: 12 | C127: 55 | D127: 55 | E127: 48 | F127: 49 | G127: 49 | H127: 40 | I127: 40 | J127: 42 | K127: 49 | L127: 26 | M127: 0 | N127: =SUM(B127:M127) -> 465
A128: Pampanga | B128: 7 | C128: 33 | D128: 33 | E128: 29 | F128: 29 | G128: 30 | H128: 24 | I128: 24 | J128: 25 | K128: 29 | L128: 15 | M128: 0 | N128: =SUM(B128:M128) -> 278
A129: Tarlac | B129: 5 | C129: 23 | D129: 23 | E129: 20 | F129: 20 | G129: 21 | H129: 17 | I129: 17 | J129: 17 | K129: 21 | L129: 11 | M129: 0 | N129: =SUM(B129:M129) -> 195
A130: Zambales | B130: 1 | C130: 1 | D130: 1 | E130: 2 | F130: 1 | G130: 2 | H130: 1 | I130: 1 | J130: 1 | K130: 1 | L130: 1 | M130: 0 | N130: =SUM(B130:M130) -> 13
B131: 31 | C131: 140 | D131: 140 | E131: 124 | F131: 124 | G131: 127 | H131: 103 | I131: 103 | J131: 106 | K131: 125 | L131: 66 | M131: 0 | N131: =SUM(N126:N130) -> 1189
A133: LGU ASST. TO WASTE DIVERSION | B133: TARGET MONTH
A134: PROVINCE | B134: 1.January | C134: 10.October | D134: 4.April | E134: 7.July | F134: Grand Total
A135: AURORA | B135: 2 | C135: 2 | D135: 1 | F135: 5
A136: BATAAN | B136: 1 | D136: 1 | E136: 1 | F136: 3
A137: NUEVA ECIJA | C137: 1 | D137: 1 | E137: 1 | F137: 3
A138: TARLAC | B138: 1 | C138: 1 | D138: 1 | E138: 2 | F138: 5
A139: ZAMBALES | B139: 1 | C139: 1 | D139: 1 | E139: 1 | F139: 4
A140: Grand Total | B140: 5 | C140: 5 | D140: 5 | E140: 5 | F140: 20
A143: Count of Target Month | B143: Target Month
A144: Province | B144: 1.January | C144: 2.February | D144: 3.March | E144: 4.April | F144: 5.May | G144: 6.June | H144: (blank) | I144: Grand Total
A145: Aurora
A146: Bataan
A147: Bulacan | B147: 6 | C147: 28 | D147: 28 | E147: 25 | F147: 25 | G147: 25 | I147: 137
A148: Nueva_Ecija | B148: 12 | C148: 55 | D148: 55 | E148: 48 | F148: 49 | G148: 49 | I148: 268
A149: Pampanga | B149: 7 | C149: 33 | D149: 33 | E149: 29 | F149: 29 | G149: 30 | I149: 161
A150: Tarlac | B150: 5 | C150: 23 | D150: 23 | E150: 20 | F150: 20 | G150: 21 | I150: 112
A151: Zambales | B151: 1 | C151: 1 | D151: 1 | E151: 2 | F151: 1 | G151: 2 | I151: 8
...

Sheet Data Validation
A1: Type of Plan | C1: SLF | H1: MRF | K1: EQUIPEMENT | M1: ODS | Q1: PDS | T1: TRASH TRAP | W1: TRANSFER STATION | AD1: RCA
A2: Municipal / City Plan | B2: YES | H2: OPERATIONAL | K2: OPERATIONAL | M2: FULLY REHABILITATED | N2: COMPLIANT | Q2: OPERATIONAL | T2: OPERATIONAL | W2: OPERATIONAL | X2: FACILITY | Y2: LGU | AD2: OPERATIONAL | AE2: FACILITY
A3: Provincial Plan | B3: NO | H3: NON-OPERATIONAL | K3: NON-OPERATIONAL | M3: PARTIAL REHABILITATED | N3: NOT COMPLIANT | Q3: NON-OPERATIONAL | T3: NON-OPERATIONAL | W3: NON-OPERATIONAL | X3: BIN | Y3: PRIVATE OWNERSHIP | AD3: NON-OPERATIONAL | AE3: BIN
H4: UNDER CONSTRUCTION | K4: PLANNING TO TRANSFER | M4: NOT YET REHABILITATED | Q4: PLANNING TO TRANSFER | W4: UNDER CONSTRUCTION | AD4: UNDER CONSTRUCTION
B5: YES | H5: OPERATING AS OPEN DUMPSITE | K5: PLANNING TO RETURN | M5: OPERATING AS OPEN DUMPSITE | Q5: OTHER | W5: OPERATING AS OPEN DUMPSITE | AD5: OPERATING AS OPEN DUMPSITE
B6: NO
A7: Type of MRF | B7: N/A
A8: EMB FUNDED MRF
A9: EMB FUNDED BRGY MRF
A10: LGU FUNDED MRF
A13: 1.January | C13: LIST OF ENMO | D13: ESWM STAFF | E13: ESWM FOCAL
A14: 2.February | C14: Queenyvel R. Laguisma | D14: Maria Cecilia S. Pascual | E14: Diozelle L. Cabalar
A15: 3.March | C15: Zaila Mae R. Leander | E15: Christle D. David
A16: 4.April | C16: Nikko Jay M. Valenzuela | E16: Zosimo P. Suyat
A17: 5.May | C17: Laurence Radasa | E17: Sherwin John Y. Loquellano
A18: 6.June | C18: John-Lester C. Signio | E18: Jun D. Guillermo
A19: 7.July | C19: Dennis G. Tolentino | E19: Jan Emerson C. Gonzales
A20: 8.August | C20: Ronaldo P. Roque Jr
A21: 9.September | C21: Jasmin Marie N. Siapco
A22: 10.October | C22: James Wilson T. Peña
A23: 11.November | C23: Aser A. Inocencio Jr.
A24: 12.December | C24: Christine Ann V. Ramos
C25: Gem C. Vicencio
C26: Christian Jem L. Buluran
C27: Hosannah R. Sabio
C28: Elyza A. Evilla
C29: Glaiza S. Gaza
C30: Roger T. Encarnacion II
C31: Joshua A. Capones
C32: Gretzhen A. Collado
C33: Jasper Kieht B. Pili
C34: Larizze Anne A. Santos
C35: Ryan Ace R. Angel
C36: Sebastian Josh V. Manalang

Sheet SUMMARY
A1: Monitoring of Approved 10 Year Plan | B1: Based on WFP 2026 Target is 126
B2: Approved Plan is 126 LGU and 4 Province
A5: EMB Funded MRF | B5: Removal of Duplicate EMB Funded MRF of Brgy Binuangan Obando Bulacan 2017
B6: Concerned regarding the status of the Funded MRF that has remarks of unsed/demolished/transform to another facility and closed due to land ownership
A8: SLF | B8: MCWMC Removal to Monitoring Target
A10: Brgy Technical Assistance | B10: Based on WFP 2026 Target is 1,677
B11: The number barangay that are not monitored is 1,248 only
A14: Transfer Station | B14: Removal of the TS that was monitored as component of Central MRF
A16: RCA | B16: Removal of the RCA that was monitored as component of Central MRF

Sheet 10-YEAR SWM PLAN
A1: Province | B1: Municipality | C1: Concatenate | D1: Manila Bay Area (MBA) | E1: Congressional District | F1: Long. | G1: Lat. | H1: Location | I1: Type of SWM Plan | J1: Resolution No. | K1: Period Covered | L1: Year Approved | M1: End Period | N1: For Renewal | O1: ENMO Assigned | P1: ESWM Staff | Q1: Focal Person | R1: Target Month | S1: IIS NUMBER | T1: Date of Monitoring | U1: Date Report Prepared (Submitted to IIS by ENMO) | V1: Date Report Reviewed (by ESWM Staff) | W1: Date Report Reviewed (by Focal Person) | X1: Date Report Approved | Y1: Total No. of Days (Report prepared) | Z1: Total No. of Days (Report Reviewed by ESWM Staff) | AA1: Total No. of Days (Report Reviewed by Focal) | AB1: Total No. of Days (Report Approved by C, ESWM) | AC1: Tracking of Reports (To be filled out by Planning Section) | AD1: PCG | AE1: Total Waste Generation | AF1: Waste Diversion Rate (%) | AG1: LGU Final Disposal | AH1: Remarks and Recommendation (Compliant/ Non-Compliant) | AI1: a. source reduction activities at source are present | AJ1: b. Collection segregated collection | AK1: c. Storage and setout (Segregation at source) | AL1: d. Processing MRF | AM1: e. Transfer Station | AN1: f. Disposal Facilities | AO1: Advise Letter/Notice Date Issued | AP1: Compliance to Advise/ Letter Issued | AQ1: Remarks | AR1: Biodegradable Wastes (kg/day) | AS1: Bio (%) | AT1: Recyclable Wastes (kg/day) | AU1: Recyclable (%) | AV1: Residual with potential (kg/day) | AW1: Residual with Potential (%) | AX1: Residual Wastes for Disposal (kg/day) | AY1: Residual (%) | AZ1: Special Wastes (kg/day) | BA1: Special (%) | BB1: Waste Diversion Rate (%) | BC1: Disposal Rate (%) | BD1: Signed Document
A2: Bataan | B2: Dinalupihan | C2: =CONCATENATE(A2,","," ",B2) -> Bataan, Dinalupihan | D2: MBA | E2: 3rd | F2: 14.866933 | G2: 120.4611 | H2: =CONCATENATE(F2,",",G2) -> 14.866933,120.461103 | I2: Municipal / City Plan | J2: NSWMC Resoution No. 149-A, Series of 2025 | K2: 2025-2034 | L2: 2025 | M2: 2034 | N2: Approved | O2: John-lester Signio | Q2: Christle D. David | R2: 1.January | S2: R3-2026-000641 | T2: 46034 | U2: 46034 | W2: 46035 | X2: 46039 | Y2: =IFERROR( IF( OR(ISBLANK(T2), ISBLANK(U2)), "", MAX( 1, IF( NETWORKDAYS(T2, U2, Holiday_Dates) <= 0, 1, NETWORKDAYS(T2, U2, Holiday_Dates) - IF(T2 = U2, 0, 1) ) ) ), "" ) -> 1 | Z2: =IF( OR(ISBLANK(U2), ISBLANK(V2)), "", MAX( 1, IF( NETWORKDAYS(U2, V2, Holiday_Dates) <= 0, 1, NETWORKDAYS(U2, V2, Holiday_Dates) - IF(U2 = V2, 0, 1) ) ) ) | AA2: =IFERROR( IF( OR(ISBLANK(W2), AND(ISBLANK(U2), ISBLANK(V2))), "", MAX( 1, IF( NETWORKDAYS(IF(NOT(ISBLANK(V2)), V2, U2), W2, Holiday_Dates) <= 0, 1, NETWORKDAYS(IF(NOT(ISBLANK(V2)), V2, U2), W2, Holiday_Dates) - IF(IF(NOT(ISBLANK(V2)), V2, U2) = W2, 0, 1) ) ) ), "" ) -> 1 | AB2: =IFERROR( IF( OR(ISBLANK(W2), ISBLANK(X2)), "", MAX( 1, IF( NETWORKDAYS(W2, X2, Holiday_Dates) <= 0, 1, NETWORKDAYS(W2, X2, Holiday_Dates) - IF(W2 = X2, 0, 1) ) ) ), "" ) -> 3 | AC2: Marshalle Julluice V. Catua | AD2: 0.668 | AE2: 82453.24 | AF2: 93.32 | AG2: Floridablanca Enviro Corporation | AH2: Compliant | AI2: YES | AJ2: YES | AK2: YES | AL2: YES | AN2: YES | AR2: 45374.02 | AS2: 0.5503 | AT2: 29402.83 | AU2: 0.3566 | AV2: 2168.52 | AW2: 0.0263 | AX2: 3042.52 | AY2: 0.0369 | AZ2: 2465.35 | BA2: 0.0299 | BB2: =SUM(AS2,AU2,AW2) -> 0.9332 | BC2: =SUM(AS2,AU2,AW2) -> 0.9332 | BD2: https://embco-my.sharepoint.com/:w:/g/personal/eswmr3_emb_gov_ph/IQD7bEqKn0GsTI_TzqPuNDVXAc0qXRdO4blA_DzluhQNwt8?e=94dpdL
A3: Bulacan | B3: Marilao | C3: =CONCATENATE(A3,","," ",B3) -> Bulacan, Marilao | D3: MBA | E3: 4th | F3: 14.774122 | G3: 120.95918 | H3: =CONCATENATE(F3,",",G3) -> 14.774122,120.959182 | I3: Municipal / City Plan | J3: No.1427 Series of 2020 | K3: 2019 - 2029 | L3: 2020 | M3: 2029 | N3: For Renewal | O3: James Wilson T. Pena | Q3: Diozelle L. Cabalar | R3: 1.January | S3: R3-2026-001826 | T3: 46043 | U3: 46043 | W3: 46043 | X3: 46044 | Y3: =IFERROR( IF( OR(ISBLANK(T3), ISBLANK(U3)), "", MAX( 1, IF( NETWORKDAYS(T3, U3, Holiday_Dates) <= 0, 1, NETWORKDAYS(T3, U3, Holiday_Dates) - IF(T3 = U3, 0, 1) ) ) ), "" ) -> 1 | Z3: =IF( OR(ISBLANK(U3), ISBLANK(V3)), "", MAX( 1, IF( NETWORKDAYS(U3, V3, Holiday_Dates) <= 0, 1, NETWORKDAYS(U3, V3, Holiday_Dates) - IF(U3 = V3, 0, 1) ) ) ) | AA3: =IFERROR( IF( OR(ISBLANK(W3), AND(ISBLANK(U3), ISBLANK(V3))), "", MAX( 1, IF( NETWORKDAYS(IF(NOT(ISBLANK(V3)), V3, U3), W3, Holiday_Dates) <= 0, 1, NETWORKDAYS(IF(NOT(ISBLANK(V3)), V3, U3), W3, Holiday_Dates) - IF(IF(NOT(ISBLANK(V3)), V3, U3) = W3, 0, 1) ) ) ), "" ) -> 1 | AB3: =IFERROR( IF( OR(ISBLANK(W3), ISBLANK(X3)), "", MAX( 1, IF( NETWORKDAYS(W3, X3, Holiday_Dates) <= 0, 1, NETWORKDAYS(W3, X3, Holiday_Dates) - IF(W3 = X3, 0, 1) ) ) ), "" ) -> 1 | AC3: Marshalle Julluice V. Catua | AD3: 0.3557 | AE3: 91843.79 | AF3: 77.44 | AG3: Eco Protect Management Corp. | AH3: Compliant | AI3: YES | AJ3: YES | AK3: YES | AL3: YES | AN3: YES | AR3: 15882.5 | AS3: 0.5825 | AT3: 5232.36 | AU3: 0.1919 | AV3: 0 | AW3: 0 | AX3: 2320.82 | AY3: 0.1031 | AZ3: 410.73 | BA3: 0.0103 | BB3: =SUM(AS3,AU3,AW3) -> 0.7744 | BC3: =SUM(AS3,AU3,AW3) -> 0.7744 | BD3: https://embco-my.sharepoint.com/:w:/g/personal/eswmr3_emb_gov_ph/IQA5WfPi4zdFQrvzvXbj5kDRAVPSzQ2YO7TZTs8ks-501do?e=sPDram
A4: Nueva Ecija | B4: City Of Cabanatuan | C4: =CONCATENATE(A4,","," ",B4) -> Nueva Ecija, City Of Cabanatuan | D4: MBA | E4: 3rd | F4: 15.470778 | G4: 120.9521 | H4: =CONCATENATE(F4,",",G4) -> 15.470778,120.952099 | I4: Municipal / City Plan | J4: NSWMC RESO NO. 1513 SERIES OF 2022 | K4: 2020 - 2029 | L4: 2022 | M4: 2029 | O4: Christian Jem L. Buluran | Q4: Zosimo P. Suyat | R4: 1.January | S4: R3-2026-002129 | T4: 46037 | U4: 46044 | W4: 46044 | X4: 46045 | Y4: =IFERROR( IF( OR(ISBLANK(T4), ISBLANK(U4)), "", MAX( 1, IF( NETWORKDAYS(T4, U4, Holiday_Dates) <= 0, 1, NETWORKDAYS(T4, U4, Holiday_Dates) - IF(T4 = U4, 0, 1) ) ) ), "" ) -> 5 | Z4: =IF( OR(ISBLANK(U4), ISBLANK(V4)), "", MAX( 1, IF( NETWORKDAYS(U4, V4, Holiday_Dates) <= 0, 1, NETWORKDAYS(U4, V4, Holiday_Dates) - IF(U4 = V4, 0, 1) ) ) ) | AA4: =IFERROR( IF( OR(ISBLANK(W4), AND(ISBLANK(U4), ISBLANK(V4))), "", MAX( 1, IF( NETWORKDAYS(IF(NOT(ISBLANK(V4)), V4, U4), W4, Holiday_Dates) <= 0, 1, NETWORKDAYS(IF(NOT(ISBLANK(V4)), V4, U4), W4, Holiday_Dates) - IF(IF(NOT(ISBLANK(V4)), V4, U4) = W4, 0, 1) ) ) ), "" ) -> 1 | AB4: =IFERROR( IF( OR(ISBLANK(W4), ISBLANK(X4)), "", MAX( 1, IF( NETWORKDAYS(W4, X4, Holiday_Dates) <= 0, 1, NETWORKDAYS(W4, X4, Holiday_Dates) - IF(W4 = X4, 0, 1) ) ) ), "" ) -> 1 | AC4: Marshalle Julluice V. Catua | AD4: 0.363 | AE4: 136116.65 | AF4: 77.37 | AG4: Primewaste Solution Inc | AH4: Compliant | AI4: YES | AJ4: YES | AK4: YES | AL4: YES | AM4: YES | AN4: YES | AR4: 70901.2 | AS4: 0.5312 | AT4: 30538.77 | AU4: 0.2425 | AV4: 0 | AW4: 0 | AX4: 31688.62 | AY4: 0.2237 | AZ4: 345.05 | BA4: 0.0026 | BB4: =SUM(AS4,AU4,AW4) -> 0.7737 | BC4: =SUM(AS4,AU4,AW4) -> 0.7737 | BD4: https://embco-my.sharepoint.com/:w:/g/personal/eswmr3_emb_gov_ph/IQDdVVBMJoeaS6SuKSU2xPh7Af_OFDLpkLTua37NCNLCOR4?e=EmbUDA
A5: Pampanga | B5: City Of San Fernando | C5: =CONCATENATE(A5,","," ",B5) -> Pampanga, City Of San Fernando | D5: MBA | E5: 3rd | F5: 15.0279 | G5: 120.6937 | H5: =CONCATENATE(F5,",",G5) -> 15.0279,120.6937 | I5: Municipal / City Plan | J5: 167A series 2025 | K5: 2025-2034 | L5: 2025 | M5: 2034 | O5: Elyza A. Evilla | Q5: Sherwin John Y. Loquellano | R5: 1.January | S5: R3-2026-001245 | T5: 46035 | U5: 46038 | W5: 46043 | X5: 46043 | Y5: =IFERROR( IF( OR(ISBLANK(T5), ISBLANK(U5)), "", MAX( 1, IF( NETWORKDAYS(T5, U5, Holiday_Dates) <= 0, 1, NETWORKDAYS(T5, U5, Holiday_Dates) - IF(T5 = U5, 0, 1) ) ) ), "" ) -> 3 | Z5: =IF( OR(ISBLANK(U5), ISBLANK(V5)), "", MAX( 1, IF( NETWORKDAYS(U5, V5, Holiday_Dates) <= 0, 1, NETWORKDAYS(U5, V5, Holiday_Dates) - IF(U5 = V5, 0, 1) ) ) ) | AA5: =IFERROR( IF( OR(ISBLANK(W5), AND(ISBLANK(U5), ISBLANK(V5))), "", MAX( 1, IF( NETWORKDAYS(IF(NOT(ISBLANK(V5)), V5, U5), W5, Holiday_Dates) <= 0, 1, NETWORKDAYS(IF(NOT(ISBLANK(V5)), V5, U5), W5, Holiday_Dates) - IF(IF(NOT(ISBLANK(V5)), V5, U5) = W5, 0, 1) ) ) ), "" ) -> 3 | AB5: =IFERROR( IF( OR(ISBLANK(W5), ISBLANK(X5)), "", MAX( 1, IF( NETWORKDAYS(W5, X5, Holiday_Dates) <= 0, 1, NETWORKDAYS(W5, X5, Holiday_Dates) - IF(W5 = X5, 0, 1) ) ) ), "" ) -> 1 | AC5: Marshalle Julluice V. Catua | AD5: 0.637 | AE5: 255469.93 | AF5: 62.27 | AG5: Eco Protect Management Corp. | AH5: Compliant | AI5: YES | AJ5: YES | AK5: YES | AL5: YES | AM5: YES | AN5: YES | AR5: 76338.593 | AS5: 0.29882 | AT5: 82735.887 | AU5: 0.32386 | AV5: 0 | AW5: 0 | AX5: 85518.274 | AY5: 0.33475 | AZ5: 10877.176 | BA5: 0.04258 | BB5: =SUM(AS5,AU5,AW5) -> 0.62268 | BC5: =SUM(AS5,AU5,AW5) -> 0.62268 | BD5: https://embco-my.sharepoint.com/:w:/g/personal/eswmr3_emb_gov_ph/IQCyadJTiBCdTraSzEK4FCgcAaqdsntGbrIKiw5WLFauhOQ?e=vL0aPp
A6: Zambales | B6: City Of Olongapo | C6: =CONCATENATE(A6,","," ",B6) -> Zambales, City Of Olongapo | D6: OUTSIDE MBA | E6: 1st | F6: 14.842411 | G6: 120.28765 | H6: =CONCATENATE(F6,",",G6) -> 14.842411,120.287647 | I6: Municipal / City Plan | J6: NSWMC Resolution No. 1639, Series of 2023 | K6: 2023 - 2032 | L6: 2023 | M6: 2032 | O6: Larizze Ann A. Santos | Q6: Jun D. Guillermo | R6: 1.January | S6: R3-2026-001347 | T6: 46037 | U6: 46040 | W6: 46040 | X6: 46041 | Y6: =IFERROR( IF( OR(ISBLANK(T6), ISBLANK(U6)), "", MAX( 1, IF( NETWORKDAYS(T6, U6, Holiday_Dates) <= 0, 1, NETWORKDAYS(T6, U6, Holiday_Dates) - IF(T6 = U6, 0, 1) ) ) ), "" ) -> 1 | Z6: =IF( OR(ISBLANK(U6), ISBLANK(V6)), "", MAX( 1, IF( NETWORKDAYS(U6, V6, Holiday_Dates) <= 0, 1, NETWORKDAYS(U6, V6, Holiday_Dates) - IF(U6 = V6, 0, 1) ) ) ) | AA6: =IFERROR( IF( OR(ISBLANK(W6), AND(ISBLANK(U6), ISBLANK(V6))), "", MAX( 1, IF( NETWORKDAYS(IF(NOT(ISBLANK(V6)), V6, U6), W6, Holiday_Dates) <= 0, 1, NETWORKDAYS(IF(NOT(ISBLANK(V6)), V6, U6), W6, Holiday_Dates) - IF(IF(NOT(ISBLANK(V6)), V6, U6) = W6, 0, 1) ) ) ), "" ) -> 1 | AB6: =IFERROR( IF( OR(ISBLANK(W6), ISBLANK(X6)), "", MAX( 1, IF( NETWORKDAYS(W6, X6, Holiday_Dates) <= 0, 1, NETWORKDAYS(W6, X6, Holiday_Dates) - IF(W6 = X6, 0, 1) ) ) ), "" ) -> 1 | AC6: Marshalle Julluice V. Catua | AD6: 0.893 | AE6: 236558.38 | AF6: 76.84 | AG6: LGU Owned SLF | AH6: Compliant | AI6: YES | AJ6: YES | AK6: YES | AL6: YES | AN6: YES | AR6: 96468.51 | AS6: 0.4078 | AT6: 73711.59 | AU6: 0.3116 | AV6: 11591.36 | AW6: 0.049 | AX6: 47311.68 | AY6: 0.2 | AZ6: 7475.24 | BA6: 0.0316 | BB6: =SUM(AS6,AU6,AW6) -> 0.7684 | BC6: =SUM(AS6,AU6,AW6) -> 0.7684 | BD6: https://embco-my.sharepoint.com/:w:/g/personal/eswmr3_emb_gov_ph/IQCq3Z8yK6pDRY7xfHsHb-yrAfdaJkvE8BTLGFYFPAFowPU?e=OG5PVQ
A7: Tarlac | B7: Concepcion | C7: =CONCATENATE(A7,","," ",B7) -> Tarlac, Concepcion | D7: MBA | E7: 3rd | F7: 15.323352 | G7: 120.65551 | H7: =CONCATENATE(F7,",",G7) -> 15.323352,120.655511 | I7: Municipal / City Plan | J7: NSWMC RESO NO. 1404SERIES OF 2020 | K7: 2018 - 2027 | L7: 2020 | M7: 2027 | O7: Gretzhen M. Apolonio | Q7: Jan Emerson C. Gonzales | R7: 1.January | S7: R3-2026-001299 | T7: 46037 | U7: 46038 | W7: 46042 | X7: 46042 | Y7: =IFERROR( IF( OR(ISBLANK(T7), ISBLANK(U7)), "", MAX( 1, IF( NETWORKDAYS(T7, U7, Holiday_Dates) <= 0, 1, NETWORKDAYS(T7, U7, Holiday_Dates) - IF(T7 = U7, 0, 1) ) ) ), "" ) -> 1 | Z7: =IF( OR(ISBLANK(U7), ISBLANK(V7)), "", MAX( 1, IF( NETWORKDAYS(U7, V7, Holiday_Dates) <= 0, 1, NETWORKDAYS(U7, V7, Holiday_Dates) - IF(U7 = V7, 0, 1) ) ) ) | AA7: =IFERROR( IF( OR(ISBLANK(W7), AND(ISBLANK(U7), ISBLANK(V7))), "", MAX( 1, IF( NETWORKDAYS(IF(NOT(ISBLANK(V7)), V7, U7), W7, Holiday_Dates) <= 0, 1, NETWORKDAYS(IF(NOT(ISBLANK(V7)), V7, U7), W7, Holiday_Dates) - IF(IF(NOT(ISBLANK(V7)), V7, U7) = W7, 0, 1) ) ) ), "" ) -> 2 | AB7: =IFERROR( IF( OR(ISBLANK(W7), ISBLANK(X7)), "", MAX( 1, IF( NETWORKDAYS(W7, X7, Holiday_Dates) <= 0, 1, NETWORKDAYS(W7, X7, Holiday_Dates) - IF(W7 = X7, 0, 1) ) ) ), "" ) -> 1 | AC7: Marshalle Julluice V. Catua | AD7: 0.55 | AE7: 88, 316 | AF7: 85.54 | AG7: International Solid Waste Integrated Management Specialist Inc. | AH7: Compliant | AI7: YES | AJ7: YES | AK7: YES | AL7: YES | AN7: YES | AR7: 56, 725.53 | AS7: 0.6423 | AT7: 18820.19 | AU7: 0.2131 | AV7: 0 | AW7: 0 | AX7: 12726.37 | AY7: 0.1441 | AZ7: 44.16 | BA7: 0.05 | BB7: =SUM(AS7,AU7,AW7) -> 0.8554 | BC7: =SUM(AS7,AU7,AW7) -> 0.8554 | BD7: https://embco-my.sharepoint.com/:w:/g/personal/eswmr3_emb_gov_ph/IQAoXqD_P-YDQoQvY1444AYSAcRHbghpemlxV3Ql5FKXax8?e=jvcigM
A8: Aurora | B8: Maria Aurora | C8: =CONCATENATE(A8,","," ",B8) -> Aurora, Maria Aurora | D8: OUTSIDE MBA | E8: Lone | F8: 15.798717 | G8: 121.47355 | H8: =CONCATENATE(F8,",",G8) -> 15.798717,121.47355 | I8: Municipal / City Plan | J8: NSWMC Resolution No. 139, Series of 2015 | K8: 2015 - 2024 | L8: 2015 | M8: 2024 | N8: Approved | O8: Nikko Jay M. Valenzuela | Q8: Diozelle L. Cabalar | R8: 2.February | S8: R3-2026-004094 | T8: 46056 | U8: 46062 | V8: 46069 | W8: 46069 | X8: 46069 | Y8: =IFERROR( IF( OR(ISBLANK(T8), ISBLANK(U8)), "", MAX( 1, IF( NETWORKDAYS(T8, U8, Holiday_Dates) <= 0, 1, NETWORKDAYS(T8, U8, Holiday_Dates) - IF(T8 = U8, 0, 1) ) ) ), "" ) -> 4 | Z8: =IF( OR(ISBLANK(U8), ISBLANK(V8)), "", MAX( 1, IF( NETWORKDAYS(U8, V8, Holiday_Dates) <= 0, 1, NETWORKDAYS(U8, V8, Holiday_Dates) - IF(U8 = V8, 0, 1) ) ) ) -> 5 | AA8: =IFERROR( IF( OR(ISBLANK(W8), AND(ISBLANK(U8), ISBLANK(V8))), "", MAX( 1, IF( NETWORKDAYS(IF(NOT(ISBLANK(V8)), V8, U8), W8, Holiday_Dates) <= 0, 1, NETWORKDAYS(IF(NOT(ISBLANK(V8)), V8, U8), W8, Holiday_Dates) - IF(IF(NOT(ISBLANK(V8)), V8, U8) = W8, 0, 1) ) ) ), "" ) -> 1 | AB8: =IFERROR( IF( OR(ISBLANK(W8), ISBLANK(X8)), "", MAX( 1, IF( NETWORKDAYS(W8, X8, Holiday_Dates) <= 0, 1, NETWORKDAYS(W8, X8, Holiday_Dates) - IF(W8 = X8, 0, 1) ) ) ), "" ) -> 1 | AC8: Marshalle Julluice V. Catua | AD8: 0.24 | AE8: 1846.31 | AF8: 8.02 | AG8: Maria Aurora SLF | AH8: Compliant | AI8: YES | AJ8: YES | AK8: YES | AL8: YES | AN8: YES | AR8: 95.66 | AS8: 0.0518 | AT8: 39.14 | AU8: 0.0211 | AV8: 13.58 | AW8: 0.0073 | AX8: 1697.93 | AY8: 0.9196 | AZ8: 0 | BA8: 0 | BB8: =SUM(AS8,AU8,AW8) -> 0.0802 | BC8: =SUM(AS8,AU8,AW8) -> 0.0802 | BD8: https://embco-my.sharepoint.com/:w:/g/personal/eswmr3_emb_gov_ph/IQBIG2IIMgPxTo3UTdguNmkXAY9AMq8I2bvdPXit5HIiqhw?e=ukKJuY
A9: Bataan | B9: Bagac | C9: =CONCATENATE(A9,","," ",B9) -> Bataan, Bagac | D9: MBA | E9: 3rd | F9: 14.607148 | G9: 120.402 | H9: =CONCATENATE(F9,",",G9) -> 14.607148,120.401997 | I9: Municipal / City Plan | J9: 975 SERIES OF 2017 | K9: 2015 - 2024 | L9: 2017 | M9: 2024 | N9: For Renewal | O9: Laurence Radasa | Q9: Christle D. David | R9: 2.February | S9: R3-2026-004255 | T9: 46062 | U9: 46063 | W9: 46064 | X9: 46064 | Y9: =IFERROR( IF( OR(ISBLANK(T9), ISBLANK(U9)), "", MAX( 1, IF( NETWORKDAYS(T9, U9, Holiday_Dates) <= 0, 1, NETWORKDAYS(T9, U9, Holiday_Dates) - IF(T9 = U9, 0, 1) ) ) ), "" ) -> 1 | Z9: =IF( OR(ISBLANK(U9), ISBLANK(V9)), "", MAX( 1, IF( NETWORKDAYS(U9, V9, Holiday_Dates) <= 0, 1, NETWORKDAYS(U9, V9, Holiday_Dates) - IF(U9 = V9, 0, 1) ) ) ) | AA9: =IFERROR( IF( OR(ISBLANK(W9), AND(ISBLANK(U9), ISBLANK(V9))), "", MAX( 1, IF( NETWORKDAYS(IF(NOT(ISBLANK(V9)), V9, U9), W9, Holiday_Dates) <= 0, 1, NETWORKDAYS(IF(NOT(ISBLANK(V9)), V9, U9), W9, Holiday_Dates) - IF(IF(NOT(ISBLANK(V9)), V9, U9) = W9, 0, 1) ) ) ), "" ) -> 1 | AB9: =IFERROR( IF( OR(ISBLANK(W9), ISBLANK(X9)), "", MAX( 1, IF( NETWORKDAYS(W9, X9, Holiday_Dates) <= 0, 1, NETWORKDAYS(W9, X9, Holiday_Dates) - IF(W9 = X9, 0, 1) ) ) ), "" ) -> 1 | AC9: Marshalle Julluice V. Catua | AD9: 0.404 | AE9: 11865.24 | AF9: 91.16 | AG9: Eco Protect Management Corporation Floridablanca Enviro Corporation | AH9: Compliant | AI9: YES | AJ9: YES | AK9: YES | AL9: YES | AM9: YES | AN9: YES | AR9: 6555.54 | AS9: 0.5525 | AT9: 3141.92 | AU9: 0.2648 | AV9: 1118.89 | AW9: 0.0943 | AX9: 1035.84 | AY9: 0.0873 | AZ9: 13.05 | BA9: 0.0011 | BB9: =SUM(AS9,AU9,AW9) -> 0.9116 | BC9: =SUM(AS9,AU9,AW9) -> 0.9116 | BD9: https://embco-my.sharepoint.com/:w:/g/personal/eswmr3_emb_gov_ph/IQBQM3HpC3GtQLTiWy-TFxP4AZLt3PRtwRxxBpO5-qYEMhk?e=W0qafE
A10: Bataan | B10: City Of Balanga | C10: =CONCATENATE(A10,","," ",B10) -> Bataan, City Of Balanga | D10: MBA | E10: 2nd | F10: 14.679914 | G10: 120.5407 | H10: =CONCATENATE(F10,",",G10) -> 14.679914,120.540698 | I10: Municipal / City Plan | J10: 482-A series of 2025 | K10: 2025-2034 | L10: 2025 | M10: 2034 | N10: For Renewal | O10: Dennis Tolentino | Q10: Christle D. David | R10: 2.February | S10: R3-2026-002980 | T10: 46051 | U10: 46052 | W10: 46053 | X10: 46055 | Y10: =IFERROR( IF( OR(ISBLANK(T10), ISBLANK(U10)), "", MAX( 1, IF( NETWORKDAYS(T10, U10, Holiday_Dates) <= 0, 1, NETWORKDAYS(T10, U10, Holiday_Dates) - IF(T10 = U10, 0, 1) ) ) ), "" ) -> 1 | Z10: =IF( OR(ISBLANK(U10), ISBLANK(V10)), "", MAX( 1, IF( NETWORKDAYS(U10, V10, Holiday_Dates) <= 0, 1, NETWORKDAYS(U10, V10, Holiday_Dates) - IF(U10 = V10, 0, 1) ) ) ) | AA10: =IFERROR( IF( OR(ISBLANK(W10), AND(ISBLANK(U10), ISBLANK(V10))), "", MAX( 1, IF( NETWORKDAYS(IF(NOT(ISBLANK(V10)), V10, U10), W10, Holiday_Dates) <= 0, 1, NETWORKDAYS(IF(NOT(ISBLANK(V10)), V10, U10), W10, Holiday_Dates) - IF(IF(NOT(ISBLANK(V10)), V10, U10) = W10, 0, 1) ) ) ), "" ) -> 1 | AB10: =IFERROR( IF( OR(ISBLANK(W10), ISBLANK(X10)), "", MAX( 1, IF( NETWORKDAYS(W10, X10, Holiday_Dates) <= 0, 1, NETWORKDAYS(W10, X10, Holiday_Dates) - IF(W10 = X10, 0, 1) ) ) ), "" ) -> 1 | AC10: Marshalle Julluice V. Catua | AD10: 0.485 | AE10: 50572.4 | AF10: 80.88 | AG10: BEST | AH10: Compliant | AI10: YES | AJ10: YES | AK10: YES | AL10: YES | AN10: YES | AR10: 19505.77 | AS10: 0.3857 | AT10: 9118.2 | AU10: 0.1803 | AV10: 12279.67 | AW10: 0.2428 | AX10: 9117.51 | AY10: 0.1803 | AZ10: 551.25 | BA10: 0.0109 | BB10: =SUM(AS10,AU10,AW10) -> 0.8088 | BC10: =SUM(AS10,AU10,AW10) -> 0.8088 | BD10: https://embco-my.sharepoint.com/:w:/g/personal/eswmr3_emb_gov_ph/IQAgMCluM58-SqQi5zpZbqF0AXvustCA0W3GmUhPUmg582k?e=gilkhF
A11: Bulacan | B11: City Of Meycauayan | C11: =CONCATENATE(A11,","," ",B11) -> Bulacan, City Of Meycauayan | D11: MBA | E11: 4th | F11: 14.774921 | G11: 120.99868 | H11: =CONCATENATE(F11,",",G11) -> 14.774921,120.998685 | I11: Municipal / City Plan | J11: NSWMC RESO NO. 1326 SERIES OF 2019 | K11: 2018 -2028 | L11: 2019 | M11: 2028 | N11: For Renewal | O11: James Wilson T. Pena | Q11: Diozelle L. Cabalar | R11: 2.February | S11: R3-2026-005241 | T11: 46069 | U11: 46070 | W11: 46071 | X11: 46071 | Y11: =IFERROR( IF( OR(ISBLANK(T11), ISBLANK(U11)), "", MAX( 1, IF( NETWORKDAYS(T11, U11, Holiday_Dates) <= 0, 1, NETWORKDAYS(T11, U11, Holiday_Dates) - IF(T11 = U11, 0, 1) ) ) ), "" ) -> 1 | Z11: =IF( OR(ISBLANK(U11), ISBLANK(V11)), "", MAX( 1, IF( NETWORKDAYS(U11, V11, Holiday_Dates) <= 0, 1, NETWORKDAYS(U11, V11, Holiday_Dates) - IF(U11 = V11, 0, 1) ) ) ) | AA11: =IFERROR( IF( OR(ISBLANK(W11), AND(ISBLANK(U11), ISBLANK(V11))), "", MAX( 1, IF( NETWORKDAYS(IF(NOT(ISBLANK(V11)), V11, U11), W11, Holiday_Dates) <= 0, 1, NETWORKDAYS(IF(NOT(ISBLANK(V11)), V11, U11), W11, Holiday_Dates) - IF(IF(NOT(ISBLANK(V11)), V11, U11) = W11, 0, 1) ) ) ), "" ) -> 1 | AB11: =IFERROR( IF( OR(ISBLANK(W11), ISBLANK(X11)), "", MAX( 1, IF( NETWORKDAYS(W11, X11, Holiday_Dates) <= 0, 1, NETWORKDAYS(W11, X11, Holiday_Dates) - IF(W11 = X11, 0, 1) ) ) ), "" ) -> 1 | AC11: Retuned to Focal | AD11: 0.255 | AE11: 34696.32 | AF11: 60.86 | AG11: ISWIMS SLF, Montalban, Rizal | AH11: Compliant | AI11: YES | AJ11: YES | AK11: YES | AL11: YES | AM11: NO | AN11: YES | AR11: 15882.5 | AS11: 0.5825 | AT11: 5232.36 | AU11: 0.1919 | AV11: 0 | AW11: 0 | AX11: 2320.82 | AY11: 0.1031 | AZ11: 410.73 | BA11: 0.0103 | BB11: =SUM(AS11,AU11,AW11) -> 0.7744 | BC11: =SUM(AS11,AU11,AW11) -> 0.7744 | BD11: https://embco-my.sharepoint.com/:w:/g/personal/eswmr3_emb_gov_ph/IQCAVxiIc-99TaOdfKCj2l4zAQKMPl3igA2xNSpjL7qjuWg?e=bJ3gJI
A12: Bulacan | B12: Plaridel | C12: =CONCATENATE(A12,","," ",B12) -> Bulacan, Plaridel | D12: MBA | E12: 2nd | F12: 14.886807 | G12: 120.85987 | H12: =CONCATENATE(F12,",",G12) -> 14.88680651,120.8598685 | I12: Municipal / City Plan | J12: 157-A Series of 2025 | K12: 2025-2034 | L12: 2025 | M12: 2034 | O12: Jasmin Marie N. Siapco | Q12: Diozelle L. Cabalar | R12: 2.February | S12: R3-2026-003662 | T12: 46057 | U12: 46058 | W12: 46067 | X12: 46069 | Y12: =IFERROR( IF( OR(ISBLANK(T12), ISBLANK(U12)), "", MAX( 1, IF( NETWORKDAYS(T12, U12, Holiday_Dates) <= 0, 1, NETWORKDAYS(T12, U12, Holiday_Dates) - IF(T12 = U12, 0, 1) ) ) ), "" ) -> 1 | Z12: =IF( OR(ISBLANK(U12), ISBLANK(V12)), "", MAX( 1, IF( NETWORKDAYS(U12, V12, Holiday_Dates) <= 0, 1, NETWORKDAYS(U12, V12, Holiday_Dates) - IF(U12 = V12, 0, 1) ) ) ) | AA12: =IFERROR( IF( OR(ISBLANK(W12), AND(ISBLANK(U12), ISBLANK(V12))), "", MAX( 1, IF( NETWORKDAYS(IF(NOT(ISBLANK(V12)), V12, U12), W12, Holiday_Dates) <= 0, 1, NETWORKDAYS(IF(NOT(ISBLANK(V12)), V12, U12), W12, Holiday_Dates) - IF(IF(NOT(ISBLANK(V12)), V12, U12) = W12, 0, 1) ) ) ), "" ) -> 6 | AB12: =IFERROR( IF( OR(ISBLANK(W12), ISBLANK(X12)), "", MAX( 1, IF( NETWORKDAYS(W12, X12, Holiday_Dates) <= 0, 1, NETWORKDAYS(W12, X12, Holiday_Dates) - IF(W12 = X12, 0, 1) ) ) ), "" ) -> 1 | AC12: Marshalle Julluice V. Catua | AD12: 0.329 | AE12: 39066.71 | AF12: 78.02 | AG12: Eco Protect Management Corporation | AH12: Compliant | AI12: YES | AJ12: YES | AK12: YES | AL12: YES | AN12: YES | AR12: 21694.27 | AS12: 0.5553 | AT12: 8832.99 | AU12: 0.2261 | AV12: 0 | AW12: 0 | AX12: 7846.2 | AY12: 0.2008 | AZ12: 693.27 | BA12: 0.0177 | BB12: =SUM(AS12,AU12,AW12) -> 0.7814 | BC12: =SUM(AS12,AU12,AW12) -> 0.7814 | BD12: https://embco-my.sharepoint.com/:w:/g/personal/eswmr3_emb_gov_ph/IQAHn3vp5f4nQrQ43iUpqvvmAU99LfYW1ONFGthYz21oHfE?e=hWfGHC
A13: Nueva Ecija | B13: Gen. Natividad | C13: =CONCATENATE(A13,","," ",B13) -> Nueva Ecija, Gen. Natividad | D13: MBA | E13: 3rd | F13: 15.602761 | G13: 121.04995 | H13: =CONCATENATE(F13,",",G13) -> 15.602761,121.049951 | I13: Municipal / City Plan | J13: 1076 series 2018 | K13: 2017 - 2027 | L13: 2018 | M13: 2027 | O13: Hosannah R. Sabio | Q13: Zosimo P. Suyat | R13: 2.February | S13: R3-2026-005353 | T13: 46069 | U13: 46071 | W13: 46071 | X13: 46071 | Y13: =IFERROR( IF( OR(ISBLANK(T13), ISBLANK(U13)), "", MAX( 1, IF( NETWORKDAYS(T13, U13, Holiday_Dates) <= 0, 1, NETWORKDAYS(T13, U13, Holiday_Dates) - IF(T13 = U13, 0, 1) ) ) ), "" ) -> 2 | Z13: =IF( OR(ISBLANK(U13), ISBLANK(V13)), "", MAX( 1, IF( NETWORKDAYS(U13, V13, Holiday_Dates) <= 0, 1, NETWORKDAYS(U13, V13, Holiday_Dates) - IF(U13 = V13, 0, 1) ) ) ) | AA13: =IFERROR( IF( OR(ISBLANK(W13), AND(ISBLANK(U13), ISBLANK(V13))), "", MAX( 1, IF( NETWORKDAYS(IF(NOT(ISBLANK(V13)), V13, U13), W13, Holiday_Dates) <= 0, 1, NETWORKDAYS(IF(NOT(ISBLANK(V13)), V13, U13), W13, Holiday_Dates) - IF(IF(NOT(ISBLANK(V13)), V13, U13) = W13, 0, 1) ) ) ), "" ) -> 1 | AB13: =IFERROR( IF( OR(ISBLANK(W13), ISBLANK(X13)), "", MAX( 1, IF( NETWORKDAYS(W13, X13, Holiday_Dates) <= 0, 1, NETWORKDAYS(W13, X13, Holiday_Dates) - IF(W13 = X13, 0, 1) ) ) ), "" ) -> 1 | AC13: Marshalle Julluice V. Catua | AD13: 0.25 | AE13: 10690 | AF13: 91.25 | AG13: Prime Waste Solution | AH13: Compliant | AI13: YES | AJ13: YES | AK13: YES | AL13: YES | AN13: YES | AR13: 6812.11 | AS13: 0.6095 | AT13: 3386.05 | AU13: 0.303 | AV13: 0 | AW13: 0 | AX13: 527.12 | AY13: 0.0472 | AZ13: 450.85 | BA13: 0.0403 | BB13: =SUM(AS13,AU13,AW13) -> 0.9125 | BC13: =SUM(AS13,AU13,AW13) -> 0.9125 | BD13: https://embco-my.sharepoint.com/:w:/g/personal/eswmr3_emb_gov_ph/IQB2HswZFbenQJlrQ5OvuLOhAUT0Ob9KeuZppjA1rXhA2X4?e=0xDsQ8
A14: Nueva Ecija | B14: Lupao | C14: =CONCATENATE(A14,","," ",B14) -> Nueva Ecija, Lupao | D14: MBA | E14: 2nd | F14: 15.877262 | G14: 120.8989 | H14: =CONCATENATE(F14,",",G14) -> 15.877262,120.898901 | I14: Municipal / City Plan | J14: 1065 Series of 2018 | K14: 2017 - 2026 | L14: 2018 | M14: 2026 | O14: Aser A. Inocencio, Jr. | Q14: Zosimo P. Suyat | R14: 2.February | S14: R3-2026-005457 | T14: 46071 | U14: 46071 | W14: 46072 | X14: 46072 | Y14: =IFERROR( IF( OR(ISBLANK(T14), ISBLANK(U14)), "", MAX( 1, IF( NETWORKDAYS(T14, U14, Holiday_Dates) <= 0, 1, NETWORKDAYS(T14, U14, Holiday_Dates) - IF(T14 = U14, 0, 1) ) ) ), "" ) -> 1 | Z14: =IF( OR(ISBLANK(U14), ISBLANK(V14)), "", MAX( 1, IF( NETWORKDAYS(U14, V14, Holiday_Dates) <= 0, 1, NETWORKDAYS(U14, V14, Holiday_Dates) - IF(U14 = V14, 0, 1) ) ) ) | AA14: =IFERROR( IF( OR(ISBLANK(W14), AND(ISBLANK(U14), ISBLANK(V14))), "", MAX( 1, IF( NETWORKDAYS(IF(NOT(ISBLANK(V14)), V14, U14), W14, Holiday_Dates) <= 0, 1, NETWORKDAYS(IF(NOT(ISBLANK(V14)), V14, U14), W14, Holiday_Dates) - IF(IF(NOT(ISBLANK(V14)), V14, U14) = W14, 0, 1) ) ) ), "" ) -> 1 | AB14: =IFERROR( IF( OR(ISBLANK(W14), ISBLANK(X14)), "", MAX( 1, IF( NETWORKDAYS(W14, X14, Holiday_Dates) <= 0, 1, NETWORKDAYS(W14, X14, Holiday_Dates) - IF(W14 = X14, 0, 1) ) ) ), "" ) -> 1 | AC14: Marshalle Julluice V. Catua | AD14: 0.605 | AE14: 28913.11 | AF14: 85.52 | AG14: Metro Waste Solid Waste Management Corporation | AH14: Compliant | AI14: YES | AJ14: YES | AK14: YES | AL14: YES | AM14: YES | AN14: YES | AR14: 17920.35 | AS14: 0.6198 | AT14: 5195.69 | AU14: 0.1797 | AV14: 1610.46 | AW14: 0.0557 | AX14: 3619.92 | AY14: 0.1252 | AZ14: 556.7 | BA14: 0.0196 | BB14: =SUM(AS14,AU14,AW14) -> 0.8552 | BC14: =SUM(AS14,AU14,AW14) -> 0.8552 | BD14: https://embco-my.sharepoint.com/:w:/g/personal/eswmr3_emb_gov_ph/IQCwaDpqubn3TYH_bx42jlxwAVkivze19aAPwXpraCl-68g?e=uTdsI3
A15: Nueva Ecija | B15: San Antonio_N | C15: =CONCATENATE(A15,","," ",B15) -> Nueva Ecija, San Antonio_N | D15: MBA | E15: 4th | F15: 15.306809 | G15: 120.85671 | H15: =CONCATENATE(F15,",",G15) -> 15.306809,120.856712 | I15: Municipal / City Plan | J15: NSWMC RESO NO. 1490 SERIES OF 2021 | K15: 2020 - 2029 | L15: 2021 | M15: 2029 | O15: Christine Ann V. Ramos | Q15: Zosimo P. Suyat | R15: 2.February | S15: R3-2026-004721 | T15: 46065 | U15: 46066 | W15: 46071 | X15: 46071 | Y15: =IFERROR( IF( OR(ISBLANK(T15), ISBLANK(U15)), "", MAX( 1, IF( NETWORKDAYS(T15, U15, Holiday_Dates) <= 0, 1, NETWORKDAYS(T15, U15, Holiday_Dates) - IF(T15 = U15, 0, 1) ) ) ), "" ) -> 1 | Z15: =IF( OR(ISBLANK(U15), ISBLANK(V15)), "", MAX( 1, IF( NETWORKDAYS(U15, V15, Holiday_Dates) <= 0, 1, NETWORKDAYS(U15, V15, Holiday_Dates) - IF(U15 = V15, 0, 1) ) ) ) | AA15: =IFERROR( IF( OR(ISBLANK(W15), AND(ISBLANK(U15), ISBLANK(V15))), "", MAX( 1, IF( NETWORKDAYS(IF(NOT(ISBLANK(V15)), V15, U15), W15, Holiday_Dates) <= 0, 1, NETWORKDAYS(IF(NOT(ISBLANK(V15)), V15, U15), W15, Holiday_Dates) - IF(IF(NOT(ISBLANK(V15)), V15, U15) = W15, 0, 1) ) ) ), "" ) -> 3 | AB15: =IFERROR( IF( OR(ISBLANK(W15), ISBLANK(X15)), "", MAX( 1, IF( NETWORKDAYS(W15, X15, Holiday_Dates) <= 0, 1, NETWORKDAYS(W15, X15, Holiday_Dates) - IF(W15 = X15, 0, 1) ) ) ), "" ) -> 1 | AC15: Marshalle Julluice V. Catua | AD15: 0.629 | AE15: 54017.28 | AF15: 84.18 | AG15: Urdaneta Waste Management | AH15: Compliant | AI15: YES | AJ15: YES | AK15: YES | AL15: YES | AN15: YES | AR15: 30562.98 | AS15: 0.5658 | AT15: 12180.9 | AU15: 0.2255 | AV15: 2727.87 | AW15: 0.0505 | AX15: 8415.89 | AY15: 0.1558 | AZ15: 129.64 | BA15: 0.24 | BB15: =SUM(AS15,AU15,AW15) -> 0.8418 | BC15: =SUM(AS15,AU15,AW15) -> 0.8418 | BD15: https://embco-my.sharepoint.com/:w:/g/personal/eswmr3_emb_gov_ph/IQDp0hTYADdoS5Hr2gs2pslnATByESpmqmHy-VmQpc7i-Yo?e=oS6hRb
A16: Pampanga | B16: City Of Angeles | C16: =CONCATENATE(A16,","," ",B16) -> Pampanga, City Of Angeles | D16: MBA | E16: 1st | F16: 15.1653 | G16: 120.6084 | H16: =CONCATENATE(F16,",",G16) -> 15.1653,120.6084 | I16: Municipal / City Plan | J16: NSWMC RESO NO. 196 SERIES OF 2015 | K16: 2015 - 2024 | L16: 2015 | M16: 2024 | N16: For Renewal | O16: Elyza A. Evilla | Q16: Sherwin John Y. Loquellano | R16: 2.February | S16: R3-2026-005383 | T16: 46069 | U16: 46071 | W16: 46071 | X16: 46071 | Y16: =IFERROR( IF( OR(ISBLANK(T16), ISBLANK(U16)), "", MAX( 1, IF( NETWORKDAYS(T16, U16, Holiday_Dates) <= 0, 1, NETWORKDAYS(T16, U16, Holiday_Dates) - IF(T16 = U16, 0, 1) ) ) ), "" ) -> 2 | Z16: =IF( OR(ISBLANK(U16), ISBLANK(V16)), "", MAX( 1, IF( NETWORKDAYS(U16, V16, Holiday_Dates) <= 0, 1, NETWORKDAYS(U16, V16, Holiday_Dates) - IF(U16 = V16, 0, 1) ) ) ) | AA16: =IFERROR( IF( OR(ISBLANK(W16), AND(ISBLANK(U16), ISBLANK(V16))), "", MAX( 1, IF( NETWORKDAYS(IF(NOT(ISBLANK(V16)), V16, U16), W16, Holiday_Dates) <= 0, 1, NETWORKDAYS(IF(NOT(ISBLANK(V16)), V16, U16), W16, Holiday_Dates) - IF(IF(NOT(ISBLANK(V16)), V16, U16) = W16, 0, 1) ) ) ), "" ) -> 1 | AB16: =IFERROR( IF( OR(ISBLANK(W16), ISBLANK(X16)), "", MAX( 1, IF( NETWORKDAYS(W16, X16, Holiday_Dates) <= 0, 1, NETWORKDAYS(W16, X16, Holiday_Dates) - IF(W16 = X16, 0, 1) ) ) ), "" ) -> 1 | AC16: Marshalle Julluice V. Catua | AD16: 0.31 | AE16: 456827.24 | AF16: 62.01 | AG16: Eco Protect Management Corp | AH16: Non Compliant | AI16: YES | AJ16: YES | AK16: YES | AM16: YES | AN16: YES | AR16: 154629.9 | AS16: 0.3385 | AT16: 128659.89 | AU16: 0.2816 | AV16: 0 | AW16: 0 | AX16: 167568.18 | AY16: 0.3668 | AZ16: 5969.29 | BA16: 0.0131 | BB16: =SUM(AS16,AU16,AW16) -> 0.6201 | BC16: =SUM(AS16,AU16,AW16) -> 0.6201 | BD16: https://embco-my.sharepoint.com/:w:/g/personal/eswmr3_emb_gov_ph/IQCOPFe6Yq9yQq33emuhsx8bAXsrfWBFLLqp4Xok8WBmUNk?e=SqsoGj
A17: Pampanga | B17: Masantol | C17: =CONCATENATE(A17,","," ",B17) -> Pampanga, Masantol | D17: MBA | E17: 4th | F17: 14.8925 | G17: 120.7053 | H17: =CONCATENATE(F17,",",G17) -> 14.8925,120.7053 | I17: Municipal / City Plan | J17: 1028-A series of 2019 | K17: 2014 - 2024 | L17: 2019 | M17: 2024 | N17: For Renewal | O17: Glaiza S.Gaza | Q17: Sherwin John Y. Loquellano | R17: 2.February | S17: R3-2026-005179 | T17: 46069 | U17: 46069 | W17: 46071 | X17: 46071 | Y17: =IFERROR( IF( OR(ISBLANK(T17), ISBLANK(U17)), "", MAX( 1, IF( NETWORKDAYS(T17, U17, Holiday_Dates) <= 0, 1, NETWORKDAYS(T17, U17, Holiday_Dates) - IF(T17 = U17, 0, 1) ) ) ), "" ) -> 1 | Z17: =IF( OR(ISBLANK(U17), ISBLANK(V17)), "", MAX( 1, IF( NETWORKDAYS(U17, V17, Holiday_Dates) <= 0, 1, NETWORKDAYS(U17, V17, Holiday_Dates) - IF(U17 = V17, 0, 1) ) ) ) | AA17: =IFERROR( IF( OR(ISBLANK(W17), AND(ISBLANK(U17), ISBLANK(V17))), "", MAX( 1, IF( NETWORKDAYS(IF(NOT(ISBLANK(V17)), V17, U17), W17, Holiday_Dates) <= 0, 1, NETWORKDAYS(IF(NOT(ISBLANK(V17)), V17, U17), W17, Holiday_Dates) - IF(IF(NOT(ISBLANK(V17)), V17, U17) = W17, 0, 1) ) ) ), "" ) -> 2 | AB17: =IFERROR( IF( OR(ISBLANK(W17), ISBLANK(X17)), "", MAX( 1, IF( NETWORKDAYS(W17, X17, Holiday_Dates) <= 0, 1, NETWORKDAYS(W17, X17, Holiday_Dates) - IF(W17 = X17, 0, 1) ) ) ), "" ) -> 1 | AC17: Marshalle Julluice V. Catua | AD17: 0.524 | AE17: 32231.17 | AF17: 69.05 | AG17: Floridablanca Enviro Corp. | AH17: Non Compliant | AI17: NO | AJ17: NO | AK17: NO | AL17: YES | AM17: YES | AN17: YES | AR17: 11163.39 | AS17: 0.3464 | AT17: 11090.75 | AU17: 0.3441 | AV17: 0 | AW17: 0 | AX17: 9200.44 | AY17: 0.2854 | AZ17: 776.59 | BA17: 0.0241 | BB17: =SUM(AS17,AU17,AW17) -> 0.6905 | BC17: =SUM(AS17,AU17,AW17) -> 0.6905 | BD17: https://embco-my.sharepoint.com/:w:/g/personal/eswmr3_emb_gov_ph/IQCCMRVJHkFtTpBAW4auNqw0AeoYIbp0vUlDQI8y7u51Nu0?e=hpwmc6
A18: Tarlac | B18: La Paz | C18: =CONCATENATE(A18,","," ",B18) -> Tarlac, La Paz | D18: MBA | E18: 3rd | F18: 15.44117 | G18: 120.72953 | H18: =CONCATENATE(F18,",",G18) -> 15.44117,120.729534 | I18: Municipal / City Plan | J18: 141, series of 2015 | K18: 2014 - 2023 | L18: 2015 | M18: 2023 | N18: For Renewal | O18: Gretzhen M. Apolonio | Q18: Jan Emerson C. Gonzales | R18: 2.February | S18: R3-2026-005180 | T18: 46056 | U18: 46069 | W18: 46071 | X18: 46071 | Y18: =IFERROR( IF( OR(ISBLANK(T18), ISBLANK(U18)), "", MAX( 1, IF( NETWORKDAYS(T18, U18, Holiday_Dates) <= 0, 1, NETWORKDAYS(T18, U18, Holiday_Dates) - IF(T18 = U18, 0, 1) ) ) ), "" ) -> 9 | Z18: =IF( OR(ISBLANK(U18), ISBLANK(V18)), "", MAX( 1, IF( NETWORKDAYS(U18, V18, Holiday_Dates) <= 0, 1, NETWORKDAYS(U18, V18, Holiday_Dates) - IF(U18 = V18, 0, 1) ) ) ) | AA18: =IFERROR( IF( OR(ISBLANK(W18), AND(ISBLANK(U18), ISBLANK(V18))), "", MAX( 1, IF( NETWORKDAYS(IF(NOT(ISBLANK(V18)), V18, U18), W18, Holiday_Dates) <= 0, 1, NETWORKDAYS(IF(NOT(ISBLANK(V18)), V18, U18), W18, Holiday_Dates) - IF(IF(NOT(ISBLANK(V18)), V18, U18) = W18, 0, 1) ) ) ), "" ) -> 2 | AB18: =IFERROR( IF( OR(ISBLANK(W18), ISBLANK(X18)), "", MAX( 1, IF( NETWORKDAYS(W18, X18, Holiday_Dates) <= 0, 1, NETWORKDAYS(W18, X18, Holiday_Dates) - IF(W18 = X18, 0, 1) ) ) ), "" ) -> 1 | AC18: Marshalle Julluice V. Catua | AD18: 0.33 | AE18: 25689.84 | AF18: 92 | AG18: MAA Integrated Solid Waste Management Corporation | AH18: Compliant | AI18: YES | AJ18: YES | AK18: YES | AL18: YES | AM18: YES | AN18: YES | AR18: 16376.51 | AS18: 0.6375 | AT18: 2761.53 | AU18: 0.1075 | AV18: 0 | AW18: 0 | AX18: 6260.98 | AY18: 0.2437 | AZ18: 290.82 | BA18: 0.0113 | BB18: =SUM(AS18,AU18,AW18) -> 0.745 | BC18: =SUM(AS18,AU18,AW18) -> 0.745 | BD18: https://embco-my.sharepoint.com/:w:/g/personal/eswmr3_emb_gov_ph/IQC2wZmNbmAaQLYiw7lc9fm5AR_UaEKllCj6-Vb4kUh389w?e=zQb5xZ
A19: Tarlac | B19: Moncada | C19: =CONCATENATE(A19,","," ",B19) -> Tarlac, Moncada | D19: OUTSIDE MBA | E19: 1st | F19: 15.733045 | G19: 120.5727 | H19: =CONCATENATE(F19,",",G19) -> 15.7330446,120.5727025 | I19: Municipal / City Plan | J19: NSWMC Resolution No. 237-A | K19: 2025 - 2034 | L19: 2025 | M19: 2034 | N19: Approved | O19: Joshua A. Capones | Q19: Jan Emerson C. Gonzales | R19: 2.February | S19: R3-2026-003829 | T19: 46057 | U19: 46059 | W19: 46069 | X19: 46069 | Y19: =IFERROR( IF( OR(ISBLANK(T19), ISBLANK(U19)), "", MAX( 1, IF( NETWORKDAYS(T19, U19, Holiday_Dates) <= 0, 1, NETWORKDAYS(T19, U19, Holiday_Dates) - IF(T19 = U19, 0, 1) ) ) ), "" ) -> 2 | Z19: =IF( OR(ISBLANK(U19), ISBLANK(V19)), "", MAX( 1, IF( NETWORKDAYS(U19, V19, Holiday_Dates) <= 0, 1, NETWORKDAYS(U19, V19, Holiday_Dates) - IF(U19 = V19, 0, 1) ) ) ) | AA19: =IFERROR( IF( OR(ISBLANK(W19), AND(ISBLANK(U19), ISBLANK(V19))), "", MAX( 1, IF( NETWORKDAYS(IF(NOT(ISBLANK(V19)), V19, U19), W19, Holiday_Dates) <= 0, 1, NETWORKDAYS(IF(NOT(ISBLANK(V19)), V19, U19), W19, Holiday_Dates) - IF(IF(NOT(ISBLANK(V19)), V19, U19) = W19, 0, 1) ) ) ), "" ) -> 6 | AB19: =IFERROR( IF( OR(ISBLANK(W19), ISBLANK(X19)), "", MAX( 1, IF( NETWORKDAYS(W19, X19, Holiday_Dates) <= 0, 1, NETWORKDAYS(W19, X19, Holiday_Dates) - IF(W19 = X19, 0, 1) ) ) ), "" ) -> 1 | AC19: Marshalle Julluice V. Catua | AD19: 0.72 | AE19: 50250.96 | AF19: 74.5 | AG19: MAA Integrated Solid Waste Management Corporation | AH19: Compliant | AI19: YES | AJ19: YES | AK19: YES | AL19: YES | AN19: YES | AR19: 23808.9 | AS19: 0.4738 | AT19: 13025.25 | AU19: 0.2592 | AV19: 351.76 | AW19: 0.007 | AX19: 6260.98 | AY19: 0.2437 | AZ19: 462.31 | BA19: 0.0288 | BB19: =SUM(AS19,AU19,AW19) -> 0.74 | BC19: =SUM(AS19,AU19,AW19) -> 0.74 | BD19: https://embco-my.sharepoint.com/:w:/g/personal/eswmr3_emb_gov_ph/IQDbaHxfL6VJR4M9sCxscKgRAQPjPXK81XVQK8jD1sItViE?e=DMh4KK
A20: Zambales | B20: Botolan | C20: =CONCATENATE(A20,","," ",B20) -> Zambales, Botolan | D20: OUTSIDE MBA | E20: 2nd | F20: 15.288611 | G20: 120.02333 | H20: =CONCATENATE(F20,",",G20) -> 15.288611,120.023333 | I20: Municipal / City Plan | J20: No. 1415 Series of 2020 | K20: 2019 - 2029 | L20: 2020 | M20: 2029 | O20: Larizze A. Santos | Q20: Jun D. Guillermo | R20: 2.February | S20: R3-2026-005273 | T20: 46069 | U20: 46071 | W20: 46071 | X20: 46071 | Y20: =IFERROR( IF( OR(ISBLANK(T20), ISBLANK(U20)), "", MAX( 1, IF( NETWORKDAYS(T20, U20, Holiday_Dates) <= 0, 1, NETWORKDAYS(T20, U20, Holiday_Dates) - IF(T20 = U20, 0, 1) ) ) ), "" ) -> 2 | Z20: =IF( OR(ISBLANK(U20), ISBLANK(V20)), "", MAX( 1, IF( NETWORKDAYS(U20, V20, Holiday_Dates) <= 0, 1, NETWORKDAYS(U20, V20, Holiday_Dates) - IF(U20 = V20, 0, 1) ) ) ) | AA20: =IFERROR( IF( OR(ISBLANK(W20), AND(ISBLANK(U20), ISBLANK(V20))), "", MAX( 1, IF( NETWORKDAYS(IF(NOT(ISBLANK(V20)), V20, U20), W20, Holiday_Dates) <= 0, 1, NETWORKDAYS(IF(NOT(ISBLANK(V20)), V20, U20), W20, Holiday_Dates) - IF(IF(NOT(ISBLANK(V20)), V20, U20) = W20, 0, 1) ) ) ), "" ) -> 1 | AB20: =IFERROR( IF( OR(ISBLANK(W20), ISBLANK(X20)), "", MAX( 1, IF( NETWORKDAYS(W20, X20, Holiday_Dates) <= 0, 1, NETWORKDAYS(W20, X20, Holiday_Dates) - IF(W20 = X20, 0, 1) ) ) ), "" ) -> 1 | AC20: Marshalle Julluice V. Catua | AD20: 0.499 | AE20: 36921.51 | AF20: 0.68 | AG20: Greentech Total Environmental Solutions Incorporated | AH20: Compliant | AI20: YES | AJ20: YES | AK20: YES | AL20: YES | AM20: YES | AN20: YES | AR20: 22614.77 | AS20: 0.6125 | AT20: 2491.86 | AU20: 0.0675 | AX20: 10974.55 | AY20: 0.2972 | AZ20: 840.33 | BA20: 0.0228 | BB20: =SUM(AS20,AU20,AW20) -> 0.68 | BC20: =SUM(AS20,AU20,AW20) -> 0.68 | BD20: https://embco-my.sharepoint.com/:w:/g/personal/eswmr3_emb_gov_ph/IQAACyXLumaqTYjQ7zLIUiv6AZWa4r6suKpCoYEUceqSB7U?e=QgYsgA
A21: Aurora | B21: Casiguran | C21: =CONCATENATE(A21,","," ",B21) -> Aurora, Casiguran | D21: OUTSIDE MBA | E21: Lone | F21: 16.277169 | G21: 122.12314 | H21: =CONCATENATE(F21,",",G21) -> 16.277169,122.123139 | I21: Municipal / City Plan | J21: 1289 | K21: 2017 - 2027 | L21: 2019 | M21: 2027 | O21: Queenyvel Laguisma | Q21: Diozelle L. Cabalar | R21: 3.March | Y21: =IFERROR( IF( OR(ISBLANK(T21), ISBLANK(U21)), "", MAX( 1, IF( NETWORKDAYS(T21, U21, Holiday_Dates) <= 0, 1, NETWORKDAYS(T21, U21, Holiday_Dates) - IF(T21 = U21, 0, 1) ) ) ), "" ) | Z21: =IF( OR(ISBLANK(U21), ISBLANK(V21)), "", MAX( 1, IF( NETWORKDAYS(U21, V21, Holiday_Dates) <= 0, 1, NETWORKDAYS(U21, V21, Holiday_Dates) - IF(U21 = V21, 0, 1) ) ) ) | AA21: =IFERROR( IF( OR(ISBLANK(W21), AND(ISBLANK(U21), ISBLANK(V21))), "", MAX( 1, IF( NETWORKDAYS(IF(NOT(ISBLANK(V21)), V21, U21), W21, Holiday_Dates) <= 0, 1, NETWORKDAYS(IF(NOT(ISBLANK(V21)), V21, U21), W21, Holiday_Dates) - IF(IF(NOT(ISBLANK(V21)), V21, U21) = W21, 0, 1) ) ) ), "" ) | AB21: =IFERROR( IF( OR(ISBLANK(W21), ISBLANK(X21)), "", MAX( 1, IF( NETWORKDAYS(W21, X21, Holiday_Dates) <= 0, 1, NETWORKDAYS(W21, X21, Holiday_Dates) - IF(W21 = X21, 0, 1) ) ) ), "" ) | BB21: =SUM(AS21,AU21,AW21) -> 0 | BC21: =SUM(AS21,AU21,AW21) -> 0
A22: Bataan | B22: Mariveles | C22: =CONCATENATE(A22,","," ",B22) -> Bataan, Mariveles | D22: MBA | E22: 3rd | F22: 14.435804 | G22: 120.49021 | H22: =CONCATENATE(F22,",",G22) -> 14.435804,120.490214 | I22: Municipal / City Plan | J22: 483 SERIES 2016 | K22: 2016 - 2025 | L22: 2016 | M22: 2025 | N22: For Renewal | O22: Laurence Radasa | Q22: Christle D. David | R22: 3.March | S22: R3-2026-006188 | T22: 46077 | U22: 46078 | W22: 46078 | X22: 46079 | Y22: =IFERROR( IF( OR(ISBLANK(T22), ISBLANK(U22)), "", MAX( 1, IF( NETWORKDAYS(T22, U22, Holiday_Dates) <= 0, 1, NETWORKDAYS(T22, U22, Holiday_Dates) - IF(T22 = U22, 0, 1) ) ) ), "" ) -> 1 | Z22: =IF( OR(ISBLANK(U22), ISBLANK(V22)), "", MAX( 1, IF( NETWORKDAYS(U22, V22, Holiday_Dates) <= 0, 1, NETWORKDAYS(U22, V22, Holiday_Dates) - IF(U22 = V22, 0, 1) ) ) ) | AA22: =IFERROR( IF( OR(ISBLANK(W22), AND(ISBLANK(U22), ISBLANK(V22))), "", MAX( 1, IF( NETWORKDAYS(IF(NOT(ISBLANK(V22)), V22, U22), W22, Holiday_Dates) <= 0, 1, NETWORKDAYS(IF(NOT(ISBLANK(V22)), V22, U22), W22, Holiday_Dates) - IF(IF(NOT(ISBLANK(V22)), V22, U22) = W22, 0, 1) ) ) ), "" ) -> 1 | AB22: =IFERROR( IF( OR(ISBLANK(W22), ISBLANK(X22)), "", MAX( 1, IF( NETWORKDAYS(W22, X22, Holiday_Dates) <= 0, 1, NETWORKDAYS(W22, X22, Holiday_Dates) - IF(W22 = X22, 0, 1) ) ) ), "" ) -> 1 | AC22: Marshalle Julluice V. Catua | AD22: 0.201 | AE22: 31392.2 | AF22: 0.9147 | AG22: Floridablanca Enviro Corporation | AH22: Compliant | AI22: YES | AJ22: YES | AK22: YES | AL22: YES | AM22: YES | AN22: YES | AR22: 6765.02 | AS22: 0.2155 | AT22: 4715.11 | AU22: 0.1502 | AV22: 17234.32 | AW22: 0.5409 | AX22: 1563.33 | AY22: 0.0498 | AZ22: 1114.42 | BA22: 0.0355 | BB22: =SUM(AS22,AU22,AW22) -> 0.9066 | BC22: =SUM(AS22,AU22,AW22) -> 0.9066
A23: Bulacan | B23: City Of San Jose Del Monte | C23: =CONCATENATE(A23,","," ",B23) -> Bulacan, City Of San Jose Del Monte | D23: MBA | E23: Lone | F23: 14.810227 | G23: 121.0477 | H23: =CONCATENATE(F23,",",G23) -> 14.810227,121.047703 | I23: Municipal / City Plan | J23: 197 Series of 2015 | K23: 2015 - 2024 | L23: 2015 | M23: 2024 | N23: For Renewal | O23: James Wilson T. Pena | Q23: Diozelle L. Cabalar | R23: 3.March | Y23: =IFERROR( IF( OR(ISBLANK(T23), ISBLANK(U23)), "", MAX( 1, IF( NETWORKDAYS(T23, U23, Holiday_Dates) <= 0, 1, NETWORKDAYS(T23, U23, Holiday_Dates) - IF(T23 = U23, 0, 1) ) ) ), "" ) | Z23: =IF( OR(ISBLANK(U23), ISBLANK(V23)), "", MAX( 1, IF( NETWORKDAYS(U23, V23, Holiday_Dates) <= 0, 1, NETWORKDAYS(U23, V23, Holiday_Dates) - IF(U23 = V23, 0, 1) ) ) ) | AA23: =IFERROR( IF( OR(ISBLANK(W23), AND(ISBLANK(U23), ISBLANK(V23))), "", MAX( 1, IF( NETWORKDAYS(IF(NOT(ISBLANK(V23)), V23, U23), W23, Holiday_Dates) <= 0, 1, NETWORKDAYS(IF(NOT(ISBLANK(V23)), V23, U23), W23, Holiday_Dates) - IF(IF(NOT(ISBLANK(V23)), V23, U23) = W23, 0, 1) ) ) ), "" ) | AB23: =IFERROR( IF( OR(ISBLANK(W23), ISBLANK(X23)), "", MAX( 1, IF( NETWORKDAYS(W23, X23, Holiday_Dates) <= 0, 1, NETWORKDAYS(W23, X23, Holiday_Dates) - IF(W23 = X23, 0, 1) ) ) ), "" ) | BB23: =SUM(AR23,AT23,AV23) -> 0 | BC23: =SUM(AS23,AU23,AW23) -> 0
A24: Bulacan | B24: Hagonoy | C24: =CONCATENATE(A24,","," ",B24) -> Bulacan, Hagonoy | D24: MBA | E24: 1st | F24: 14.836099 | G24: 120.7341 | H24: =CONCATENATE(F24,",",G24) -> 14.836099,120.734098 | I24: Municipal / City Plan | J24: 499A | K24: 2016 - 2025 | L24: 2018 | M24: 2025 | N24: For Renewal | O24: Ronaldo P. Roque, Jr. | Q24: Diozelle L. Cabalar | R24: 3.March | Y24: =IFERROR( IF( OR(ISBLANK(T24), ISBLANK(U24)), "", MAX( 1, IF( NETWORKDAYS(T24, U24, Holiday_Dates) <= 0, 1, NETWORKDAYS(T24, U24, Holiday_Dates) - IF(T24 = U24, 0, 1) ) ) ), "" ) | Z24: =IF( OR(ISBLANK(U24), ISBLANK(V24)), "", MAX( 1, IF( NETWORKDAYS(U24, V24, Holiday_Dates) <= 0, 1, NETWORKDAYS(U24, V24, Holiday_Dates) - IF(U24 = V24, 0, 1) ) ) ) | AA24: =IFERROR( IF( OR(ISBLANK(W24), AND(ISBLANK(U24), ISBLANK(V24))), "", MAX( 1, IF( NETWORKDAYS(IF(NOT(ISBLANK(V24)), V24, U24), W24, Holiday_Dates) <= 0, 1, NETWORKDAYS(IF(NOT(ISBLANK(V24)), V24, U24), W24, Holiday_Dates) - IF(IF(NOT(ISBLANK(V24)), V24, U24) = W24, 0, 1) ) ) ), "" ) | AB24: =IFERROR( IF( OR(ISBLANK(W24), ISBLANK(X24)), "", MAX( 1, IF( NETWORKDAYS(W24, X24, Holiday_Dates) <= 0, 1, NETWORKDAYS(W24, X24, Holiday_Dates) - IF(W24 = X24, 0, 1) ) ) ), "" ) | BB24: =SUM(AR24,AT24,AV24) -> 0 | BC24: =SUM(AS24,AU24,AW24) -> 0
A25: Nueva Ecija | B25: Jaen | C25: =CONCATENATE(A25,","," ",B25) -> Nueva Ecija, Jaen | D25: MBA | E25: 4th | F25: 15.33763 | G25: 120.90542 | H25: =CONCATENATE(F25,",",G25) -> 15.33763,120.905423 | I25: Municipal / City Plan | J25: 760 Series of 2016 | K25: 2016 - 2025 | L25: 2016 | M25: 2025 | N25: For Renewal | O25: Christine Ann V. Ramos | Q25: Zosimo P. Suyat | R25: 3.March | Y25: =IFERROR( IF( OR(ISBLANK(T25), ISBLANK(U25)), "", MAX( 1, IF( NETWORKDAYS(T25, U25, Holiday_Dates) <= 0, 1, NETWORKDAYS(T25, U25, Holiday_Dates) - IF(T25 = U25, 0, 1) ) ) ), "" ) | Z25: =IF( OR(ISBLANK(U25), ISBLANK(V25)), "", MAX( 1, IF( NETWORKDAYS(U25, V25, Holiday_Dates) <= 0, 1, NETWORKDAYS(U25, V25, Holiday_Dates) - IF(U25 = V25, 0, 1) ) ) ) | AA25: =IFERROR( IF( OR(ISBLANK(W25), AND(ISBLANK(U25), ISBLANK(V25))), "", MAX( 1, IF( NETWORKDAYS(IF(NOT(ISBLANK(V25)), V25, U25), W25, Holiday_Dates) <= 0, 1, NETWORKDAYS(IF(NOT(ISBLANK(V25)), V25, U25), W25, Holiday_Dates) - IF(IF(NOT(ISBLANK(V25)), V25, U25) = W25, 0, 1) ) ) ), "" ) | AB25: =IFERROR( IF( OR(ISBLANK(W25), ISBLANK(X25)), "", MAX( 1, IF( NETWORKDAYS(W25, X25, Holiday_Dates) <= 0, 1, NETWORKDAYS(W25, X25, Holiday_Dates) - IF(W25 = X25, 0, 1) ) ) ), "" ) | BB25: =SUM(AR25,AT25,AV25) -> 0 | BC25: =SUM(AS25,AU25,AW25) -> 0
A26: Nueva Ecija | B26: Laur | C26: =CONCATENATE(A26,","," ",B26) -> Nueva Ecija, Laur | D26: MBA | E26: 3rd | F26: 15.571914 | G26: 121.16846 | H26: =CONCATENATE(F26,",",G26) -> 15.571914,121.168456 | I26: Municipal / City Plan | J26: 195 | K26: 2016 - 2025 | L26: 2015 | M26: 2025 | N26: For Renewal | O26: Christian Jem L. Buluran | Q26: Zosimo P. Suyat | R26: 3.March | Y26: =IFERROR( IF( OR(ISBLANK(T26), ISBLANK(U26)), "", MAX( 1, IF( NETWORKDAYS(T26, U26, Holiday_Dates) <= 0, 1, NETWORKDAYS(T26, U26, Holiday_Dates) - IF(T26 = U26, 0, 1) ) ) ), "" ) | Z26: =IF( OR(ISBLANK(U26), ISBLANK(V26)), "", MAX( 1, IF( NETWORKDAYS(U26, V26, Holiday_Dates) <= 0, 1, NETWORKDAYS(U26, V26, Holiday_Dates) - IF(U26 = V26, 0, 1) ) ) ) | AA26: =IFERROR( IF( OR(ISBLANK(W26), AND(ISBLANK(U26), ISBLANK(V26))), "", MAX( 1, IF( NETWORKDAYS(IF(NOT(ISBLANK(V26)), V26, U26), W26, Holiday_Dates) <= 0, 1, NETWORKDAYS(IF(NOT(ISBLANK(V26)), V26, U26), W26, Holiday_Dates) - IF(IF(NOT(ISBLANK(V26)), V26, U26) = W26, 0, 1) ) ) ), "" ) | AB26: =IFERROR( IF( OR(ISBLANK(W26), ISBLANK(X26)), "", MAX( 1, IF( NETWORKDAYS(W26, X26, Holiday_Dates) <= 0, 1, NETWORKDAYS(W26, X26, Holiday_Dates) - IF(W26 = X26, 0, 1) ) ) ), "" ) | BB26: =SUM(AR26,AT26,AV26) -> 0 | BC26: =SUM(AS26,AU26,AW26) -> 0
A27: Nueva Ecija | B27: Peñaranda | C27: =CONCATENATE(A27,","," ",B27) -> Nueva Ecija, Peñaranda | D27: MBA | E27: 4th | F27: 15.36518 | G27: 121.01418 | H27: =CONCATENATE(F27,",",G27) -> 15.36518,121.014179 | I27: Municipal / City Plan | J27: 1357, Series of 2019 | K27: 2017 - 2027 | L27: 2019 | M27: 2027 | O27: Christine Ann V. Ramos | Q27: Zosimo P. Suyat | R27: 3.March | S27: R3-2026-007119 | Y27: =IFERROR( IF( OR(ISBLANK(T27), ISBLANK(U27)), "", MAX( 1, IF( NETWORKDAYS(T27, U27, Holiday_Dates) <= 0, 1, NETWORKDAYS(T27, U27, Holiday_Dates) - IF(T27 = U27, 0, 1) ) ) ), "" ) | Z27: =IF( OR(ISBLANK(U27), ISBLANK(V27)), "", MAX( 1, IF( NETWORKDAYS(U27, V27, Holiday_Dates) <= 0, 1, NETWORKDAYS(U27, V27, Holiday_Dates) - IF(U27 = V27, 0, 1) ) ) ) | AA27: =IFERROR( IF( OR(ISBLANK(W27), AND(ISBLANK(U27), ISBLANK(V27))), "", MAX( 1, IF( NETWORKDAYS(IF(NOT(ISBLANK(V27)), V27, U27), W27, Holiday_Dates) <= 0, 1, NETWORKDAYS(IF(NOT(ISBLANK(V27)), V27, U27), W27, Holiday_Dates) - IF(IF(NOT(ISBLANK(V27)), V27, U27) = W27, 0, 1) ) ) ), "" ) | AB27: =IFERROR( IF( OR(ISBLANK(W27), ISBLANK(X27)), "", MAX( 1, IF( NETWORKDAYS(W27, X27, Holiday_Dates) <= 0, 1, NETWORKDAYS(W27, X27, Holiday_Dates) - IF(W27 = X27, 0, 1) ) ) ), "" ) | BB27: =SUM(AR27,AT27,AV27) -> 0 | BC27: =SUM(AS27,AU27,AW27) -> 0
A28: Pampanga | B28: Apalit | C28: =CONCATENATE(A28,","," ",B28) -> Pampanga, Apalit | D28: MBA | E28: 4th | F28: 14.9536 | G28: 120.7685 | H28: =CONCATENATE(F28,",",G28) -> 14.9536,120.7685 | I28: Municipal / City Plan | J28: 1241 | K28: 2017 - 2027 | L28: 2019 | M28: 2027 | O28: Glaiza S.Gaza | Q28: Sherwin John Y. Loquellano | R28: 3.March | Y28: =IFERROR( IF( OR(ISBLANK(T28), ISBLANK(U28)), "", MAX( 1, IF( NETWORKDAYS(T28, U28, Holiday_Dates) <= 0, 1, NETWORKDAYS(T28, U28, Holiday_Dates) - IF(T28 = U28, 0, 1) ) ) ), "" ) | Z28: =IF( OR(ISBLANK(U28), ISBLANK(V28)), "", MAX( 1, IF( NETWORKDAYS(U28, V28, Holiday_Dates) <= 0, 1, NETWORKDAYS(U28, V28, Holiday_Dates) - IF(U28 = V28, 0, 1) ) ) ) | AA28: =IFERROR( IF( OR(ISBLANK(W28), AND(ISBLANK(U28), ISBLANK(V28))), "", MAX( 1, IF( NETWORKDAYS(IF(NOT(ISBLANK(V28)), V28, U28), W28, Holiday_Dates) <= 0, 1, NETWORKDAYS(IF(NOT(ISBLANK(V28)), V28, U28), W28, Holiday_Dates) - IF(IF(NOT(ISBLANK(V28)), V28, U28) = W28, 0, 1) ) ) ), "" ) | AB28: =IFERROR( IF( OR(ISBLANK(W28), ISBLANK(X28)), "", MAX( 1, IF( NETWORKDAYS(W28, X28, Holiday_Dates) <= 0, 1, NETWORKDAYS(W28, X28, Holiday_Dates) - IF(W28 = X28, 0, 1) ) ) ), "" ) | BB28: =SUM(AR28,AT28,AV28) -> 0 | BC28: =SUM(AS28,AU28,AW28) -> 0
A29: Pampanga | B29: Candaba | C29: =CONCATENATE(A29,","," ",B29) -> Pampanga, Candaba | D29: MBA | E29: 4th | F29: 15.092935 | G29: 120.82806 | H29: =CONCATENATE(F29,",",G29) -> 15.092935,120.828063 | I29: Municipal / City Plan | J29: 240 series of 2015 | K29: 2015 - 2024 | L29: 2015 | M29: 2024 | N29: For Renewal | O29: Roger T. Encarnacion II | Q29: Jun D. Guillermo | R29: 3.March | Y29: =IFERROR( IF( OR(ISBLANK(T29), ISBLANK(U29)), "", MAX( 1, IF( NETWORKDAYS(T29, U29, Holiday_Dates) <= 0, 1, NETWORKDAYS(T29, U29, Holiday_Dates) - IF(T29 = U29, 0, 1) ) ) ), "" ) | Z29: =IF( OR(ISBLANK(U29), ISBLANK(V29)), "", MAX( 1, IF( NETWORKDAYS(U29, V29, Holiday_Dates) <= 0, 1, NETWORKDAYS(U29, V29, Holiday_Dates) - IF(U29 = V29, 0, 1) ) ) ) | AA29: =IFERROR( IF( OR(ISBLANK(W29), AND(ISBLANK(U29), ISBLANK(V29))), "", MAX( 1, IF( NETWORKDAYS(IF(NOT(ISBLANK(V29)), V29, U29), W29, Holiday_Dates) <= 0, 1, NETWORKDAYS(IF(NOT(ISBLANK(V29)), V29, U29), W29, Holiday_Dates) - IF(IF(NOT(ISBLANK(V29)), V29, U29) = W29, 0, 1) ) ) ), "" ) | AB29: =IFERROR( IF( OR(ISBLANK(W29), ISBLANK(X29)), "", MAX( 1, IF( NETWORKDAYS(W29, X29, Holiday_Dates) <= 0, 1, NETWORKDAYS(W29, X29, Holiday_Dates) - IF(W29 = X29, 0, 1) ) ) ), "" ) | BB29: =SUM(AR29,AT29,AV29) -> 0 | BC29: =SUM(AS29,AU29,AW29) -> 0
A30: Pampanga | B30: Guagua | C30: =CONCATENATE(A30,","," ",B30) -> Pampanga, Guagua | D30: MBA | E30: 2nd | F30: 14.965207 | G30: 120.63334 | H30: =CONCATENATE(F30,",",G30) -> 14.965207,120.633338 | I30: Municipal / City Plan | J30: 158 | K30: 2015 - 2024 | L30: 2015 | M30: 2024 | N30: For Renewal | O30: Sebastian Josh V. Manalang | Q30: Jun D. Guillermo | R30: 3.March | Y30: =IFERROR( IF( OR(ISBLANK(T30), ISBLANK(U30)), "", MAX( 1, IF( NETWORKDAYS(T30, U30, Holiday_Dates) <= 0, 1, NETWORKDAYS(T30, U30, Holiday_Dates) - IF(T30 = U30, 0, 1) ) ) ), "" ) | Z30: =IF( OR(ISBLANK(U30), ISBLANK(V30)), "", MAX( 1, IF( NETWORKDAYS(U30, V30, Holiday_Dates) <= 0, 1, NETWORKDAYS(U30, V30, Holiday_Dates) - IF(U30 = V30, 0, 1) ) ) ) | AA30: =IFERROR( IF( OR(ISBLANK(W30), AND(ISBLANK(U30), ISBLANK(V30))), "", MAX( 1, IF( NETWORKDAYS(IF(NOT(ISBLANK(V30)), V30, U30), W30, Holiday_Dates) <= 0, 1, NETWORKDAYS(IF(NOT(ISBLANK(V30)), V30, U30), W30, Holiday_Dates) - IF(IF(NOT(ISBLANK(V30)), V30, U30) = W30, 0, 1) ) ) ), "" ) | AB30: =IFERROR( IF( OR(ISBLANK(W30), ISBLANK(X30)), "", MAX( 1, IF( NETWORKDAYS(W30, X30, Holiday_Dates) <= 0, 1, NETWORKDAYS(W30, X30, Holiday_Dates) - IF(W30 = X30, 0, 1) ) ) ), "" ) | BB30: =SUM(AR30,AT30,AV30) -> 0 | BC30: =SUM(AS30,AU30,AW30) -> 0
A31: Zambales | B31: San Marcelino | C31: =CONCATENATE(A31,","," ",B31) -> Zambales, San Marcelino | D31: OUTSIDE MBA | E31: 1st | F31: 14.974092 | G31: 120.15555 | H31: =CONCATENATE(F31,",",G31) -> 14.974092,120.155547 | I31: Municipal / City Plan | J31: 1253 | K31: 2017 - 2027 | L31: 2019 | M31: 2027 | O31: Ryan Ace R. Angel | Q31: Jun D. Guillermo | R31: 3.March | S31: R3-2026-008553 | T31: 46085 | U31: 46094 | W31: 46097 | Y31: =IFERROR( IF( OR(ISBLANK(T31), ISBLANK(U31)), "", MAX( 1, IF( NETWORKDAYS(T31, U31, Holiday_Dates) <= 0, 1, NETWORKDAYS(T31, U31, Holiday_Dates) - IF(T31 = U31, 0, 1) ) ) ), "" ) -> 7 | Z31: =IF( OR(ISBLANK(U31), ISBLANK(V31)), "", MAX( 1, IF( NETWORKDAYS(U31, V31, Holiday_Dates) <= 0, 1, NETWORKDAYS(U31, V31, Holiday_Dates) - IF(U31 = V31, 0, 1) ) ) ) | AA31: =IFERROR( IF( OR(ISBLANK(W31), AND(ISBLANK(U31), ISBLANK(V31))), "", MAX( 1, IF( NETWORKDAYS(IF(NOT(ISBLANK(V31)), V31, U31), W31, Holiday_Dates) <= 0, 1, NETWORKDAYS(IF(NOT(ISBLANK(V31)), V31, U31), W31, Holiday_Dates) - IF(IF(NOT(ISBLANK(V31)), V31, U31) = W31, 0, 1) ) ) ), "" ) -> 1 | AB31: =IFERROR( IF( OR(ISBLANK(W31), ISBLANK(X31)), "", MAX( 1, IF( NETWORKDAYS(W31, X31, Holiday_Dates) <= 0, 1, NETWORKDAYS(W31, X31, Holiday_Dates) - IF(W31 = X31, 0, 1) ) ) ), "" ) | BB31: =SUM(AR31,AT31,AV31) -> 0 | BC31: =SUM(AS31,AU31,AW31) -> 0
A32: Tarlac | B32: San Manuel | C32: =CONCATENATE(A32,","," ",B32) -> Tarlac, San Manuel | D32: OUTSIDE MBA | E32: 1st | F32: 15.799371 | G32: 120.60732 | H32: =CONCATENATE(F32,",",G32) -> 15.7993705,120.6073187 | I32: Municipal / City Plan | J32: Resolution No. 1604, Series of 2023 | K32: 2022 - 2031 | L32: 2023 | M32: 2031 | O32: Jasper Kieht B. Pili | Q32: Jan Emerson C. Gonzales | R32: 3.March | Y32: =IFERROR( IF( OR(ISBLANK(T32), ISBLANK(U32)), "", MAX( 1, IF( NETWORKDAYS(T32, U32, Holiday_Dates) <= 0, 1, NETWORKDAYS(T32, U32, Holiday_Dates) - IF(T32 = U32, 0, 1) ) ) ), "" ) | Z32: =IF( OR(ISBLANK(U32), ISBLANK(V32)), "", MAX( 1, IF( NETWORKDAYS(U32, V32, Holiday_Dates) <= 0, 1, NETWORKDAYS(U32, V32, Holiday_Dates) - IF(U32 = V32, 0, 1) ) ) ) | AA32: =IFERROR( IF( OR(ISBLANK(W32), AND(ISBLANK(U32), ISBLANK(V32))), "", MAX( 1, IF( NETWORKDAYS(IF(NOT(ISBLANK(V32)), V32, U32), W32, Holiday_Dates) <= 0, 1, NETWORKDAYS(IF(NOT(ISBLANK(V32)), V32, U32), W32, Holiday_Dates) - IF(IF(NOT(ISBLANK(V32)), V32, U32) = W32, 0, 1) ) ) ), "" ) | AB32: =IFERROR( IF( OR(ISBLANK(W32), ISBLANK(X32)), "", MAX( 1, IF( NETWORKDAYS(W32, X32, Holiday_Dates) <= 0, 1, NETWORKDAYS(W32, X32, Holiday_Dates) - IF(W32 = X32, 0, 1) ) ) ), "" ) | BB32: =SUM(AR32,AT32,AV32) -> 0 | BC32: =SUM(AS32,AU32,AW32) -> 0
A33: Tarlac | B33: Victoria | C33: =CONCATENATE(A33,","," ",B33) -> Tarlac, Victoria | D33: MBA | E33: 2nd | F33: 15.575934 | G33: 120.68148 | H33: =CONCATENATE(F33,",",G33) -> 15.575934,120.681484 | I33: Municipal / City Plan | J33: NSWMC RESO NO. 116 SERIES OF 2015 | K33: 2015 - 2025 | L33: 2015 | M33: 2025 | N33: For Renewal | O33: Gretzhen M. Apolonio | Q33: Jan Emerson C. Gonzales | R33: 3.March | S33: R3-2026-007696 | T33: 46084 | U33: 46089 | W33: 46090 | X33: 46090 | Y33: =IFERROR( IF( OR(ISBLANK(T33), ISBLANK(U33)), "", MAX( 1, IF( NETWORKDAYS(T33, U33, Holiday_Dates) <= 0, 1, NETWORKDAYS(T33, U33, Holiday_Dates) - IF(T33 = U33, 0, 1) ) ) ), "" ) -> 3 | Z33: =IF( OR(ISBLANK(U33), ISBLANK(V33)), "", MAX( 1, IF( NETWORKDAYS(U33, V33, Holiday_Dates) <= 0, 1, NETWORKDAYS(U33, V33, Holiday_Dates) - IF(U33 = V33, 0, 1) ) ) ) | AA33: =IFERROR( IF( OR(ISBLANK(W33), AND(ISBLANK(U33), ISBLANK(V33))), "", MAX( 1, IF( NETWORKDAYS(IF(NOT(ISBLANK(V33)), V33, U33), W33, Holiday_Dates) <= 0, 1, NETWORKDAYS(IF(NOT(ISBLANK(V33)), V33, U33), W33, Holiday_Dates) - IF(IF(NOT(ISBLANK(V33)), V33, U33) = W33, 0, 1) ) ) ), "" ) -> 1 | AB33: =IFERROR( IF( OR(ISBLANK(W33), ISBLANK(X33)), "", MAX( 1, IF( NETWORKDAYS(W33, X33, Holiday_Dates) <= 0, 1, NETWORKDAYS(W33, X33, Holiday_Dates) - IF(W33 = X33, 0, 1) ) ) ), "" ) -> 1 | AD33: 0.36 | AE33: 25159.26 | AF33: 0.6704 | AG33: M.A.A. Integrated Waset Solutions Corp. | AH33: Compliant | AI33: YES | AJ33: YES | AK33: YES | AL33: YES | AM33: YES | AN33: YES | AR33: 11310.48 | AS33: 0.4496 | AT33: 5556.83 | AU33: 0.2209 | AX33: 5440.38 | AY33: 21.62 %, | AZ33: 2852.05 | BB33: =SUM(AR33,AT33,AV33) -> 16867.31 | BC33: =SUM(AS33,AU33,AW33) -> 0.6705
A34: Tarlac | B34: Bamban | C34: =CONCATENATE(A34,","," ",B34) -> Tarlac, Bamban | D34: MBA | E34: 3rd | F34: 15.289574 | G34: 120.57066 | H34: =CONCATENATE(F34,",",G34) -> 15.289574,120.570662 | I34: Municipal / City Plan | J34: 1248 | K34: 2016 - 2027 | L34: 2019 | M34: 2027 | O34: Gretzhen M. Apolonio | Q34: Jan Emerson C. Gonzales | R34: 4.April | Y34: =IFERROR( IF( OR(ISBLANK(T34), ISBLANK(U34)), "", MAX( 1, IF( NETWORKDAYS(T34, U34, Holiday_Dates) <= 0, 1, NETWORKDAYS(T34, U34, Holiday_Dates) - IF(T34 = U34, 0, 1) ) ) ), "" ) | Z34: =IF( OR(ISBLANK(U34), ISBLANK(V34)), "", MAX( 1, IF( NETWORKDAYS(U34, V34, Holiday_Dates) <= 0, 1, NETWORKDAYS(U34, V34, Holiday_Dates) - IF(U34 = V34, 0, 1) ) ) ) | AA34: =IFERROR( IF( OR(ISBLANK(W34), AND(ISBLANK(U34), ISBLANK(V34))), "", MAX( 1, IF( NETWORKDAYS(IF(NOT(ISBLANK(V34)), V34, U34), W34, Holiday_Dates) <= 0, 1, NETWORKDAYS(IF(NOT(ISBLANK(V34)), V34, U34), W34, Holiday_Dates) - IF(IF(NOT(ISBLANK(V34)), V34, U34) = W34, 0, 1) ) ) ), "" ) | AB34: =IFERROR( IF( OR(ISBLANK(W34), ISBLANK(X34)), "", MAX( 1, IF( NETWORKDAYS(W34, X34, Holiday_Dates) <= 0, 1, NETWORKDAYS(W34, X34, Holiday_Dates) - IF(W34 = X34, 0, 1) ) ) ), "" ) | BB34: =SUM(AR34,AT34,AV34) -> 0 | BC34: =SUM(AS34,AU34,AW34) -> 0
A35: Tarlac | B35: Camiling | C35: =CONCATENATE(A35,","," ",B35) -> Tarlac, Camiling | D35: OUTSIDE MBA | E35: 1st | F35: 15.686329 | G35: 120.41465 | H35: =CONCATENATE(F35,",",G35) -> 15.6863285,120.4146513 | I35: Municipal / City Plan | J35: 1090 series of 2018 | K35: 2018 - 2027 | L35: 2018 | M35: 2027 | O35: Jasper Kieht B. Pili | Q35: Jan Emerson C. Gonzales | R35: 4.April | Y35: =IFERROR( IF( OR(ISBLANK(T35), ISBLANK(U35)), "", MAX( 1, IF( NETWORKDAYS(T35, U35, Holiday_Dates) <= 0, 1, NETWORKDAYS(T35, U35, Holiday_Dates) - IF(T35 = U35, 0, 1) ) ) ), "" ) | Z35: =IF( OR(ISBLANK(U35), ISBLANK(V35)), "", MAX( 1, IF( NETWORKDAYS(U35, V35, Holiday_Dates) <= 0, 1, NETWORKDAYS(U35, V35, Holiday_Dates) - IF(U35 = V35, 0, 1) ) ) ) | AA35: =IFERROR( IF( OR(ISBLANK(W35), AND(ISBLANK(U35), ISBLANK(V35))), "", MAX( 1, IF( NETWORKDAYS(IF(NOT(ISBLANK(V35)), V35, U35), W35, Holiday_Dates) <= 0, 1, NETWORKDAYS(IF(NOT(ISBLANK(V35)), V35, U35), W35, Holiday_Dates) - IF(IF(NOT(ISBLANK(V35)), V35, U35) = W35, 0, 1) ) ) ), "" ) | AB35: =IFERROR( IF( OR(ISBLANK(W35), ISBLANK(X35)), "", MAX( 1, IF( NETWORKDAYS(W35, X35, Holiday_Dates) <= 0, 1, NETWORKDAYS(W35, X35, Holiday_Dates) - IF(W35 = X35, 0, 1) ) ) ), "" ) | BB35: =SUM(AR35,AT35,AV35) -> 0 | BC35: =SUM(AS35,AU35,AW35) -> 0
A36: Aurora | B36: Baler | C36: =CONCATENATE(A36,","," ",B36) -> Aurora, Baler | D36: OUTSIDE MBA | E36: Lone | F36: 15.759064 | G36: 121.56307 | H36: =CONCATENATE(F36,",",G36) -> 15.759064,121.563075 | I36: Municipal / City Plan | J36: 859 series of 2018 | K36: 2017 - 2027 | L36: 2018 | M36: 2027 | O36: Zaila Mae Leander | Q36: Diozelle L. Cabalar | R36: 4.April | Y36: =IFERROR( IF( OR(ISBLANK(T36), ISBLANK(U36)), "", MAX( 1, IF( NETWORKDAYS(T36, U36, Holiday_Dates) <= 0, 1, NETWORKDAYS(T36, U36, Holiday_Dates) - IF(T36 = U36, 0, 1) ) ) ), "" ) | Z36: =IF( OR(ISBLANK(U36), ISBLANK(V36)), "", MAX( 1, IF( NETWORKDAYS(U36, V36, Holiday_Dates) <= 0, 1, NETWORKDAYS(U36, V36, Holiday_Dates) - IF(U36 = V36, 0, 1) ) ) ) | AA36: =IFERROR( IF( OR(ISBLANK(W36), AND(ISBLANK(U36), ISBLANK(V36))), "", MAX( 1, IF( NETWORKDAYS(IF(NOT(ISBLANK(V36)), V36, U36), W36, Holiday_Dates) <= 0, 1, NETWORKDAYS(IF(NOT(ISBLANK(V36)), V36, U36), W36, Holiday_Dates) - IF(IF(NOT(ISBLANK(V36)), V36, U36) = W36, 0, 1) ) ) ), "" ) | AB36: =IFERROR( IF( OR(ISBLANK(W36), ISBLANK(X36)), "", MAX( 1, IF( NETWORKDAYS(W36, X36, Holiday_Dates) <= 0, 1, NETWORKDAYS(W36, X36, Holiday_Dates) - IF(W36 = X36, 0, 1) ) ) ), "" ) | BB36: =SUM(AR36,AT36,AV36) -> 0 | BC36: =SUM(AS36,AU36,AW36) -> 0
A37: Bataan | B37: Orion | C37: =CONCATENATE(A37,","," ",B37) -> Bataan, Orion | D37: MBA | E37: 2nd | F37: 14.621155 | G37: 120.57647 | H37: =CONCATENATE(F37,",",G37) -> 14.621155,120.576472 | I37: Municipal / City Plan | J37: nswmc res.974 s2017 | K37: 2015 - 2025 | L37: 2017 | M37: 2025 | N37: For Renewal | O37: Dennis Tolentino | Q37: Christle D. David | R37: 4.April | Y37: =IFERROR( IF( OR(ISBLANK(T37), ISBLANK(U37)), "", MAX( 1, IF( NETWORKDAYS(T37, U37, Holiday_Dates) <= 0, 1, NETWORKDAYS(T37, U37, Holiday_Dates) - IF(T37 = U37, 0, 1) ) ) ), "" ) | Z37: =IF( OR(ISBLANK(U37), ISBLANK(V37)), "", MAX( 1, IF( NETWORKDAYS(U37, V37, Holiday_Dates) <= 0, 1, NETWORKDAYS(U37, V37, Holiday_Dates) - IF(U37 = V37, 0, 1) ) ) ) | AA37: =IFERROR( IF( OR(ISBLANK(W37), AND(ISBLANK(U37), ISBLANK(V37))), "", MAX( 1, IF( NETWORKDAYS(IF(NOT(ISBLANK(V37)), V37, U37), W37, Holiday_Dates) <= 0, 1, NETWORKDAYS(IF(NOT(ISBLANK(V37)), V37, U37), W37, Holiday_Dates) - IF(IF(NOT(ISBLANK(V37)), V37, U37) = W37, 0, 1) ) ) ), "" ) | AB37: =IFERROR( IF( OR(ISBLANK(W37), ISBLANK(X37)), "", MAX( 1, IF( NETWORKDAYS(W37, X37, Holiday_Dates) <= 0, 1, NETWORKDAYS(W37, X37, Holiday_Dates) - IF(W37 = X37, 0, 1) ) ) ), "" ) | BB37: =SUM(AR37,AT37,AV37) -> 0 | BC37: =SUM(AS37,AU37,AW37) -> 0
A38: Bulacan | B38: Doña Remedios Trinidad | C38: =CONCATENATE(A38,","," ",B38) -> Bulacan, Doña Remedios Trinidad | D38: MBA | E38: 3rd | F38: 14.97066 | G38: 121.06453 | H38: =CONCATENATE(F38,",",G38) -> 14.97066,121.064527 | I38: Municipal / City Plan | J38: 774 A series of 2017 | K38: 2016 - 2025 | L38: 2017 | M38: 2025 | N38: For Renewal | O38: VACANT | Q38: Diozelle L. Cabalar | R38: 4.April | Y38: =IFERROR( IF( OR(ISBLANK(T38), ISBLANK(U38)), "", MAX( 1, IF( NETWORKDAYS(T38, U38, Holiday_Dates) <= 0, 1, NETWORKDAYS(T38, U38, Holiday_Dates) - IF(T38 = U38, 0, 1) ) ) ), "" ) | Z38: =IF( OR(ISBLANK(U38), ISBLANK(V38)), "", MAX( 1, IF( NETWORKDAYS(U38, V38, Holiday_Dates) <= 0, 1, NETWORKDAYS(U38, V38, Holiday_Dates) - IF(U38 = V38, 0, 1) ) ) ) | AA38: =IFERROR( IF( OR(ISBLANK(W38), AND(ISBLANK(U38), ISBLANK(V38))), "", MAX( 1, IF( NETWORKDAYS(IF(NOT(ISBLANK(V38)), V38, U38), W38, Holiday_Dates) <= 0, 1, NETWORKDAYS(IF(NOT(ISBLANK(V38)), V38, U38), W38, Holiday_Dates) - IF(IF(NOT(ISBLANK(V38)), V38, U38) = W38, 0, 1) ) ) ), "" ) | AB38: =IFERROR( IF( OR(ISBLANK(W38), ISBLANK(X38)), "", MAX( 1, IF( NETWORKDAYS(W38, X38, Holiday_Dates) <= 0, 1, NETWORKDAYS(W38, X38, Holiday_Dates) - IF(W38 = X38, 0, 1) ) ) ), "" ) | BB38: =SUM(AR38,AT38,AV38) -> 0 | BC38: =SUM(AS38,AU38,AW38) -> 0
A39: Bulacan | B39: San Rafael | C39: =CONCATENATE(A39,","," ",B39) -> Bulacan, San Rafael | D39: MBA | E39: 3rd | F39: 14.982975 | G39: 120.92765 | H39: =CONCATENATE(F39,",",G39) -> 14.982975,120.927646 | I39: Municipal / City Plan | J39: NSWMC RESO NO. 168 SERIES OF 2015 | K39: 2015 - 2024 | L39: 2015 | M39: 2024 | N39: For Renewal | O39: VACANT | Q39: Diozelle L. Cabalar | R39: 4.April | Y39: =IFERROR( IF( OR(ISBLANK(T39), ISBLANK(U39)), "", MAX( 1, IF( NETWORKDAYS(T39, U39, Holiday_Dates) <= 0, 1, NETWORKDAYS(T39, U39, Holiday_Dates) - IF(T39 = U39, 0, 1) ) ) ), "" ) | Z39: =IF( OR(ISBLANK(U39), ISBLANK(V39)), "", MAX( 1, IF( NETWORKDAYS(U39, V39, Holiday_Dates) <= 0, 1, NETWORKDAYS(U39, V39, Holiday_Dates) - IF(U39 = V39, 0, 1) ) ) ) | AA39: =IFERROR( IF( OR(ISBLANK(W39), AND(ISBLANK(U39), ISBLANK(V39))), "", MAX( 1, IF( NETWORKDAYS(IF(NOT(ISBLANK(V39)), V39, U39), W39, Holiday_Dates) <= 0, 1, NETWORKDAYS(IF(NOT(ISBLANK(V39)), V39, U39), W39, Holiday_Dates) - IF(IF(NOT(ISBLANK(V39)), V39, U39) = W39, 0, 1) ) ) ), "" ) | AB39: =IFERROR( IF( OR(ISBLANK(W39), ISBLANK(X39)), "", MAX( 1, IF( NETWORKDAYS(W39, X39, Holiday_Dates) <= 0, 1, NETWORKDAYS(W39, X39, Holiday_Dates) - IF(W39 = X39, 0, 1) ) ) ), "" ) | BB39: =SUM(AR39,AT39,AV39) -> 0 | BC39: =SUM(AS39,AU39,AW39) -> 0
A40: Bulacan | B40: Santa Maria | C40: =CONCATENATE(A40,","," ",B40) -> Bulacan, Santa Maria | D40: MBA | E40: 6th | F40: 14.819555 | G40: 120.9601 | H40: =CONCATENATE(F40,",",G40) -> 14.81955522,120.9601016 | I40: Municipal / City Plan | J40: 201 s.2015 | K40: 2015 - 2024 | L40: 2015 | M40: 2024 | N40: For Renewal | O40: James Wilson T. Pena | Q40: Diozelle L. Cabalar | R40: 4.April | Y40: =IFERROR( IF( OR(ISBLANK(T40), ISBLANK(U40)), "", MAX( 1, IF( NETWORKDAYS(T40, U40, Holiday_Dates) <= 0, 1, NETWORKDAYS(T40, U40, Holiday_Dates) - IF(T40 = U40, 0, 1) ) ) ), "" ) | Z40: =IF( OR(ISBLANK(U40), ISBLANK(V40)), "", MAX( 1, IF( NETWORKDAYS(U40, V40, Holiday_Dates) <= 0, 1, NETWORKDAYS(U40, V40, Holiday_Dates) - IF(U40 = V40, 0, 1) ) ) ) | AA40: =IFERROR( IF( OR(ISBLANK(W40), AND(ISBLANK(U40), ISBLANK(V40))), "", MAX( 1, IF( NETWORKDAYS(IF(NOT(ISBLANK(V40)), V40, U40), W40, Holiday_Dates) <= 0, 1, NETWORKDAYS(IF(NOT(ISBLANK(V40)), V40, U40), W40, Holiday_Dates) - IF(IF(NOT(ISBLANK(V40)), V40, U40) = W40, 0, 1) ) ) ), "" ) | AB40: =IFERROR( IF( OR(ISBLANK(W40), ISBLANK(X40)), "", MAX( 1, IF( NETWORKDAYS(W40, X40, Holiday_Dates) <= 0, 1, NETWORKDAYS(W40, X40, Holiday_Dates) - IF(W40 = X40, 0, 1) ) ) ), "" ) | BB40: =SUM(AR40,AT40,AV40) -> 0 | BC40: =SUM(AS40,AU40,AW40) -> 0
A41: Nueva Ecija | B41: Aliaga | C41: =CONCATENATE(A41,","," ",B41) -> Nueva Ecija, Aliaga | D41: MBA | E41: 1st | F41: 15.449174 | G41: 120.79347 | H41: =CONCATENATE(F41,",",G41) -> 15.449174,120.793468 | I41: Municipal / City Plan | J41: 199 | K41: 2016 - 2025 | L41: 2015 | M41: 2025 | N41: For Renewal | O41: Gem C. Vicencio | Q41: Zosimo P. Suyat | R41: 4.April | Y41: =IFERROR( IF( OR(ISBLANK(T41), ISBLANK(U41)), "", MAX( 1, IF( NETWORKDAYS(T41, U41, Holiday_Dates) <= 0, 1, NETWORKDAYS(T41, U41, Holiday_Dates) - IF(T41 = U41, 0, 1) ) ) ), "" ) | Z41: =IF( OR(ISBLANK(U41), ISBLANK(V41)), "", MAX( 1, IF( NETWORKDAYS(U41, V41, Holiday_Dates) <= 0, 1, NETWORKDAYS(U41, V41, Holiday_Dates) - IF(U41 = V41, 0, 1) ) ) ) | AA41: =IFERROR( IF( OR(ISBLANK(W41), AND(ISBLANK(U41), ISBLANK(V41))), "", MAX( 1, IF( NETWORKDAYS(IF(NOT(ISBLANK(V41)), V41, U41), W41, Holiday_Dates) <= 0, 1, NETWORKDAYS(IF(NOT(ISBLANK(V41)), V41, U41), W41, Holiday_Dates) - IF(IF(NOT(ISBLANK(V41)), V41, U41) = W41, 0, 1) ) ) ), "" ) | AB41: =IFERROR( IF( OR(ISBLANK(W41), ISBLANK(X41)), "", MAX( 1, IF( NETWORKDAYS(W41, X41, Holiday_Dates) <= 0, 1, NETWORKDAYS(W41, X41, Holiday_Dates) - IF(W41 = X41, 0, 1) ) ) ), "" ) | BB41: =SUM(AR41,AT41,AV41) -> 0 | BC41: =SUM(AS41,AU41,AW41) -> 0
A42: Nueva Ecija | B42: Bongabon | C42: =CONCATENATE(A42,","," ",B42) -> Nueva Ecija, Bongabon | D42: MBA | E42: 3rd | F42: 15.627503 | G42: 121.14521 | H42: =CONCATENATE(F42,",",G42) -> 15.627503,121.145207 | I42: Municipal / City Plan | J42: 1075 series 2018 | K42: 2017 - 2026 | L42: 2018 | M42: 2026 | O42: Christian Jem L. Buluran | Q42: Zosimo P. Suyat | R42: 4.April | Y42: =IFERROR( IF( OR(ISBLANK(T42), ISBLANK(U42)), "", MAX( 1, IF( NETWORKDAYS(T42, U42, Holiday_Dates) <= 0, 1, NETWORKDAYS(T42, U42, Holiday_Dates) - IF(T42 = U42, 0, 1) ) ) ), "" ) | Z42: =IF( OR(ISBLANK(U42), ISBLANK(V42)), "", MAX( 1, IF( NETWORKDAYS(U42, V42, Holiday_Dates) <= 0, 1, NETWORKDAYS(U42, V42, Holiday_Dates) - IF(U42 = V42, 0, 1) ) ) ) | AA42: =IFERROR( IF( OR(ISBLANK(W42), AND(ISBLANK(U42), ISBLANK(V42))), "", MAX( 1, IF( NETWORKDAYS(IF(NOT(ISBLANK(V42)), V42, U42), W42, Holiday_Dates) <= 0, 1, NETWORKDAYS(IF(NOT(ISBLANK(V42)), V42, U42), W42, Holiday_Dates) - IF(IF(NOT(ISBLANK(V42)), V42, U42) = W42, 0, 1) ) ) ), "" ) | AB42: =IFERROR( IF( OR(ISBLANK(W42), ISBLANK(X42)), "", MAX( 1, IF( NETWORKDAYS(W42, X42, Holiday_Dates) <= 0, 1, NETWORKDAYS(W42, X42, Holiday_Dates) - IF(W42 = X42, 0, 1) ) ) ), "" ) | BB42: =SUM(AR42,AT42,AV42) -> 0 | BC42: =SUM(AS42,AU42,AW42) -> 0
A43: Nueva Ecija | B43: Gabaldon | C43: =CONCATENATE(A43,","," ",B43) -> Nueva Ecija, Gabaldon | D43: MBA | E43: 3rd | F43: 15.455567 | G43: 121.33825 | H43: =CONCATENATE(F43,",",G43) -> 15.455567,121.33825 | I43: Municipal / City Plan | J43: 1246 series of 2019 | K43: 2016 - 2027 | L43: 2019 | M43: 2027 | O43: Christian Jem L. Buluran | Q43: Zosimo P. Suyat | R43: 4.April | Y43: =IFERROR( IF( OR(ISBLANK(T43), ISBLANK(U43)), "", MAX( 1, IF( NETWORKDAYS(T43, U43, Holiday_Dates) <= 0, 1, NETWORKDAYS(T43, U43, Holiday_Dates) - IF(T43 = U43, 0, 1) ) ) ), "" ) | Z43: =IF( OR(ISBLANK(U43), ISBLANK(V43)), "", MAX( 1, IF( NETWORKDAYS(U43, V43, Holiday_Dates) <= 0, 1, NETWORKDAYS(U43, V43, Holiday_Dates) - IF(U43 = V43, 0, 1) ) ) ) | AA43: =IFERROR( IF( OR(ISBLANK(W43), AND(ISBLANK(U43), ISBLANK(V43))), "", MAX( 1, IF( NETWORKDAYS(IF(NOT(ISBLANK(V43)), V43, U43), W43, Holiday_Dates) <= 0, 1, NETWORKDAYS(IF(NOT(ISBLANK(V43)), V43, U43), W43, Holiday_Dates) - IF(IF(NOT(ISBLANK(V43)), V43, U43) = W43, 0, 1) ) ) ), "" ) | AB43: =IFERROR( IF( OR(ISBLANK(W43), ISBLANK(X43)), "", MAX( 1, IF( NETWORKDAYS(W43, X43, Holiday_Dates) <= 0, 1, NETWORKDAYS(W43, X43, Holiday_Dates) - IF(W43 = X43, 0, 1) ) ) ), "" ) | BB43: =SUM(AR43,AT43,AV43) -> 0 | BC43: =SUM(AS43,AU43,AW43) -> 0
A44: Nueva Ecija | B44: San Jose City | C44: =CONCATENATE(A44,","," ",B44) -> Nueva Ecija, San Jose City | D44: MBA | E44: 2nd | F44: 15.792271 | G44: 120.98886 | H44: =CONCATENATE(F44,",",G44) -> 15.792271,120.988859 | I44: Municipal / City Plan | J44: 129 | K44: 2014 - 2023 | L44: 2015 | M44: 2023 | N44: For Renewal | O44: Hosannah R. Sabio | Q44: Zosimo P. Suyat | R44: 4.April | Y44: =IFERROR( IF( OR(ISBLANK(T44), ISBLANK(U44)), "", MAX( 1, IF( NETWORKDAYS(T44, U44, Holiday_Dates) <= 0, 1, NETWORKDAYS(T44, U44, Holiday_Dates) - IF(T44 = U44, 0, 1) ) ) ), "" ) | Z44: =IF( OR(ISBLANK(U44), ISBLANK(V44)), "", MAX( 1, IF( NETWORKDAYS(U44, V44, Holiday_Dates) <= 0, 1, NETWORKDAYS(U44, V44, Holiday_Dates) - IF(U44 = V44, 0, 1) ) ) ) | AA44: =IFERROR( IF( OR(ISBLANK(W44), AND(ISBLANK(U44), ISBLANK(V44))), "", MAX( 1, IF( NETWORKDAYS(IF(NOT(ISBLANK(V44)), V44, U44), W44, Holiday_Dates) <= 0, 1, NETWORKDAYS(IF(NOT(ISBLANK(V44)), V44, U44), W44, Holiday_Dates) - IF(IF(NOT(ISBLANK(V44)), V44, U44) = W44, 0, 1) ) ) ), "" ) | AB44: =IFERROR( IF( OR(ISBLANK(W44), ISBLANK(X44)), "", MAX( 1, IF( NETWORKDAYS(W44, X44, Holiday_Dates) <= 0, 1, NETWORKDAYS(W44, X44, Holiday_Dates) - IF(W44 = X44, 0, 1) ) ) ), "" ) | BB44: =SUM(AR44,AT44,AV44) -> 0 | BC44: =SUM(AS44,AU44,AW44) -> 0
A45: Pampanga | B45: Arayat | C45: =CONCATENATE(A45,","," ",B45) -> Pampanga, Arayat | D45: MBA | E45: 3rd | F45: 15.154167 | G45: 120.7716 | H45: =CONCATENATE(F45,",",G45) -> 15.154167,120.771598 | I45: Municipal / City Plan | J45: 1038-A Series of 2019 | K45: 2017 -2028 | L45: 2019 | M45: 2028 | O45: Roger T. Encarnacion II | Q45: Jun D. Guillermo | R45: 4.April | Y45: =IFERROR( IF( OR(ISBLANK(T45), ISBLANK(U45)), "", MAX( 1, IF( NETWORKDAYS(T45, U45, Holiday_Dates) <= 0, 1, NETWORKDAYS(T45, U45, Holiday_Dates) - IF(T45 = U45, 0, 1) ) ) ), "" ) | Z45: =IF( OR(ISBLANK(U45), ISBLANK(V45)), "", MAX( 1, IF( NETWORKDAYS(U45, V45, Holiday_Dates) <= 0, 1, NETWORKDAYS(U45, V45, Holiday_Dates) - IF(U45 = V45, 0, 1) ) ) ) | AA45: =IFERROR( IF( OR(ISBLANK(W45), AND(ISBLANK(U45), ISBLANK(V45))), "", MAX( 1, IF( NETWORKDAYS(IF(NOT(ISBLANK(V45)), V45, U45), W45, Holiday_Dates) <= 0, 1, NETWORKDAYS(IF(NOT(ISBLANK(V45)), V45, U45), W45, Holiday_Dates) - IF(IF(NOT(ISBLANK(V45)), V45, U45) = W45, 0, 1) ) ) ), "" ) | AB45: =IFERROR( IF( OR(ISBLANK(W45), ISBLANK(X45)), "", MAX( 1, IF( NETWORKDAYS(W45, X45, Holiday_Dates) <= 0, 1, NETWORKDAYS(W45, X45, Holiday_Dates) - IF(W45 = X45, 0, 1) ) ) ), "" ) | BB45: =SUM(AR45,AT45,AV45) -> 0 | BC45: =SUM(AS45,AU45,AW45) -> 0
A46: Pampanga | B46: Minalin | C46: =CONCATENATE(A46,","," ",B46) -> Pampanga, Minalin | D46: MBA | E46: 4th | F46: 14.9704 | G46: 120.6861 | H46: =CONCATENATE(F46,",",G46) -> 14.9704,120.6861 | I46: Municipal / City Plan | J46: 763 s. 2016 | K46: 2015 - 2024 | L46: 2016 | M46: 2024 | N46: For Renewal | O46: Glaiza S.Gaza | Q46: Sherwin John Y. Loquellano | R46: 4.April | Y46: =IFERROR( IF( OR(ISBLANK(T46), ISBLANK(U46)), "", MAX( 1, IF( NETWORKDAYS(T46, U46, Holiday_Dates) <= 0, 1, NETWORKDAYS(T46, U46, Holiday_Dates) - IF(T46 = U46, 0, 1) ) ) ), "" ) | Z46: =IF( OR(ISBLANK(U46), ISBLANK(V46)), "", MAX( 1, IF( NETWORKDAYS(U46, V46, Holiday_Dates) <= 0, 1, NETWORKDAYS(U46, V46, Holiday_Dates) - IF(U46 = V46, 0, 1) ) ) ) | AA46: =IFERROR( IF( OR(ISBLANK(W46), AND(ISBLANK(U46), ISBLANK(V46))), "", MAX( 1, IF( NETWORKDAYS(IF(NOT(ISBLANK(V46)), V46, U46), W46, Holiday_Dates) <= 0, 1, NETWORKDAYS(IF(NOT(ISBLANK(V46)), V46, U46), W46, Holiday_Dates) - IF(IF(NOT(ISBLANK(V46)), V46, U46) = W46, 0, 1) ) ) ), "" ) | AB46: =IFERROR( IF( OR(ISBLANK(W46), ISBLANK(X46)), "", MAX( 1, IF( NETWORKDAYS(W46, X46, Holiday_Dates) <= 0, 1, NETWORKDAYS(W46, X46, Holiday_Dates) - IF(W46 = X46, 0, 1) ) ) ), "" ) | BB46: =SUM(AR46,AT46,AV46) -> 0 | BC46: =SUM(AS46,AU46,AW46) -> 0
A47: Pampanga | B47: Sasmuan | C47: =CONCATENATE(A47,","," ",B47) -> Pampanga, Sasmuan | D47: MBA | E47: 2nd | F47: 14.9363 | G47: 120.6223 | H47: =CONCATENATE(F47,",",G47) -> 14.9363,120.6223 | I47: Municipal / City Plan | J47: NSWMC RESO NO. 1332 SERIES OF 2019 | K47: 2017 - 2028 | L47: 2019 | M47: 2028 | O47: Sebastian Josh V. Manalang | Q47: Jun D. Guillermo | R47: 4.April | Y47: =IFERROR( IF( OR(ISBLANK(T47), ISBLANK(U47)), "", MAX( 1, IF( NETWORKDAYS(T47, U47, Holiday_Dates) <= 0, 1, NETWORKDAYS(T47, U47, Holiday_Dates) - IF(T47 = U47, 0, 1) ) ) ), "" ) | Z47: =IF( OR(ISBLANK(U47), ISBLANK(V47)), "", MAX( 1, IF( NETWORKDAYS(U47, V47, Holiday_Dates) <= 0, 1, NETWORKDAYS(U47, V47, Holiday_Dates) - IF(U47 = V47, 0, 1) ) ) ) | AA47: =IFERROR( IF( OR(ISBLANK(W47), AND(ISBLANK(U47), ISBLANK(V47))), "", MAX( 1, IF( NETWORKDAYS(IF(NOT(ISBLANK(V47)), V47, U47), W47, Holiday_Dates) <= 0, 1, NETWORKDAYS(IF(NOT(ISBLANK(V47)), V47, U47), W47, Holiday_Dates) - IF(IF(NOT(ISBLANK(V47)), V47, U47) = W47, 0, 1) ) ) ), "" ) | AB47: =IFERROR( IF( OR(ISBLANK(W47), ISBLANK(X47)), "", MAX( 1, IF( NETWORKDAYS(W47, X47, Holiday_Dates) <= 0, 1, NETWORKDAYS(W47, X47, Holiday_Dates) - IF(W47 = X47, 0, 1) ) ) ), "" ) | BB47: =SUM(AR47,AT47,AV47) -> 0 | BC47: =SUM(AS47,AU47,AW47) -> 0
A48: Zambales | B48: Castillejos | C48: =CONCATENATE(A48,","," ",B48) -> Zambales, Castillejos | D48: OUTSIDE MBA | E48: 1st | F48: 14.93211 | G48: 120.19998 | H48: =CONCATENATE(F48,",",G48) -> 14.93211,120.199976 | I48: Municipal / City Plan | J48: No.1414 Series of 2020 | K48: 2017 - 2027 | L48: 2020 | M48: 2027 | O48: Ryan Ace R. Angel | Q48: Jun D. Guillermo | R48: 4.April | Y48: =IFERROR( IF( OR(ISBLANK(T48), ISBLANK(U48)), "", MAX( 1, IF( NETWORKDAYS(T48, U48, Holiday_Dates) <= 0, 1, NETWORKDAYS(T48, U48, Holiday_Dates) - IF(T48 = U48, 0, 1) ) ) ), "" ) | Z48: =IF( OR(ISBLANK(U48), ISBLANK(V48)), "", MAX( 1, IF( NETWORKDAYS(U48, V48, Holiday_Dates) <= 0, 1, NETWORKDAYS(U48, V48, Holiday_Dates) - IF(U48 = V48, 0, 1) ) ) ) | AA48: =IFERROR( IF( OR(ISBLANK(W48), AND(ISBLANK(U48), ISBLANK(V48))), "", MAX( 1, IF( NETWORKDAYS(IF(NOT(ISBLANK(V48)), V48, U48), W48, Holiday_Dates) <= 0, 1, NETWORKDAYS(IF(NOT(ISBLANK(V48)), V48, U48), W48, Holiday_Dates) - IF(IF(NOT(ISBLANK(V48)), V48, U48) = W48, 0, 1) ) ) ), "" ) | AB48: =IFERROR( IF( OR(ISBLANK(W48), ISBLANK(X48)), "", MAX( 1, IF( NETWORKDAYS(W48, X48, Holiday_Dates) <= 0, 1, NETWORKDAYS(W48, X48, Holiday_Dates) - IF(W48 = X48, 0, 1) ) ) ), "" ) | BB48: =SUM(AR48,AT48,AV48) -> 0 | BC48: =SUM(AS48,AU48,AW48) -> 0
A49: Bataan | B49: Pilar | C49: =CONCATENATE(A49,","," ",B49) -> Bataan, Pilar | D49: MBA | E49: 2nd | F49: 14.66851 | G49: 120.55284 | H49: =CONCATENATE(F49,",",G49) -> 14.66851,120.552837 | I49: Municipal / City Plan | J49: NSWMC Res. No. 138 s. 2015 | K49: 2015 - 2024 | L49: 2015 | M49: 2024 | N49: For Renewal | O49: Dennis Tolentino | Q49: Christle D. David | R49: 5.May | Y49: =IFERROR( IF( OR(ISBLANK(T49), ISBLANK(U49)), "", MAX( 1, IF( NETWORKDAYS(T49, U49, Holiday_Dates) <= 0, 1, NETWORKDAYS(T49, U49, Holiday_Dates) - IF(T49 = U49, 0, 1) ) ) ), "" ) | Z49: =IF( OR(ISBLANK(U49), ISBLANK(V49)), "", MAX( 1, IF( NETWORKDAYS(U49, V49, Holiday_Dates) <= 0, 1, NETWORKDAYS(U49, V49, Holiday_Dates) - IF(U49 = V49, 0, 1) ) ) ) | AA49: =IFERROR( IF( OR(ISBLANK(W49), AND(ISBLANK(U49), ISBLANK(V49))), "", MAX( 1, IF( NETWORKDAYS(IF(NOT(ISBLANK(V49)), V49, U49), W49, Holiday_Dates) <= 0, 1, NETWORKDAYS(IF(NOT(ISBLANK(V49)), V49, U49), W49, Holiday_Dates) - IF(IF(NOT(ISBLANK(V49)), V49, U49) = W49, 0, 1) ) ) ), "" ) | AB49: =IFERROR( IF( OR(ISBLANK(W49), ISBLANK(X49)), "", MAX( 1, IF( NETWORKDAYS(W49, X49, Holiday_Dates) <= 0, 1, NETWORKDAYS(W49, X49, Holiday_Dates) - IF(W49 = X49, 0, 1) ) ) ), "" ) | BB49: =SUM(AR49,AT49,AV49) -> 0 | BC49: =SUM(AS49,AU49,AW49) -> 0
A50: Bulacan | B50: Balagtas | C50: =CONCATENATE(A50,","," ",B50) -> Bulacan, Balagtas | D50: MBA | E50: 5th | F50: 14.81736 | G50: 120.90809 | H50: =CONCATENATE(F50,",",G50) -> 14.81736,120.908093 | I50: Municipal / City Plan | J50: 1179 Series of 2018 | K50: 2017 - 2027 | L50: 2018 | M50: 2027 | O50: Jasmin Marie N. Siapco | Q50: Diozelle L. Cabalar | R50: 5.May | Y50: =IFERROR( IF( OR(ISBLANK(T50), ISBLANK(U50)), "", MAX( 1, IF( NETWORKDAYS(T50, U50, Holiday_Dates) <= 0, 1, NETWORKDAYS(T50, U50, Holiday_Dates) - IF(T50 = U50, 0, 1) ) ) ), "" ) | Z50: =IF( OR(ISBLANK(U50), ISBLANK(V50)), "", MAX( 1, IF( NETWORKDAYS(U50, V50, Holiday_Dates) <= 0, 1, NETWORKDAYS(U50, V50, Holiday_Dates) - IF(U50 = V50, 0, 1) ) ) ) | AA50: =IFERROR( IF( OR(ISBLANK(W50), AND(ISBLANK(U50), ISBLANK(V50))), "", MAX( 1, IF( NETWORKDAYS(IF(NOT(ISBLANK(V50)), V50, U50), W50, Holiday_Dates) <= 0, 1, NETWORKDAYS(IF(NOT(ISBLANK(V50)), V50, U50), W50, Holiday_Dates) - IF(IF(NOT(ISBLANK(V50)), V50, U50) = W50, 0, 1) ) ) ), "" ) | AB50: =IFERROR( IF( OR(ISBLANK(W50), ISBLANK(X50)), "", MAX( 1, IF( NETWORKDAYS(W50, X50, Holiday_Dates) <= 0, 1, NETWORKDAYS(W50, X50, Holiday_Dates) - IF(W50 = X50, 0, 1) ) ) ), "" ) | BB50: =SUM(AR50,AT50,AV50) -> 0 | BC50: =SUM(AS50,AU50,AW50) -> 0
A51: Bulacan | B51: Bulakan | C51: =CONCATENATE(A51,","," ",B51) -> Bulacan, Bulakan | D51: MBA | E51: 1st | F51: 14.794464 | G51: 120.87892 | H51: =CONCATENATE(F51,",",G51) -> 14.79446412,120.8789154 | I51: Municipal / City Plan | J51: 1180 | K51: 2017 - 2027 | L51: 2018 | M51: 2027 | O51: Jasmin Marie N. Siapco | Q51: Diozelle L. Cabalar | R51: 5.May | Y51: =IFERROR( IF( OR(ISBLANK(T51), ISBLANK(U51)), "", MAX( 1, IF( NETWORKDAYS(T51, U51, Holiday_Dates) <= 0, 1, NETWORKDAYS(T51, U51, Holiday_Dates) - IF(T51 = U51, 0, 1) ) ) ), "" ) | Z51: =IF( OR(ISBLANK(U51), ISBLANK(V51)), "", MAX( 1, IF( NETWORKDAYS(U51, V51, Holiday_Dates) <= 0, 1, NETWORKDAYS(U51, V51, Holiday_Dates) - IF(U51 = V51, 0, 1) ) ) ) | AA51: =IFERROR( IF( OR(ISBLANK(W51), AND(ISBLANK(U51), ISBLANK(V51))), "", MAX( 1, IF( NETWORKDAYS(IF(NOT(ISBLANK(V51)), V51, U51), W51, Holiday_Dates) <= 0, 1, NETWORKDAYS(IF(NOT(ISBLANK(V51)), V51, U51), W51, Holiday_Dates) - IF(IF(NOT(ISBLANK(V51)), V51, U51) = W51, 0, 1) ) ) ), "" ) | AB51: =IFERROR( IF( OR(ISBLANK(W51), ISBLANK(X51)), "", MAX( 1, IF( NETWORKDAYS(W51, X51, Holiday_Dates) <= 0, 1, NETWORKDAYS(W51, X51, Holiday_Dates) - IF(W51 = X51, 0, 1) ) ) ), "" ) | BB51: =SUM(AR51,AT51,AV51) -> 0 | BC51: =SUM(AS51,AU51,AW51) -> 0
A52: Bulacan | B52: City Of Baliwag | C52: =CONCATENATE(A52,","," ",B52) -> Bulacan, City Of Baliwag | D52: MBA | E52: 2nd | F52: 14.959281 | G52: 120.89952 | H52: =CONCATENATE(F52,",",G52) -> 14.959281,120.899518 | I52: Municipal / City Plan | J52: 653 A Series of 2018 | K52: 2017 - 2027 | L52: 2018 | M52: 2027 | O52: VACANT | Q52: Diozelle L. Cabalar | R52: 5.May | Y52: =IFERROR( IF( OR(ISBLANK(T52), ISBLANK(U52)), "", MAX( 1, IF( NETWORKDAYS(T52, U52, Holiday_Dates) <= 0, 1, NETWORKDAYS(T52, U52, Holiday_Dates) - IF(T52 = U52, 0, 1) ) ) ), "" ) | Z52: =IF( OR(ISBLANK(U52), ISBLANK(V52)), "", MAX( 1, IF( NETWORKDAYS(U52, V52, Holiday_Dates) <= 0, 1, NETWORKDAYS(U52, V52, Holiday_Dates) - IF(U52 = V52, 0, 1) ) ) ) | AA52: =IFERROR( IF( OR(ISBLANK(W52), AND(ISBLANK(U52), ISBLANK(V52))), "", MAX( 1, IF( NETWORKDAYS(IF(NOT(ISBLANK(V52)), V52, U52), W52, Holiday_Dates) <= 0, 1, NETWORKDAYS(IF(NOT(ISBLANK(V52)), V52, U52), W52, Holiday_Dates) - IF(IF(NOT(ISBLANK(V52)), V52, U52) = W52, 0, 1) ) ) ), "" ) | AB52: =IFERROR( IF( OR(ISBLANK(W52), ISBLANK(X52)), "", MAX( 1, IF( NETWORKDAYS(W52, X52, Holiday_Dates) <= 0, 1, NETWORKDAYS(W52, X52, Holiday_Dates) - IF(W52 = X52, 0, 1) ) ) ), "" ) | BB52: =SUM(AR52,AT52,AV52) -> 0 | BC52: =SUM(AS52,AU52,AW52) -> 0
A53: Nueva Ecija | B53: Cabiao | C53: =CONCATENATE(A53,","," ",B53) -> Nueva Ecija, Cabiao | D53: MBA | E53: 4th | F53: 15.252382 | G53: 120.86015 | H53: =CONCATENATE(F53,",",G53) -> 15.252382,120.860145 | I53: Municipal / City Plan | J53: 1365 series of 2019 | K53: 2017 - 2027 | L53: 2019 | M53: 2027 | O53: Christine Ann V. Ramos | Q53: Zosimo P. Suyat | R53: 5.May | Y53: =IFERROR( IF( OR(ISBLANK(T53), ISBLANK(U53)), "", MAX( 1, IF( NETWORKDAYS(T53, U53, Holiday_Dates) <= 0, 1, NETWORKDAYS(T53, U53, Holiday_Dates) - IF(T53 = U53, 0, 1) ) ) ), "" ) | Z53: =IF( OR(ISBLANK(U53), ISBLANK(V53)), "", MAX( 1, IF( NETWORKDAYS(U53, V53, Holiday_Dates) <= 0, 1, NETWORKDAYS(U53, V53, Holiday_Dates) - IF(U53 = V53, 0, 1) ) ) ) | AA53: =IFERROR( IF( OR(ISBLANK(W53), AND(ISBLANK(U53), ISBLANK(V53))), "", MAX( 1, IF( NETWORKDAYS(IF(NOT(ISBLANK(V53)), V53, U53), W53, Holiday_Dates) <= 0, 1, NETWORKDAYS(IF(NOT(ISBLANK(V53)), V53, U53), W53, Holiday_Dates) - IF(IF(NOT(ISBLANK(V53)), V53, U53) = W53, 0, 1) ) ) ), "" ) | AB53: =IFERROR( IF( OR(ISBLANK(W53), ISBLANK(X53)), "", MAX( 1, IF( NETWORKDAYS(W53, X53, Holiday_Dates) <= 0, 1, NETWORKDAYS(W53, X53, Holiday_Dates) - IF(W53 = X53, 0, 1) ) ) ), "" ) | BB53: =SUM(AR53,AT53,AV53) -> 0 | BC53: =SUM(AS53,AU53,AW53) -> 0
A54: Nueva Ecija | B54: Carranglan | C54: =CONCATENATE(A54,","," ",B54) -> Nueva Ecija, Carranglan | D54: MBA | E54: 2nd | F54: 15.960408 | G54: 121.06312 | H54: =CONCATENATE(F54,",",G54) -> 15.960408,121.063117 | I54: Municipal / City Plan | J54: 1329 | K54: 2017 - 2027 | L54: 2019 | M54: 2027 | O54: Aser A. Inocencio, Jr. | Q54: Zosimo P. Suyat | R54: 5.May | Y54: =IFERROR( IF( OR(ISBLANK(T54), ISBLANK(U54)), "", MAX( 1, IF( NETWORKDAYS(T54, U54, Holiday_Dates) <= 0, 1, NETWORKDAYS(T54, U54, Holiday_Dates) - IF(T54 = U54, 0, 1) ) ) ), "" ) | Z54: =IF( OR(ISBLANK(U54), ISBLANK(V54)), "", MAX( 1, IF( NETWORKDAYS(U54, V54, Holiday_Dates) <= 0, 1, NETWORKDAYS(U54, V54, Holiday_Dates) - IF(U54 = V54, 0, 1) ) ) ) | AA54: =IFERROR( IF( OR(ISBLANK(W54), AND(ISBLANK(U54), ISBLANK(V54))), "", MAX( 1, IF( NETWORKDAYS(IF(NOT(ISBLANK(V54)), V54, U54), W54, Holiday_Dates) <= 0, 1, NETWORKDAYS(IF(NOT(ISBLANK(V54)), V54, U54), W54, Holiday_Dates) - IF(IF(NOT(ISBLANK(V54)), V54, U54) = W54, 0, 1) ) ) ), "" ) | AB54: =IFERROR( IF( OR(ISBLANK(W54), ISBLANK(X54)), "", MAX( 1, IF( NETWORKDAYS(W54, X54, Holiday_Dates) <= 0, 1, NETWORKDAYS(W54, X54, Holiday_Dates) - IF(W54 = X54, 0, 1) ) ) ), "" ) | BB54: =SUM(AR54,AT54,AV54) -> 0 | BC54: =SUM(AS54,AU54,AW54) -> 0
A55: Nueva Ecija | B55: Quezon | C55: =CONCATENATE(A55,","," ",B55) -> Nueva Ecija, Quezon | D55: MBA | E55: 1st | F55: 15.551573 | G55: 120.81476 | H55: =CONCATENATE(F55,",",G55) -> 15.551573,120.814763 | I55: Municipal / City Plan | J55: 1086 series of 2018 | K55: 2017 - 2026 | L55: 2018 | M55: 2026 | O55: Gem C. Vicencio | Q55: Zosimo P. Suyat | R55: 5.May | Y55: =IFERROR( IF( OR(ISBLANK(T55), ISBLANK(U55)), "", MAX( 1, IF( NETWORKDAYS(T55, U55, Holiday_Dates) <= 0, 1, NETWORKDAYS(T55, U55, Holiday_Dates) - IF(T55 = U55, 0, 1) ) ) ), "" ) | Z55: =IF( OR(ISBLANK(U55), ISBLANK(V55)), "", MAX( 1, IF( NETWORKDAYS(U55, V55, Holiday_Dates) <= 0, 1, NETWORKDAYS(U55, V55, Holiday_Dates) - IF(U55 = V55, 0, 1) ) ) ) | AA55: =IFERROR( IF( OR(ISBLANK(W55), AND(ISBLANK(U55), ISBLANK(V55))), "", MAX( 1, IF( NETWORKDAYS(IF(NOT(ISBLANK(V55)), V55, U55), W55, Holiday_Dates) <= 0, 1, NETWORKDAYS(IF(NOT(ISBLANK(V55)), V55, U55), W55, Holiday_Dates) - IF(IF(NOT(ISBLANK(V55)), V55, U55) = W55, 0, 1) ) ) ), "" ) | AB55: =IFERROR( IF( OR(ISBLANK(W55), ISBLANK(X55)), "", MAX( 1, IF( NETWORKDAYS(W55, X55, Holiday_Dates) <= 0, 1, NETWORKDAYS(W55, X55, Holiday_Dates) - IF(W55 = X55, 0, 1) ) ) ), "" ) | BB55: =SUM(AR55,AT55,AV55) -> 0 | BC55: =SUM(AS55,AU55,AW55) -> 0
A56: Nueva Ecija | B56: Science City Of Muñoz | C56: =CONCATENATE(A56,","," ",B56) -> Nueva Ecija, Science City Of Muñoz | D56: MBA | E56: 2nd | F56: 15.713327 | G56: 120.90397 | H56: =CONCATENATE(F56,",",G56) -> 15.713327,120.903968 | I56: Municipal / City Plan | J56: 1085 s. 2018 | K56: 2018 - 2027 | L56: 2018 | M56: 2027 | O56: Aser A. Inocencio, Jr. | Q56: Zosimo P. Suyat | R56: 5.May | Y56: =IFERROR( IF( OR(ISBLANK(T56), ISBLANK(U56)), "", MAX( 1, IF( NETWORKDAYS(T56, U56, Holiday_Dates) <= 0, 1, NETWORKDAYS(T56, U56, Holiday_Dates) - IF(T56 = U56, 0, 1) ) ) ), "" ) | Z56: =IF( OR(ISBLANK(U56), ISBLANK(V56)), "", MAX( 1, IF( NETWORKDAYS(U56, V56, Holiday_Dates) <= 0, 1, NETWORKDAYS(U56, V56, Holiday_Dates) - IF(U56 = V56, 0, 1) ) ) ) | AA56: =IFERROR( IF( OR(ISBLANK(W56), AND(ISBLANK(U56), ISBLANK(V56))), "", MAX( 1, IF( NETWORKDAYS(IF(NOT(ISBLANK(V56)), V56, U56), W56, Holiday_Dates) <= 0, 1, NETWORKDAYS(IF(NOT(ISBLANK(V56)), V56, U56), W56, Holiday_Dates) - IF(IF(NOT(ISBLANK(V56)), V56, U56) = W56, 0, 1) ) ) ), "" ) | AB56: =IFERROR( IF( OR(ISBLANK(W56), ISBLANK(X56)), "", MAX( 1, IF( NETWORKDAYS(W56, X56, Holiday_Dates) <= 0, 1, NETWORKDAYS(W56, X56, Holiday_Dates) - IF(W56 = X56, 0, 1) ) ) ), "" ) | BB56: =SUM(AR56,AT56,AV56) -> 0 | BC56: =SUM(AS56,AU56,AW56) -> 0
A57: Pampanga | B57: Bacolor | C57: =CONCATENATE(A57,","," ",B57) -> Pampanga, Bacolor | D57: MBA | E57: 3rd | F57: 14.9966 | G57: 120.6517 | H57: =CONCATENATE(F57,",",G57) -> 14.9966,120.6517 | I57: Municipal / City Plan | J57: NSWMC Resolution No. 1638, Series of 2023 | K57: 2022 - 2031 | L57: 2022 | M57: 2031 | O57: Sebastian Josh V. Manalang | Q57: Jun D. Guillermo | R57: 5.May | Y57: =IFERROR( IF( OR(ISBLANK(T57), ISBLANK(U57)), "", MAX( 1, IF( NETWORKDAYS(T57, U57, Holiday_Dates) <= 0, 1, NETWORKDAYS(T57, U57, Holiday_Dates) - IF(T57 = U57, 0, 1) ) ) ), "" ) | Z57: =IF( OR(ISBLANK(U57), ISBLANK(V57)), "", MAX( 1, IF( NETWORKDAYS(U57, V57, Holiday_Dates) <= 0, 1, NETWORKDAYS(U57, V57, Holiday_Dates) - IF(U57 = V57, 0, 1) ) ) ) | AA57: =IFERROR( IF( OR(ISBLANK(W57), AND(ISBLANK(U57), ISBLANK(V57))), "", MAX( 1, IF( NETWORKDAYS(IF(NOT(ISBLANK(V57)), V57, U57), W57, Holiday_Dates) <= 0, 1, NETWORKDAYS(IF(NOT(ISBLANK(V57)), V57, U57), W57, Holiday_Dates) - IF(IF(NOT(ISBLANK(V57)), V57, U57) = W57, 0, 1) ) ) ), "" ) | AB57: =IFERROR( IF( OR(ISBLANK(W57), ISBLANK(X57)), "", MAX( 1, IF( NETWORKDAYS(W57, X57, Holiday_Dates) <= 0, 1, NETWORKDAYS(W57, X57, Holiday_Dates) - IF(W57 = X57, 0, 1) ) ) ), "" ) | BB57: =SUM(AR57,AT57,AV57) -> 0 | BC57: =SUM(AS57,AU57,AW57) -> 0
A58: Pampanga | B58: Porac | C58: =CONCATENATE(A58,","," ",B58) -> Pampanga, Porac | D58: MBA | E58: 2nd | F58: 15.0732 | G58: 120.5406 | H58: =CONCATENATE(F58,",",G58) -> 15.0732,120.5406 | I58: Municipal / City Plan | J58: 787 A series of 2018 | K58: 2018 - 2027 | L58: 2018 | M58: 2027 | O58: Elyza A. Evilla | Q58: Sherwin John Y. Loquellano | R58: 5.May | Y58: =IFERROR( IF( OR(ISBLANK(T58), ISBLANK(U58)), "", MAX( 1, IF( NETWORKDAYS(T58, U58, Holiday_Dates) <= 0, 1, NETWORKDAYS(T58, U58, Holiday_Dates) - IF(T58 = U58, 0, 1) ) ) ), "" ) | Z58: =IF( OR(ISBLANK(U58), ISBLANK(V58)), "", MAX( 1, IF( NETWORKDAYS(U58, V58, Holiday_Dates) <= 0, 1, NETWORKDAYS(U58, V58, Holiday_Dates) - IF(U58 = V58, 0, 1) ) ) ) | AA58: =IFERROR( IF( OR(ISBLANK(W58), AND(ISBLANK(U58), ISBLANK(V58))), "", MAX( 1, IF( NETWORKDAYS(IF(NOT(ISBLANK(V58)), V58, U58), W58, Holiday_Dates) <= 0, 1, NETWORKDAYS(IF(NOT(ISBLANK(V58)), V58, U58), W58, Holiday_Dates) - IF(IF(NOT(ISBLANK(V58)), V58, U58) = W58, 0, 1) ) ) ), "" ) | AB58: =IFERROR( IF( OR(ISBLANK(W58), ISBLANK(X58)), "", MAX( 1, IF( NETWORKDAYS(W58, X58, Holiday_Dates) <= 0, 1, NETWORKDAYS(W58, X58, Holiday_Dates) - IF(W58 = X58, 0, 1) ) ) ), "" ) | BB58: =SUM(AR58,AT58,AV58) -> 0 | BC58: =SUM(AS58,AU58,AW58) -> 0
A59: Pampanga | B59: San Luis | C59: =CONCATENATE(A59,","," ",B59) -> Pampanga, San Luis | D59: MBA | E59: 4th | F59: 15.038968 | G59: 120.78928 | H59: =CONCATENATE(F59,",",G59) -> 15.038968,120.789279 | I59: Municipal / City Plan | J59: NSWMC RESO NO. 1113 SERIES OF 2018 | K59: 2018 - 2027 | L59: 2018 | M59: 2027 | O59: Glaiza S.Gaza | Q59: Sherwin John Y. Loquellano | R59: 5.May | Y59: =IFERROR( IF( OR(ISBLANK(T59), ISBLANK(U59)), "", MAX( 1, IF( NETWORKDAYS(T59, U59, Holiday_Dates) <= 0, 1, NETWORKDAYS(T59, U59, Holiday_Dates) - IF(T59 = U59, 0, 1) ) ) ), "" ) | Z59: =IF( OR(ISBLANK(U59), ISBLANK(V59)), "", MAX( 1, IF( NETWORKDAYS(U59, V59, Holiday_Dates) <= 0, 1, NETWORKDAYS(U59, V59, Holiday_Dates) - IF(U59 = V59, 0, 1) ) ) ) | AA59: =IFERROR( IF( OR(ISBLANK(W59), AND(ISBLANK(U59), ISBLANK(V59))), "", MAX( 1, IF( NETWORKDAYS(IF(NOT(ISBLANK(V59)), V59, U59), W59, Holiday_Dates) <= 0, 1, NETWORKDAYS(IF(NOT(ISBLANK(V59)), V59, U59), W59, Holiday_Dates) - IF(IF(NOT(ISBLANK(V59)), V59, U59) = W59, 0, 1) ) ) ), "" ) | AB59: =IFERROR( IF( OR(ISBLANK(W59), ISBLANK(X59)), "", MAX( 1, IF( NETWORKDAYS(W59, X59, Holiday_Dates) <= 0, 1, NETWORKDAYS(W59, X59, Holiday_Dates) - IF(W59 = X59, 0, 1) ) ) ), "" ) | BB59: =SUM(AR59,AT59,AV59) -> 0 | BC59: =SUM(AS59,AU59,AW59) -> 0
A60: Tarlac | B60: Mayantoc | C60: =CONCATENATE(A60,","," ",B60) -> Tarlac, Mayantoc | D60: OUTSIDE MBA | E60: 1st | F60: 15.618876 | G60: 120.37812 | H60: =CONCATENATE(F60,",",G60) -> 15.6188757,120.3781159 | I60: Municipal / City Plan | J60: NSWMC Reso No. 1359 s 2019 | K60: 2017 - 2027 | L60: 2019 | M60: 2027 | O60: Jasper Kieht B. Pili | Q60: Jan Emerson C. Gonzales | R60: 5.May | Y60: =IFERROR( IF( OR(ISBLANK(T60), ISBLANK(U60)), "", MAX( 1, IF( NETWORKDAYS(T60, U60, Holiday_Dates) <= 0, 1, NETWORKDAYS(T60, U60, Holiday_Dates) - IF(T60 = U60, 0, 1) ) ) ), "" ) | Z60: =IF( OR(ISBLANK(U60), ISBLANK(V60)), "", MAX( 1, IF( NETWORKDAYS(U60, V60, Holiday_Dates) <= 0, 1, NETWORKDAYS(U60, V60, Holiday_Dates) - IF(U60 = V60, 0, 1) ) ) ) | AA60: =IFERROR( IF( OR(ISBLANK(W60), AND(ISBLANK(U60), ISBLANK(V60))), "", MAX( 1, IF( NETWORKDAYS(IF(NOT(ISBLANK(V60)), V60, U60), W60, Holiday_Dates) <= 0, 1, NETWORKDAYS(IF(NOT(ISBLANK(V60)), V60, U60), W60, Holiday_Dates) - IF(IF(NOT(ISBLANK(V60)), V60, U60) = W60, 0, 1) ) ) ), "" ) | AB60: =IFERROR( IF( OR(ISBLANK(W60), ISBLANK(X60)), "", MAX( 1, IF( NETWORKDAYS(W60, X60, Holiday_Dates) <= 0, 1, NETWORKDAYS(W60, X60, Holiday_Dates) - IF(W60 = X60, 0, 1) ) ) ), "" ) | BB60: =SUM(AR60,AT60,AV60) -> 0 | BC60: =SUM(AS60,AU60,AW60) -> 0
A61: Zambales | B61: Iba | C61: =CONCATENATE(A61,","," ",B61) -> Zambales, Iba | D61: OUTSIDE MBA | E61: 2nd | F61: 15.327714 | G61: 119.97639 | H61: =CONCATENATE(F61,",",G61) -> 15.327714,119.976389 | I61: Municipal / City Plan | J61: NSWMC RESO NO. 1445 SERIES OF 2021 | K61: 2020 - 2029 | L61: 2021 | M61: 2029 | O61: Larizze A. Santos | Q61: Jun D. Guillermo | R61: 5.May | Y61: =IFERROR( IF( OR(ISBLANK(T61), ISBLANK(U61)), "", MAX( 1, IF( NETWORKDAYS(T61, U61, Holiday_Dates) <= 0, 1, NETWORKDAYS(T61, U61, Holiday_Dates) - IF(T61 = U61, 0, 1) ) ) ), "" ) | Z61: =IF( OR(ISBLANK(U61), ISBLANK(V61)), "", MAX( 1, IF( NETWORKDAYS(U61, V61, Holiday_Dates) <= 0, 1, NETWORKDAYS(U61, V61, Holiday_Dates) - IF(U61 = V61, 0, 1) ) ) ) | AA61: =IFERROR( IF( OR(ISBLANK(W61), AND(ISBLANK(U61), ISBLANK(V61))), "", MAX( 1, IF( NETWORKDAYS(IF(NOT(ISBLANK(V61)), V61, U61), W61, Holiday_Dates) <= 0, 1, NETWORKDAYS(IF(NOT(ISBLANK(V61)), V61, U61), W61, Holiday_Dates) - IF(IF(NOT(ISBLANK(V61)), V61, U61) = W61, 0, 1) ) ) ), "" ) | AB61: =IFERROR( IF( OR(ISBLANK(W61), ISBLANK(X61)), "", MAX( 1, IF( NETWORKDAYS(W61, X61, Holiday_Dates) <= 0, 1, NETWORKDAYS(W61, X61, Holiday_Dates) - IF(W61 = X61, 0, 1) ) ) ), "" ) | BB61: =SUM(AR61,AT61,AV61) -> 0 | BC61: =SUM(AS61,AU61,AW61) -> 0
A62: Tarlac | B62: Paniqui | C62: =CONCATENATE(A62,","," ",B62) -> Tarlac, Paniqui | D62: OUTSIDE MBA | E62: 1st | F62: 15.667914 | G62: 120.57778 | H62: =CONCATENATE(F62,",",G62) -> 15.6679138,120.5777846 | I62: Municipal / City Plan | J62: 1300 series of 2019 | K62: 2019 - 2028 | L62: 2019 | M62: 2028 | O62: Joshua A. Capones | Q62: Jan Emerson C. Gonzales | R62: 5.May | Y62: =IFERROR( IF( OR(ISBLANK(T62), ISBLANK(U62)), "", MAX( 1, IF( NETWORKDAYS(T62, U62, Holiday_Dates) <= 0, 1, NETWORKDAYS(T62, U62, Holiday_Dates) - IF(T62 = U62, 0, 1) ) ) ), "" ) | Z62: =IF( OR(ISBLANK(U62), ISBLANK(V62)), "", MAX( 1, IF( NETWORKDAYS(U62, V62, Holiday_Dates) <= 0, 1, NETWORKDAYS(U62, V62, Holiday_Dates) - IF(U62 = V62, 0, 1) ) ) ) | AA62: =IFERROR( IF( OR(ISBLANK(W62), AND(ISBLANK(U62), ISBLANK(V62))), "", MAX( 1, IF( NETWORKDAYS(IF(NOT(ISBLANK(V62)), V62, U62), W62, Holiday_Dates) <= 0, 1, NETWORKDAYS(IF(NOT(ISBLANK(V62)), V62, U62), W62, Holiday_Dates) - IF(IF(NOT(ISBLANK(V62)), V62, U62) = W62, 0, 1) ) ) ), "" ) | AB62: =IFERROR( IF( OR(ISBLANK(W62), ISBLANK(X62)), "", MAX( 1, IF( NETWORKDAYS(W62, X62, Holiday_Dates) <= 0, 1, NETWORKDAYS(W62, X62, Holiday_Dates) - IF(W62 = X62, 0, 1) ) ) ), "" ) | BB62: =SUM(AR62,AT62,AV62) -> 0 | BC62: =SUM(AS62,AU62,AW62) -> 0
A63: Tarlac | B63: San Jose | C63: =CONCATENATE(A63,","," ",B63) -> Tarlac, San Jose | D63: OUTSIDE MBA | E63: 2nd | F63: 15.477382 | G63: 120.46389 | H63: =CONCATENATE(F63,",",G63) -> 15.477382,120.463888 | I63: Municipal / City Plan | J63: NSWMC RESO NO. 1299 SERIES OF 2019 | K63: 2018 -2027 | L63: 2019 | M63: 2027 | O63: Gretzhen M. Apolonio | Q63: Jan Emerson C. Gonzales | R63: 5.May | Y63: =IFERROR( IF( OR(ISBLANK(T63), ISBLANK(U63)), "", MAX( 1, IF( NETWORKDAYS(T63, U63, Holiday_Dates) <= 0, 1, NETWORKDAYS(T63, U63, Holiday_Dates) - IF(T63 = U63, 0, 1) ) ) ), "" ) | Z63: =IF( OR(ISBLANK(U63), ISBLANK(V63)), "", MAX( 1, IF( NETWORKDAYS(U63, V63, Holiday_Dates) <= 0, 1, NETWORKDAYS(U63, V63, Holiday_Dates) - IF(U63 = V63, 0, 1) ) ) ) | AA63: =IFERROR( IF( OR(ISBLANK(W63), AND(ISBLANK(U63), ISBLANK(V63))), "", MAX( 1, IF( NETWORKDAYS(IF(NOT(ISBLANK(V63)), V63, U63), W63, Holiday_Dates) <= 0, 1, NETWORKDAYS(IF(NOT(ISBLANK(V63)), V63, U63), W63, Holiday_Dates) - IF(IF(NOT(ISBLANK(V63)), V63, U63) = W63, 0, 1) ) ) ), "" ) | AB63: =IFERROR( IF( OR(ISBLANK(W63), ISBLANK(X63)), "", MAX( 1, IF( NETWORKDAYS(W63, X63, Holiday_Dates) <= 0, 1, NETWORKDAYS(W63, X63, Holiday_Dates) - IF(W63 = X63, 0, 1) ) ) ), "" ) | BB63: =SUM(AR63,AT63,AV63) -> 0 | BC63: =SUM(AS63,AU63,AW63) -> 0
A64: Tarlac | B64: Anao | C64: =CONCATENATE(A64,","," ",B64) -> Tarlac, Anao | D64: OUTSIDE MBA | E64: 1st | F64: 15.730196 | G64: 120.6266 | H64: =CONCATENATE(F64,",",G64) -> 15.730196,120.6265988 | I64: Municipal / City Plan | J64: 1089 s.2018 | K64: 2018 - 2027 | L64: 2018 | M64: 2027 | O64: Jasper Kieht B. Pili | Q64: Jan Emerson C. Gonzales | R64: 6.June | Y64: =IFERROR( IF( OR(ISBLANK(T64), ISBLANK(U64)), "", MAX( 1, IF( NETWORKDAYS(T64, U64, Holiday_Dates) <= 0, 1, NETWORKDAYS(T64, U64, Holiday_Dates) - IF(T64 = U64, 0, 1) ) ) ), "" ) | Z64: =IF( OR(ISBLANK(U64), ISBLANK(V64)), "", MAX( 1, IF( NETWORKDAYS(U64, V64, Holiday_Dates) <= 0, 1, NETWORKDAYS(U64, V64, Holiday_Dates) - IF(U64 = V64, 0, 1) ) ) ) | AA64: =IFERROR( IF( OR(ISBLANK(W64), AND(ISBLANK(U64), ISBLANK(V64))), "", MAX( 1, IF( NETWORKDAYS(IF(NOT(ISBLANK(V64)), V64, U64), W64, Holiday_Dates) <= 0, 1, NETWORKDAYS(IF(NOT(ISBLANK(V64)), V64, U64), W64, Holiday_Dates) - IF(IF(NOT(ISBLANK(V64)), V64, U64) = W64, 0, 1) ) ) ), "" ) | AB64: =IFERROR( IF( OR(ISBLANK(W64), ISBLANK(X64)), "", MAX( 1, IF( NETWORKDAYS(W64, X64, Holiday_Dates) <= 0, 1, NETWORKDAYS(W64, X64, Holiday_Dates) - IF(W64 = X64, 0, 1) ) ) ), "" ) | BB64: =SUM(AR64,AT64,AV64) -> 0 | BC64: =SUM(AS64,AU64,AW64) -> 0
A65: Bataan | B65: Samal | C65: =CONCATENATE(A65,","," ",B65) -> Bataan, Samal | D65: MBA | E65: 1st | F65: 14.768971 | G65: 120.54241 | H65: =CONCATENATE(F65,",",G65) -> 14.768971,120.542407 | I65: Municipal / City Plan | J65: 975 Series of 2017 | K65: 2015 - 2024 | L65: 2017 | M65: 2024 | N65: For Renewal | O65: John-lester Signio | Q65: Christle D. David | R65: 6.June | Y65: =IFERROR( IF( OR(ISBLANK(T65), ISBLANK(U65)), "", MAX( 1, IF( NETWORKDAYS(T65, U65, Holiday_Dates) <= 0, 1, NETWORKDAYS(T65, U65, Holiday_Dates) - IF(T65 = U65, 0, 1) ) ) ), "" ) | Z65: =IF( OR(ISBLANK(U65), ISBLANK(V65)), "", MAX( 1, IF( NETWORKDAYS(U65, V65, Holiday_Dates) <= 0, 1, NETWORKDAYS(U65, V65, Holiday_Dates) - IF(U65 = V65, 0, 1) ) ) ) | AA65: =IFERROR( IF( OR(ISBLANK(W65), AND(ISBLANK(U65), ISBLANK(V65))), "", MAX( 1, IF( NETWORKDAYS(IF(NOT(ISBLANK(V65)), V65, U65), W65, Holiday_Dates) <= 0, 1, NETWORKDAYS(IF(NOT(ISBLANK(V65)), V65, U65), W65, Holiday_Dates) - IF(IF(NOT(ISBLANK(V65)), V65, U65) = W65, 0, 1) ) ) ), "" ) | AB65: =IFERROR( IF( OR(ISBLANK(W65), ISBLANK(X65)), "", MAX( 1, IF( NETWORKDAYS(W65, X65, Holiday_Dates) <= 0, 1, NETWORKDAYS(W65, X65, Holiday_Dates) - IF(W65 = X65, 0, 1) ) ) ), "" ) | BB65: =SUM(AR65,AT65,AV65) -> 0 | BC65: =SUM(AS65,AU65,AW65) -> 0
A66: Bulacan | B66: Norzagaray | C66: =CONCATENATE(A66,","," ",B66) -> Bulacan, Norzagaray | D66: MBA | E66: 6th | F66: 14.905204 | G66: 121.04232 | H66: =CONCATENATE(F66,",",G66) -> 14.90520408,121.0423168 | I66: Municipal / City Plan | J66: 1327 SERIES OF 2019 | K66: 2018 - 2028 | L66: 2019 | M66: 2028 | O66: James Wilson T. Pena | Q66: Diozelle L. Cabalar | R66: 6.June | Y66: =IFERROR( IF( OR(ISBLANK(T66), ISBLANK(U66)), "", MAX( 1, IF( NETWORKDAYS(T66, U66, Holiday_Dates) <= 0, 1, NETWORKDAYS(T66, U66, Holiday_Dates) - IF(T66 = U66, 0, 1) ) ) ), "" ) | Z66: =IF( OR(ISBLANK(U66), ISBLANK(V66)), "", MAX( 1, IF( NETWORKDAYS(U66, V66, Holiday_Dates) <= 0, 1, NETWORKDAYS(U66, V66, Holiday_Dates) - IF(U66 = V66, 0, 1) ) ) ) | AA66: =IFERROR( IF( OR(ISBLANK(W66), AND(ISBLANK(U66), ISBLANK(V66))), "", MAX( 1, IF( NETWORKDAYS(IF(NOT(ISBLANK(V66)), V66, U66), W66, Holiday_Dates) <= 0, 1, NETWORKDAYS(IF(NOT(ISBLANK(V66)), V66, U66), W66, Holiday_Dates) - IF(IF(NOT(ISBLANK(V66)), V66, U66) = W66, 0, 1) ) ) ), "" ) | AB66: =IFERROR( IF( OR(ISBLANK(W66), ISBLANK(X66)), "", MAX( 1, IF( NETWORKDAYS(W66, X66, Holiday_Dates) <= 0, 1, NETWORKDAYS(W66, X66, Holiday_Dates) - IF(W66 = X66, 0, 1) ) ) ), "" ) | BB66: =SUM(AR66,AT66,AV66) -> 0 | BC66: =SUM(AS66,AU66,AW66) -> 0
A67: Bulacan | B67: Obando | C67: =CONCATENATE(A67,","," ",B67) -> Bulacan, Obando | D67: MBA | E67: 4th | F67: 14.709363 | G67: 120.9374 | H67: =CONCATENATE(F67,",",G67) -> 14.709363,120.9374 | I67: Municipal / City Plan | J67: NSWMC RESO NO. 1328 SERIES OF 2019 | K67: 2017 - 2027 | L67: 2019 | M67: 2027 | O67: James Wilson T. Pena | Q67: Diozelle L. Cabalar | R67: 6.June | Y67: =IFERROR( IF( OR(ISBLANK(T67), ISBLANK(U67)), "", MAX( 1, IF( NETWORKDAYS(T67, U67, Holiday_Dates) <= 0, 1, NETWORKDAYS(T67, U67, Holiday_Dates) - IF(T67 = U67, 0, 1) ) ) ), "" ) | Z67: =IF( OR(ISBLANK(U67), ISBLANK(V67)), "", MAX( 1, IF( NETWORKDAYS(U67, V67, Holiday_Dates) <= 0, 1, NETWORKDAYS(U67, V67, Holiday_Dates) - IF(U67 = V67, 0, 1) ) ) ) | AA67: =IFERROR( IF( OR(ISBLANK(W67), AND(ISBLANK(U67), ISBLANK(V67))), "", MAX( 1, IF( NETWORKDAYS(IF(NOT(ISBLANK(V67)), V67, U67), W67, Holiday_Dates) <= 0, 1, NETWORKDAYS(IF(NOT(ISBLANK(V67)), V67, U67), W67, Holiday_Dates) - IF(IF(NOT(ISBLANK(V67)), V67, U67) = W67, 0, 1) ) ) ), "" ) | AB67: =IFERROR( IF( OR(ISBLANK(W67), ISBLANK(X67)), "", MAX( 1, IF( NETWORKDAYS(W67, X67, Holiday_Dates) <= 0, 1, NETWORKDAYS(W67, X67, Holiday_Dates) - IF(W67 = X67, 0, 1) ) ) ), "" ) | BB67: =SUM(AR67,AT67,AV67) -> 0 | BC67: =SUM(AS67,AU67,AW67) -> 0
A68: Bulacan | B68: San Ildefonso | C68: =CONCATENATE(A68,","," ",B68) -> Bulacan, San Ildefonso | D68: MBA | E68: 3rd | F68: 15.077944 | G68: 120.94288 | H68: =CONCATENATE(F68,",",G68) -> 15.07794373,120.9428805 | I68: Municipal / City Plan | J68: 1245 | K68: 2017 - 2027 | L68: 2019 | M68: 2027 | O68: VACANT | Q68: Diozelle L. Cabalar | R68: 6.June | Y68: =IFERROR( IF( OR(ISBLANK(T68), ISBLANK(U68)), "", MAX( 1, IF( NETWORKDAYS(T68, U68, Holiday_Dates) <= 0, 1, NETWORKDAYS(T68, U68, Holiday_Dates) - IF(T68 = U68, 0, 1) ) ) ), "" ) | Z68: =IF( OR(ISBLANK(U68), ISBLANK(V68)), "", MAX( 1, IF( NETWORKDAYS(U68, V68, Holiday_Dates) <= 0, 1, NETWORKDAYS(U68, V68, Holiday_Dates) - IF(U68 = V68, 0, 1) ) ) ) | AA68: =IFERROR( IF( OR(ISBLANK(W68), AND(ISBLANK(U68), ISBLANK(V68))), "", MAX( 1, IF( NETWORKDAYS(IF(NOT(ISBLANK(V68)), V68, U68), W68, Holiday_Dates) <= 0, 1, NETWORKDAYS(IF(NOT(ISBLANK(V68)), V68, U68), W68, Holiday_Dates) - IF(IF(NOT(ISBLANK(V68)), V68, U68) = W68, 0, 1) ) ) ), "" ) | AB68: =IFERROR( IF( OR(ISBLANK(W68), ISBLANK(X68)), "", MAX( 1, IF( NETWORKDAYS(W68, X68, Holiday_Dates) <= 0, 1, NETWORKDAYS(W68, X68, Holiday_Dates) - IF(W68 = X68, 0, 1) ) ) ), "" ) | BB68: =SUM(AR68,AT68,AV68) -> 0 | BC68: =SUM(AS68,AU68,AW68) -> 0
A69: Bulacan | B69: San Miguel | C69: =CONCATENATE(A69,","," ",B69) -> Bulacan, San Miguel | D69: MBA | E69: 3rd | F69: 15.140474 | G69: 120.97742 | H69: =CONCATENATE(F69,",",G69) -> 15.140474,120.977422 | I69: Municipal / City Plan | J69: NSWMC RESO NO. 179A S 2015 | K69: 2015 - 2025 | L69: 2015 | M69: 2025 | N69: For Renewal | O69: VACANT | Q69: Diozelle L. Cabalar | R69: 6.June | Y69: =IFERROR( IF( OR(ISBLANK(T69), ISBLANK(U69)), "", MAX( 1, IF( NETWORKDAYS(T69, U69, Holiday_Dates) <= 0, 1, NETWORKDAYS(T69, U69, Holiday_Dates) - IF(T69 = U69, 0, 1) ) ) ), "" ) | Z69: =IF( OR(ISBLANK(U69), ISBLANK(V69)), "", MAX( 1, IF( NETWORKDAYS(U69, V69, Holiday_Dates) <= 0, 1, NETWORKDAYS(U69, V69, Holiday_Dates) - IF(U69 = V69, 0, 1) ) ) ) | AA69: =IFERROR( IF( OR(ISBLANK(W69), AND(ISBLANK(U69), ISBLANK(V69))), "", MAX( 1, IF( NETWORKDAYS(IF(NOT(ISBLANK(V69)), V69, U69), W69, Holiday_Dates) <= 0, 1, NETWORKDAYS(IF(NOT(ISBLANK(V69)), V69, U69), W69, Holiday_Dates) - IF(IF(NOT(ISBLANK(V69)), V69, U69) = W69, 0, 1) ) ) ), "" ) | AB69: =IFERROR( IF( OR(ISBLANK(W69), ISBLANK(X69)), "", MAX( 1, IF( NETWORKDAYS(W69, X69, Holiday_Dates) <= 0, 1, NETWORKDAYS(W69, X69, Holiday_Dates) - IF(W69 = X69, 0, 1) ) ) ), "" ) | BB69: =SUM(AR69,AT69,AV69) -> 0 | BC69: =SUM(AS69,AU69,AW69) -> 0
A70: Nueva Ecija | B70: City Of Gapan | C70: =CONCATENATE(A70,","," ",B70) -> Nueva Ecija, City Of Gapan | D70: MBA | E70: 4th | F70: 15.293716 | G70: 120.9486 | H70: =CONCATENATE(F70,",",G70) -> 15.293716,120.948601 | I70: Municipal / City Plan | J70: 1064 S. 2018 | K70: 2017 - 2026 | L70: 2018 | M70: 2026 | O70: Christine Ann V. Ramos | Q70: Zosimo P. Suyat | R70: 6.June | Y70: =IFERROR( IF( OR(ISBLANK(T70), ISBLANK(U70)), "", MAX( 1, IF( NETWORKDAYS(T70, U70, Holiday_Dates) <= 0, 1, NETWORKDAYS(T70, U70, Holiday_Dates) - IF(T70 = U70, 0, 1) ) ) ), "" ) | Z70: =IF( OR(ISBLANK(U70), ISBLANK(V70)), "", MAX( 1, IF( NETWORKDAYS(U70, V70, Holiday_Dates) <= 0, 1, NETWORKDAYS(U70, V70, Holiday_Dates) - IF(U70 = V70, 0, 1) ) ) ) | AA70: =IFERROR( IF( OR(ISBLANK(W70), AND(ISBLANK(U70), ISBLANK(V70))), "", MAX( 1, IF( NETWORKDAYS(IF(NOT(ISBLANK(V70)), V70, U70), W70, Holiday_Dates) <= 0, 1, NETWORKDAYS(IF(NOT(ISBLANK(V70)), V70, U70), W70, Holiday_Dates) - IF(IF(NOT(ISBLANK(V70)), V70, U70) = W70, 0, 1) ) ) ), "" ) | AB70: =IFERROR( IF( OR(ISBLANK(W70), ISBLANK(X70)), "", MAX( 1, IF( NETWORKDAYS(W70, X70, Holiday_Dates) <= 0, 1, NETWORKDAYS(W70, X70, Holiday_Dates) - IF(W70 = X70, 0, 1) ) ) ), "" ) | BB70: =SUM(AR70,AT70,AV70) -> 0 | BC70: =SUM(AS70,AU70,AW70) -> 0
A71: Nueva Ecija | B71: Rizal | C71: =CONCATENATE(A71,","," ",B71) -> Nueva Ecija, Rizal | D71: MBA | E71: 2nd | F71: 15.707877 | G71: 121.10188 | H71: =CONCATENATE(F71,",",G71) -> 15.707877,121.101882 | I71: Municipal / City Plan | J71: 1288 SERIES 2019 | K71: 2017 - 2027 | L71: 2019 | M71: 2027 | O71: Hosannah R. Sabio | Q71: Zosimo P. Suyat | R71: 6.June | Y71: =IFERROR( IF( OR(ISBLANK(T71), ISBLANK(U71)), "", MAX( 1, IF( NETWORKDAYS(T71, U71, Holiday_Dates) <= 0, 1, NETWORKDAYS(T71, U71, Holiday_Dates) - IF(T71 = U71, 0, 1) ) ) ), "" ) | Z71: =IF( OR(ISBLANK(U71), ISBLANK(V71)), "", MAX( 1, IF( NETWORKDAYS(U71, V71, Holiday_Dates) <= 0, 1, NETWORKDAYS(U71, V71, Holiday_Dates) - IF(U71 = V71, 0, 1) ) ) ) | AA71: =IFERROR( IF( OR(ISBLANK(W71), AND(ISBLANK(U71), ISBLANK(V71))), "", MAX( 1, IF( NETWORKDAYS(IF(NOT(ISBLANK(V71)), V71, U71), W71, Holiday_Dates) <= 0, 1, NETWORKDAYS(IF(NOT(ISBLANK(V71)), V71, U71), W71, Holiday_Dates) - IF(IF(NOT(ISBLANK(V71)), V71, U71) = W71, 0, 1) ) ) ), "" ) | AB71: =IFERROR( IF( OR(ISBLANK(W71), ISBLANK(X71)), "", MAX( 1, IF( NETWORKDAYS(W71, X71, Holiday_Dates) <= 0, 1, NETWORKDAYS(W71, X71, Holiday_Dates) - IF(W71 = X71, 0, 1) ) ) ), "" ) | BB71: =SUM(AR71,AT71,AV71) -> 0 | BC71: =SUM(AS71,AU71,AW71) -> 0
A72: Nueva Ecija | B72: Talavera | C72: =CONCATENATE(A72,","," ",B72) -> Nueva Ecija, Talavera | D72: MBA | E72: 1st | F72: 15.584241 | G72: 120.9184 | H72: =CONCATENATE(F72,",",G72) -> 15.584241,120.918404 | I72: Municipal / City Plan | J72: 1063 s. 2018 | K72: 2017 - 2026 | L72: 2018 | M72: 2026 | O72: Gem C. Vicencio | Q72: Zosimo P. Suyat | R72: 6.June | Y72: =IFERROR( IF( OR(ISBLANK(T72), ISBLANK(U72)), "", MAX( 1, IF( NETWORKDAYS(T72, U72, Holiday_Dates) <= 0, 1, NETWORKDAYS(T72, U72, Holiday_Dates) - IF(T72 = U72, 0, 1) ) ) ), "" ) | Z72: =IF( OR(ISBLANK(U72), ISBLANK(V72)), "", MAX( 1, IF( NETWORKDAYS(U72, V72, Holiday_Dates) <= 0, 1, NETWORKDAYS(U72, V72, Holiday_Dates) - IF(U72 = V72, 0, 1) ) ) ) | AA72: =IFERROR( IF( OR(ISBLANK(W72), AND(ISBLANK(U72), ISBLANK(V72))), "", MAX( 1, IF( NETWORKDAYS(IF(NOT(ISBLANK(V72)), V72, U72), W72, Holiday_Dates) <= 0, 1, NETWORKDAYS(IF(NOT(ISBLANK(V72)), V72, U72), W72, Holiday_Dates) - IF(IF(NOT(ISBLANK(V72)), V72, U72) = W72, 0, 1) ) ) ), "" ) | AB72: =IFERROR( IF( OR(ISBLANK(W72), ISBLANK(X72)), "", MAX( 1, IF( NETWORKDAYS(W72, X72, Holiday_Dates) <= 0, 1, NETWORKDAYS(W72, X72, Holiday_Dates) - IF(W72 = X72, 0, 1) ) ) ), "" ) | BB72: =SUM(AR72,AT72,AV72) -> 0 | BC72: =SUM(AS72,AU72,AW72) -> 0
A73: Pampanga | B73: Floridablanca | C73: =CONCATENATE(A73,","," ",B73) -> Pampanga, Floridablanca | D73: MBA | E73: 2nd | F73: 14.9745 | G73: 120.5281 | H73: =CONCATENATE(F73,",",G73) -> 14.9745,120.5281 | I73: Municipal / City Plan | J73: NSWMC NO. 684 A S 2018 | K73: 2018 - 2027 | L73: 2018 | M73: 2027 | O73: Elyza A. Evilla | Q73: Sherwin John Y. Loquellano | R73: 6.June | Y73: =IFERROR( IF( OR(ISBLANK(T73), ISBLANK(U73)), "", MAX( 1, IF( NETWORKDAYS(T73, U73, Holiday_Dates) <= 0, 1, NETWORKDAYS(T73, U73, Holiday_Dates) - IF(T73 = U73, 0, 1) ) ) ), "" ) | Z73: =IF( OR(ISBLANK(U73), ISBLANK(V73)), "", MAX( 1, IF( NETWORKDAYS(U73, V73, Holiday_Dates) <= 0, 1, NETWORKDAYS(U73, V73, Holiday_Dates) - IF(U73 = V73, 0, 1) ) ) ) | AA73: =IFERROR( IF( OR(ISBLANK(W73), AND(ISBLANK(U73), ISBLANK(V73))), "", MAX( 1, IF( NETWORKDAYS(IF(NOT(ISBLANK(V73)), V73, U73), W73, Holiday_Dates) <= 0, 1, NETWORKDAYS(IF(NOT(ISBLANK(V73)), V73, U73), W73, Holiday_Dates) - IF(IF(NOT(ISBLANK(V73)), V73, U73) = W73, 0, 1) ) ) ), "" ) | AB73: =IFERROR( IF( OR(ISBLANK(W73), ISBLANK(X73)), "", MAX( 1, IF( NETWORKDAYS(W73, X73, Holiday_Dates) <= 0, 1, NETWORKDAYS(W73, X73, Holiday_Dates) - IF(W73 = X73, 0, 1) ) ) ), "" ) | BB73: =SUM(AR73,AT73,AV73) -> 0 | BC73: =SUM(AS73,AU73,AW73) -> 0
A74: Pampanga | B74: San Simon | C74: =CONCATENATE(A74,","," ",B74) -> Pampanga, San Simon | D74: MBA | E74: 4th | F74: 14.9848 | G74: 120.7514 | H74: =CONCATENATE(F74,",",G74) -> 14.9848,120.7514 | I74: Municipal / City Plan | J74: 1333 series of 2019 | K74: 2017 - 2028 | L74: 2019 | M74: 2028 | O74: Glaiza S.Gaza | Q74: Sherwin John Y. Loquellano | R74: 6.June | Y74: =IFERROR( IF( OR(ISBLANK(T74), ISBLANK(U74)), "", MAX( 1, IF( NETWORKDAYS(T74, U74, Holiday_Dates) <= 0, 1, NETWORKDAYS(T74, U74, Holiday_Dates) - IF(T74 = U74, 0, 1) ) ) ), "" ) | Z74: =IF( OR(ISBLANK(U74), ISBLANK(V74)), "", MAX( 1, IF( NETWORKDAYS(U74, V74, Holiday_Dates) <= 0, 1, NETWORKDAYS(U74, V74, Holiday_Dates) - IF(U74 = V74, 0, 1) ) ) ) | AA74: =IFERROR( IF( OR(ISBLANK(W74), AND(ISBLANK(U74), ISBLANK(V74))), "", MAX( 1, IF( NETWORKDAYS(IF(NOT(ISBLANK(V74)), V74, U74), W74, Holiday_Dates) <= 0, 1, NETWORKDAYS(IF(NOT(ISBLANK(V74)), V74, U74), W74, Holiday_Dates) - IF(IF(NOT(ISBLANK(V74)), V74, U74) = W74, 0, 1) ) ) ), "" ) | AB74: =IFERROR( IF( OR(ISBLANK(W74), ISBLANK(X74)), "", MAX( 1, IF( NETWORKDAYS(W74, X74, Holiday_Dates) <= 0, 1, NETWORKDAYS(W74, X74, Holiday_Dates) - IF(W74 = X74, 0, 1) ) ) ), "" ) | BB74: =SUM(AR74,AT74,AV74) -> 0 | BC74: =SUM(AS74,AU74,AW74) -> 0
A75: Pampanga | B75: Santa Ana | C75: =CONCATENATE(A75,","," ",B75) -> Pampanga, Santa Ana | D75: MBA | E75: 3rd | F75: 15.0839 | G75: 120.7631 | H75: =CONCATENATE(F75,",",G75) -> 15.0839,120.7631 | I75: Municipal / City Plan | J75: 1244 of 2019 | K75: 2016 - 2027 | L75: 2019 | M75: 2027 | O75: Roger T. Encarnacion II | Q75: Jun D. Guillermo | R75: 6.June | Y75: =IFERROR( IF( OR(ISBLANK(T75), ISBLANK(U75)), "", MAX( 1, IF( NETWORKDAYS(T75, U75, Holiday_Dates) <= 0, 1, NETWORKDAYS(T75, U75, Holiday_Dates) - IF(T75 = U75, 0, 1) ) ) ), "" ) | Z75: =IF( OR(ISBLANK(U75), ISBLANK(V75)), "", MAX( 1, IF( NETWORKDAYS(U75, V75, Holiday_Dates) <= 0, 1, NETWORKDAYS(U75, V75, Holiday_Dates) - IF(U75 = V75, 0, 1) ) ) ) | AA75: =IFERROR( IF( OR(ISBLANK(W75), AND(ISBLANK(U75), ISBLANK(V75))), "", MAX( 1, IF( NETWORKDAYS(IF(NOT(ISBLANK(V75)), V75, U75), W75, Holiday_Dates) <= 0, 1, NETWORKDAYS(IF(NOT(ISBLANK(V75)), V75, U75), W75, Holiday_Dates) - IF(IF(NOT(ISBLANK(V75)), V75, U75) = W75, 0, 1) ) ) ), "" ) | AB75: =IFERROR( IF( OR(ISBLANK(W75), ISBLANK(X75)), "", MAX( 1, IF( NETWORKDAYS(W75, X75, Holiday_Dates) <= 0, 1, NETWORKDAYS(W75, X75, Holiday_Dates) - IF(W75 = X75, 0, 1) ) ) ), "" ) | BB75: =SUM(AR75,AT75,AV75) -> 0 | BC75: =SUM(AS75,AU75,AW75) -> 0
A76: Tarlac | B76: Pura | C76: =CONCATENATE(A76,","," ",B76) -> Tarlac, Pura | D76: OUTSIDE MBA | E76: 1st | F76: 15.623962 | G76: 120.64759 | H76: =CONCATENATE(F76,",",G76) -> 15.623962,120.647586 | I76: Municipal / City Plan | J76: 1335 series of 2019 | K76: 2018 - 2027 | L76: 2019 | M76: 2027 | O76: Joshua A. Capones | Q76: Jan Emerson C. Gonzales | R76: 6.June | Y76: =IFERROR( IF( OR(ISBLANK(T76), ISBLANK(U76)), "", MAX( 1, IF( NETWORKDAYS(T76, U76, Holiday_Dates) <= 0, 1, NETWORKDAYS(T76, U76, Holiday_Dates) - IF(T76 = U76, 0, 1) ) ) ), "" ) | Z76: =IF( OR(ISBLANK(U76), ISBLANK(V76)), "", MAX( 1, IF( NETWORKDAYS(U76, V76, Holiday_Dates) <= 0, 1, NETWORKDAYS(U76, V76, Holiday_Dates) - IF(U76 = V76, 0, 1) ) ) ) | AA76: =IFERROR( IF( OR(ISBLANK(W76), AND(ISBLANK(U76), ISBLANK(V76))), "", MAX( 1, IF( NETWORKDAYS(IF(NOT(ISBLANK(V76)), V76, U76), W76, Holiday_Dates) <= 0, 1, NETWORKDAYS(IF(NOT(ISBLANK(V76)), V76, U76), W76, Holiday_Dates) - IF(IF(NOT(ISBLANK(V76)), V76, U76) = W76, 0, 1) ) ) ), "" ) | AB76: =IFERROR( IF( OR(ISBLANK(W76), ISBLANK(X76)), "", MAX( 1, IF( NETWORKDAYS(W76, X76, Holiday_Dates) <= 0, 1, NETWORKDAYS(W76, X76, Holiday_Dates) - IF(W76 = X76, 0, 1) ) ) ), "" ) | BB76: =SUM(AR76,AT76,AV76) -> 0 | BC76: =SUM(AS76,AU76,AW76) -> 0
A77: Zambales | B77: Masinloc | C77: =CONCATENATE(A77,","," ",B77) -> Zambales, Masinloc | D77: OUTSIDE MBA | E77: 2nd | F77: 15.532744 | G77: 119.95791 | H77: =CONCATENATE(F77,",",G77) -> 15.532744,119.957914 | I77: Municipal / City Plan | J77: 1348 series of 2019 | K77: 2019 - 2028 | L77: 2019 | M77: 2028 | O77: Ryan Ace R. Angel | Q77: Jun D. Guillermo | R77: 6.June | Y77: =IFERROR( IF( OR(ISBLANK(T77), ISBLANK(U77)), "", MAX( 1, IF( NETWORKDAYS(T77, U77, Holiday_Dates) <= 0, 1, NETWORKDAYS(T77, U77, Holiday_Dates) - IF(T77 = U77, 0, 1) ) ) ), "" ) | Z77: =IF( OR(ISBLANK(U77), ISBLANK(V77)), "", MAX( 1, IF( NETWORKDAYS(U77, V77, Holiday_Dates) <= 0, 1, NETWORKDAYS(U77, V77, Holiday_Dates) - IF(U77 = V77, 0, 1) ) ) ) | AA77: =IFERROR( IF( OR(ISBLANK(W77), AND(ISBLANK(U77), ISBLANK(V77))), "", MAX( 1, IF( NETWORKDAYS(IF(NOT(ISBLANK(V77)), V77, U77), W77, Holiday_Dates) <= 0, 1, NETWORKDAYS(IF(NOT(ISBLANK(V77)), V77, U77), W77, Holiday_Dates) - IF(IF(NOT(ISBLANK(V77)), V77, U77) = W77, 0, 1) ) ) ), "" ) | AB77: =IFERROR( IF( OR(ISBLANK(W77), ISBLANK(X77)), "", MAX( 1, IF( NETWORKDAYS(W77, X77, Holiday_Dates) <= 0, 1, NETWORKDAYS(W77, X77, Holiday_Dates) - IF(W77 = X77, 0, 1) ) ) ), "" ) | BB77: =SUM(AR77,AT77,AV77) -> 0 | BC77: =SUM(AS77,AU77,AW77) -> 0
A78: Tarlac | B78: Santa Ignacia | C78: =CONCATENATE(A78,","," ",B78) -> Tarlac, Santa Ignacia | D78: OUTSIDE MBA | E78: 1st | F78: 15.616387 | G78: 120.43469 | H78: =CONCATENATE(F78,",",G78) -> 15.616387,120.434693 | I78: Municipal / City Plan | J78: 1334 series of 2019 | K78: 2018 - 2027 | L78: 2019 | M78: 2027 | O78: Joshua A. Capones | Q78: Jan Emerson C. Gonzales | R78: 6.June | Y78: =IFERROR( IF( OR(ISBLANK(T78), ISBLANK(U78)), "", MAX( 1, IF( NETWORKDAYS(T78, U78, Holiday_Dates) <= 0, 1, NETWORKDAYS(T78, U78, Holiday_Dates) - IF(T78 = U78, 0, 1) ) ) ), "" ) | Z78: =IF( OR(ISBLANK(U78), ISBLANK(V78)), "", MAX( 1, IF( NETWORKDAYS(U78, V78, Holiday_Dates) <= 0, 1, NETWORKDAYS(U78, V78, Holiday_Dates) - IF(U78 = V78, 0, 1) ) ) ) | AA78: =IFERROR( IF( OR(ISBLANK(W78), AND(ISBLANK(U78), ISBLANK(V78))), "", MAX( 1, IF( NETWORKDAYS(IF(NOT(ISBLANK(V78)), V78, U78), W78, Holiday_Dates) <= 0, 1, NETWORKDAYS(IF(NOT(ISBLANK(V78)), V78, U78), W78, Holiday_Dates) - IF(IF(NOT(ISBLANK(V78)), V78, U78) = W78, 0, 1) ) ) ), "" ) | AB78: =IFERROR( IF( OR(ISBLANK(W78), ISBLANK(X78)), "", MAX( 1, IF( NETWORKDAYS(W78, X78, Holiday_Dates) <= 0, 1, NETWORKDAYS(W78, X78, Holiday_Dates) - IF(W78 = X78, 0, 1) ) ) ), "" ) | BB78: =SUM(AR78,AT78,AV78) -> 0 | BC78: =SUM(AS78,AU78,AW78) -> 0
A79: Tarlac | B79: Capas | C79: =CONCATENATE(A79,","," ",B79) -> Tarlac, Capas | D79: MBA | E79: 3rd | F79: 15.346305 | G79: 120.59294 | H79: =CONCATENATE(F79,",",G79) -> 15.346305,120.592937 | I79: Municipal / City Plan | J79: 1250 series of 2019 | K79: 2018 - 2027 | L79: 2019 | M79: 2027 | O79: Gretzhen M. Apolonio | Q79: Jan Emerson C. Gonzales | Y79: =IFERROR( IF( OR(ISBLANK(T79), ISBLANK(U79)), "", MAX( 1, IF( NETWORKDAYS(T79, U79, Holiday_Dates) <= 0, 1, NETWORKDAYS(T79, U79, Holiday_Dates) - IF(T79 = U79, 0, 1) ) ) ), "" ) | Z79: =IF( OR(ISBLANK(U79), ISBLANK(V79)), "", MAX( 1, IF( NETWORKDAYS(U79, V79, Holiday_Dates) <= 0, 1, NETWORKDAYS(U79, V79, Holiday_Dates) - IF(U79 = V79, 0, 1) ) ) ) | AA79: =IFERROR( IF( OR(ISBLANK(W79), AND(ISBLANK(U79), ISBLANK(V79))), "", MAX( 1, IF( NETWORKDAYS(IF(NOT(ISBLANK(V79)), V79, U79), W79, Holiday_Dates) <= 0, 1, NETWORKDAYS(IF(NOT(ISBLANK(V79)), V79, U79), W79, Holiday_Dates) - IF(IF(NOT(ISBLANK(V79)), V79, U79) = W79, 0, 1) ) ) ), "" ) | AB79: =IFERROR( IF( OR(ISBLANK(W79), ISBLANK(X79)), "", MAX( 1, IF( NETWORKDAYS(W79, X79, Holiday_Dates) <= 0, 1, NETWORKDAYS(W79, X79, Holiday_Dates) - IF(W79 = X79, 0, 1) ) ) ), "" ) | BB79: =SUM(AR79,AT79,AV79) -> 0 | BC79: =SUM(AS79,AU79,AW79) -> 0
A80: Tarlac | B80: City Of Tarlac | C80: =CONCATENATE(A80,","," ",B80) -> Tarlac, City Of Tarlac | D80: MBA | E80: 2nd | F80: 15.486853 | G80: 120.58989 | H80: =CONCATENATE(F80,",",G80) -> 15.486853,120.589888 | I80: Municipal / City Plan | J80: 1251 | K80: 2017 - 2027 | L80: 2019 | M80: 2027 | O80: Joshua A. Capones | Q80: Jan Emerson C. Gonzales | Y80: =IFERROR( IF( OR(ISBLANK(T80), ISBLANK(U80)), "", MAX( 1, IF( NETWORKDAYS(T80, U80, Holiday_Dates) <= 0, 1, NETWORKDAYS(T80, U80, Holiday_Dates) - IF(T80 = U80, 0, 1) ) ) ), "" ) | Z80: =IF( OR(ISBLANK(U80), ISBLANK(V80)), "", MAX( 1, IF( NETWORKDAYS(U80, V80, Holiday_Dates) <= 0, 1, NETWORKDAYS(U80, V80, Holiday_Dates) - IF(U80 = V80, 0, 1) ) ) ) | AA80: =IFERROR( IF( OR(ISBLANK(W80), AND(ISBLANK(U80), ISBLANK(V80))), "", MAX( 1, IF( NETWORKDAYS(IF(NOT(ISBLANK(V80)), V80, U80), W80, Holiday_Dates) <= 0, 1, NETWORKDAYS(IF(NOT(ISBLANK(V80)), V80, U80), W80, Holiday_Dates) - IF(IF(NOT(ISBLANK(V80)), V80, U80) = W80, 0, 1) ) ) ), "" ) | AB80: =IFERROR( IF( OR(ISBLANK(W80), ISBLANK(X80)), "", MAX( 1, IF( NETWORKDAYS(W80, X80, Holiday_Dates) <= 0, 1, NETWORKDAYS(W80, X80, Holiday_Dates) - IF(W80 = X80, 0, 1) ) ) ), "" ) | BB80: =SUM(AR80,AT80,AV80) -> 0 | BC80: =SUM(AS80,AU80,AW80) -> 0
A81: Tarlac | B81: Gerona | C81: =CONCATENATE(A81,","," ",B81) -> Tarlac, Gerona | D81: OUTSIDE MBA | E81: 2nd | F81: 15.606548 | G81: 120.59955 | H81: =CONCATENATE(F81,",",G81) -> 15.606548,120.599554 | I81: Municipal / City Plan | J81: 685-A series of 2019 | K81: 2016 - 2026 | L81: 2019 | M81: 2026 | O81: Joshua A. Capones | Q81: Jan Emerson C. Gonzales | Y81: =IFERROR( IF( OR(ISBLANK(T81), ISBLANK(U81)), "", MAX( 1, IF( NETWORKDAYS(T81, U81, Holiday_Dates) <= 0, 1, NETWORKDAYS(T81, U81, Holiday_Dates) - IF(T81 = U81, 0, 1) ) ) ), "" ) | Z81: =IF( OR(ISBLANK(U81), ISBLANK(V81)), "", MAX( 1, IF( NETWORKDAYS(U81, V81, Holiday_Dates) <= 0, 1, NETWORKDAYS(U81, V81, Holiday_Dates) - IF(U81 = V81, 0, 1) ) ) ) | AA81: =IFERROR( IF( OR(ISBLANK(W81), AND(ISBLANK(U81), ISBLANK(V81))), "", MAX( 1, IF( NETWORKDAYS(IF(NOT(ISBLANK(V81)), V81, U81), W81, Holiday_Dates) <= 0, 1, NETWORKDAYS(IF(NOT(ISBLANK(V81)), V81, U81), W81, Holiday_Dates) - IF(IF(NOT(ISBLANK(V81)), V81, U81) = W81, 0, 1) ) ) ), "" ) | AB81: =IFERROR( IF( OR(ISBLANK(W81), ISBLANK(X81)), "", MAX( 1, IF( NETWORKDAYS(W81, X81, Holiday_Dates) <= 0, 1, NETWORKDAYS(W81, X81, Holiday_Dates) - IF(W81 = X81, 0, 1) ) ) ), "" ) | BB81: =SUM(AR81,AT81,AV81) -> 0 | BC81: =SUM(AS81,AU81,AW81) -> 0
A82: Tarlac | B82: Ramos | C82: =CONCATENATE(A82,","," ",B82) -> Tarlac, Ramos | D82: OUTSIDE MBA | E82: 1st | F82: 15.665793 | G82: 120.63928 | H82: =CONCATENATE(F82,",",G82) -> 15.665793,120.6392786 | I82: Municipal / City Plan | J82: NSWMC RESO NO. 1419 SERIES OF 2021 | K82: 2020 - 2029 | L82: 2021 | M82: 2029 | O82: Jasper Kieht B. Pili | Q82: Jan Emerson C. Gonzales | Y82: =IFERROR( IF( OR(ISBLANK(T82), ISBLANK(U82)), "", MAX( 1, IF( NETWORKDAYS(T82, U82, Holiday_Dates) <= 0, 1, NETWORKDAYS(T82, U82, Holiday_Dates) - IF(T82 = U82, 0, 1) ) ) ), "" ) | Z82: =IF( OR(ISBLANK(U82), ISBLANK(V82)), "", MAX( 1, IF( NETWORKDAYS(U82, V82, Holiday_Dates) <= 0, 1, NETWORKDAYS(U82, V82, Holiday_Dates) - IF(U82 = V82, 0, 1) ) ) ) | AA82: =IFERROR( IF( OR(ISBLANK(W82), AND(ISBLANK(U82), ISBLANK(V82))), "", MAX( 1, IF( NETWORKDAYS(IF(NOT(ISBLANK(V82)), V82, U82), W82, Holiday_Dates) <= 0, 1, NETWORKDAYS(IF(NOT(ISBLANK(V82)), V82, U82), W82, Holiday_Dates) - IF(IF(NOT(ISBLANK(V82)), V82, U82) = W82, 0, 1) ) ) ), "" ) | AB82: =IFERROR( IF( OR(ISBLANK(W82), ISBLANK(X82)), "", MAX( 1, IF( NETWORKDAYS(W82, X82, Holiday_Dates) <= 0, 1, NETWORKDAYS(W82, X82, Holiday_Dates) - IF(W82 = X82, 0, 1) ) ) ), "" ) | BB82: =SUM(AR82,AT82,AV82) -> 0 | BC82: =SUM(AS82,AU82,AW82) -> 0
A83: Aurora | B83: Dilasag | C83: =CONCATENATE(A83,","," ",B83) -> Aurora, Dilasag | D83: OUTSIDE MBA | E83: Lone | F83: 16.392731 | G83: 122.21173 | H83: =CONCATENATE(F83,",",G83) -> 16.392731,122.211731 | I83: Municipal / City Plan | J83: 504 A series of 2018 | K83: 2017 - 2027 | L83: 2018 | M83: 2027 | O83: Queenyvel Laguisma | Q83: Diozelle L. Cabalar | Y83: =IFERROR( IF( OR(ISBLANK(T83), ISBLANK(U83)), "", MAX( 1, IF( NETWORKDAYS(T83, U83, Holiday_Dates) <= 0, 1, NETWORKDAYS(T83, U83, Holiday_Dates) - IF(T83 = U83, 0, 1) ) ) ), "" ) | Z83: =IF( OR(ISBLANK(U83), ISBLANK(V83)), "", MAX( 1, IF( NETWORKDAYS(U83, V83, Holiday_Dates) <= 0, 1, NETWORKDAYS(U83, V83, Holiday_Dates) - IF(U83 = V83, 0, 1) ) ) ) | AA83: =IFERROR( IF( OR(ISBLANK(W83), AND(ISBLANK(U83), ISBLANK(V83))), "", MAX( 1, IF( NETWORKDAYS(IF(NOT(ISBLANK(V83)), V83, U83), W83, Holiday_Dates) <= 0, 1, NETWORKDAYS(IF(NOT(ISBLANK(V83)), V83, U83), W83, Holiday_Dates) - IF(IF(NOT(ISBLANK(V83)), V83, U83) = W83, 0, 1) ) ) ), "" ) | AB83: =IFERROR( IF( OR(ISBLANK(W83), ISBLANK(X83)), "", MAX( 1, IF( NETWORKDAYS(W83, X83, Holiday_Dates) <= 0, 1, NETWORKDAYS(W83, X83, Holiday_Dates) - IF(W83 = X83, 0, 1) ) ) ), "" ) | BB83: =SUM(AR83,AT83,AV83) -> 0 | BC83: =SUM(AS83,AU83,AW83) -> 0
A84: Aurora | B84: Dinalungan | C84: =CONCATENATE(A84,","," ",B84) -> Aurora, Dinalungan | D84: OUTSIDE MBA | E84: Lone | F84: 16.140247 | G84: 121.95705 | H84: =CONCATENATE(F84,",",G84) -> 16.140247,121.957053 | I84: Municipal / City Plan | J84: NSWMC RESO NO. 1368 SERIES OF 2020 | K84: 2017 - 2027 | L84: 2020 | M84: 2027 | O84: Queenyvel Laguisma | Q84: Diozelle L. Cabalar | Y84: =IFERROR( IF( OR(ISBLANK(T84), ISBLANK(U84)), "", MAX( 1, IF( NETWORKDAYS(T84, U84, Holiday_Dates) <= 0, 1, NETWORKDAYS(T84, U84, Holiday_Dates) - IF(T84 = U84, 0, 1) ) ) ), "" ) | Z84: =IF( OR(ISBLANK(U84), ISBLANK(V84)), "", MAX( 1, IF( NETWORKDAYS(U84, V84, Holiday_Dates) <= 0, 1, NETWORKDAYS(U84, V84, Holiday_Dates) - IF(U84 = V84, 0, 1) ) ) ) | AA84: =IFERROR( IF( OR(ISBLANK(W84), AND(ISBLANK(U84), ISBLANK(V84))), "", MAX( 1, IF( NETWORKDAYS(IF(NOT(ISBLANK(V84)), V84, U84), W84, Holiday_Dates) <= 0, 1, NETWORKDAYS(IF(NOT(ISBLANK(V84)), V84, U84), W84, Holiday_Dates) - IF(IF(NOT(ISBLANK(V84)), V84, U84) = W84, 0, 1) ) ) ), "" ) | AB84: =IFERROR( IF( OR(ISBLANK(W84), ISBLANK(X84)), "", MAX( 1, IF( NETWORKDAYS(W84, X84, Holiday_Dates) <= 0, 1, NETWORKDAYS(W84, X84, Holiday_Dates) - IF(W84 = X84, 0, 1) ) ) ), "" ) | BB84: =SUM(AR84,AT84,AV84) -> 0 | BC84: =SUM(AS84,AU84,AW84) -> 0
A85: Aurora | B85: Dingalan | C85: =CONCATENATE(A85,","," ",B85) -> Aurora, Dingalan | D85: OUTSIDE MBA | E85: Lone | F85: 15.388964 | G85: 121.39117 | H85: =CONCATENATE(F85,",",G85) -> 15.388964,121.39117 | I85: Municipal / City Plan | J85: 1234 Series 2019 | K85: 2017 - 2027 | L85: 2019 | M85: 2027 | O85: Nikko Jay M. Valenzuela | Q85: Diozelle L. Cabalar | Y85: =IFERROR( IF( OR(ISBLANK(T85), ISBLANK(U85)), "", MAX( 1, IF( NETWORKDAYS(T85, U85, Holiday_Dates) <= 0, 1, NETWORKDAYS(T85, U85, Holiday_Dates) - IF(T85 = U85, 0, 1) ) ) ), "" ) | Z85: =IF( OR(ISBLANK(U85), ISBLANK(V85)), "", MAX( 1, IF( NETWORKDAYS(U85, V85, Holiday_Dates) <= 0, 1, NETWORKDAYS(U85, V85, Holiday_Dates) - IF(U85 = V85, 0, 1) ) ) ) | AA85: =IFERROR( IF( OR(ISBLANK(W85), AND(ISBLANK(U85), ISBLANK(V85))), "", MAX( 1, IF( NETWORKDAYS(IF(NOT(ISBLANK(V85)), V85, U85), W85, Holiday_Dates) <= 0, 1, NETWORKDAYS(IF(NOT(ISBLANK(V85)), V85, U85), W85, Holiday_Dates) - IF(IF(NOT(ISBLANK(V85)), V85, U85) = W85, 0, 1) ) ) ), "" ) | AB85: =IFERROR( IF( OR(ISBLANK(W85), ISBLANK(X85)), "", MAX( 1, IF( NETWORKDAYS(W85, X85, Holiday_Dates) <= 0, 1, NETWORKDAYS(W85, X85, Holiday_Dates) - IF(W85 = X85, 0, 1) ) ) ), "" ) | BB85: =SUM(AR85,AT85,AV85) -> 0 | BC85: =SUM(AS85,AU85,AW85) -> 0
A86: Aurora | B86: Dipaculao | C86: =CONCATENATE(A86,","," ",B86) -> Aurora, Dipaculao | D86: OUTSIDE MBA | E86: Lone | F86: 15.848967 | G86: 121.53746 | H86: =CONCATENATE(F86,",",G86) -> 15.848967,121.537459 | I86: Municipal / City Plan | J86: NSWMC RESO NO. 502 SERIES OF 2018 | K86: 2017 - 2027 | L86: 2018 | M86: 2027 | O86: Zaila Mae Leander | Q86: Diozelle L. Cabalar | Y86: =IFERROR( IF( OR(ISBLANK(T86), ISBLANK(U86)), "", MAX( 1, IF( NETWORKDAYS(T86, U86, Holiday_Dates) <= 0, 1, NETWORKDAYS(T86, U86, Holiday_Dates) - IF(T86 = U86, 0, 1) ) ) ), "" ) | Z86: =IF( OR(ISBLANK(U86), ISBLANK(V86)), "", MAX( 1, IF( NETWORKDAYS(U86, V86, Holiday_Dates) <= 0, 1, NETWORKDAYS(U86, V86, Holiday_Dates) - IF(U86 = V86, 0, 1) ) ) ) | AA86: =IFERROR( IF( OR(ISBLANK(W86), AND(ISBLANK(U86), ISBLANK(V86))), "", MAX( 1, IF( NETWORKDAYS(IF(NOT(ISBLANK(V86)), V86, U86), W86, Holiday_Dates) <= 0, 1, NETWORKDAYS(IF(NOT(ISBLANK(V86)), V86, U86), W86, Holiday_Dates) - IF(IF(NOT(ISBLANK(V86)), V86, U86) = W86, 0, 1) ) ) ), "" ) | AB86: =IFERROR( IF( OR(ISBLANK(W86), ISBLANK(X86)), "", MAX( 1, IF( NETWORKDAYS(W86, X86, Holiday_Dates) <= 0, 1, NETWORKDAYS(W86, X86, Holiday_Dates) - IF(W86 = X86, 0, 1) ) ) ), "" ) | BB86: =SUM(AR86,AT86,AV86) -> 0 | BC86: =SUM(AS86,AU86,AW86) -> 0
A87: Aurora | B87: San Luis_A | C87: =CONCATENATE(A87,","," ",B87) -> Aurora, San Luis_A | D87: OUTSIDE MBA | E87: Lone | F87: 15.720408 | G87: 121.52094 | H87: =CONCATENATE(F87,",",G87) -> 15.720408,121.520939 | I87: Municipal / City Plan | J87: 857 | K87: 2018 - 2027 | L87: 2018 | M87: 2027 | O87: Zaila Mae Leander | Q87: Diozelle L. Cabalar | Y87: =IFERROR( IF( OR(ISBLANK(T87), ISBLANK(U87)), "", MAX( 1, IF( NETWORKDAYS(T87, U87, Holiday_Dates) <= 0, 1, NETWORKDAYS(T87, U87, Holiday_Dates) - IF(T87 = U87, 0, 1) ) ) ), "" ) | Z87: =IF( OR(ISBLANK(U87), ISBLANK(V87)), "", MAX( 1, IF( NETWORKDAYS(U87, V87, Holiday_Dates) <= 0, 1, NETWORKDAYS(U87, V87, Holiday_Dates) - IF(U87 = V87, 0, 1) ) ) ) | AA87: =IFERROR( IF( OR(ISBLANK(W87), AND(ISBLANK(U87), ISBLANK(V87))), "", MAX( 1, IF( NETWORKDAYS(IF(NOT(ISBLANK(V87)), V87, U87), W87, Holiday_Dates) <= 0, 1, NETWORKDAYS(IF(NOT(ISBLANK(V87)), V87, U87), W87, Holiday_Dates) - IF(IF(NOT(ISBLANK(V87)), V87, U87) = W87, 0, 1) ) ) ), "" ) | AB87: =IFERROR( IF( OR(ISBLANK(W87), ISBLANK(X87)), "", MAX( 1, IF( NETWORKDAYS(W87, X87, Holiday_Dates) <= 0, 1, NETWORKDAYS(W87, X87, Holiday_Dates) - IF(W87 = X87, 0, 1) ) ) ), "" ) | BB87: =SUM(AR87,AT87,AV87) -> 0 | BC87: =SUM(AS87,AU87,AW87) -> 0
A88: Bataan | B88: Abucay | C88: =CONCATENATE(A88,","," ",B88) -> Bataan, Abucay | D88: MBA | E88: 1st | F88: 14.722283 | G88: 120.53544 | H88: =CONCATENATE(F88,",",G88) -> 14.722283,120.535442 | I88: Municipal / City Plan | J88: 1252 Series of 2019 | K88: 2017 -2027 | L88: 2019 | M88: 2027 | O88: Dennis Tolentino | Q88: Christle D. David | Y88: =IFERROR( IF( OR(ISBLANK(T88), ISBLANK(U88)), "", MAX( 1, IF( NETWORKDAYS(T88, U88, Holiday_Dates) <= 0, 1, NETWORKDAYS(T88, U88, Holiday_Dates) - IF(T88 = U88, 0, 1) ) ) ), "" ) | Z88: =IF( OR(ISBLANK(U88), ISBLANK(V88)), "", MAX( 1, IF( NETWORKDAYS(U88, V88, Holiday_Dates) <= 0, 1, NETWORKDAYS(U88, V88, Holiday_Dates) - IF(U88 = V88, 0, 1) ) ) ) | AA88: =IFERROR( IF( OR(ISBLANK(W88), AND(ISBLANK(U88), ISBLANK(V88))), "", MAX( 1, IF( NETWORKDAYS(IF(NOT(ISBLANK(V88)), V88, U88), W88, Holiday_Dates) <= 0, 1, NETWORKDAYS(IF(NOT(ISBLANK(V88)), V88, U88), W88, Holiday_Dates) - IF(IF(NOT(ISBLANK(V88)), V88, U88) = W88, 0, 1) ) ) ), "" ) | AB88: =IFERROR( IF( OR(ISBLANK(W88), ISBLANK(X88)), "", MAX( 1, IF( NETWORKDAYS(W88, X88, Holiday_Dates) <= 0, 1, NETWORKDAYS(W88, X88, Holiday_Dates) - IF(W88 = X88, 0, 1) ) ) ), "" ) | BB88: =SUM(AR88,AT88,AV88) -> 0 | BC88: =SUM(AS88,AU88,AW88) -> 0
A89: Bataan | B89: Hermosa | C89: =CONCATENATE(A89,","," ",B89) -> Bataan, Hermosa | D89: MBA | E89: 1st | F89: 14.830649 | G89: 120.50857 | H89: =CONCATENATE(F89,",",G89) -> 14.830649,120.508569 | I89: Municipal / City Plan | J89: NSWMC Resolution No. 1173 | K89: 2017 - 2027 | L89: 2018 | M89: 2027 | O89: John-lester Signio | Q89: Christle D. David | Y89: =IFERROR( IF( OR(ISBLANK(T89), ISBLANK(U89)), "", MAX( 1, IF( NETWORKDAYS(T89, U89, Holiday_Dates) <= 0, 1, NETWORKDAYS(T89, U89, Holiday_Dates) - IF(T89 = U89, 0, 1) ) ) ), "" ) | Z89: =IF( OR(ISBLANK(U89), ISBLANK(V89)), "", MAX( 1, IF( NETWORKDAYS(U89, V89, Holiday_Dates) <= 0, 1, NETWORKDAYS(U89, V89, Holiday_Dates) - IF(U89 = V89, 0, 1) ) ) ) | AA89: =IFERROR( IF( OR(ISBLANK(W89), AND(ISBLANK(U89), ISBLANK(V89))), "", MAX( 1, IF( NETWORKDAYS(IF(NOT(ISBLANK(V89)), V89, U89), W89, Holiday_Dates) <= 0, 1, NETWORKDAYS(IF(NOT(ISBLANK(V89)), V89, U89), W89, Holiday_Dates) - IF(IF(NOT(ISBLANK(V89)), V89, U89) = W89, 0, 1) ) ) ), "" ) | AB89: =IFERROR( IF( OR(ISBLANK(W89), ISBLANK(X89)), "", MAX( 1, IF( NETWORKDAYS(W89, X89, Holiday_Dates) <= 0, 1, NETWORKDAYS(W89, X89, Holiday_Dates) - IF(W89 = X89, 0, 1) ) ) ), "" ) | BB89: =SUM(AR89,AT89,AV89) -> 0 | BC89: =SUM(AS89,AU89,AW89) -> 0
A90: Bataan | B90: Limay | C90: =CONCATENATE(A90,","," ",B90) -> Bataan, Limay | D90: MBA | E90: 2nd | F90: 14.561871 | G90: 120.59492 | H90: =CONCATENATE(F90,",",G90) -> 14.561871,120.594915 | I90: Municipal / City Plan | J90: No.501-A Series of 2020 | K90: 2019 - 2029 | L90: 2020 | M90: 2029 | O90: Dennis Tolentino | Q90: Christle D. David | Y90: =IFERROR( IF( OR(ISBLANK(T90), ISBLANK(U90)), "", MAX( 1, IF( NETWORKDAYS(T90, U90, Holiday_Dates) <= 0, 1, NETWORKDAYS(T90, U90, Holiday_Dates) - IF(T90 = U90, 0, 1) ) ) ), "" ) | Z90: =IF( OR(ISBLANK(U90), ISBLANK(V90)), "", MAX( 1, IF( NETWORKDAYS(U90, V90, Holiday_Dates) <= 0, 1, NETWORKDAYS(U90, V90, Holiday_Dates) - IF(U90 = V90, 0, 1) ) ) ) | AA90: =IFERROR( IF( OR(ISBLANK(W90), AND(ISBLANK(U90), ISBLANK(V90))), "", MAX( 1, IF( NETWORKDAYS(IF(NOT(ISBLANK(V90)), V90, U90), W90, Holiday_Dates) <= 0, 1, NETWORKDAYS(IF(NOT(ISBLANK(V90)), V90, U90), W90, Holiday_Dates) - IF(IF(NOT(ISBLANK(V90)), V90, U90) = W90, 0, 1) ) ) ), "" ) | AB90: =IFERROR( IF( OR(ISBLANK(W90), ISBLANK(X90)), "", MAX( 1, IF( NETWORKDAYS(W90, X90, Holiday_Dates) <= 0, 1, NETWORKDAYS(W90, X90, Holiday_Dates) - IF(W90 = X90, 0, 1) ) ) ), "" ) | BB90: =SUM(AR90,AT90,AV90) -> 0 | BC90: =SUM(AS90,AU90,AW90) -> 0
A91: Bataan | B91: Morong | C91: =CONCATENATE(A91,","," ",B91) -> Bataan, Morong | D91: MBA | E91: 3rd | F91: 14.678464 | G91: 120.2652 | H91: =CONCATENATE(F91,",",G91) -> 14.678464,120.265204 | I91: Municipal / City Plan | J91: NSWMC Res. No. 1083 Series 2017 | K91: 2017 - 2027 | L91: 2018 | M91: 2027 | O91: Laurence Radasa | Q91: Christle D. David | Y91: =IFERROR( IF( OR(ISBLANK(T91), ISBLANK(U91)), "", MAX( 1, IF( NETWORKDAYS(T91, U91, Holiday_Dates) <= 0, 1, NETWORKDAYS(T91, U91, Holiday_Dates) - IF(T91 = U91, 0, 1) ) ) ), "" ) | Z91: =IF( OR(ISBLANK(U91), ISBLANK(V91)), "", MAX( 1, IF( NETWORKDAYS(U91, V91, Holiday_Dates) <= 0, 1, NETWORKDAYS(U91, V91, Holiday_Dates) - IF(U91 = V91, 0, 1) ) ) ) | AA91: =IFERROR( IF( OR(ISBLANK(W91), AND(ISBLANK(U91), ISBLANK(V91))), "", MAX( 1, IF( NETWORKDAYS(IF(NOT(ISBLANK(V91)), V91, U91), W91, Holiday_Dates) <= 0, 1, NETWORKDAYS(IF(NOT(ISBLANK(V91)), V91, U91), W91, Holiday_Dates) - IF(IF(NOT(ISBLANK(V91)), V91, U91) = W91, 0, 1) ) ) ), "" ) | AB91: =IFERROR( IF( OR(ISBLANK(W91), ISBLANK(X91)), "", MAX( 1, IF( NETWORKDAYS(W91, X91, Holiday_Dates) <= 0, 1, NETWORKDAYS(W91, X91, Holiday_Dates) - IF(W91 = X91, 0, 1) ) ) ), "" ) | BB91: =SUM(AR91,AT91,AV91) -> 0 | BC91: =SUM(AS91,AU91,AW91) -> 0
A92: Bataan | B92: Orani | C92: =CONCATENATE(A92,","," ",B92) -> Bataan, Orani | D92: MBA | E92: 1st | F92: 14.802093 | G92: 120.53664 | H92: =CONCATENATE(F92,",",G92) -> 14.802093,120.536636 | I92: Municipal / City Plan | J92: 1084 series of 2018 | K92: 2017 - 2028 | L92: 2018 | M92: 2028 | O92: John-lester Signio | Q92: Christle D. David | Y92: =IFERROR( IF( OR(ISBLANK(T92), ISBLANK(U92)), "", MAX( 1, IF( NETWORKDAYS(T92, U92, Holiday_Dates) <= 0, 1, NETWORKDAYS(T92, U92, Holiday_Dates) - IF(T92 = U92, 0, 1) ) ) ), "" ) | Z92: =IF( OR(ISBLANK(U92), ISBLANK(V92)), "", MAX( 1, IF( NETWORKDAYS(U92, V92, Holiday_Dates) <= 0, 1, NETWORKDAYS(U92, V92, Holiday_Dates) - IF(U92 = V92, 0, 1) ) ) ) | AA92: =IFERROR( IF( OR(ISBLANK(W92), AND(ISBLANK(U92), ISBLANK(V92))), "", MAX( 1, IF( NETWORKDAYS(IF(NOT(ISBLANK(V92)), V92, U92), W92, Holiday_Dates) <= 0, 1, NETWORKDAYS(IF(NOT(ISBLANK(V92)), V92, U92), W92, Holiday_Dates) - IF(IF(NOT(ISBLANK(V92)), V92, U92) = W92, 0, 1) ) ) ), "" ) | AB92: =IFERROR( IF( OR(ISBLANK(W92), ISBLANK(X92)), "", MAX( 1, IF( NETWORKDAYS(W92, X92, Holiday_Dates) <= 0, 1, NETWORKDAYS(W92, X92, Holiday_Dates) - IF(W92 = X92, 0, 1) ) ) ), "" ) | BB92: =SUM(AR92,AT92,AV92) -> 0 | BC92: =SUM(AS92,AU92,AW92) -> 0
A93: Bulacan | B93: Angat | C93: =CONCATENATE(A93,","," ",B93) -> Bulacan, Angat | D93: MBA | E93: 6th | F93: 14.928065 | G93: 121.02828 | H93: =CONCATENATE(F93,",",G93) -> 14.92806531,121.0282841 | I93: Municipal / City Plan | J93: 1079 Series of 2018 | K93: 2017 - 2027 | L93: 2018 | M93: 2027 | O93: Ronaldo P. Roque, Jr. | Q93: Diozelle L. Cabalar | Y93: =IFERROR( IF( OR(ISBLANK(T93), ISBLANK(U93)), "", MAX( 1, IF( NETWORKDAYS(T93, U93, Holiday_Dates) <= 0, 1, NETWORKDAYS(T93, U93, Holiday_Dates) - IF(T93 = U93, 0, 1) ) ) ), "" ) | Z93: =IF( OR(ISBLANK(U93), ISBLANK(V93)), "", MAX( 1, IF( NETWORKDAYS(U93, V93, Holiday_Dates) <= 0, 1, NETWORKDAYS(U93, V93, Holiday_Dates) - IF(U93 = V93, 0, 1) ) ) ) | AA93: =IFERROR( IF( OR(ISBLANK(W93), AND(ISBLANK(U93), ISBLANK(V93))), "", MAX( 1, IF( NETWORKDAYS(IF(NOT(ISBLANK(V93)), V93, U93), W93, Holiday_Dates) <= 0, 1, NETWORKDAYS(IF(NOT(ISBLANK(V93)), V93, U93), W93, Holiday_Dates) - IF(IF(NOT(ISBLANK(V93)), V93, U93) = W93, 0, 1) ) ) ), "" ) | AB93: =IFERROR( IF( OR(ISBLANK(W93), ISBLANK(X93)), "", MAX( 1, IF( NETWORKDAYS(W93, X93, Holiday_Dates) <= 0, 1, NETWORKDAYS(W93, X93, Holiday_Dates) - IF(W93 = X93, 0, 1) ) ) ), "" ) | BB93: =SUM(AR93,AT93,AV93) -> 0 | BC93: =SUM(AS93,AU93,AW93) -> 0
A94: Bulacan | B94: Bustos | C94: =CONCATENATE(A94,","," ",B94) -> Bulacan, Bustos | D94: MBA | E94: 2nd | F94: 14.953785 | G94: 120.91889 | H94: =CONCATENATE(F94,",",G94) -> 14.95378487,120.9188855 | I94: Municipal / City Plan | J94: 1325 s.2019 | K94: 2017 - 2027 | L94: 2019 | M94: 2027 | O94: Ronaldo P. Roque, Jr. | Q94: Diozelle L. Cabalar | Y94: =IFERROR( IF( OR(ISBLANK(T94), ISBLANK(U94)), "", MAX( 1, IF( NETWORKDAYS(T94, U94, Holiday_Dates) <= 0, 1, NETWORKDAYS(T94, U94, Holiday_Dates) - IF(T94 = U94, 0, 1) ) ) ), "" ) | Z94: =IF( OR(ISBLANK(U94), ISBLANK(V94)), "", MAX( 1, IF( NETWORKDAYS(U94, V94, Holiday_Dates) <= 0, 1, NETWORKDAYS(U94, V94, Holiday_Dates) - IF(U94 = V94, 0, 1) ) ) ) | AA94: =IFERROR( IF( OR(ISBLANK(W94), AND(ISBLANK(U94), ISBLANK(V94))), "", MAX( 1, IF( NETWORKDAYS(IF(NOT(ISBLANK(V94)), V94, U94), W94, Holiday_Dates) <= 0, 1, NETWORKDAYS(IF(NOT(ISBLANK(V94)), V94, U94), W94, Holiday_Dates) - IF(IF(NOT(ISBLANK(V94)), V94, U94) = W94, 0, 1) ) ) ), "" ) | AB94: =IFERROR( IF( OR(ISBLANK(W94), ISBLANK(X94)), "", MAX( 1, IF( NETWORKDAYS(W94, X94, Holiday_Dates) <= 0, 1, NETWORKDAYS(W94, X94, Holiday_Dates) - IF(W94 = X94, 0, 1) ) ) ), "" ) | BB94: =SUM(AR94,AT94,AV94) -> 0 | BC94: =SUM(AS94,AU94,AW94) -> 0
A95: Bulacan | B95: Calumpit | C95: =CONCATENATE(A95,","," ",B95) -> Bulacan, Calumpit | D95: MBA | E95: 1st | F95: 14.91396 | G95: 120.76478 | H95: =CONCATENATE(F95,",",G95) -> 14.91396,120.764777 | I95: Municipal / City Plan | J95: 1082 series of 2018 | K95: 2017 - 2028 | L95: 2018 | M95: 2028 | O95: VACANT | Q95: Diozelle L. Cabalar | Y95: =IFERROR( IF( OR(ISBLANK(T95), ISBLANK(U95)), "", MAX( 1, IF( NETWORKDAYS(T95, U95, Holiday_Dates) <= 0, 1, NETWORKDAYS(T95, U95, Holiday_Dates) - IF(T95 = U95, 0, 1) ) ) ), "" ) | Z95: =IF( OR(ISBLANK(U95), ISBLANK(V95)), "", MAX( 1, IF( NETWORKDAYS(U95, V95, Holiday_Dates) <= 0, 1, NETWORKDAYS(U95, V95, Holiday_Dates) - IF(U95 = V95, 0, 1) ) ) ) | AA95: =IFERROR( IF( OR(ISBLANK(W95), AND(ISBLANK(U95), ISBLANK(V95))), "", MAX( 1, IF( NETWORKDAYS(IF(NOT(ISBLANK(V95)), V95, U95), W95, Holiday_Dates) <= 0, 1, NETWORKDAYS(IF(NOT(ISBLANK(V95)), V95, U95), W95, Holiday_Dates) - IF(IF(NOT(ISBLANK(V95)), V95, U95) = W95, 0, 1) ) ) ), "" ) | AB95: =IFERROR( IF( OR(ISBLANK(W95), ISBLANK(X95)), "", MAX( 1, IF( NETWORKDAYS(W95, X95, Holiday_Dates) <= 0, 1, NETWORKDAYS(W95, X95, Holiday_Dates) - IF(W95 = X95, 0, 1) ) ) ), "" ) | BB95: =SUM(AR95,AT95,AV95) -> 0 | BC95: =SUM(AS95,AU95,AW95) -> 0
A96: Bulacan | B96: City Of Malolos | C96: =CONCATENATE(A96,","," ",B96) -> Bulacan, City Of Malolos | D96: MBA | E96: 1st | F96: 14.843702 | G96: 120.81114 | H96: =CONCATENATE(F96,",",G96) -> 14.843702,120.811145 | I96: Municipal / City Plan | J96: NSWMC RESO NO. 503-A SERIES OF 2019 | K96: 2018-2028 | L96: 2019 | M96: 2028 | O96: Ronaldo P. Roque, Jr. | Q96: Diozelle L. Cabalar | Y96: =IFERROR( IF( OR(ISBLANK(T96), ISBLANK(U96)), "", MAX( 1, IF( NETWORKDAYS(T96, U96, Holiday_Dates) <= 0, 1, NETWORKDAYS(T96, U96, Holiday_Dates) - IF(T96 = U96, 0, 1) ) ) ), "" ) | Z96: =IF( OR(ISBLANK(U96), ISBLANK(V96)), "", MAX( 1, IF( NETWORKDAYS(U96, V96, Holiday_Dates) <= 0, 1, NETWORKDAYS(U96, V96, Holiday_Dates) - IF(U96 = V96, 0, 1) ) ) ) | AA96: =IFERROR( IF( OR(ISBLANK(W96), AND(ISBLANK(U96), ISBLANK(V96))), "", MAX( 1, IF( NETWORKDAYS(IF(NOT(ISBLANK(V96)), V96, U96), W96, Holiday_Dates) <= 0, 1, NETWORKDAYS(IF(NOT(ISBLANK(V96)), V96, U96), W96, Holiday_Dates) - IF(IF(NOT(ISBLANK(V96)), V96, U96) = W96, 0, 1) ) ) ), "" ) | AB96: =IFERROR( IF( OR(ISBLANK(W96), ISBLANK(X96)), "", MAX( 1, IF( NETWORKDAYS(W96, X96, Holiday_Dates) <= 0, 1, NETWORKDAYS(W96, X96, Holiday_Dates) - IF(W96 = X96, 0, 1) ) ) ), "" ) | BB96: =SUM(AR96,AT96,AV96) -> 0 | BC96: =SUM(AS96,AU96,AW96) -> 0
A97: Bulacan | B97: Guiguinto | C97: =CONCATENATE(A97,","," ",B97) -> Bulacan, Guiguinto | D97: MBA | E97: 5th | F97: 14.827419 | G97: 120.87897 | H97: =CONCATENATE(F97,",",G97) -> 14.8274194,120.87897 | I97: Municipal / City Plan | J97: 1080 series of 2018 | K97: 2017 - 2027 | L97: 2018 | M97: 2027 | O97: Jasmin Marie N. Siapco | Q97: Diozelle L. Cabalar | Y97: =IFERROR( IF( OR(ISBLANK(T97), ISBLANK(U97)), "", MAX( 1, IF( NETWORKDAYS(T97, U97, Holiday_Dates) <= 0, 1, NETWORKDAYS(T97, U97, Holiday_Dates) - IF(T97 = U97, 0, 1) ) ) ), "" ) | Z97: =IF( OR(ISBLANK(U97), ISBLANK(V97)), "", MAX( 1, IF( NETWORKDAYS(U97, V97, Holiday_Dates) <= 0, 1, NETWORKDAYS(U97, V97, Holiday_Dates) - IF(U97 = V97, 0, 1) ) ) ) | AA97: =IFERROR( IF( OR(ISBLANK(W97), AND(ISBLANK(U97), ISBLANK(V97))), "", MAX( 1, IF( NETWORKDAYS(IF(NOT(ISBLANK(V97)), V97, U97), W97, Holiday_Dates) <= 0, 1, NETWORKDAYS(IF(NOT(ISBLANK(V97)), V97, U97), W97, Holiday_Dates) - IF(IF(NOT(ISBLANK(V97)), V97, U97) = W97, 0, 1) ) ) ), "" ) | AB97: =IFERROR( IF( OR(ISBLANK(W97), ISBLANK(X97)), "", MAX( 1, IF( NETWORKDAYS(W97, X97, Holiday_Dates) <= 0, 1, NETWORKDAYS(W97, X97, Holiday_Dates) - IF(W97 = X97, 0, 1) ) ) ), "" ) | BB97: =SUM(AR97,AT97,AV97) -> 0 | BC97: =SUM(AS97,AU97,AW97) -> 0
A98: Bulacan | B98: Pandi | C98: =CONCATENATE(A98,","," ",B98) -> Bulacan, Pandi | D98: MBA | E98: 5th | F98: 14.865724 | G98: 120.95814 | H98: =CONCATENATE(F98,",",G98) -> 14.86572366,120.9581422 | I98: Municipal / City Plan | J98: No. 1403 Series of 2020 | K98: 2019 - 2028 | L98: 2020 | M98: 2028 | O98: Ronaldo P. Roque, Jr. | Q98: Diozelle L. Cabalar | Y98: =IFERROR( IF( OR(ISBLANK(T98), ISBLANK(U98)), "", MAX( 1, IF( NETWORKDAYS(T98, U98, Holiday_Dates) <= 0, 1, NETWORKDAYS(T98, U98, Holiday_Dates) - IF(T98 = U98, 0, 1) ) ) ), "" ) | Z98: =IF( OR(ISBLANK(U98), ISBLANK(V98)), "", MAX( 1, IF( NETWORKDAYS(U98, V98, Holiday_Dates) <= 0, 1, NETWORKDAYS(U98, V98, Holiday_Dates) - IF(U98 = V98, 0, 1) ) ) ) | AA98: =IFERROR( IF( OR(ISBLANK(W98), AND(ISBLANK(U98), ISBLANK(V98))), "", MAX( 1, IF( NETWORKDAYS(IF(NOT(ISBLANK(V98)), V98, U98), W98, Holiday_Dates) <= 0, 1, NETWORKDAYS(IF(NOT(ISBLANK(V98)), V98, U98), W98, Holiday_Dates) - IF(IF(NOT(ISBLANK(V98)), V98, U98) = W98, 0, 1) ) ) ), "" ) | AB98: =IFERROR( IF( OR(ISBLANK(W98), ISBLANK(X98)), "", MAX( 1, IF( NETWORKDAYS(W98, X98, Holiday_Dates) <= 0, 1, NETWORKDAYS(W98, X98, Holiday_Dates) - IF(W98 = X98, 0, 1) ) ) ), "" ) | BB98: =SUM(AR98,AT98,AV98) -> 0 | BC98: =SUM(AS98,AU98,AW98) -> 0
A99: Bulacan | B99: Paombong | C99: =CONCATENATE(A99,","," ",B99) -> Bulacan, Paombong | D99: MBA | E99: 1st | F99: 14.836511 | G99: 120.78777 | H99: =CONCATENATE(F99,",",G99) -> 14.83651081,120.7877692 | I99: Municipal / City Plan | J99: 664-A series of 2019 | K99: 2017 - 2026 | L99: 2019 | M99: 2026 | O99: VACANT | Q99: Diozelle L. Cabalar | Y99: =IFERROR( IF( OR(ISBLANK(T99), ISBLANK(U99)), "", MAX( 1, IF( NETWORKDAYS(T99, U99, Holiday_Dates) <= 0, 1, NETWORKDAYS(T99, U99, Holiday_Dates) - IF(T99 = U99, 0, 1) ) ) ), "" ) | Z99: =IF( OR(ISBLANK(U99), ISBLANK(V99)), "", MAX( 1, IF( NETWORKDAYS(U99, V99, Holiday_Dates) <= 0, 1, NETWORKDAYS(U99, V99, Holiday_Dates) - IF(U99 = V99, 0, 1) ) ) ) | AA99: =IFERROR( IF( OR(ISBLANK(W99), AND(ISBLANK(U99), ISBLANK(V99))), "", MAX( 1, IF( NETWORKDAYS(IF(NOT(ISBLANK(V99)), V99, U99), W99, Holiday_Dates) <= 0, 1, NETWORKDAYS(IF(NOT(ISBLANK(V99)), V99, U99), W99, Holiday_Dates) - IF(IF(NOT(ISBLANK(V99)), V99, U99) = W99, 0, 1) ) ) ), "" ) | AB99: =IFERROR( IF( OR(ISBLANK(W99), ISBLANK(X99)), "", MAX( 1, IF( NETWORKDAYS(W99, X99, Holiday_Dates) <= 0, 1, NETWORKDAYS(W99, X99, Holiday_Dates) - IF(W99 = X99, 0, 1) ) ) ), "" ) | BB99: =SUM(AR99,AT99,AV99) -> 0 | BC99: =SUM(AS99,AU99,AW99) -> 0
... A103: Nueva Ecija | B103: Gen. Tinio | C103: =CONCATENATE(A103,","," ",B103) -> Nueva Ecija, Gen. Tinio | D103: MBA | E103: 4th | F103: 15.3499 | G103: 121.04583 | H103: =CONCATENATE(F103,",",G103) -> 15.3499,121.045834 | I103: Municipal / City Plan | J103: no.1247 series of 2019 | K103: 2016 - 2027 | L103: 2019 | M103: 2027 | O103: Christian Jem L. Buluran | Q103: Zosimo P. Suyat | Y103: =IFERROR( IF( OR(ISBLANK(T103), ISBLANK(U103)), "", MAX( 1, IF( NETWORKDAYS(T103, U103, Holiday_Dates) <= 0, 1, NETWORKDAYS(T103, U103, Holiday_Dates) - IF(T103 = U103, 0, 1) ) ) ), "" ) | Z103: =IF( OR(ISBLANK(U103), ISBLANK(V103)), "", MAX( 1, IF( NETWORKDAYS(U103, V103, Holiday_Dates) <= 0, 1, NETWORKDAYS(U103, V103, Holiday_Dates) - IF(U103 = V103, 0, 1) ) ) ) | AA103: =IFERROR( IF( OR(ISBLANK(W103), AND(ISBLANK(U103), ISBLANK(V103))), "", MAX( 1, IF( NETWORKDAYS(IF(NOT(ISBLANK(V103)), V103, U103), W103, Holiday_Dates) <= 0, 1, NETWORKDAYS(IF(NOT(ISBLANK(V103)), V103, U103), W103, Holiday_Dates) - IF(IF(NOT(ISBLANK(V103)), V103, U103) = W103, 0, 1) ) ) ), "" ) | AB103: =IFERROR( IF( OR(ISBLANK(W103), ISBLANK(X103)), "", MAX( 1, IF( NETWORKDAYS(W103, X103, Holiday_Dates) <= 0, 1, NETWORKDAYS(W103, X103, Holiday_Dates) - IF(W103 = X103, 0, 1) ) ) ), "" ) | BB103: =SUM(AR103,AT103,AV103) -> 0 | BC103: =SUM(AS103,AU103,AW103) -> 0
...

Sheet FUNDED MRF
A1: Province | B1: Municipality | C1: Barangay | D1: Manila Bay Area (MBA) | E1: Congressional District | F1: Lat | G1: Long | H1: Coordinates | I1: Type of MRF | J1: No Funding Support | K1: Year Granted | L1: Amount Granted | M1: ENMO Assigned | N1: ESWM Staff | O1: Focal Person | P1: Target Month | Q1: IIS NUMBER | R1: Date of Monitoring | S1: Date Report Prepared (Submitted to IIS by ENMO) | T1: Date Report Reviewed (by ESWM Staff) | U1: Date Report Reviewed (by Focal Person) | V1: Date Report Approved | W1: Total No. of Days (Report prepared) | X1: Total No. of Days (Report Reviewed by ESWM Staff) | Y1: Total No. of Days (Report Reviewed by Focal) | Z1: Total No. of Days (Report Approved by C, ESWM) | AA1: Tracking of Reports (To be Filled out by Planning Section) | AB1: No. of Brgy. Served | AC1: Equipment used in the Operation of the MRF | AD1: Type of wastes received | AE1: Quantity of waste diverted (kg) | AF1: Total Waste Generation (kg/day) | AG1: Waste Diversion Rate (%) | AH1: Status of MRF | AI1: Remarks (If Not Operational) | AJ1: Remarks and Recommendation (Compliant/ Non-Compliant) | AK1: Findings (If not compliant) | AL1: Advise Letter/Notice Date Issued | AM1: Compliance of LGU to Issued Advise/ Letter | AN1: Docket No. / NOV | AO1: Violation (Sec. ___ ) | AP1: Date of Issuance of NOV | AQ1: Date of Technical Conference | AR1: Commitment/s | AS1: Signed Document
A2: Aurora | B2: Baler | C2: Pingit | D2: OUTSIDE MBA | E2: Lone | F2: 15.735856 | G2: 121.56295 | H2: =CONCATENATE(F2,",",G2) -> 15.735856,121.562947 | I2: EMB FUNDED MRF | J2: 1 | K2: 2016 | L2: 270000 | M2: Zaila Mae R. Leander | O2: Diozelle L. Cabalar | P2: 1.January | Q2: R3-2026-001747 | R2: 46042 | S2: 46043 | U2: 46043 | V2: 46043 | W2: =IFERROR( IF( OR(ISBLANK(R2), ISBLANK(S2)), "", MAX( 1, IF( NETWORKDAYS(R2, S2, Holiday_Dates) <= 0, 1, NETWORKDAYS(R2, S2, Holiday_Dates) - IF(R2 = S2, 0, 1) ) ) ), "" ) -> 1 | X2: =IF( OR(ISBLANK(S2), ISBLANK(T2)), "", MAX( 1, IF( NETWORKDAYS(S2, T2, Holiday_Dates) <= 0, 1, NETWORKDAYS(S2, T2, Holiday_Dates) - IF(S2 = T2, 0, 1) ) ) ) | Y2: =IFERROR( IF( OR(ISBLANK(S2), AND(ISBLANK(T2), ISBLANK(U2))), "", MAX( 1, IF( NETWORKDAYS(IF(NOT(ISBLANK(U2)), U2, T2), U2, Holiday_Dates) <= 0, 1, NETWORKDAYS(IF(NOT(ISBLANK(U2)), U2, T2), U2, Holiday_Dates) - IF(IF(NOT(ISBLANK(U2)), U2, T2) = U2, 0, 1) ) ) ), "" ) -> 1 | Z2: =IF( OR(ISBLANK(U2), ISBLANK(V2)), "", MAX(1, IF( NETWORKDAYS(U2, V2) <= 0, 1, NETWORKDAYS(U2, V2) - IF(U2 = V2, 0, 1) )) ) -> 1 | AA2: Marshalle Julluice V. Catua | AB2: 7 | AC2: Composter | AD2: Biowaste | AE2: 15, 440 | AF2: 17430.2 | AG2: 0.89 | AH2: OPERATIONAL | AS2: https://embco-my.sharepoint.com/:w:/g/personal/eswmr3_emb_gov_ph/IQBGHioor-MSSJwMAqN8db4PARdBONPqcCDUZ7rATf_Riuw?e=JRdVwL
A3: Bulacan | B3: City Of San Jose Del Monte | C3: Tungkong Mangga | D3: MBA | E3: Lone | F3: 14.803364 | G3: 121.07045 | H3: =CONCATENATE(F3,",",G3) -> 14.8033642,121.0704497 | I3: EMB FUNDED BRGY MRF | J3: 1 | K3: 2017 | L3: 460000 | M3: James Wilson T. Pena | O3: Diozelle L. Cabalar | P3: 1.January | Q3: R3-2026-001524 | R3: 46037 | S3: 46041 | U3: 46043 | V3: 46045 | W3: =IFERROR( IF( OR(ISBLANK(R3), ISBLANK(S3)), "", MAX( 1, IF( NETWORKDAYS(R3, S3, Holiday_Dates) <= 0, 1, NETWORKDAYS(R3, S3, Holiday_Dates) - IF(R3 = S3, 0, 1) ) ) ), "" ) -> 2 | X3: =IF( OR(ISBLANK(S3), ISBLANK(T3)), "", MAX( 1, IF( NETWORKDAYS(S3, T3, Holiday_Dates) <= 0, 1, NETWORKDAYS(S3, T3, Holiday_Dates) - IF(S3 = T3, 0, 1) ) ) ) | Y3: =IFERROR( IF( OR(ISBLANK(S3), AND(ISBLANK(T3), ISBLANK(U3))), "", MAX( 1, IF( NETWORKDAYS(IF(NOT(ISBLANK(U3)), U3, T3), U3, Holiday_Dates) <= 0, 1, NETWORKDAYS(IF(NOT(ISBLANK(U3)), U3, T3), U3, Holiday_Dates) - IF(IF(NOT(ISBLANK(U3)), U3, T3) = U3, 0, 1) ) ) ), "" ) -> 1 | Z3: =IF( OR(ISBLANK(U3), ISBLANK(V3)), "", MAX(1, IF( NETWORKDAYS(U3, V3) <= 0, 1, NETWORKDAYS(U3, V3) - IF(U3 = V3, 0, 1) )) ) -> 2 | AA3: Marshalle Julluice V. Catua | AB3: 1 | AC3: Weiging Scale, Electric power | AD3: Biowaste, Paper, Plastic, Glass, Biodegradable | AE3: 1430 | AF3: 11000 | AG3: 0.13 | AH3: OPERATIONAL | AS3: https://embco-my.sharepoint.com/:w:/g/personal/eswmr3_emb_gov_ph/IQATxYnWcWFBR6ntBIhwVQvTAevTLLXNlKNRp3BUOPF269A?e=dvco6t
A4: Nueva Ecija | B4: Gabaldon | C4: Pantoc | D4: MBA | E4: 3rd | F4: 15.4709 | G4: 121.3436 | H4: =CONCATENATE(F4,",",G4) -> 15.4709,121.3436 | I4: EMB FUNDED MRF | J4: 1 | K4: 2019 | L4: 500000 | M4: Christian Jem L. Buluran | O4: Zosimo P. Suyat | P4: 1.January | Q4: R3-2026-001897 | R4: 46043 | S4: 46044 | U4: 46044 | V4: 46045 | W4: =IFERROR( IF( OR(ISBLANK(R4), ISBLANK(S4)), "", MAX( 1, IF( NETWORKDAYS(R4, S4, Holiday_Dates) <= 0, 1, NETWORKDAYS(R4, S4, Holiday_Dates) - IF(R4 = S4, 0, 1) ) ) ), "" ) -> 1 | X4: =IF( OR(ISBLANK(S4), ISBLANK(T4)), "", MAX( 1, IF( NETWORKDAYS(S4, T4, Holiday_Dates) <= 0, 1, NETWORKDAYS(S4, T4, Holiday_Dates) - IF(S4 = T4, 0, 1) ) ) ) | Y4: =IFERROR( IF( OR(ISBLANK(S4), AND(ISBLANK(T4), ISBLANK(U4))), "", MAX( 1, IF( NETWORKDAYS(IF(NOT(ISBLANK(U4)), U4, T4), U4, Holiday_Dates) <= 0, 1, NETWORKDAYS(IF(NOT(ISBLANK(U4)), U4, T4), U4, Holiday_Dates) - IF(IF(NOT(ISBLANK(U4)), U4, T4) = U4, 0, 1) ) ) ), "" ) -> 1 | Z4: =IF( OR(ISBLANK(U4), ISBLANK(V4)), "", MAX(1, IF( NETWORKDAYS(U4, V4) <= 0, 1, NETWORKDAYS(U4, V4) - IF(U4 = V4, 0, 1) )) ) -> 1 | AA4: Marshalle Julluice V. Catua | AB4: 16 | AC4: Bricks Mixer Machine, Plastic shredder, Glass shredder/ pulverizer, Vermicomposting bed/bins, Vermicomposting bed/bins, Bricks maker/molder, Electric power | AD4: Biodegradable waste, Recyclables, Residual Wastes | AE4: 1589.032 | AF4: 13044.836 | AG4: 0.12181 | AH4: OPERATIONAL | AS4: https://embco-my.sharepoint.com/:w:/g/personal/eswmr3_emb_gov_ph/IQATxYnWcWFBR6ntBIhwVQvTAevTLLXNlKNRp3BUOPF269A?e=dvco6t
A5: Pampanga | B5: City Of San Fernando | C5: Del Rosario | D5: MBA | E5: 3rd | F5: 15.067883 | G5: 120.64 | H5: =CONCATENATE(F5,",",G5) -> 15.06788333,120.64 | I5: EMB FUNDED MRF | J5: 1 | K5: 2012 | L5: 500000 | M5: Elyza A. Evilla | O5: John Sherwin Loquellano | P5: 1.January | Q5: R3-2026-001248 | R5: 46035 | S5: 46038 | T5: 46042 | U5: 46042 | V5: 46042 | W5: =IFERROR( IF( OR(ISBLANK(R5), ISBLANK(S5)), "", MAX( 1, IF( NETWORKDAYS(R5, S5, Holiday_Dates) <= 0, 1, NETWORKDAYS(R5, S5, Holiday_Dates) - IF(R5 = S5, 0, 1) ) ) ), "" ) -> 3 | X5: =IF( OR(ISBLANK(S5), ISBLANK(T5)), "", MAX( 1, IF( NETWORKDAYS(S5, T5, Holiday_Dates) <= 0, 1, NETWORKDAYS(S5, T5, Holiday_Dates) - IF(S5 = T5, 0, 1) ) ) ) -> 2 | Y5: =IFERROR( IF( OR(ISBLANK(S5), AND(ISBLANK(T5), ISBLANK(U5))), "", MAX( 1, IF( NETWORKDAYS(IF(NOT(ISBLANK(U5)), U5, T5), U5, Holiday_Dates) <= 0, 1, NETWORKDAYS(IF(NOT(ISBLANK(U5)), U5, T5), U5, Holiday_Dates) - IF(IF(NOT(ISBLANK(U5)), U5, T5) = U5, 0, 1) ) ) ), "" ) -> 1 | Z5: =IF( OR(ISBLANK(U5), ISBLANK(V5)), "", MAX(1, IF( NETWORKDAYS(U5, V5) <= 0, 1, NETWORKDAYS(U5, V5) - IF(U5 = V5, 0, 1) )) ) -> 1 | AA5: Marshalle Julluice V. Catua | AB5: 1 | AC5: None | AD5: Biowaste, Recyclables | AE5: No available data | AF5: 648.4 | AG5: No available data | AH5: OPERATIONAL | AJ5: • Provide accomplished and precise total weights of waste diversion • Assign a personnel for recording of daily waste collected. | AK5: • No logbook or records of daily wastes collected presented during the monitoring | AS5: https://embco-my.sharepoint.com/:w:/g/personal/eswmr3_emb_gov_ph/IQCafMGtJtv8QruYylnMGz3QAfITuShEc0gugkArm5ovznM?e=TH1hLt
A6: Zambales | B6: Masinloc | C6: North Poblacion | D6: OUTSIDE MBA | E6: 2nd | F6: 15.548492 | G6: 119.94657 | H6: =CONCATENATE(F6,",",G6) -> 15.548492,119.946567 | I6: EMB FUNDED BRGY MRF | J6: 1 | K6: 2018 | L6: 427500 | M6: Ryan Ace R. Angel | O6: Jun D. Guillermo | P6: 1.January | Q6: R3-2026-001337 | R6: 46035 | S6: 46040 | U6: 46041 | V6: 46041 | W6: =IFERROR( IF( OR(ISBLANK(R6), ISBLANK(S6)), "", MAX( 1, IF( NETWORKDAYS(R6, S6, Holiday_Dates) <= 0, 1, NETWORKDAYS(R6, S6, Holiday_Dates) - IF(R6 = S6, 0, 1) ) ) ), "" ) -> 3 | X6: =IF( OR(ISBLANK(S6), ISBLANK(T6)), "", MAX( 1, IF( NETWORKDAYS(S6, T6, Holiday_Dates) <= 0, 1, NETWORKDAYS(S6, T6, Holiday_Dates) - IF(S6 = T6, 0, 1) ) ) ) | Y6: =IFERROR( IF( OR(ISBLANK(S6), AND(ISBLANK(T6), ISBLANK(U6))), "", MAX( 1, IF( NETWORKDAYS(IF(NOT(ISBLANK(U6)), U6, T6), U6, Holiday_Dates) <= 0, 1, NETWORKDAYS(IF(NOT(ISBLANK(U6)), U6, T6), U6, Holiday_Dates) - IF(IF(NOT(ISBLANK(U6)), U6, T6) = U6, 0, 1) ) ) ), "" ) -> 1 | Z6: =IF( OR(ISBLANK(U6), ISBLANK(V6)), "", MAX(1, IF( NETWORKDAYS(U6, V6) <= 0, 1, NETWORKDAYS(U6, V6) - IF(U6 = V6, 0, 1) )) ) -> 1 | AA6: Marshalle Julluice V. Catua | AB6: None | AC6: None | AD6: N/A | AE6: N/A | AF6: N/A | AG6: N/A | AH6: NON-OPERATIONAL | AI6: The Barangay South Poblacion and North Poblacion are clustered MRF. The barangay EMB-funded MRF lot is not owned by the LGU, the lease has ended, and the infrastructure is now fenced and inaccessible. | AS6: https://embco-my.sharepoint.com/:w:/g/personal/eswmr3_emb_gov_ph/IQD9oLbo0KlDS5xQ9QDnadDSAa4h3YHxSTDXep5IBPnUY8Q?e=0dgyk0
A7: Zambales | B7: Masinloc | C7: South Poblacion | D7: OUTSIDE MBA | E7: 2nd | F7: 15.539333 | G7: 119.94764 | H7: =CONCATENATE(F7,",",G7) -> 15.539333,119.947636 | I7: EMB FUNDED BRGY MRF | J7: 1 | K7: 2018 | L7: 427500 | M7: Ryan Ace R. Angel | O7: Jun D. Guillermo | P7: 1.January | Q7: R3-2026-001340 | R7: 46035 | S7: 46040 | U7: 46041 | V7: 46041 | W7: =IFERROR( IF( OR(ISBLANK(R7), ISBLANK(S7)), "", MAX( 1, IF( NETWORKDAYS(R7, S7, Holiday_Dates) <= 0, 1, NETWORKDAYS(R7, S7, Holiday_Dates) - IF(R7 = S7, 0, 1) ) ) ), "" ) -> 3 | X7: =IF( OR(ISBLANK(S7), ISBLANK(T7)), "", MAX( 1, IF( NETWORKDAYS(S7, T7, Holiday_Dates) <= 0, 1, NETWORKDAYS(S7, T7, Holiday_Dates) - IF(S7 = T7, 0, 1) ) ) ) | Y7: =IFERROR( IF( OR(ISBLANK(S7), AND(ISBLANK(T7), ISBLANK(U7))), "", MAX( 1, IF( NETWORKDAYS(IF(NOT(ISBLANK(U7)), U7, T7), U7, Holiday_Dates) <= 0, 1, NETWORKDAYS(IF(NOT(ISBLANK(U7)), U7, T7), U7, Holiday_Dates) - IF(IF(NOT(ISBLANK(U7)), U7, T7) = U7, 0, 1) ) ) ), "" ) -> 1 | Z7: =IF( OR(ISBLANK(U7), ISBLANK(V7)), "", MAX(1, IF( NETWORKDAYS(U7, V7) <= 0, 1, NETWORKDAYS(U7, V7) - IF(U7 = V7, 0, 1) )) ) -> 1 | AA7: Marshalle Julluice V. Catua | AB7: None | AC7: None | AD7: N/A | AE7: N/A | AF7: N/A | AG7: N/A | AH7: NON-OPERATIONAL | AI7: The Barangay South Poblacion and North Poblacion are clustered MRF. The barangay EMB-funded MRF lot is not owned by the LGU, the lease has ended, and the infrastructure is now fenced and inaccessible. | AS7: https://embco-my.sharepoint.com/:w:/g/personal/eswmr3_emb_gov_ph/IQAO5Q4md6I7RrvDBL1kMUaOAYUFCDkx0tDP5q5G6shCMu0?e=RlF4ow
A8: Aurora | B8: Maria Aurora | C8: San Joaquin | D8: OUTSIDE MBA | E8: Lone | F8: 15.807801 | G8: 121.45867 | H8: =CONCATENATE(F8,",",G8) -> 15.807801,121.458669 | I8: EMB FUNDED MRF | J8: 2 | K8: 2015//2020 | L8: 500000/190,000 | M8: Nikko Jay M. Valenzuela | O8: Diozelle L. Cabalar | P8: 2.February | Q8: R3-2026-004121 | R8: 46057 | S8: 46062 | U8: 46069 | V8: 46069 | W8: =IFERROR( IF( OR(ISBLANK(R8), ISBLANK(S8)), "", MAX( 1, IF( NETWORKDAYS(R8, S8, Holiday_Dates) <= 0, 1, NETWORKDAYS(R8, S8, Holiday_Dates) - IF(R8 = S8, 0, 1) ) ) ), "" ) -> 3 | X8: =IF( OR(ISBLANK(S8), ISBLANK(T8)), "", MAX( 1, IF( NETWORKDAYS(S8, T8, Holiday_Dates) <= 0, 1, NETWORKDAYS(S8, T8, Holiday_Dates) - IF(S8 = T8, 0, 1) ) ) ) | Y8: =IFERROR( IF( OR(ISBLANK(S8), AND(ISBLANK(T8), ISBLANK(U8))), "", MAX( 1, IF( NETWORKDAYS(IF(NOT(ISBLANK(U8)), U8, T8), U8, Holiday_Dates) <= 0, 1, NETWORKDAYS(IF(NOT(ISBLANK(U8)), U8, T8), U8, Holiday_Dates) - IF(IF(NOT(ISBLANK(U8)), U8, T8) = U8, 0, 1) ) ) ), "" ) -> 1 | Z8: =IF( OR(ISBLANK(U8), ISBLANK(V8)), "", MAX(1, IF( NETWORKDAYS(U8, V8) <= 0, 1, NETWORKDAYS(U8, V8) - IF(U8 = V8, 0, 1) )) ) -> 1 | AA8: Ask clarification | AH8: NON-OPERATIONAL | AS8: https://embco-my.sharepoint.com/:w:/g/personal/eswmr3_emb_gov_ph/IQBzIGae-ZoiQYo4Ej4CvLR3AcUtEHlvx2TTR0XNmUZkmFQ?e=Cn9XuZ
A9: Bataan | B9: Bagac | C9: Pasyawan | D9: MBA | E9: 3rd | F9: 14.535556 | G9: 120.39278 | H9: =CONCATENATE(F9,",",G9) -> 14.535556,120.392778 | I9: EMB FUNDED BRGY MRF | J9: 1 | K9: 2018 | L9: 285000 | M9: Laurence Radasa | O9: Christle D. David | P9: 2.February | Q9: R3-2026-002721 | R9: 46050 | S9: 46050 | U9: 46053 | V9: 46055 | W9: =IFERROR( IF( OR(ISBLANK(R9), ISBLANK(S9)), "", MAX( 1, IF( NETWORKDAYS(R9, S9, Holiday_Dates) <= 0, 1, NETWORKDAYS(R9, S9, Holiday_Dates) - IF(R9 = S9, 0, 1) ) ) ), "" ) -> 1 | X9: =IF( OR(ISBLANK(S9), ISBLANK(T9)), "", MAX( 1, IF( NETWORKDAYS(S9, T9, Holiday_Dates) <= 0, 1, NETWORKDAYS(S9, T9, Holiday_Dates) - IF(S9 = T9, 0, 1) ) ) ) | Y9: =IFERROR( IF( OR(ISBLANK(S9), AND(ISBLANK(T9), ISBLANK(U9))), "", MAX( 1, IF( NETWORKDAYS(IF(NOT(ISBLANK(U9)), U9, T9), U9, Holiday_Dates) <= 0, 1, NETWORKDAYS(IF(NOT(ISBLANK(U9)), U9, T9), U9, Holiday_Dates) - IF(IF(NOT(ISBLANK(U9)), U9, T9) = U9, 0, 1) ) ) ), "" ) -> 1 | Z9: =IF( OR(ISBLANK(U9), ISBLANK(V9)), "", MAX(1, IF( NETWORKDAYS(U9, V9) <= 0, 1, NETWORKDAYS(U9, V9) - IF(U9 = V9, 0, 1) )) ) -> 1 | AA9: Marshalle Julluice V. Catua | AB9: 1 | AC9: Biowaste Shredder | AD9: Biodegradable, Recyclable, Residual | AE9: 42.62 | AF9: 139.42 | AG9: 0.3057 | AH9: OPERATIONAL | AS9: https://embco-my.sharepoint.com/:w:/g/personal/eswmr3_emb_gov_ph/IQA3Ea8hTt7yQ4sVG5j-IFbFAUZdJagNWmR5TjPeFVVK2IY?e=4azSz4
A10: Bataan | B10: City Of Balanga | C10: Cabog Cabog | D10: MBA | E10: 2nd | F10: 14.671575 | G10: 120.53445 | H10: =CONCATENATE(F10,",",G10) -> 14.671575,120.534451 | I10: EMB FUNDED BRGY MRF | J10: 1 | K10: 2018 | L10: 285000 | M10: Dennis Tolentino | O10: Christle D. David | P10: 2.February | Q10: R3-2026-004562 | R10: 46064 | S10: 46064 | U10: 46067 | V10: 46069 | W10: =IFERROR( IF( OR(ISBLANK(R10), ISBLANK(S10)), "", MAX( 1, IF( NETWORKDAYS(R10, S10, Holiday_Dates) <= 0, 1, NETWORKDAYS(R10, S10, Holiday_Dates) - IF(R10 = S10, 0, 1) ) ) ), "" ) -> 1 | X10: =IF( OR(ISBLANK(S10), ISBLANK(T10)), "", MAX( 1, IF( NETWORKDAYS(S10, T10, Holiday_Dates) <= 0, 1, NETWORKDAYS(S10, T10, Holiday_Dates) - IF(S10 = T10, 0, 1) ) ) ) | Y10: =IFERROR( IF( OR(ISBLANK(S10), AND(ISBLANK(T10), ISBLANK(U10))), "", MAX( 1, IF( NETWORKDAYS(IF(NOT(ISBLANK(U10)), U10, T10), U10, Holiday_Dates) <= 0, 1, NETWORKDAYS(IF(NOT(ISBLANK(U10)), U10, T10), U10, Holiday_Dates) - IF(IF(NOT(ISBLANK(U10)), U10, T10) = U10, 0, 1) ) ) ), "" ) -> 1 | Z10: =IF( OR(ISBLANK(U10), ISBLANK(V10)), "", MAX(1, IF( NETWORKDAYS(U10, V10) <= 0, 1, NETWORKDAYS(U10, V10) - IF(U10 = V10, 0, 1) )) ) -> 1 | AB10: 1 | AC10: Biowaste Shredder | AD10: Biodegradable, Recyclable | AE10: No Updated Records | AF10: 946.65 | AG10: Cannot be determined | AH10: OPERATIONAL | AS10: https://embco-my.sharepoint.com/:w:/g/personal/eswmr3_emb_gov_ph/IQAhj2GLY3MwR5Bi51a1WS7DAQtvJwdzYUbKXtQ7BUDbX4Q?e=teUCy7
A11: Bulacan | B11: Balagtas | C11: Santol | D11: MBA | E11: 5th | F11: 14.862786 | G11: 120.91716 | H11: =CONCATENATE(F11,",",G11) -> 14.862786,120.91716 | I11: EMB FUNDED MRF | J11: 1 | K11: 2017 | L11: 460000 | M11: Jasmin Marie N. Siapco | O11: Diozelle L. Cabalar | P11: 2.February | Q11: R3-2026-005196 | R11: 46069 | S11: 46070 | U11: 46071 | V11: 46071 | W11: =IFERROR( IF( OR(ISBLANK(R11), ISBLANK(S11)), "", MAX( 1, IF( NETWORKDAYS(R11, S11, Holiday_Dates) <= 0, 1, NETWORKDAYS(R11, S11, Holiday_Dates) - IF(R11 = S11, 0, 1) ) ) ), "" ) -> 1 | X11: =IF( OR(ISBLANK(S11), ISBLANK(T11)), "", MAX( 1, IF( NETWORKDAYS(S11, T11, Holiday_Dates) <= 0, 1, NETWORKDAYS(S11, T11, Holiday_Dates) - IF(S11 = T11, 0, 1) ) ) ) | Y11: =IFERROR( IF( OR(ISBLANK(S11), AND(ISBLANK(T11), ISBLANK(U11))), "", MAX( 1, IF( NETWORKDAYS(IF(NOT(ISBLANK(U11)), U11, T11), U11, Holiday_Dates) <= 0, 1, NETWORKDAYS(IF(NOT(ISBLANK(U11)), U11, T11), U11, Holiday_Dates) - IF(IF(NOT(ISBLANK(U11)), U11, T11) = U11, 0, 1) ) ) ), "" ) -> 1 | Z11: =IF( OR(ISBLANK(U11), ISBLANK(V11)), "", MAX(1, IF( NETWORKDAYS(U11, V11) <= 0, 1, NETWORKDAYS(U11, V11) - IF(U11 = V11, 0, 1) )) ) -> 1 | AA11: Marshalle Julluice V. Catua | AB11: 0 | AC11: Biowaste Shredder | AD11: N/A | AE11: N/A | AF11: N/A | AG11: N/A | AH11: NON-OPERATIONAL | AI11:  To immediately operate the MRF and strict implementation of Ecological Solid Waste Management within the Local Government Unit.  To utilize the equipment donated by EMB for the operation of the MRF.  The LGU of Balagtas shall strictly monitor the MRF and ensure the proper operation of MRFs based on the guidelines on Material Recovery Facility (MRF) as stated in Article 4, Section 33 of RA 9003 or the Ecological Solid Waste Management Act.  To conduct information and education campaigns aimed at raising awareness among residents about importance of RA 9003 in solid waste management. | AS11: https://embco-my.sharepoint.com/:w:/g/personal/eswmr3_emb_gov_ph/IQAaIzPQAdOpSblYMaAIxTrOAViKZlSSh19qi5n3R8g3Fug?e=tNY4Uq
A12: Bulacan | B12: City Of San Jose Del Monte | C12: Minuyan III | D12: MBA | E12: Lone | F12: 14.8477 | G12: 121.0722 | H12: =CONCATENATE(F12,",",G12) -> 14.8477,121.0722 | I12: EMB FUNDED MRF | J12: 2 | K12: 2018 & 2018 | L12: 285000 & 285000 | M12: James Wilson T. Pena | O12: Diozelle L. Cabalar | P12: 2.February | Q12: R3-2026-005243 | R12: 46065 | S12: 46070 | U12: 46071 | V12: 46071 | W12: =IFERROR( IF( OR(ISBLANK(R12), ISBLANK(S12)), "", MAX( 1, IF( NETWORKDAYS(R12, S12, Holiday_Dates) <= 0, 1, NETWORKDAYS(R12, S12, Holiday_Dates) - IF(R12 = S12, 0, 1) ) ) ), "" ) -> 3 | X12: =IF( OR(ISBLANK(S12), ISBLANK(T12)), "", MAX( 1, IF( NETWORKDAYS(S12, T12, Holiday_Dates) <= 0, 1, NETWORKDAYS(S12, T12, Holiday_Dates) - IF(S12 = T12, 0, 1) ) ) ) | Y12: =IFERROR( IF( OR(ISBLANK(S12), AND(ISBLANK(T12), ISBLANK(U12))), "", MAX( 1, IF( NETWORKDAYS(IF(NOT(ISBLANK(U12)), U12, T12), U12, Holiday_Dates) <= 0, 1, NETWORKDAYS(IF(NOT(ISBLANK(U12)), U12, T12), U12, Holiday_Dates) - IF(IF(NOT(ISBLANK(U12)), U12, T12) = U12, 0, 1) ) ) ), "" ) -> 1 | Z12: =IF( OR(ISBLANK(U12), ISBLANK(V12)), "", MAX(1, IF( NETWORKDAYS(U12, V12) <= 0, 1, NETWORKDAYS(U12, V12) - IF(U12 = V12, 0, 1) )) ) -> 1 | AA12: Marshalle Julluice V. Catua | AB12: 0 | AC12: N/A | AD12: N/A | AE12: N/A | AF12: N/A | AG12: N/A | AH12: NON-OPERATIONAL | AI12: • To immediately operate the Barangay MRF. • Strict implementation of Ecological Solid Waste Management within the Local Government Unit. | AS12: https://embco-my.sharepoint.com/:w:/g/personal/eswmr3_emb_gov_ph/IQBo9Bub6MHTTrA2JRn3gbTqAY8PP-5Wg73gkxe4FU7hh5g?e=s4jZTk
A13: Nueva Ecija | B13: General Mamerto Natividad | C13: Balaring | D13: MBA | E13: 3rd | F13: 15.606326 | G13: 121.11079 | H13: =CONCATENATE(F13,",",G13) -> 15.606326,121.110789 | I13: EMB FUNDED MRF | J13: 1 | K13: 2019 | L13: 530642.86 | M13: Hosannah R. Sabio | O13: Zosimo P. Suyat | P13: 2.February | Q13: R3-2026-005343 | R13: 46069 | S13: 46071 | U13: 46071 | V13: 46071 | W13: =IFERROR( IF( OR(ISBLANK(R13), ISBLANK(S13)), "", MAX( 1, IF( NETWORKDAYS(R13, S13, Holiday_Dates) <= 0, 1, NETWORKDAYS(R13, S13, Holiday_Dates) - IF(R13 = S13, 0, 1) ) ) ), "" ) -> 2 | X13: =IF( OR(ISBLANK(S13), ISBLANK(T13)), "", MAX( 1, IF( NETWORKDAYS(S13, T13, Holiday_Dates) <= 0, 1, NETWORKDAYS(S13, T13, Holiday_Dates) - IF(S13 = T13, 0, 1) ) ) ) | Y13: =IFERROR( IF( OR(ISBLANK(S13), AND(ISBLANK(T13), ISBLANK(U13))), "", MAX( 1, IF( NETWORKDAYS(IF(NOT(ISBLANK(U13)), U13, T13), U13, Holiday_Dates) <= 0, 1, NETWORKDAYS(IF(NOT(ISBLANK(U13)), U13, T13), U13, Holiday_Dates) - IF(IF(NOT(ISBLANK(U13)), U13, T13) = U13, 0, 1) ) ) ), "" ) -> 1 | Z13: =IF( OR(ISBLANK(U13), ISBLANK(V13)), "", MAX(1, IF( NETWORKDAYS(U13, V13) <= 0, 1, NETWORKDAYS(U13, V13) - IF(U13 = V13, 0, 1) )) ) -> 1 | AA13: Marshalle Julluice V. Catua | AB13: 19 | AC13: Weighing scale, Bottle Crusher, Biowaste shredder, Windrows for composting, Electric power, Loader | AD13: Biodegradable, Recyclables, Residuals | AE13: 49.44 | AF13: 11077.75 | AG13: 0.0045 | AH13: OPERATIONAL | AS13: https://embco-my.sharepoint.com/:w:/g/personal/eswmr3_emb_gov_ph/IQDGOIigIqYIRp92spdOFP9fAQu3D_NrZECd7k9M-xVHHqY?e=uMxKyJ
A14: Nueva Ecija | B14: Jaen | C14: Niyugan | D14: MBA | E14: 4th | F14: 15.335854 | G14: 120.89266 | H14: =CONCATENATE(F14,",",G14) -> 15.335854,120.892661 | I14: EMB FUNDED MRF | J14: 1 | K14: 2019 | L14: 502714.29 | M14: Christine Ann V. Ramos | O14: Zosimo P. Suyat | P14: 2.February | Q14: R3-2026-005164 | R14: 46069 | S14: 46069 | U14: 46071 | V14: 46071 | W14: =IFERROR( IF( OR(ISBLANK(R14), ISBLANK(S14)), "", MAX( 1, IF( NETWORKDAYS(R14, S14, Holiday_Dates) <= 0, 1, NETWORKDAYS(R14, S14, Holiday_Dates) - IF(R14 = S14, 0, 1) ) ) ), "" ) -> 1 | X14: =IF( OR(ISBLANK(S14), ISBLANK(T14)), "", MAX( 1, IF( NETWORKDAYS(S14, T14, Holiday_Dates) <= 0, 1, NETWORKDAYS(S14, T14, Holiday_Dates) - IF(S14 = T14, 0, 1) ) ) ) | Y14: =IFERROR( IF( OR(ISBLANK(S14), AND(ISBLANK(T14), ISBLANK(U14))), "", MAX( 1, IF( NETWORKDAYS(IF(NOT(ISBLANK(U14)), U14, T14), U14, Holiday_Dates) <= 0, 1, NETWORKDAYS(IF(NOT(ISBLANK(U14)), U14, T14), U14, Holiday_Dates) - IF(IF(NOT(ISBLANK(U14)), U14, T14) = U14, 0, 1) ) ) ), "" ) -> 1 | Z14: =IF( OR(ISBLANK(U14), ISBLANK(V14)), "", MAX(1, IF( NETWORKDAYS(U14, V14) <= 0, 1, NETWORKDAYS(U14, V14) - IF(U14 = V14, 0, 1) )) ) -> 1 | AA14: Marshalle Julluice V. Catua | AB14: 27 | AC14: Weighing scale | AD14: Biodegradable, Recyclables, Residuals | AE14: No available data | AF14: 21458.24 | AG14: No available data | AH14: OPERATIONAL | AJ14: Non Compliant | AK14: 1. During the monitoring, a significant volume of piled-up waste was found adjacent to the Material Recovery Facility (MRF) covering approximately 1,500 square meters. and a height of approximately 1 meter. 2. The solid waste was found outside the covered shed of the MRF. The waste was left exposed to environmental elements,, causing issues such as foul odor dispersion, insect/animal infestation and surface leachate generation. 3. The solid waste is in direct contact with the soil surface, posing potential leachate and contamination of the groundwater resources due to the absence of proper storage, such as flooring, roof, and drainage canal. | AL14: 46071 | AP14: 46084 | AS14: https://embco-my.sharepoint.com/:w:/g/personal/eswmr3_emb_gov_ph/IQADS3wcWNwsTaexAkO_kT3nAf8i2fZB-d2qfLs1PVQY6Zg?e=v3CNgW
A15: Nueva Ecija | B15: Licab | C15: Villa Rosa | D15: MBA | E15: 1st | F15: 15.547317 | G15: 120.7532 | H15: =CONCATENATE(F15,",",G15) -> 15.547317,120.753197 | I15: EMB FUNDED MRF | J15: 1 | K15: 2016 | L15: 270000 | M15: Gem C. Vicencio | O15: Zosimo P. Suyat | P15: 2.February | Q15: R3-2026-002923 | R15: 46050 | S15: 46066 | U15: 46071 | V15: 46071 | W15: =IFERROR( IF( OR(ISBLANK(R15), ISBLANK(S15)), "", MAX( 1, IF( NETWORKDAYS(R15, S15, Holiday_Dates) <= 0, 1, NETWORKDAYS(R15, S15, Holiday_Dates) - IF(R15 = S15, 0, 1) ) ) ), "" ) -> 12 | X15: =IF( OR(ISBLANK(S15), ISBLANK(T15)), "", MAX( 1, IF( NETWORKDAYS(S15, T15, Holiday_Dates) <= 0, 1, NETWORKDAYS(S15, T15, Holiday_Dates) - IF(S15 = T15, 0, 1) ) ) ) | Y15: =IFERROR( IF( OR(ISBLANK(S15), AND(ISBLANK(T15), ISBLANK(U15))), "", MAX( 1, IF( NETWORKDAYS(IF(NOT(ISBLANK(U15)), U15, T15), U15, Holiday_Dates) <= 0, 1, NETWORKDAYS(IF(NOT(ISBLANK(U15)), U15, T15), U15, Holiday_Dates) - IF(IF(NOT(ISBLANK(U15)), U15, T15) = U15, 0, 1) ) ) ), "" ) -> 1 | Z15: =IF( OR(ISBLANK(U15), ISBLANK(V15)), "", MAX(1, IF( NETWORKDAYS(U15, V15) <= 0, 1, NETWORKDAYS(U15, V15) - IF(U15 = V15, 0, 1) )) ) -> 1 | AA15: Marshalle Julluice V. Catua | AB15: 11 | AC15: Rotary Composters, Biowaste shredder | AD15: Biodegradable, Recyclables, Residuals | AE15: No available data | AF15: 8506.8 | AG15: No available data | AH15: OPERATIONAL | AJ15: Non Compliant | AK15: Waste piles were present at the entrance and surrounding areas, exposed to rain and environmental elements. Mixed solid waste inside the facility lacked clearly designated areas for segregation. Wall panels showed signs of deterioration, including visible holes. Two rotary composters were installed but not fully utilized. Housekeeping and sanitation practices were inadequate. No clear safety markings were present. Workers did not have or consistently use personal protective equipment (PPE). Improper storage of recyclables. Absence of record-keeping. Operational efficiency and compliance of the facility were negatively affected. | AL15: 46079 | AS15: https://embco-my.sharepoint.com/:w:/g/personal/eswmr3_emb_gov_ph/IQDD4f04XQcgSYOEbGd72zeOATIn86sOI-5cUuHBPRjLg3M?e=9pHWTO
A16: Pampanga | B16: Sto. Tomas | C16: San Vicente | D16: MBA | E16: 4th | F16: 15.003997 | G16: 120.69708 | H16: =CONCATENATE(F16,",",G16) -> 15.003997,120.697078 | I16: EMB FUNDED MRF | J16: 1 | K16: 2017 | L16: 270000 | M16: Elyza A. Evilla | O16: John Sherwin Loquellano | P16: 2.February | Q16: R3-2026-003792 | R16: 46058 | S16: 46059 | U16: 46065 | V16: 46065 | W16: =IFERROR( IF( OR(ISBLANK(R16), ISBLANK(S16)), "", MAX( 1, IF( NETWORKDAYS(R16, S16, Holiday_Dates) <= 0, 1, NETWORKDAYS(R16, S16, Holiday_Dates) - IF(R16 = S16, 0, 1) ) ) ), "" ) -> 1 | X16: =IF( OR(ISBLANK(S16), ISBLANK(T16)), "", MAX( 1, IF( NETWORKDAYS(S16, T16, Holiday_Dates) <= 0, 1, NETWORKDAYS(S16, T16, Holiday_Dates) - IF(S16 = T16, 0, 1) ) ) ) | Y16: =IFERROR( IF( OR(ISBLANK(S16), AND(ISBLANK(T16), ISBLANK(U16))), "", MAX( 1, IF( NETWORKDAYS(IF(NOT(ISBLANK(U16)), U16, T16), U16, Holiday_Dates) <= 0, 1, NETWORKDAYS(IF(NOT(ISBLANK(U16)), U16, T16), U16, Holiday_Dates) - IF(IF(NOT(ISBLANK(U16)), U16, T16) = U16, 0, 1) ) ) ), "" ) -> 1 | Z16: =IF( OR(ISBLANK(U16), ISBLANK(V16)), "", MAX(1, IF( NETWORKDAYS(U16, V16) <= 0, 1, NETWORKDAYS(U16, V16) - IF(U16 = V16, 0, 1) )) ) -> 1 | AB16: 7 | AC16: Wheel Loader, Rotary Composter | AD16: Biodegradable, Recyclables,Residual | AE16: No available data | AF16: No available data | AG16: No available data | AH16: OPERATIONAL | AJ16: • The LGU Sto. Tomas is advised to comply with Section 37 of RA 9003 or the Prohibition Against the Use of Open Dumps for Solid Waste, which states that “no open dumps shall be established and operated, nor any practice or disposal of solid waste by any person, including LGUs…” • Recommended for issuance of a show cause order/cease and desist order (CDO) to discuss the issue and elicit a formal commitment from the LGU to comply with the provisions of RA 9003. • Ensure that there is an adequate power source to utilize the use of both equipment as per agreed in the signed MOA under Article III, Section 4 : Responsibilities of the LGU Paragraphs (a),(c)(d) (e) (f) and (g) | AK16: • The MRF has an open dumping of waste beside the facility. • As per MENRO Manalese, both equipment were non-functional since there is no electricity in the Municipal MRF and due to lack of knowledge in operating the equipments. | AS16: https://embco-my.sharepoint.com/:w:/g/personal/eswmr3_emb_gov_ph/IQCIg2KVghdkTIIYCLM0gFeaAdwWp1-e6e57rggX_kmkDyc?e=E81uzu
A17: Tarlac | B17: Capas | C17: Cutcut 1st | D17: MBA | E17: 3rd | F17: 15.320422 | G17: 120.5893 | H17: =CONCATENATE(F17,",",G17) -> 15.32042229,120.5892983 | I17: EMB FUNDED MRF | J17: 1 | K17: 2019 | L17: 502714.29 | M17: Gretzhen M. Apolonio | O17: Jan Emerson C. Gonzales | P17: 2.February | Q17: R3-2026-004714 | R17: 46057 | S17: 46065 | U17: 46069 | V17: 46069 | W17: =IFERROR( IF( OR(ISBLANK(R17), ISBLANK(S17)), "", MAX( 1, IF( NETWORKDAYS(R17, S17, Holiday_Dates) <= 0, 1, NETWORKDAYS(R17, S17, Holiday_Dates) - IF(R17 = S17, 0, 1) ) ) ), "" ) -> 6 | X17: =IF( OR(ISBLANK(S17), ISBLANK(T17)), "", MAX( 1, IF( NETWORKDAYS(S17, T17, Holiday_Dates) <= 0, 1, NETWORKDAYS(S17, T17, Holiday_Dates) - IF(S17 = T17, 0, 1) ) ) ) | Y17: =IFERROR( IF( OR(ISBLANK(S17), AND(ISBLANK(T17), ISBLANK(U17))), "", MAX( 1, IF( NETWORKDAYS(IF(NOT(ISBLANK(U17)), U17, T17), U17, Holiday_Dates) <= 0, 1, NETWORKDAYS(IF(NOT(ISBLANK(U17)), U17, T17), U17, Holiday_Dates) - IF(IF(NOT(ISBLANK(U17)), U17, T17) = U17, 0, 1) ) ) ), "" ) -> 1 | Z17: =IF( OR(ISBLANK(U17), ISBLANK(V17)), "", MAX(1, IF( NETWORKDAYS(U17, V17) <= 0, 1, NETWORKDAYS(U17, V17) - IF(U17 = V17, 0, 1) )) ) -> 1 | AC17: Bio shredder, Bio Composter | AD17: Biodegradable, Recyclables,Residual | AS17: https://embco-my.sharepoint.com/:w:/g/personal/eswmr3_emb_gov_ph/IQCrq8yD-9zgRYo_CnBgc3JwAXW5C7jjkDK0zNir7n04ypA?e=kdITBn
A18: Tarlac | B18: City Of Tarlac | C18: Tibag | D18: MBA | E18: 2nd | F18: 15.487158 | G18: 120.57139 | H18: =CONCATENATE(F18,",",G18) -> 15.487158,120.571386 | I18: EMB FUNDED MRF | J18: 1 | K18: 2019 | L18: 502714.29 | M18: Joshua A. Capones | O18: Jan Emerson C. Gonzales | P18: 2.February | Q18: R3-2026-003834 | R18: 46058 | S18: 46059 | U18: 46069 | V18: 46069 | W18: =IFERROR( IF( OR(ISBLANK(R18), ISBLANK(S18)), "", MAX( 1, IF( NETWORKDAYS(R18, S18, Holiday_Dates) <= 0, 1, NETWORKDAYS(R18, S18, Holiday_Dates) - IF(R18 = S18, 0, 1) ) ) ), "" ) -> 1 | X18: =IF( OR(ISBLANK(S18), ISBLANK(T18)), "", MAX( 1, IF( NETWORKDAYS(S18, T18, Holiday_Dates) <= 0, 1, NETWORKDAYS(S18, T18, Holiday_Dates) - IF(S18 = T18, 0, 1) ) ) ) | Y18: =IFERROR( IF( OR(ISBLANK(S18), AND(ISBLANK(T18), ISBLANK(U18))), "", MAX( 1, IF( NETWORKDAYS(IF(NOT(ISBLANK(U18)), U18, T18), U18, Holiday_Dates) <= 0, 1, NETWORKDAYS(IF(NOT(ISBLANK(U18)), U18, T18), U18, Holiday_Dates) - IF(IF(NOT(ISBLANK(U18)), U18, T18) = U18, 0, 1) ) ) ), "" ) -> 1 | Z18: =IF( OR(ISBLANK(U18), ISBLANK(V18)), "", MAX(1, IF( NETWORKDAYS(U18, V18) <= 0, 1, NETWORKDAYS(U18, V18) - IF(U18 = V18, 0, 1) )) ) -> 1 | AB18: 1 | AC18: Bottle Crusher, Brix mixer Machine, Sand Mixer, BioWaste Shredder, Glass Shredder, Rotary Composter, Vermi Composting, Bricks Maker, Charcoal Briquetting | AD18: Biodegradable, Recyclables | AE18: 305 | AF18: 287036.96 | AG18: 0.001 | AH18: OPERATIONAL | AS18: https://embco-my.sharepoint.com/:w:/g/personal/eswmr3_emb_gov_ph/IQDmiAEOWoA5TICVNYuIX7oQAYbBk5z0pUOWpiCpZPt1x_s?e=vyM27X
A19: Bataan | B19: Bagac | C19: Binuangan | D19: MBA | E19: 3rd | F19: 14.516517 | G19: 120.38641 | H19: =CONCATENATE(F19,",",G19) -> 14.516517,120.386411 | I19: EMB FUNDED BRGY MRF | J19: 1 | K19: 2018 | L19: 285000 | M19: Laurence Radasa | O19: Christle D. David | P19: 3.March | Q19: R3-2026-006187 | R19: 46076 | S19: 46078 | U19: 46078 | V19: 46079 | W19: =IFERROR( IF( OR(ISBLANK(R19), ISBLANK(S19)), "", MAX( 1, IF( NETWORKDAYS(R19, S19, Holiday_Dates) <= 0, 1, NETWORKDAYS(R19, S19, Holiday_Dates) - IF(R19 = S19, 0, 1) ) ) ), "" ) -> 2 | X19: =IF( OR(ISBLANK(S19), ISBLANK(T19)), "", MAX( 1, IF( NETWORKDAYS(S19, T19, Holiday_Dates) <= 0, 1, NETWORKDAYS(S19, T19, Holiday_Dates) - IF(S19 = T19, 0, 1) ) ) ) | Y19: =IFERROR( IF( OR(ISBLANK(S19), AND(ISBLANK(T19), ISBLANK(U19))), "", MAX( 1, IF( NETWORKDAYS(IF(NOT(ISBLANK(U19)), U19, T19), U19, Holiday_Dates) <= 0, 1, NETWORKDAYS(IF(NOT(ISBLANK(U19)), U19, T19), U19, Holiday_Dates) - IF(IF(NOT(ISBLANK(U19)), U19, T19) = U19, 0, 1) ) ) ), "" ) -> 1 | Z19: =IF( OR(ISBLANK(U19), ISBLANK(V19)), "", MAX(1, IF( NETWORKDAYS(U19, V19) <= 0, 1, NETWORKDAYS(U19, V19) - IF(U19 = V19, 0, 1) )) ) -> 1 | AB19: 1 | AC19: None | AD19: Recyclable | AE19: 45 | AF19: 58.61 | AG19: 0.7678 | AH19: OPERATIONAL | AI19: MRS
A20: Bataan | B20: City Of Balanga | C20: San Jose | D20: MBA | E20: 2nd | F20: 14.671465 | G20: 120.53447 | H20: =CONCATENATE(F20,",",G20) -> 14.671465,120.534471 | I20: EMB FUNDED BRGY MRF | J20: 1 | K20: 2018 | L20: 285000 | M20: Dennis Tolentino | O20: Christle D. David | P20: 3.March | W20: =IFERROR( IF( OR(ISBLANK(R20), ISBLANK(S20)), "", MAX( 1, IF( NETWORKDAYS(R20, S20, Holiday_Dates) <= 0, 1, NETWORKDAYS(R20, S20, Holiday_Dates) - IF(R20 = S20, 0, 1) ) ) ), "" ) | X20: =IF( OR(ISBLANK(S20), ISBLANK(T20)), "", MAX( 1, IF( NETWORKDAYS(S20, T20, Holiday_Dates) <= 0, 1, NETWORKDAYS(S20, T20, Holiday_Dates) - IF(S20 = T20, 0, 1) ) ) ) | Y20: =IFERROR( IF( OR(ISBLANK(S20), AND(ISBLANK(T20), ISBLANK(U20))), "", MAX( 1, IF( NETWORKDAYS(IF(NOT(ISBLANK(U20)), U20, T20), U20, Holiday_Dates) <= 0, 1, NETWORKDAYS(IF(NOT(ISBLANK(U20)), U20, T20), U20, Holiday_Dates) - IF(IF(NOT(ISBLANK(U20)), U20, T20) = U20, 0, 1) ) ) ), "" ) | Z20: =IF( OR(ISBLANK(U20), ISBLANK(V20)), "", MAX(1, IF( NETWORKDAYS(U20, V20) <= 0, 1, NETWORKDAYS(U20, V20) - IF(U20 = V20, 0, 1) )) )
A21: Bulacan | B21: Bustos | C21: Catacte | D21: MBA | E21: 2nd | F21: 14.929217 | G21: 120.94235 | H21: =CONCATENATE(F21,",",G21) -> 14.929217,120.942353 | I21: EMB FUNDED MRF | J21: 1 | K21: 2019 | L21: 502714 | M21: Ronaldo P. Roque, Jr. | O21: Diozelle L. Cabalar | P21: 3.March | W21: =IFERROR( IF( OR(ISBLANK(R21), ISBLANK(S21)), "", MAX( 1, IF( NETWORKDAYS(R21, S21, Holiday_Dates) <= 0, 1, NETWORKDAYS(R21, S21, Holiday_Dates) - IF(R21 = S21, 0, 1) ) ) ), "" ) | X21: =IF( OR(ISBLANK(S21), ISBLANK(T21)), "", MAX( 1, IF( NETWORKDAYS(S21, T21, Holiday_Dates) <= 0, 1, NETWORKDAYS(S21, T21, Holiday_Dates) - IF(S21 = T21, 0, 1) ) ) ) | Y21: =IFERROR( IF( OR(ISBLANK(S21), AND(ISBLANK(T21), ISBLANK(U21))), "", MAX( 1, IF( NETWORKDAYS(IF(NOT(ISBLANK(U21)), U21, T21), U21, Holiday_Dates) <= 0, 1, NETWORKDAYS(IF(NOT(ISBLANK(U21)), U21, T21), U21, Holiday_Dates) - IF(IF(NOT(ISBLANK(U21)), U21, T21) = U21, 0, 1) ) ) ), "" ) | Z21: =IF( OR(ISBLANK(U21), ISBLANK(V21)), "", MAX(1, IF( NETWORKDAYS(U21, V21) <= 0, 1, NETWORKDAYS(U21, V21) - IF(U21 = V21, 0, 1) )) )
A22: Bulacan | B22: City Of Meycauyan | C22: Caingin | D22: MBA | E22: 4th | F22: 14.725394 | G22: 120.96915 | H22: =CONCATENATE(F22,",",G22) -> 14.725394,120.969152 | I22: EMB FUNDED BRGY MRF | J22: 1 | K22: 2017 | L22: 460000 | M22: James Wilson T. Pena | O22: Diozelle L. Cabalar | P22: 3.March | W22: =IFERROR( IF( OR(ISBLANK(R22), ISBLANK(S22)), "", MAX( 1, IF( NETWORKDAYS(R22, S22, Holiday_Dates) <= 0, 1, NETWORKDAYS(R22, S22, Holiday_Dates) - IF(R22 = S22, 0, 1) ) ) ), "" ) | X22: =IF( OR(ISBLANK(S22), ISBLANK(T22)), "", MAX( 1, IF( NETWORKDAYS(S22, T22, Holiday_Dates) <= 0, 1, NETWORKDAYS(S22, T22, Holiday_Dates) - IF(S22 = T22, 0, 1) ) ) ) | Y22: =IFERROR( IF( OR(ISBLANK(S22), AND(ISBLANK(T22), ISBLANK(U22))), "", MAX( 1, IF( NETWORKDAYS(IF(NOT(ISBLANK(U22)), U22, T22), U22, Holiday_Dates) <= 0, 1, NETWORKDAYS(IF(NOT(ISBLANK(U22)), U22, T22), U22, Holiday_Dates) - IF(IF(NOT(ISBLANK(U22)), U22, T22) = U22, 0, 1) ) ) ), "" ) | Z22: =IF( OR(ISBLANK(U22), ISBLANK(V22)), "", MAX(1, IF( NETWORKDAYS(U22, V22) <= 0, 1, NETWORKDAYS(U22, V22) - IF(U22 = V22, 0, 1) )) )
A23: Bulacan | B23: Guiguinto | C23: Tuktukan | D23: MBA | E23: 5th | F23: 14.742097 | G23: 120.91224 | H23: =CONCATENATE(F23,",",G23) -> 14.742097,120.912244 | I23: EMB FUNDED MRF | J23: 2 | K23: 2014 & 2021 | L23: 250000 & 179444.44 | M23: Jasmin Marie N. Siapco | O23: Diozelle L. Cabalar | P23: 3.March | W23: =IFERROR( IF( OR(ISBLANK(R23), ISBLANK(S23)), "", MAX( 1, IF( NETWORKDAYS(R23, S23, Holiday_Dates) <= 0, 1, NETWORKDAYS(R23, S23, Holiday_Dates) - IF(R23 = S23, 0, 1) ) ) ), "" ) | X23: =IF( OR(ISBLANK(S23), ISBLANK(T23)), "", MAX( 1, IF( NETWORKDAYS(S23, T23, Holiday_Dates) <= 0, 1, NETWORKDAYS(S23, T23, Holiday_Dates) - IF(S23 = T23, 0, 1) ) ) ) | Y23: =IFERROR( IF( OR(ISBLANK(S23), AND(ISBLANK(T23), ISBLANK(U23))), "", MAX( 1, IF( NETWORKDAYS(IF(NOT(ISBLANK(U23)), U23, T23), U23, Holiday_Dates) <= 0, 1, NETWORKDAYS(IF(NOT(ISBLANK(U23)), U23, T23), U23, Holiday_Dates) - IF(IF(NOT(ISBLANK(U23)), U23, T23) = U23, 0, 1) ) ) ), "" ) | Z23: =IF( OR(ISBLANK(U23), ISBLANK(V23)), "", MAX(1, IF( NETWORKDAYS(U23, V23) <= 0, 1, NETWORKDAYS(U23, V23) - IF(U23 = V23, 0, 1) )) )
A24: Nueva Ecija | B24: City Of Cabanatuan | C24: Pagas | D24: MBA | E24: 3rd | F24: 15.505076 | G24: 120.94996 | H24: =CONCATENATE(F24,",",G24) -> 15.505076,120.949955 | I24: EMB FUNDED MRF | J24: 1 | K24: 2018 | L24: 475000 | M24: Christian Jem L. Buluran | O24: Zosimo P. Suyat | P24: 3.March | W24: =IFERROR( IF( OR(ISBLANK(R24), ISBLANK(S24)), "", MAX( 1, IF( NETWORKDAYS(R24, S24, Holiday_Dates) <= 0, 1, NETWORKDAYS(R24, S24, Holiday_Dates) - IF(R24 = S24, 0, 1) ) ) ), "" ) | X24: =IF( OR(ISBLANK(S24), ISBLANK(T24)), "", MAX( 1, IF( NETWORKDAYS(S24, T24, Holiday_Dates) <= 0, 1, NETWORKDAYS(S24, T24, Holiday_Dates) - IF(S24 = T24, 0, 1) ) ) ) | Y24: =IFERROR( IF( OR(ISBLANK(S24), AND(ISBLANK(T24), ISBLANK(U24))), "", MAX( 1, IF( NETWORKDAYS(IF(NOT(ISBLANK(U24)), U24, T24), U24, Holiday_Dates) <= 0, 1, NETWORKDAYS(IF(NOT(ISBLANK(U24)), U24, T24), U24, Holiday_Dates) - IF(IF(NOT(ISBLANK(U24)), U24, T24) = U24, 0, 1) ) ) ), "" ) | Z24: =IF( OR(ISBLANK(U24), ISBLANK(V24)), "", MAX(1, IF( NETWORKDAYS(U24, V24) <= 0, 1, NETWORKDAYS(U24, V24) - IF(U24 = V24, 0, 1) )) )
A25: Nueva Ecija | B25: Llanera | C25: San Felipe | D25: MBA | E25: 2nd | F25: 15.704369 | G25: 121.04777 | H25: =CONCATENATE(F25,",",G25) -> 15.704369,121.047766 | I25: EMB FUNDED MRF | J25: 3 | K25: 2014 & 2019 & 2020 | L25: 250000 & 502714.29 & 190000 | M25: Hosannah R. Sabio | O25: Zosimo P. Suyat | P25: 3.March | W25: =IFERROR( IF( OR(ISBLANK(R25), ISBLANK(S25)), "", MAX( 1, IF( NETWORKDAYS(R25, S25, Holiday_Dates) <= 0, 1, NETWORKDAYS(R25, S25, Holiday_Dates) - IF(R25 = S25, 0, 1) ) ) ), "" ) | X25: =IF( OR(ISBLANK(S25), ISBLANK(T25)), "", MAX( 1, IF( NETWORKDAYS(S25, T25, Holiday_Dates) <= 0, 1, NETWORKDAYS(S25, T25, Holiday_Dates) - IF(S25 = T25, 0, 1) ) ) ) | Y25: =IFERROR( IF( OR(ISBLANK(S25), AND(ISBLANK(T25), ISBLANK(U25))), "", MAX( 1, IF( NETWORKDAYS(IF(NOT(ISBLANK(U25)), U25, T25), U25, Holiday_Dates) <= 0, 1, NETWORKDAYS(IF(NOT(ISBLANK(U25)), U25, T25), U25, Holiday_Dates) - IF(IF(NOT(ISBLANK(U25)), U25, T25) = U25, 0, 1) ) ) ), "" ) | Z25: =IF( OR(ISBLANK(U25), ISBLANK(V25)), "", MAX(1, IF( NETWORKDAYS(U25, V25) <= 0, 1, NETWORKDAYS(U25, V25) - IF(U25 = V25, 0, 1) )) )
A26: Nueva Ecija | B26: San Isidro | C26: Tabon | D26: MBA | E26: 4th | F26: 15.293813 | G26: 120.90636 | H26: =CONCATENATE(F26,",",G26) -> 15.293813,120.906358 | I26: EMB FUNDED MRF | J26: 1 | K26: 2019 | L26: 502714.29 | M26: Christine Ann V. Ramos | O26: Zosimo P. Suyat | P26: 3.March | Q26: R3-2026-002000 | R26: 46057 | S26: 46058 | U26: 46063 | W26: =IFERROR( IF( OR(ISBLANK(R26), ISBLANK(S26)), "", MAX( 1, IF( NETWORKDAYS(R26, S26, Holiday_Dates) <= 0, 1, NETWORKDAYS(R26, S26, Holiday_Dates) - IF(R26 = S26, 0, 1) ) ) ), "" ) -> 1 | X26: =IF( OR(ISBLANK(S26), ISBLANK(T26)), "", MAX( 1, IF( NETWORKDAYS(S26, T26, Holiday_Dates) <= 0, 1, NETWORKDAYS(S26, T26, Holiday_Dates) - IF(S26 = T26, 0, 1) ) ) ) | Y26: =IFERROR( IF( OR(ISBLANK(S26), AND(ISBLANK(T26), ISBLANK(U26))), "", MAX( 1, IF( NETWORKDAYS(IF(NOT(ISBLANK(U26)), U26, T26), U26, Holiday_Dates) <= 0, 1, NETWORKDAYS(IF(NOT(ISBLANK(U26)), U26, T26), U26, Holiday_Dates) - IF(IF(NOT(ISBLANK(U26)), U26, T26) = U26, 0, 1) ) ) ), "" ) -> 1 | Z26: =IF( OR(ISBLANK(U26), ISBLANK(V26)), "", MAX(1, IF( NETWORKDAYS(U26, V26) <= 0, 1, NETWORKDAYS(U26, V26) - IF(U26 = V26, 0, 1) )) ) | AB26: 9 | AD26: Recyclables, Biodegradables, Residuals | AE26: 3252.89 | AF26: 18543.6 | AG26: 0.1754 | AH26: OPERATIONAL | AI26: Operational | AJ26: Compliant | AK26: n/a | AL26: n/a
A27: Pampanga | B27: Mabalacat City | C27: Sapang Balen | D27: MBA | E27: 1st | F27: 15.259975 | G27: 120.59637 | H27: =CONCATENATE(F27,",",G27) -> 15.259975,120.596369 | I27: EMB FUNDED MRF | J27: 1 | K27: 2013 | L27: 500000 | M27: Roger T. Encarnacion II | O27: Jun D. Guillermo | P27: 3.March | Q27: R3-2026-008578 | R27: 46091 | S27: 46094 | U27: 46097 | W27: =IFERROR( IF( OR(ISBLANK(R27), ISBLANK(S27)), "", MAX( 1, IF( NETWORKDAYS(R27, S27, Holiday_Dates) <= 0, 1, NETWORKDAYS(R27, S27, Holiday_Dates) - IF(R27 = S27, 0, 1) ) ) ), "" ) -> 3 | X27: =IF( OR(ISBLANK(S27), ISBLANK(T27)), "", MAX( 1, IF( NETWORKDAYS(S27, T27, Holiday_Dates) <= 0, 1, NETWORKDAYS(S27, T27, Holiday_Dates) - IF(S27 = T27, 0, 1) ) ) ) | Y27: =IFERROR( IF( OR(ISBLANK(S27), AND(ISBLANK(T27), ISBLANK(U27))), "", MAX( 1, IF( NETWORKDAYS(IF(NOT(ISBLANK(U27)), U27, T27), U27, Holiday_Dates) <= 0, 1, NETWORKDAYS(IF(NOT(ISBLANK(U27)), U27, T27), U27, Holiday_Dates) - IF(IF(NOT(ISBLANK(U27)), U27, T27) = U27, 0, 1) ) ) ), "" ) -> 1 | Z27: =IF( OR(ISBLANK(U27), ISBLANK(V27)), "", MAX(1, IF( NETWORKDAYS(U27, V27) <= 0, 1, NETWORKDAYS(U27, V27) - IF(U27 = V27, 0, 1) )) ) | AB27: 27 | AC27: Weighing scale Biowaste shredder Rotary composter | AD27: Recyclables, Biodegradables, Residuals | AE27: 111058.51 | AF27: 159635.63 | AG27: 76.67 | AH27: OPERATIONAL
A28: Tarlac | B28: La Paz | C28: Sierra | D28: MBA | E28: 3rd | F28: 15.42272 | G28: 120.70819 | H28: =CONCATENATE(F28,",",G28) -> 15.42272,120.708189 | I28: EMB FUNDED MRF | J28: 1 | K28: 2019 | L28: 502714.29 | M28: Gretzhen M. Apolonio | O28: Jan Emerson C. Gonzales | P28: 3.March | Q28: R3-2026-007692 | R28: 46085 | S28: 46089 | U28: 46090 | V28: 46090 | W28: =IFERROR( IF( OR(ISBLANK(R28), ISBLANK(S28)), "", MAX( 1, IF( NETWORKDAYS(R28, S28, Holiday_Dates) <= 0, 1, NETWORKDAYS(R28, S28, Holiday_Dates) - IF(R28 = S28, 0, 1) ) ) ), "" ) -> 2 | X28: =IF( OR(ISBLANK(S28), ISBLANK(T28)), "", MAX( 1, IF( NETWORKDAYS(S28, T28, Holiday_Dates) <= 0, 1, NETWORKDAYS(S28, T28, Holiday_Dates) - IF(S28 = T28, 0, 1) ) ) ) | Y28: =IFERROR( IF( OR(ISBLANK(S28), AND(ISBLANK(T28), ISBLANK(U28))), "", MAX( 1, IF( NETWORKDAYS(IF(NOT(ISBLANK(U28)), U28, T28), U28, Holiday_Dates) <= 0, 1, NETWORKDAYS(IF(NOT(ISBLANK(U28)), U28, T28), U28, Holiday_Dates) - IF(IF(NOT(ISBLANK(U28)), U28, T28) = U28, 0, 1) ) ) ), "" ) -> 1 | Z28: =IF( OR(ISBLANK(U28), ISBLANK(V28)), "", MAX(1, IF( NETWORKDAYS(U28, V28) <= 0, 1, NETWORKDAYS(U28, V28) - IF(U28 = V28, 0, 1) )) ) -> 1 | AC28: Granuling Machine, Bottle Crusher, plastic granulating machine, Bircks Mixer Machine, Rotary Mixre, Bio Shredder, Bio COmposter, Bricks Molder | AD28: Recyclables, Biodegradables, Residuals | AE28: no data | AF28: 16802.72 | AG28: no data | AH28: OPERATIONAL
A29: Zambales | B29: San Narciso | C29: San Pascual | D29: OUTSIDE MBA | E29: 2nd | F29: 15.016275 | G29: 120.08732 | H29: =CONCATENATE(F29,",",G29) -> 15.016275,120.087317 | I29: EMB FUNDED MRF | J29: 2 | K29: 2019 & 2021 | L29: 682158.73 / 179444.44 | M29: Larizze Anne Santos | O29: Jun D. Guillermo | P29: 3.March | Q29: R3-2026-008795 | R29: 46092 | S29: 46097 | W29: =IFERROR( IF( OR(ISBLANK(R29), ISBLANK(S29)), "", MAX( 1, IF( NETWORKDAYS(R29, S29, Holiday_Dates) <= 0, 1, NETWORKDAYS(R29, S29, Holiday_Dates) - IF(R29 = S29, 0, 1) ) ) ), "" ) -> 3 | X29: =IF( OR(ISBLANK(S29), ISBLANK(T29)), "", MAX( 1, IF( NETWORKDAYS(S29, T29, Holiday_Dates) <= 0, 1, NETWORKDAYS(S29, T29, Holiday_Dates) - IF(S29 = T29, 0, 1) ) ) ) | Y29: =IFERROR( IF( OR(ISBLANK(S29), AND(ISBLANK(T29), ISBLANK(U29))), "", MAX( 1, IF( NETWORKDAYS(IF(NOT(ISBLANK(U29)), U29, T29), U29, Holiday_Dates) <= 0, 1, NETWORKDAYS(IF(NOT(ISBLANK(U29)), U29, T29), U29, Holiday_Dates) - IF(IF(NOT(ISBLANK(U29)), U29, T29) = U29, 0, 1) ) ) ), "" ) | Z29: =IF( OR(ISBLANK(U29), ISBLANK(V29)), "", MAX(1, IF( NETWORKDAYS(U29, V29) <= 0, 1, NETWORKDAYS(U29, V29) - IF(U29 = V29, 0, 1) )) ) | AB29: 17 | AC29: Biowaste shredder Rotary composter | AD29: Recyclables,, Residuals | AE29: No records | AF29: No records | AG29: N/A | AH29: OPERATIONAL
A30: Aurora | B30: Baler | C30: Buhangin | D30: OUTSIDE MBA | E30: Lone | F30: 15.768186 | G30: 121.55754 | H30: =CONCATENATE(F30,",",G30) -> 15.768186,121.557544 | I30: EMB FUNDED BRGY MRF | J30: 1 | K30: 2018 | L30: 427500 | M30: Zaila Mae R. Leander | O30: Diozelle L. Cabalar | P30: 4.April | W30: =IFERROR( IF( OR(ISBLANK(R30), ISBLANK(S30)), "", MAX( 1, IF( NETWORKDAYS(R30, S30, Holiday_Dates) <= 0, 1, NETWORKDAYS(R30, S30, Holiday_Dates) - IF(R30 = S30, 0, 1) ) ) ), "" ) | X30: =IF( OR(ISBLANK(S30), ISBLANK(T30)), "", MAX( 1, IF( NETWORKDAYS(S30, T30, Holiday_Dates) <= 0, 1, NETWORKDAYS(S30, T30, Holiday_Dates) - IF(S30 = T30, 0, 1) ) ) ) | Y30: =IFERROR( IF( OR(ISBLANK(S30), AND(ISBLANK(T30), ISBLANK(U30))), "", MAX( 1, IF( NETWORKDAYS(IF(NOT(ISBLANK(U30)), U30, T30), U30, Holiday_Dates) <= 0, 1, NETWORKDAYS(IF(NOT(ISBLANK(U30)), U30, T30), U30, Holiday_Dates) - IF(IF(NOT(ISBLANK(U30)), U30, T30) = U30, 0, 1) ) ) ), "" ) | Z30: =IF( OR(ISBLANK(U30), ISBLANK(V30)), "", MAX(1, IF( NETWORKDAYS(U30, V30) <= 0, 1, NETWORKDAYS(U30, V30) - IF(U30 = V30, 0, 1) )) )
A31: Aurora | B31: Casiguran | C31: Calantas | D31: OUTSIDE MBA | E31: Lone | F31: 16.288091 | G31: 122.12228 | H31: =CONCATENATE(F31,",",G31) -> 16.288091,122.122282 | I31: EMB FUNDED MRF | J31: 1 | K31: 2019 | L31: 502714.29 | M31: Queenyvel Laguisma | O31: Diozelle L. Cabalar | P31: 4.April | W31: =IFERROR( IF( OR(ISBLANK(R31), ISBLANK(S31)), "", MAX( 1, IF( NETWORKDAYS(R31, S31, Holiday_Dates) <= 0, 1, NETWORKDAYS(R31, S31, Holiday_Dates) - IF(R31 = S31, 0, 1) ) ) ), "" ) | X31: =IF( OR(ISBLANK(S31), ISBLANK(T31)), "", MAX( 1, IF( NETWORKDAYS(S31, T31, Holiday_Dates) <= 0, 1, NETWORKDAYS(S31, T31, Holiday_Dates) - IF(S31 = T31, 0, 1) ) ) ) | Y31: =IFERROR( IF( OR(ISBLANK(S31), AND(ISBLANK(T31), ISBLANK(U31))), "", MAX( 1, IF( NETWORKDAYS(IF(NOT(ISBLANK(U31)), U31, T31), U31, Holiday_Dates) <= 0, 1, NETWORKDAYS(IF(NOT(ISBLANK(U31)), U31, T31), U31, Holiday_Dates) - IF(IF(NOT(ISBLANK(U31)), U31, T31) = U31, 0, 1) ) ) ), "" ) | Z31: =IF( OR(ISBLANK(U31), ISBLANK(V31)), "", MAX(1, IF( NETWORKDAYS(U31, V31) <= 0, 1, NETWORKDAYS(U31, V31) - IF(U31 = V31, 0, 1) )) )
A32: Aurora | B32: Maria Aurora | C32: Bannawag | D32: OUTSIDE MBA | E32: Lone | F32: 15.81486 | G32: 121.48001 | H32: =CONCATENATE(F32,",",G32) -> 15.81486,121.48001 | I32: EMB FUNDED MRF | J32: 1 | K32: 2020 | L32: 190000 | M32: Nikko Jay M. Valenzuela | O32: Diozelle L. Cabalar | P32: 4.April
A33: Bataan | B33: Dinalupihan | C33: Pagalanggang | D33: MBA | E33: 3rd | F33: 14.915296 | G33: 120.45313 | H33: =CONCATENATE(F33,",",G33) -> 14.915296,120.453133 | I33: EMB FUNDED MRF | J33: 1 | K33: 2015 | L33: 500000 | M33: John-lester Signio | O33: Christle D. David | P33: 4.April | W33: =IFERROR( IF( OR(ISBLANK(R33), ISBLANK(S33)), "", MAX( 1, IF( NETWORKDAYS(R33, S33, Holiday_Dates) <= 0, 1, NETWORKDAYS(R33, S33, Holiday_Dates) - IF(R33 = S33, 0, 1) ) ) ), "" ) | X33: =IF( OR(ISBLANK(S33), ISBLANK(T33)), "", MAX( 1, IF( NETWORKDAYS(S33, T33, Holiday_Dates) <= 0, 1, NETWORKDAYS(S33, T33, Holiday_Dates) - IF(S33 = T33, 0, 1) ) ) ) | Y33: =IFERROR( IF( OR(ISBLANK(S33), AND(ISBLANK(T33), ISBLANK(U33))), "", MAX( 1, IF( NETWORKDAYS(IF(NOT(ISBLANK(U33)), U33, T33), U33, Holiday_Dates) <= 0, 1, NETWORKDAYS(IF(NOT(ISBLANK(U33)), U33, T33), U33, Holiday_Dates) - IF(IF(NOT(ISBLANK(U33)), U33, T33) = U33, 0, 1) ) ) ), "" ) | Z33: =IF( OR(ISBLANK(U33), ISBLANK(V33)), "", MAX(1, IF( NETWORKDAYS(U33, V33) <= 0, 1, NETWORKDAYS(U33, V33) - IF(U33 = V33, 0, 1) )) )
A34: Bataan | B34: Limay | C34: San Franciso De Asis | D34: MBA | E34: 2nd | F34: 14.569686 | G34: 120.55153 | H34: =CONCATENATE(F34,",",G34) -> 14.569686,120.551528 | I34: EMB FUNDED MRF | J34: 1 | K34: 2019 | L34: 502714.29 | M34: Dennis Tolentino | O34: Christle D. David | P34: 4.April | W34: =IFERROR( IF( OR(ISBLANK(R34), ISBLANK(S34)), "", MAX( 1, IF( NETWORKDAYS(R34, S34, Holiday_Dates) <= 0, 1, NETWORKDAYS(R34, S34, Holiday_Dates) - IF(R34 = S34, 0, 1) ) ) ), "" ) | X34: =IF( OR(ISBLANK(S34), ISBLANK(T34)), "", MAX( 1, IF( NETWORKDAYS(S34, T34, Holiday_Dates) <= 0, 1, NETWORKDAYS(S34, T34, Holiday_Dates) - IF(S34 = T34, 0, 1) ) ) ) | Y34: =IFERROR( IF( OR(ISBLANK(S34), AND(ISBLANK(T34), ISBLANK(U34))), "", MAX( 1, IF( NETWORKDAYS(IF(NOT(ISBLANK(U34)), U34, T34), U34, Holiday_Dates) <= 0, 1, NETWORKDAYS(IF(NOT(ISBLANK(U34)), U34, T34), U34, Holiday_Dates) - IF(IF(NOT(ISBLANK(U34)), U34, T34) = U34, 0, 1) ) ) ), "" ) | Z34: =IF( OR(ISBLANK(U34), ISBLANK(V34)), "", MAX(1, IF( NETWORKDAYS(U34, V34) <= 0, 1, NETWORKDAYS(U34, V34) - IF(U34 = V34, 0, 1) )) )
A35: Bulacan | B35: Bocaue | C35: Batia | D35: MBA | E35: 5th | F35: 14.807481 | G35: 120.94629 | H35: =CONCATENATE(F35,",",G35) -> 14.807481,120.946294 | I35: EMB FUNDED MRF | J35: 2 | K35: 2016 & 2017 | L35: 270000 & 460000 | M35: Jasmin Marie N. Siapco | O35: Diozelle L. Cabalar | P35: 4.April | W35: =IFERROR( IF( OR(ISBLANK(R35), ISBLANK(S35)), "", MAX( 1, IF( NETWORKDAYS(R35, S35, Holiday_Dates) <= 0, 1, NETWORKDAYS(R35, S35, Holiday_Dates) - IF(R35 = S35, 0, 1) ) ) ), "" ) | X35: =IF( OR(ISBLANK(S35), ISBLANK(T35)), "", MAX( 1, IF( NETWORKDAYS(S35, T35, Holiday_Dates) <= 0, 1, NETWORKDAYS(S35, T35, Holiday_Dates) - IF(S35 = T35, 0, 1) ) ) ) | Y35: =IFERROR( IF( OR(ISBLANK(S35), AND(ISBLANK(T35), ISBLANK(U35))), "", MAX( 1, IF( NETWORKDAYS(IF(NOT(ISBLANK(U35)), U35, T35), U35, Holiday_Dates) <= 0, 1, NETWORKDAYS(IF(NOT(ISBLANK(U35)), U35, T35), U35, Holiday_Dates) - IF(IF(NOT(ISBLANK(U35)), U35, T35) = U35, 0, 1) ) ) ), "" ) | Z35: =IF( OR(ISBLANK(U35), ISBLANK(V35)), "", MAX(1, IF( NETWORKDAYS(U35, V35) <= 0, 1, NETWORKDAYS(U35, V35) - IF(U35 = V35, 0, 1) )) )
