Workbook

Sheet ENMO TARGET
A1: No. | B1: PROVINCE | C1: ENMO | D1: 10 Year Plan | E1: MRF | F1: Equipment | G1: ODS | H1: SLF | I1: Transfer Station | J1: RCA | K1: Trash Trap | L1: Preliminary Disinpection Facility
A2: 1 | B2: AURORA | C2: Zaila Mae R. Leander | D2: 4 | E2: 12 | F2: 3 | G2: 1 | H2: 1 | J2: 2 | L2: 1
A3: 2 | B3: AURORA | C3: Nikko Jay M. Valenzuela | D3: 2 | E3: 4 | F3: 2 | H3: 2 | L3: 1
A4: 3 | B4: AURORA | C4: Queenyvel R. Laguisma | D4: 3 | E4: 3 | F4: 3 | J4: 3 | L4: 1
A5: 4 | B5: BATAAN | C5: Dennis G. Tolentino | D5: 6 | E5: 10 | F5: 6 | G5: 2 | H5: 3 | L5: 1
A6: 5 | B6: BATAAN | C6: John-lester C. Signio | D6: 4 | E6: 4 | F6: 4 | G6: 3 | L6: 1
A7: 6 | B7: BATAAN | C7: Laurence Radasa | D7: 3 | E7: 12 | F7: 3 | G7: 2 | I7: 1 | J7: 2
A8: 7 | B8: BULACAN | C8: Jasmine Marie J. Nicolas | D8: 5 | E8: 7 | F8: 6 | I8: 3 | K8: 21
A9: 8 | B9: BULACAN | C9: Ronaldo P. Roque Jr. | D9: 5 | E9: 5 | F9: 5 | G9: 2 | I9: 2 | K9: 8
A10: 9 | B10: BULACAN | C10: Vacant
A11: 10 | B11: BULACAN | C11: James Wilson T. Peña | D11: 6 | E11: 8 | F11: 6 | G11: 2 | K11: 7 | L11: 2
A12: 11 | B12: NUEVA ECIJA | C12: Hosannah R. Sabio | D12: 6 | E12: 6 | F12: 7 | G12: 4 | I12: 6 | L12: 2
A13: 12 | B13: NUEVA ECIJA | C13: Gem C. Vicencio | D13: 6 | E13: 6 | F13: 6 | G13: 5 | I13: 6
A14: 13 | B14: NUEVA ECIJA | C14: Jan Emerson C. Gonzales | D14: 7 | E14: 9 | F14: 7 | H14: 2 | I14: 4 | J14: 1
A15: 14 | B15: NUEVA ECIJA | C15: Aser A. Inocencio, Jr. | D15: 7 | E15: 10 | F15: 8 | G15: 1 | H15: 1 | I15: 3 | J15: 3 | L15: 1
A16: 15 | B16: NUEVA ECIJA | C16: Christine Ann V. Ramos | D16: 6 | E16: 7 | F16: 7 | G16: 4 | I16: 6 | K16: 11 | L16: 1
A17: 16 | B17: PAMPANGA | C17: Roger T. Encarnacion II | D17: 6 | E17: 7 | F17: 6 | G17: 6 | K17: 8
A18: 17 | B18: PAMPANGA | C18: Elyza A. Evilla | D18: 5 | E18: 6 | F18: 5 | H18: 3 | I18: 2 | K18: 31 | L18: 4
A19: 18 | B19: PAMPANGA | C19: Glaiza S.Gaza | D19: 5 | E19: 6 | F19: 5 | G19: 4 | I19: 2 | K19: 14
A20: 19 | B20: PAMPANGA | C20: Ivy M. Castro | D20: 5 | E20: 4 | F20: 5 | G20: 2 | I20: 2 | K20: 13
A21: 20 | B21: TARLAC | C21: Joshua A. Capones | D21: 7 | E21: 6 | F21: 6 | G21: 1 | I21: 1 | L21: 2
A22: 21 | B22: TARLAC | C22: Jasper Kieht B. Pili | D22: 6 | E22: 5 | F22: 6 | G22: 1
A23: 22 | B23: TARLAC | C23: Gretzhen M. Apolonio | D23: 6 | E23: 7 | F23: 7 | H23: 1
A24: 23 | B24: ZAMBALES | C24: Larizze A. Santos | D24: 5 | E24: 5 | F24: 5 | G24: 2 | H24: 1 | I24: 2 | J24: 2 | L24: 2
A25: 24 | B25: ZAMBALES | C25: Vacant
A26: 25 | B26: ZAMBALES | C26: Ryan Ace R. Angel | D26: 3 | E26: 12 | F26: 3 | G26: 1 | H26: 2

Sheet Data Validation
A1: Type of Plan | C1: SLF | H1: MRF | K1: EQUIPEMENT | M1: ODS | Q1: PDS | T1: TRASH TRAP | W1: TRANSFER STATION | AD1: RCA
A2: Municipal / City Plan | B2: YES | H2: OPERATIONAL | K2: OPERATIONAL | M2: FULLY REHABILITATED | N2: COMPLIANT | Q2: OPERATIONAL | T2: OPERATIONAL | W2: OPERATIONAL | X2: FACILITY | Y2: LGU | AD2: OPERATIONAL | AE2: FACILITY
A3: Provincial Plan | B3: NO | H3: NON-OPERATIONAL | K3: NON-OPERATIONAL | M3: PARTIAL REHABILITATED | N3: NOT COMPLIANT | Q3: NON-OPERATIONAL | T3: NON-OPERATIONAL | W3: NON-OPERATIONAL | X3: BIN | Y3: PRIVATE OWNERSHIP | AD3: NON-OPERATIONAL | AE3: BIN
H4: UNDER CONSTRUCTION | K4: PLANNING TO TRANSFER | M4: NOT YET REHABILITATED | Q4: PLANNING TO TRANSFER | W4: UNDER CONSTRUCTION | AD4: UNDER CONSTRUCTION
B5: YES | H5: OPERATING AS OPEN DUMPSITE | K5: PLANNING TO RETURN | M5: OPERATING AS OPEN DUMPSITE | Q5: OTHER | W5: OPERATING AS OPEN DUMPSITE | AD5: OPERATING AS OPEN DUMPSITE
B6: NO
A7: Type of MRF | B7: N/A
A8: EMB FUNDED MRF
A9: EMB FUNDED BRGY MRF
A10: LGU FUNDED MRF
A13: 1.January
A14: 2.February
A15: 3.March
A16: 4.April
A17: 5.May
A18: 6.June
A19: 7.July
A20: 8.August
A21: 9.September
... A24: 12.December

Sheet Sheet2
A1: Province | B1: Nueva_Ecija
A3: Count of Accomplishment for the month of | B3: Accomplishment for the month of
A4: Municipality | B4: July | C4: August | D4: September | E4: October | F4: November | G4: Grand Total
A5: Aliaga | C5: 2 | D5: 2 | E5: 3 | G5: 7
A6: Bongabon | D6: 2 | G6: 2
A7: Cabanatuan City | C7: 4 | D7: 2 | E7: 3 | F7: 3 | G7: 12
A8: Cabiao | C8: 1 | D8: 2 | E8: 1 | G8: 4
A9: Carranglan | E9: 3 | G9: 3
A10: City of Gapan | D10: 4 | F10: 2 | G10: 6
A11: City of Palayan (Capital) | C11: 5 | E11: 3 | G11: 8
A12: Cuyapo | E12: 3 | G12: 3
A13: Guimba | C13: 4 | D13: 1 | G13: 5
A14: Jaen | B14: 1 | C14: 2 | D14: 1 | E14: 4 | G14: 8
A15: Laur | D15: 1 | G15: 1
A16: Licab | C16: 1 | G16: 1
A17: Llanera | C17: 1 | D17: 1 | E17: 3 | G17: 5
A18: Lupao | B18: 1 | D18: 2 | G18: 3
A19: Penaranda | E19: 3 | G19: 3
A20: Quezon | B20: 1 | D20: 1 | E20: 2 | F20: 3 | G20: 7
A21: Rizal | D21: 5 | G21: 5
A22: San Antonio | C22: 3 | F22: 3 | G22: 6
A23: San Jose City | C23: 3 | D23: 2 | F23: 2 | G23: 7
A24: San Leonardo | E24: 1 | G24: 1
A25: Santa Rosa | B25: 1 | C25: 2 | D25: 3 | E25: 1 | G25: 7
A26: Santo Domingo | B26: 3 | G26: 3
A27: Science City of Munoz | B27: 6 | C27: 1 | G27: 7
A28: Talavera | B28: 1 | C28: 2 | E28: 1 | G28: 4
A29: Grand Total | B29: 14 | C29: 31 | D29: 29 | E29: 31 | F29: 13 | G29: 118

Sheet Sheet3
A3: Province | B3: Count of Manila Bay Area (MBA)
A4: Aurora | B4: 19
A5: Bataan | B5: 22
A6: Bataan | B6: 4
A7: Bulacan | B7: 44
A8: Nueva Ecija | B8: 38
A9: Pampanga | B9: 24
A10: Tarlac | B10: 20
A11: Zambales | B11: 23
A12: Grand Total | B12: 194

Sheet 10-YEAR SWM PLAN
A1: Province | B1: Municipality | C1: CONCATENATE | D1: Manila Bay Area (MBA) | E1: Congressional District | F1: Long. | G1: Lat. | H1: Location | I1: Type of SWM Plan | J1: Resolution No. | K1: Period Covered | L1: Year Approved | M1: End Period | N1: For Renewal | O1: Target Month | P1: ENMO Assigned | Q1: ESWM Staff | R1: Focal Person | S1: IIS NUMBER | T1: Date of Monitoring | U1: Date Report Prepared (Submitted to IIS by ENMO) | V1: Date Report Reviewed (by ESWM Staff) | W1: Date Report Reviewed (by Focal Person) | X1: Date Report Approved | Y1: Total No. of Days (Report prepared) | Z1: Total No. of Days (Report Reviewed by ESWM Staff) | AA1: Total No. of Days (Report Reviewed by Focal) | AB1: Total No. of Days (Report Approved by C, ESWM) | AC1: Tracking of Reports (To be filled out by Planning Section) | AD1: PCG | AE1: Total Waste Generation | AF1: Waste Diversion Rate (%) | AG1: LGU Final Disposal | AH1: Remarks and Recommendation (Compliant/ Non-Compliant) | AI1: a. source reduction activities at source are present | AJ1: b. Collection segregated collection | AK1: c. Storage and setout (Segregation at source) | AL1: d. Processing MRF | AM1: e. Transfer Station | AN1: f. Disposal Facilities | AO1: Advise Letter/Notice Date Issued | AP1: Compliance to Advise/ Letter Issued | AQ1: Remarks | AR1: Total Waste Generation | AS1: Per Capita Per Day | AT1: Biodegradable Wastes (kg/day) | AU1: Bio (%) | AV1: Recyclable Wastes (kg/day) | AW1: Recyclable (%) | AX1: Residual with potential (kg/day) | AY1: Residual with Potential (%) | AZ1: Residual Wastes for Disposal (kg/day) | BA1: Residual (%) | BB1: Special Wastes (kg/day) | BC1: Special (%) | BD1: Total Waste Generation | BE1: Per Capita Per Day | BF1: Biodegradable Wastes (kg/day) | BG1: Bio (%) | BH1: Recyclable Wastes (kg/day) | BI1: Recyclable (%) | BJ1: Residual with potential (kg/day) | BK1: Residual with Potential (%) | BL1: Residual Wastes for Disposal (kg/day) | BM1: Residual (%) | BN1: Special Wastes (kg/day) | BO1: Special (%) | BP1: Waste Diversion Rate (%) | BQ1: Disposal Rate (%)
A2: PAMPANGA | B2: BACOLOR | C2: PAMPANGA, BACOLOR | D2: MBA | E2: 3rd | F2: 14.9966 | G2: 120.6517 | H2: =CONCATENATE(F2,",",G2) -> 14.9966,120.6517 | I2: Municipal / City Plan | J2: NSWMC Resolution No. 1638, Series of 2023 | K2: 2022 - 2031 | L2: 2022 | M2: 2031 | O2: 1.January | P2: Ivy M. Castro | Q2: Maria Cecilia Pascual | R2: Yves Yshmael M. Balagtas | S2: R3-2025-001650 | T2: 45673 | U2: 45677 | W2: 45681 | X2: 45681 | Y2: =IF( OR(ISBLANK(T2), ISBLANK(U2)), "", MAX(1, IF( NETWORKDAYS(T2, U2) <= 0, 1, NETWORKDAYS(T2, U2) - IF(T2 = U2, 0, 1) )) ) -> 2 | Z2: =IF( OR(ISBLANK(U2), ISBLANK(V2)), "", MAX(1, IF( NETWORKDAYS(U2, V2) <= 0, 1, NETWORKDAYS(U2, V2) - IF(U2 = V2, 0, 1) )) ) | AA2: =IF( OR(IF(V2<>"", V2, U2)="", W2=""), "", MAX(1, IF( NETWORKDAYS(IF(V2<>"", V2, U2), W2) <= 0, 1, NETWORKDAYS(IF(V2<>"", V2, U2), W2) - IF(IF(V2<>"", V2, U2)=W2, 0, 1) ) ) ) -> 4 | AB2: =IF( OR(ISBLANK(W2), ISBLANK(X2)), "", MAX(1, IF( NETWORKDAYS(W2, X2) <= 0, 1, NETWORKDAYS(W2, X2) - IF(W2 = X2, 0, 1) )) ) -> 1 | AC2: Received by Planning | AD2: 236 | AE2: 18436.48 | AH2: Compliant | AI2: YES | AJ2: YES | AK2: YES | AL2: YES | AM2: YES | AN2: YES | AR2: 25115.75 | AT2: 9280.27 | AV2: 8469.03 | AX2: 1444.16 | AZ2: 2732.59 | BB2: 3189.7 | BD2: =SUM(BF2,BH2,BJ2,BL2,BN2) -> 0 | BP2: =SUM(BF2,BH2,BJ2)/BD2*100 -> #DIV/0! | BQ2: =SUM(BL2,BN2)/BD2*100 -> #DIV/0!
A3: PAMPANGA | B3: CITY OF SAN FERNANDO | C3: PAMPANGA, CITY OF SAN FERNANDO | D3: MBA | E3: 3rd | F3: 15.0279 | G3: 120.6937 | H3: =CONCATENATE(F3,",",G3) -> 15.0279,120.6937 | I3: Municipal / City Plan | J3: 167 series 2015 | K3: 2015 - 2024 | L3: 2015 | M3: 2024 | N3: For Renewal | O3: 1.January | P3: Elyza A. Evilla | Q3: Maria Cecilia Pascual | R3: Yves Yshmael M. Balagtas | S3: R3-2025-002191 | T3: 45678 | U3: 45680 | W3: 45681 | X3: 45681 | Y3: =IF( OR(ISBLANK(T3), ISBLANK(U3)), "", MAX(1, IF( NETWORKDAYS(T3, U3) <= 0, 1, NETWORKDAYS(T3, U3) - IF(T3 = U3, 0, 1) )) ) -> 2 | Z3: =IF( OR(ISBLANK(U3), ISBLANK(V3)), "", MAX(1, IF( NETWORKDAYS(U3, V3) <= 0, 1, NETWORKDAYS(U3, V3) - IF(U3 = V3, 0, 1) )) ) | AA3: =IF( OR(IF(V3<>"", V3, U3)="", W3=""), "", MAX(1, IF( NETWORKDAYS(IF(V3<>"", V3, U3), W3) <= 0, 1, NETWORKDAYS(IF(V3<>"", V3, U3), W3) - IF(IF(V3<>"", V3, U3)=W3, 0, 1) ) ) ) -> 1 | AB3: =IF( OR(ISBLANK(W3), ISBLANK(X3)), "", MAX(1, IF( NETWORKDAYS(W3, X3) <= 0, 1, NETWORKDAYS(W3, X3) - IF(W3 = X3, 0, 1) )) ) -> 1 | AC3: Received by Planning | AD3: 0.72 | AE3: 214860.78 | AH3: Compliant | AI3: YES | AJ3: YES | AK3: YES | AL3: YES | AM3: YES | AN3: YES | AR3: 327929.32 | AT3: 196331.28 | AV3: 64208.56 | AX3: 27546.06 | AZ3: 32497.8 | BB3: 7345.62 | BD3: =SUM(BF3,BH3,BJ3,BL3,BN3) -> 0 | BP3: =SUM(BF3,BH3,BJ3)/BD3*100 -> #DIV/0! | BQ3: =SUM(BL3,BN3)/BD3*100 -> #DIV/0!
A4: ZAMBALES | B4: OLONGAPO CITY | C4: ZAMBALES, OLONGAPO CITY | D4: OUTSIDE MBA | E4: 1st | F4: 14.842411 | G4: 120.28765 | H4: =CONCATENATE(F4,",",G4) -> 14.842411,120.287647 | I4: Municipal / City Plan | J4: NSWMC Resolution No. 1639, Series of 2023 | K4: 2023 - 2032 | L4: 2023 | M4: 2032 | O4: 1.January | P4: Larizze A. Santos | Q4: Ryan Christian R. Nunag | R4: Jun D. Guillermo | S4: R3-2025-001966 | T4: 45673 | U4: 45679 | V4: 45679 | W4: 45680 | X4: 45680 | Y4: =IF( OR(ISBLANK(T4), ISBLANK(U4)), "", MAX(1, IF( NETWORKDAYS(T4, U4) <= 0, 1, NETWORKDAYS(T4, U4) - IF(T4 = U4, 0, 1) )) ) -> 4 | Z4: =IF( OR(ISBLANK(U4), ISBLANK(V4)), "", MAX(1, IF( NETWORKDAYS(U4, V4) <= 0, 1, NETWORKDAYS(U4, V4) - IF(U4 = V4, 0, 1) )) ) -> 1 | AA4: =IF( OR(ISBLANK(U4), ISBLANK(W4)), "", MAX(1, IF( NETWORKDAYS(U4, W4) <= 0, 1, NETWORKDAYS(U4, W4) - IF(U4 = W4, 0, 1) )) ) -> 1 | AB4: =IF( OR(ISBLANK(W4), ISBLANK(X4)), "", MAX(1, IF( NETWORKDAYS(W4, X4) <= 0, 1, NETWORKDAYS(W4, X4) - IF(W4 = X4, 0, 1) )) ) -> 1 | AC4: Received by Planning | AD4: 0.893 | AE4: 252160.88 | AF4: 0.7684 | AG4: LGU SLF | AH4: Compliant | AI4: YES | AJ4: YES | AK4: YES | AL4: YES | AN4: YES | AR4: 303429.12 | AT4: 123738.39 | AV4: 94548.51 | AX4: 14868.03 | AZ4: 60685.82 | BB4: 9588.36 | BD4: =SUM(BF4,BH4,BJ4,BL4,BN4) -> 0 | BP4: =SUM(BF4,BH4,BJ4)/BD4*100 -> #DIV/0! | BQ4: =SUM(BL4,BN4)/BD4*100 -> #DIV/0!
A5: AURORA | B5: PROVINCIAL GOVERNMENT OF AURORA | C5: AURORA, PROVINCIAL GOVERNMENT OF AURORA | D5: OUTSIDE MBA | F5: 15.755878 | G5: 121.55054 | H5: =CONCATENATE(F5,",",G5) -> 15.755878,121.550537 | I5: Provincial Plan | J5: NSWMC RESO NO. 855A SERIES OF 2019 | K5: 2018 - 2028 | L5: 2019 | M5: s | O5: 10.October | P5: Zaila Mae Leander | R5: Ryan Christian R. Nunag | S5: R3-2025-033200 | T5: 45930 | U5: 45932 | W5: 45938 | X5: 45940 | Y5: =IF( OR(ISBLANK(T5), ISBLANK(U5)), "", MAX(1, IF( NETWORKDAYS(T5, U5) <= 0, 1, NETWORKDAYS(T5, U5) - IF(T5 = U5, 0, 1) )) ) -> 2 | Z5: =IF( OR(ISBLANK(U5), ISBLANK(V5)), "", MAX(1, IF( NETWORKDAYS(U5, V5) <= 0, 1, NETWORKDAYS(U5, V5) - IF(U5 = V5, 0, 1) )) ) | AA5: =IF( OR(IF(V5<>"", V5, U5)="", W5=""), "", MAX(1, IF( NETWORKDAYS(IF(V5<>"", V5, U5), W5) <= 0, 1, NETWORKDAYS(IF(V5<>"", V5, U5), W5) - IF(IF(V5<>"", V5, U5)=W5, 0, 1) ) ) ) -> 4 | AB5: =IF( OR(ISBLANK(W5), ISBLANK(X5)), "", MAX(1, IF( NETWORKDAYS(W5, X5) <= 0, 1, NETWORKDAYS(W5, X5) - IF(W5 = X5, 0, 1) )) ) -> 2 | AC5: Received by Planning | AD5: 0.36 | AE5: 37538.47 | AF5: 86.22 | AG5: LGU owned SLF (Ma. Aurora, Dingalan and Dipaculao) | AH5: Compliant | AI5: YES | AJ5: YES | AK5: YES | AM5: YES | AN5: YES | AR5: 37538.47 | AT5: 13920.56 | AV5: 7540.04 | AZ5: 7540.04 | BB5: 1920.8 | BD5: =SUM(BF5,BH5,BJ5,BL5,BN5) -> 0 | BP5: =SUM(BF5,BH5,BJ5)/BD5*100 -> #DIV/0! | BQ5: =SUM(BL5,BN5)/BD5*100 -> #DIV/0!
A6: BATAAN | B6: ORANI | C6: BATAAN, ORANI | D6: MBA | E6: 1st | F6: 14.802093 | G6: 120.53664 | H6: =CONCATENATE(F6,",",G6) -> 14.802093,120.536636 | I6: Municipal / City Plan | J6: 1084 series of 2018 | K6: 2017 - 2028 | L6: 2018 | M6: 2028 | O6: 10.October | P6: John-lester Signio | R6: Christle D. David | S6: R3-2025-034269 | T6: 45939 | U6: 45940 | W6: 45943 | X6: 45945 | Y6: =IF( OR(ISBLANK(T6), ISBLANK(U6)), "", MAX(1, IF( NETWORKDAYS(T6, U6) <= 0, 1, NETWORKDAYS(T6, U6) - IF(T6 = U6, 0, 1) )) ) -> 1 | Z6: =IF( OR(ISBLANK(U6), ISBLANK(V6)), "", MAX(1, IF( NETWORKDAYS(U6, V6) <= 0, 1, NETWORKDAYS(U6, V6) - IF(U6 = V6, 0, 1) )) ) | AA6: =IF( OR(IF(V6<>"", V6, U6)="", W6=""), "", MAX(1, IF( NETWORKDAYS(IF(V6<>"", V6, U6), W6) <= 0, 1, NETWORKDAYS(IF(V6<>"", V6, U6), W6) - IF(IF(V6<>"", V6, U6)=W6, 0, 1) ) ) ) -> 1 | AB6: =IF( OR(ISBLANK(W6), ISBLANK(X6)), "", MAX(1, IF( NETWORKDAYS(W6, X6) <= 0, 1, NETWORKDAYS(W6, X6) - IF(W6 = X6, 0, 1) )) ) -> 2 | AC6: Received by Planning | AD6: 0.765 | AE6: 52223.13 | AF6: 0.77 | AG6: Floridablanca Enviro Corporation | AH6: =IF(AND(AI6 = "YES", AJ6 = "YES", AK6 = "YES", AL6 = "YES", AN6 = "YES"), "Compliant", "Not Compliant") -> Compliant | AI6: YES | AJ6: YES | AK6: YES | AL6: YES | AM6: YES | AN6: YES | AR6: 20513.15 | AT6: 8342.7 | AV6: 5222.65 | AX6: 4244.17 | AZ6: 1238.99 | BB6: 1464.64 | BD6: =SUM(BF6,BH6,BJ6,BL6,BN6) -> 0 | BP6: =SUM(BF6,BH6,BJ6)/BD6*100 -> #DIV/0! | BQ6: =SUM(BL6,BN6)/BD6*100 -> #DIV/0!
A7: BATAAN | B7: ORION | C7: BATAAN, ORION | D7: MBA | E7: 2nd | F7: 14.621155 | G7: 120.57647 | H7: =CONCATENATE(F7,",",G7) -> 14.621155,120.576472 | I7: Municipal / City Plan | J7: nswmc res.974 s2017 | K7: 2015 - 2025 | L7: 2017 | M7: 2025 | N7: For Renewal | O7: 10.October | P7: Dennis Tolentino | R7: Christle D. David | S7: R3-2025-034326 | T7: 45940 | U7: 45942 | W7: 45943 | X7: 45944 | Y7: =IF( OR(ISBLANK(T7), ISBLANK(U7)), "", MAX(1, IF( NETWORKDAYS(T7, U7) <= 0, 1, NETWORKDAYS(T7, U7) - IF(T7 = U7, 0, 1) )) ) -> 1 | Z7: =IF( OR(ISBLANK(U7), ISBLANK(V7)), "", MAX(1, IF( NETWORKDAYS(U7, V7) <= 0, 1, NETWORKDAYS(U7, V7) - IF(U7 = V7, 0, 1) )) ) | AA7: =IF( OR(IF(V7<>"", V7, U7)="", W7=""), "", MAX(1, IF( NETWORKDAYS(IF(V7<>"", V7, U7), W7) <= 0, 1, NETWORKDAYS(IF(V7<>"", V7, U7), W7) - IF(IF(V7<>"", V7, U7)=W7, 0, 1) ) ) ) -> 1 | AB7: =IF( OR(ISBLANK(W7), ISBLANK(X7)), "", MAX(1, IF( NETWORKDAYS(W7, X7) <= 0, 1, NETWORKDAYS(W7, X7) - IF(W7 = X7, 0, 1) )) ) -> 1 | AC7: Received by Planning | AD7: 0.593 | AE7: 33610 | AF7: 77.57 | AG7: Pyrolysis Equipment | AH7: =IF(AND(AI7 = "YES", AJ7 = "YES", AK7 = "YES", AL7 = "YES", AN7 = "YES"), "Compliant", "Not Compliant") -> Not Compliant | AR7: 18803.44 | AT7: 7647.36 | AV7: 3634.71 | AX7: 5043.08 | AZ7: 1135.73 | BB7: 1342.57 | BD7: =SUM(BF7,BH7,BJ7,BL7,BN7) -> 0 | BP7: =SUM(BF7,BH7,BJ7)/BD7*100 -> #DIV/0! | BQ7: =SUM(BL7,BN7)/BD7*100 -> #DIV/0!
A8: BATAAN | B8: PROVINCIAL GOVERNMENT OF BATAAN | C8: BATAAN, PROVINCIAL GOVERNMENT OF BATAAN | D8: OUTSIDE MBA | F8: 14.676 | G8: 120.5295 | H8: =CONCATENATE(F8,",",G8) -> 14.676,120.5295 | I8: Provincial Plan | J8: NSWMC RESO NO. 1460 SERIES OF 2021 | K8: 2020 - 2030 | L8: 2021 | M8: 2030 | O8: 10.October | R8: Christle D. David | S8: R3-2025-035372 | T8: 45947 | U8: 45950 | W8: 45950 | X8: 45950 | Y8: =IF( OR(ISBLANK(T8), ISBLANK(U8)), "", MAX(1, IF( NETWORKDAYS(T8, U8) <= 0, 1, NETWORKDAYS(T8, U8) - IF(T8 = U8, 0, 1) )) ) -> 1 | Z8: =IF( OR(ISBLANK(U8), ISBLANK(V8)), "", MAX(1, IF( NETWORKDAYS(U8, V8) <= 0, 1, NETWORKDAYS(U8, V8) - IF(U8 = V8, 0, 1) )) ) | AA8: =IF( OR(IF(V8<>"", V8, U8)="", W8=""), "", MAX(1, IF( NETWORKDAYS(IF(V8<>"", V8, U8), W8) <= 0, 1, NETWORKDAYS(IF(V8<>"", V8, U8), W8) - IF(IF(V8<>"", V8, U8)=W8, 0, 1) ) ) ) -> 1 | AB8: =IF( OR(ISBLANK(W8), ISBLANK(X8)), "", MAX(1, IF( NETWORKDAYS(W8, X8) <= 0, 1, NETWORKDAYS(W8, X8) - IF(W8 = X8, 0, 1) )) ) -> 1 | AC8: Received by Planning | AD8: 0.394 | AE8: 367171.2 | AF8: 75.85 | AG8: Bataan Integrated Waste Management Facility | AH8: =IF(AND(AI8 = "YES", AJ8 = "YES", AK8 = "YES", AL8 = "YES", AN8 = "YES"), "Compliant", "Not Compliant") -> Compliant | AI8: YES | AJ8: YES | AK8: YES | AL8: YES | AN8: YES | BD8: =SUM(BF8,BH8,BJ8,BL8,BN8) -> 0 | BP8: =SUM(BF8,BH8,BJ8)/BD8*100 -> #DIV/0! | BQ8: =SUM(BL8,BN8)/BD8*100 -> #DIV/0!
A9: BULACAN | B9: SAN ILDEFONSO | C9: BULACAN, SAN ILDEFONSO | D9: MBA | E9: 3rd | F9: 15.077944 | G9: 120.94288 | H9: =CONCATENATE(F9,",",G9) -> 15.07794373,120.9428805 | I9: Municipal / City Plan | J9: 1245 | K9: 2017 - 2027 | L9: 2019 | M9: 2027 | O9: 10.October | P9: Ronaldo P. Roque, Jr. | Q9: Maria Cecilia Pascual | R9: Diozelle A. Lazatin | S9: R3-2025-034956 | T9: 45944 | U9: 45945 | V9: 45946 | W9: 45946 | X9: 45950 | Y9: 1 | Z9: =IF( OR(ISBLANK(U9), ISBLANK(V9)), "", MAX(1, IF( NETWORKDAYS(U9, V9) <= 0, 1, NETWORKDAYS(U9, V9) - IF(U9 = V9, 0, 1) )) ) -> 1 | AA9: =IF( OR(IF(V9<>"", V9, U9)="", W9=""), "", MAX(1, IF( NETWORKDAYS(IF(V9<>"", V9, U9), W9) <= 0, 1, NETWORKDAYS(IF(V9<>"", V9, U9), W9) - IF(IF(V9<>"", V9, U9)=W9, 0, 1) ) ) ) -> 1 | AB9: 2 | AC9: Received by Planning | AD9: 0.382 | AE9: 48,262.64kgs | AF9: 65 | AG9: ECO Protect | AH9: Compliant | AI9: YES | AJ9: YES | AK9: YES | AL9: YES | AM9: YES | AN9: YES | AR9: 54413.03 | AT9: 21025.2 | AV9: 14381.36 | AX9: 13369.28 | AZ9: 1708.57 | BB9: 3928.62 | BD9: =SUM(BF9,BH9,BJ9,BL9,BN9) -> 0 | BP9: =SUM(BF9,BH9,BJ9)/BD9*100 -> #DIV/0! | BQ9: =SUM(BL9,BN9)/BD9*100 -> #DIV/0!
A10: BULACAN | B10: SAN RAFAEL | C10: BULACAN, SAN RAFAEL | D10: MBA | E10: 3rd | F10: 14.982975 | G10: 120.92765 | H10: =CONCATENATE(F10,",",G10) -> 14.982975,120.927646 | I10: Municipal / City Plan | J10: NSWMC RESO NO. 168 SERIES OF 2015 | K10: 2015 - 2024 | L10: 2015 | M10: 2024 | N10: For Renewal | O10: 10.October | P10: Ronaldo P. Roque, Jr. | Q10: Maria Cecilia Pascual | R10: Diozelle A. Lazatin | S10: R3-2025-034066 | T10: 45938 | U10: 45939 | V10: 45945 | W10: 45945 | X10: 45950 | Y10: 1 | Z10: =IF( OR(ISBLANK(U10), ISBLANK(V10)), "", MAX(1, IF( NETWORKDAYS(U10, V10) <= 0, 1, NETWORKDAYS(U10, V10) - IF(U10 = V10, 0, 1) )) ) -> 4 | AA10: =IF( OR(IF(V10<>"", V10, U10)="", W10=""), "", MAX(1, IF( NETWORKDAYS(IF(V10<>"", V10, U10), W10) <= 0, 1, NETWORKDAYS(IF(V10<>"", V10, U10), W10) - IF(IF(V10<>"", V10, U10)=W10, 0, 1) ) ) ) -> 1 | AB10: =IF( OR(ISBLANK(W10), ISBLANK(X10)), "", MAX(1, IF( NETWORKDAYS(W10, X10) <= 0, 1, NETWORKDAYS(W10, X10) - IF(W10 = X10, 0, 1) )) ) -> 3 | AC10: Received by Planning | AH10: Compliant | AI10: YES | AJ10: YES | AK10: YES | AL10: YES | AM10: YES | AN10: YES | AR10: 61135.47 | AT10: 38857.71 | AV10: 11145 | AX10: 6969.44 | AZ10: 3631.45 | BB10: 531.88 | BD10: =SUM(BF10,BH10,BJ10,BL10,BN10) -> 0 | BP10: =SUM(BF10,BH10,BJ10)/BD10*100 -> #DIV/0! | BQ10: =SUM(BL10,BN10)/BD10*100 -> #DIV/0!
A11: NUEVA ECIJA | B11: CARRANGLAN | C11: NUEVA ECIJA, CARRANGLAN | D11: MBA | E11: 2nd | F11: 15.960408 | G11: 121.06312 | H11: =CONCATENATE(F11,",",G11) -> 15.960408,121.063117 | I11: Municipal / City Plan | J11: 1329 | K11: 2017 - 2027 | L11: 2019 | M11: 2027 | O11: 10.October | P11: Aser A. Inocencio, Jr. | Q11: Jaypee Ordoñez | R11: Zosimo P. Suyat | S11: R3-2025-035170 | T11: 45944 | U11: 45946 | V11: 45947 | W11: 45947 | X11: 45947 | Y11: =IF( OR(ISBLANK(T11), ISBLANK(U11)), "", MAX(1, IF( NETWORKDAYS(T11, U11) <= 0, 1, NETWORKDAYS(T11, U11) - IF(T11 = U11, 0, 1) )) ) -> 2 | Z11: =IF( OR(ISBLANK(U11), ISBLANK(V11)), "", MAX(1, IF( NETWORKDAYS(U11, V11) <= 0, 1, NETWORKDAYS(U11, V11) - IF(U11 = V11, 0, 1) )) ) -> 1 | AA11: =IF( OR(IF(V11<>"", V11, U11)="", W11=""), "", MAX(1, IF( NETWORKDAYS(IF(V11<>"", V11, U11), W11) <= 0, 1, NETWORKDAYS(IF(V11<>"", V11, U11), W11) - IF(IF(V11<>"", V11, U11)=W11, 0, 1) ) ) ) -> 1 | AB11: =IF( OR(ISBLANK(W11), ISBLANK(X11)), "", MAX(1, IF( NETWORKDAYS(W11, X11) <= 0, 1, NETWORKDAYS(W11, X11) - IF(W11 = X11, 0, 1) )) ) -> 1 | AC11: Received by Planning | AD11: 0.25 | AE11: 10605 | AF11: 88 | AG11: Primawaste | AH11: =IF(AND(AI11 = "YES", AJ11 = "YES", AK11 = "YES", AL11 = "YES", AN11 = "YES"), "Compliant", "Not Compliant") -> Not Compliant | AI11: YES | AJ11: YES | AK11: YES | AM11: YES | AN11: YES | AR11: 12429.33 | AT11: 7073.53 | AV11: 3222.93 | AX11: 646.33 | AZ11: 1378.41 | BB11: 108.14 | BD11: =SUM(BF11,BH11,BJ11,BL11,BN11) -> 0 | BP11: =SUM(BF11,BH11,BJ11)/BD11*100 -> #DIV/0! | BQ11: =SUM(BL11,BN11)/BD11*100 -> #DIV/0!
A12: NUEVA ECIJA | B12: SCIENCE CITY OF MUñOZ | C12: NUEVA ECIJA, SCIENCE CITY OF MUñOZ | D12: MBA | E12: 2nd | F12: 15.713327 | G12: 120.90397 | H12: =CONCATENATE(F12,",",G12) -> 15.713327,120.903968 | I12: Municipal / City Plan | J12: 1085 s. 2018 | K12: 2018 - 2027 | L12: 2018 | M12: 2027 | O12: 10.October | P12: Aser A. Inocencio, Jr. | Q12: Jaypee Ordoñez | R12: Zosimo P. Suyat | S12: R3-2025-035172 | T12: 45945 | U12: 45946 | V12: 45947 | W12: 45947 | X12: 45947 | Y12: =IF( OR(ISBLANK(T12), ISBLANK(U12)), "", MAX(1, IF( NETWORKDAYS(T12, U12) <= 0, 1, NETWORKDAYS(T12, U12) - IF(T12 = U12, 0, 1) )) ) -> 1 | Z12: =IF( OR(ISBLANK(U12), ISBLANK(V12)), "", MAX(1, IF( NETWORKDAYS(U12, V12) <= 0, 1, NETWORKDAYS(U12, V12) - IF(U12 = V12, 0, 1) )) ) -> 1 | AA12: =IF( OR(IF(V12<>"", V12, U12)="", W12=""), "", MAX(1, IF( NETWORKDAYS(IF(V12<>"", V12, U12), W12) <= 0, 1, NETWORKDAYS(IF(V12<>"", V12, U12), W12) - IF(IF(V12<>"", V12, U12)=W12, 0, 1) ) ) ) -> 1 | AB12: =IF( OR(ISBLANK(W12), ISBLANK(X12)), "", MAX(1, IF( NETWORKDAYS(W12, X12) <= 0, 1, NETWORKDAYS(W12, X12) - IF(W12 = X12, 0, 1) )) ) -> 1 | AC12: Received by Planning | AD12: 0.376 | AE12: 31699.81 | AF12: 89 | AG12: Metro Waste | AH12: =IF(AND(AI12 = "YES", AJ12 = "YES", AK12 = "YES", AL12 = "YES", AN12 = "YES"), "Compliant", "Not Compliant") -> Compliant | AI12: YES | AJ12: YES | AK12: YES | AL12: YES | AM12: YES | AN12: YES | AR12: 37520.29 | AT12: 22095.7 | AV12: 6794.92 | AX12: 4584.98 | AZ12: 3902.11 | BB12: 142.58 | BD12: =SUM(BF12,BH12,BJ12,BL12,BN12) -> 0 | BP12: =SUM(BF12,BH12,BJ12)/BD12*100 -> #DIV/0! | BQ12: =SUM(BL12,BN12)/BD12*100 -> #DIV/0!
A13: NUEVA ECIJA | B13: STO DOMINGO | C13: NUEVA ECIJA, STO DOMINGO | D13: MBA | E13: 1st | F13: 15.596054 | G13: 120.8774 | H13: =CONCATENATE(F13,",",G13) -> 15.596054,120.877399 | I13: Municipal / City Plan | J13: NSWMC RESO NO. 588-A SERIES OF 2020 | K13: 2017 - 2027 | L13: 2020 | M13: 2027 | O13: 10.October | P13: Gem C. Vicencio | Q13: Jaypee Ordoñez | R13: Zosimo P. Suyat | S13: R3-2025-035071 | T13: 45945 | U13: 45946 | V13: 45947 | W13: 45947 | X13: 45947 | Y13: =IF( OR(ISBLANK(T13), ISBLANK(U13)), "", MAX(1, IF( NETWORKDAYS(T13, U13) <= 0, 1, NETWORKDAYS(T13, U13) - IF(T13 = U13, 0, 1) )) ) -> 1 | Z13: =IF( OR(ISBLANK(U13), ISBLANK(V13)), "", MAX(1, IF( NETWORKDAYS(U13, V13) <= 0, 1, NETWORKDAYS(U13, V13) - IF(U13 = V13, 0, 1) )) ) -> 1 | AA13: =IF( OR(IF(V13<>"", V13, U13)="", W13=""), "", MAX(1, IF( NETWORKDAYS(IF(V13<>"", V13, U13), W13) <= 0, 1, NETWORKDAYS(IF(V13<>"", V13, U13), W13) - IF(IF(V13<>"", V13, U13)=W13, 0, 1) ) ) ) -> 1 | AB13: =IF( OR(ISBLANK(W13), ISBLANK(X13)), "", MAX(1, IF( NETWORKDAYS(W13, X13) <= 0, 1, NETWORKDAYS(W13, X13) - IF(W13 = X13, 0, 1) )) ) -> 1 | AC13: Received by Planning | AD13: 0.378 | AE13: 23092.78 | AF13: 81 | AG13: Metro Waste | AH13: =IF(AND(AI13 = "YES", AJ13 = "YES", AK13 = "YES", AL13 = "YES", AN13 = "YES"), "Compliant", "Not Compliant") -> Compliant | AI13: YES | AJ13: YES | AK13: YES | AL13: YES | AM13: YES | AN13: YES | AR13: 24761.15 | AT13: 13509.68 | AV13: 4033.59 | AX13: 2545.45 | AZ13: 4286.16 | BB13: 386.27 | BD13: =SUM(BF13,BH13,BJ13,BL13,BN13) -> 0 | BP13: =SUM(BF13,BH13,BJ13)/BD13*100 -> #DIV/0! | BQ13: =SUM(BL13,BN13)/BD13*100 -> #DIV/0!
A14: NUEVA ECIJA | B14: TALAVERA | C14: NUEVA ECIJA, TALAVERA | D14: MBA | E14: 1st | F14: 15.584241 | G14: 120.9184 | H14: =CONCATENATE(F14,",",G14) -> 15.584241,120.918404 | I14: Municipal / City Plan | J14: 1063 s. 2018 | K14: 2017 - 2026 | L14: 2018 | M14: 2026 | O14: 10.October | P14: Gem C. Vicencio | Q14: Jaypee Ordoñez | R14: Zosimo P. Suyat | S14: R3-2025-034954 | T14: 45944 | U14: 45946 | V14: 45947 | W14: 45947 | X14: 45947 | Y14: =IF( OR(ISBLANK(T14), ISBLANK(U14)), "", MAX(1, IF( NETWORKDAYS(T14, U14) <= 0, 1, NETWORKDAYS(T14, U14) - IF(T14 = U14, 0, 1) )) ) -> 2 | Z14: =IF( OR(ISBLANK(U14), ISBLANK(V14)), "", MAX(1, IF( NETWORKDAYS(U14, V14) <= 0, 1, NETWORKDAYS(U14, V14) - IF(U14 = V14, 0, 1) )) ) -> 1 | AA14: =IF( OR(IF(V14<>"", V14, U14)="", W14=""), "", MAX(1, IF( NETWORKDAYS(IF(V14<>"", V14, U14), W14) <= 0, 1, NETWORKDAYS(IF(V14<>"", V14, U14), W14) - IF(IF(V14<>"", V14, U14)=W14, 0, 1) ) ) ) -> 1 | AB14: =IF( OR(ISBLANK(W14), ISBLANK(X14)), "", MAX(1, IF( NETWORKDAYS(W14, X14) <= 0, 1, NETWORKDAYS(W14, X14) - IF(W14 = X14, 0, 1) )) ) -> 1 | AC14: Received by Planning | AD14: 0.277 | AE14: 36657.63 | AF14: 93 | AG14: Metro Waste | AH14: =IF(AND(AI14 = "YES", AJ14 = "YES", AK14 = "YES", AL14 = "YES", AN14 = "YES"), "Compliant", "Not Compliant") -> Compliant | AI14: YES | AJ14: YES | AK14: YES | AL14: YES | AM14: YES | AN14: YES | AR14: 41301.85 | AT14: 25520.41 | AV14: 9598.55 | AX14: 3312.41 | AZ14: 2643.32 | BB14: 227.16 | BD14: =SUM(BF14,BH14,BJ14,BL14,BN14) -> 0 | BP14: =SUM(BF14,BH14,BJ14)/BD14*100 -> #DIV/0! | BQ14: =SUM(BL14,BN14)/BD14*100 -> #DIV/0!
A15: PAMPANGA | B15: SAN SIMON | C15: PAMPANGA, SAN SIMON | D15: MBA | E15: 4th | F15: 14.9848 | G15: 120.7514 | H15: =CONCATENATE(F15,",",G15) -> 14.9848,120.7514 | I15: Municipal / City Plan | J15: 1333 series of 2019 | K15: 2017 - 2028 | L15: 2019 | M15: 2028 | O15: 10.October | P15: Glaiza S.Gaza | R15: Yves Yshmael M. Balagtas | S15: R3-2025-034978 | T15: 45944 | U15: 45945 | W15: 45946 | X15: 45950 | Y15: =IF( OR(ISBLANK(T15), ISBLANK(U15)), "", MAX(1, IF( NETWORKDAYS(T15, U15) <= 0, 1, NETWORKDAYS(T15, U15) - IF(T15 = U15, 0, 1) )) ) -> 1 | Z15: =IF( OR(ISBLANK(U15), ISBLANK(V15)), "", MAX(1, IF( NETWORKDAYS(U15, V15) <= 0, 1, NETWORKDAYS(U15, V15) - IF(U15 = V15, 0, 1) )) ) | AA15: =IF( OR(IF(V15<>"", V15, U15)="", W15=""), "", MAX(1, IF( NETWORKDAYS(IF(V15<>"", V15, U15), W15) <= 0, 1, NETWORKDAYS(IF(V15<>"", V15, U15), W15) - IF(IF(V15<>"", V15, U15)=W15, 0, 1) ) ) ) -> 1 | AB15: =IF( OR(ISBLANK(W15), ISBLANK(X15)), "", MAX(1, IF( NETWORKDAYS(W15, X15) <= 0, 1, NETWORKDAYS(W15, X15) - IF(W15 = X15, 0, 1) )) ) -> 2 | AC15: Received by Planning | AD15: 0.498 | AE15: 29472.63 | AF15: 45.65 | AG15: Floridablanca Enviro Corp. | AH15: =IF(AND(AI15 = "YES", AJ15 = "YES", AK15 = "YES", AL15 = "YES", AN15 = "YES"), "Compliant", "Not Compliant") -> Not Compliant | AI15: YES | AJ15: NO | AK15: YES | AL15: YES | AM15: YES | AN15: YES | AR15: 38991.91 | AT15: 12516.4 | AV15: 6020.35 | AX15: 10543.41 | AZ15: 2706.04 | BB15: 7205.7 | BD15: =SUM(BF15,BH15,BJ15,BL15,BN15) -> 0 | BP15: =SUM(BF15,BH15,BJ15)/BD15*100 -> #DIV/0! | BQ15: =SUM(BL15,BN15)/BD15*100 -> #DIV/0!
A16: TARLAC | B16: MAYANTOC | C16: TARLAC, MAYANTOC | D16: OUTSIDE MBA | E16: 1st | F16: 15.618876 | G16: 120.37812 | H16: =CONCATENATE(F16,",",G16) -> 15.6188757,120.3781159 | I16: Municipal / City Plan | J16: NSWMC Reso No. 1359 s 2019 | K16: 2017 - 2027 | L16: 2019 | M16: 2027 | O16: 10.October | P16: Jasper Kieht B. Pili | R16: Jan Emerson C. Gonzales | S16: R3-2025-035011 | T16: 45946 | U16: 45946 | W16: 45946 | X16: 45947 | Y16: =IF( OR(ISBLANK(T16), ISBLANK(U16)), "", MAX(1, IF( NETWORKDAYS(T16, U16) <= 0, 1, NETWORKDAYS(T16, U16) - IF(T16 = U16, 0, 1) )) ) -> 1 | Z16: =IF( OR(ISBLANK(U16), ISBLANK(V16)), "", MAX(1, IF( NETWORKDAYS(U16, V16) <= 0, 1, NETWORKDAYS(U16, V16) - IF(U16 = V16, 0, 1) )) ) | AA16: =IF( OR(ISBLANK(U16), ISBLANK(W16)), "", MAX(1, IF( NETWORKDAYS(U16, W16) <= 0, 1, NETWORKDAYS(U16, W16) - IF(U16 = W16, 0, 1) )) ) -> 1 | AB16: =IF( OR(ISBLANK(W16), ISBLANK(X16)), "", MAX(1, IF( NETWORKDAYS(W16, X16) <= 0, 1, NETWORKDAYS(W16, X16) - IF(W16 = X16, 0, 1) )) ) -> 1 | AC16: Received by Planning | AD16: 0.28 | AE16: 9933.56 | AF16: 3.27 | AG16: MAA Integraded Waste Solution Corporation | AH16: =IF(AND(AI16 = "YES", AJ16 = "YES", AK16 = "YES", AL16 = "YES", AN16 = "YES"), "Compliant", "Not Compliant") -> Not Compliant | AI16: YES | AJ16: YES | AK16: NO | AL16: NO | AM16: NO | AN16: YES | AR16: 9311.35 | AT16: 6343.83 | AV16: 1469.33 | AX16: 744.91 | AZ16: 593.13 | BB16: 160.16 | BD16: =SUM(BF16,BH16,BJ16,BL16,BN16) -> 0 | BP16: =SUM(BF16,BH16,BJ16)/BD16*100 -> #DIV/0! | BQ16: =SUM(BL16,BN16)/BD16*100 -> #DIV/0!
A17: ZAMBALES | B17: CANDELARIA | C17: ZAMBALES, CANDELARIA | D17: OUTSIDE MBA | E17: 2nd | F17: 15.626389 | G17: 119.93139 | H17: =CONCATENATE(F17,",",G17) -> 15.626389,119.931389 | I17: Municipal / City Plan | J17: NSWMC RESO NO. 1446 SERIES OF 2021 | K17: 2020 - 2029 | L17: 2021 | M17: 2029 | O17: 10.October | P17: Ryan Ace R. Angel | Q17: Ryan Christian R. Nunag | R17: Jun D. Guillermo | S17: R3-2025-033415 | T17: 45932 | U17: 45936 | V17: 45936 | W17: 45936 | X17: 45940 | Y17: =IF( OR(ISBLANK(T17), ISBLANK(U17)), "", MAX(1, IF( NETWORKDAYS(T17, U17) <= 0, 1, NETWORKDAYS(T17, U17) - IF(T17 = U17, 0, 1) )) ) -> 2 | Z17: =IF( OR(ISBLANK(U17), ISBLANK(V17)), "", MAX(1, IF( NETWORKDAYS(U17, V17) <= 0, 1, NETWORKDAYS(U17, V17) - IF(U17 = V17, 0, 1) )) ) -> 1 | AA17: =IF( OR(ISBLANK(U17), ISBLANK(W17)), "", MAX(1, IF( NETWORKDAYS(U17, W17) <= 0, 1, NETWORKDAYS(U17, W17) - IF(U17 = W17, 0, 1) )) ) -> 1 | AB17: =IF( OR(ISBLANK(W17), ISBLANK(X17)), "", MAX(1, IF( NETWORKDAYS(W17, X17) <= 0, 1, NETWORKDAYS(W17, X17) - IF(W17 = X17, 0, 1) )) ) -> 4 | AC17: Received by Planning | AH17: Compliant | AR17: 13091.82 | AT17: 3686.66 | AV17: 4443.37 | AX17: 864.06 | AZ17: 4019.19 | BB17: 78.55 | BD17: =SUM(BF17,BH17,BJ17,BL17,BN17) -> 0 | BP17: =SUM(BF17,BH17,BJ17)/BD17*100 -> #DIV/0! | BQ17: =SUM(BL17,BN17)/BD17*100 -> #DIV/0!
A18: AURORA | B18: DILASAG | C18: AURORA, DILASAG | D18: OUTSIDE MBA | E18: Lone | F18: 16.392731 | G18: 122.21173 | H18: =CONCATENATE(F18,",",G18) -> 16.392731,122.211731 | I18: Municipal / City Plan | J18: 504 A series of 2018 | K18: 2017 - 2027 | L18: 2018 | M18: 2027 | O18: 11.November | P18: Queenyvel Laguisma | R18: Ryan Christian R. Nunag | S18: R3-2025-037356 | T18: 45967 | U18: 45968 | W18: 45972 | X18: 45975 | Y18: =IF( OR(ISBLANK(T18), ISBLANK(U18)), "", MAX(1, IF( NETWORKDAYS(T18, U18) <= 0, 1, NETWORKDAYS(T18, U18) - IF(T18 = U18, 0, 1) )) ) -> 1 | Z18: =IF( OR(ISBLANK(U18), ISBLANK(V18)), "", MAX(1, IF( NETWORKDAYS(U18, V18) <= 0, 1, NETWORKDAYS(U18, V18) - IF(U18 = V18, 0, 1) )) ) | AA18: =IF( OR(IF(V18<>"", V18, U18)="", W18=""), "", MAX(1, IF( NETWORKDAYS(IF(V18<>"", V18, U18), W18) <= 0, 1, NETWORKDAYS(IF(V18<>"", V18, U18), W18) - IF(IF(V18<>"", V18, U18)=W18, 0, 1) ) ) ) -> 2 | AB18: =IF( OR(ISBLANK(W18), ISBLANK(X18)), "", MAX(1, IF( NETWORKDAYS(W18, X18) <= 0, 1, NETWORKDAYS(W18, X18) - IF(W18 = X18, 0, 1) )) ) -> 3 | AC18: Received by Planning | AD18: 0.3 | AE18: 5,260.80 kg/day | AF18: 0.9374 | AG18: Floridablanca Enviro Corporation | AH18: =IF(AND(AI18 = "YES", AJ18 = "YES", AK18 = "YES", AL18 = "YES", AN18 = "YES"), "Compliant", "Not Compliant") -> Compliant | AI18: YES | AJ18: YES | AK18: YES | AL18: YES | AM18: YES | AN18: YES | AR18: 6013.19 | AT18: 4195.41 | AV18: 1334.33 | AX18: 107.03 | AZ18: 234.51 | BB18: 141.91 | BD18: =SUM(BF18,BH18,BJ18,BL18,BN18) -> 0 | BP18: =SUM(BF18,BH18,BJ18)/BD18*100 -> #DIV/0! | BQ18: =SUM(BL18,BN18)/BD18*100 -> #DIV/0!
A19: AURORA | B19: DINGALAN | C19: AURORA, DINGALAN | D19: OUTSIDE MBA | E19: Lone | F19: 15.388964 | G19: 121.39117 | H19: =CONCATENATE(F19,",",G19) -> 15.388964,121.39117 | I19: Municipal / City Plan | J19: 1234 Series 2019 | K19: 2017 - 2027 | L19: 2019 | M19: 2027 | O19: 11.November | P19: Nikko Jay M. Valenzuela | R19: Ryan Christian R. Nunag | S19: R3-2025-037799 | T19: 45960 | U19: 45972 | W19: 45972 | X19: 45975 | Y19: =IF( OR(ISBLANK(T19), ISBLANK(U19)), "", MAX(1, IF( NETWORKDAYS(T19, U19) <= 0, 1, NETWORKDAYS(T19, U19) - IF(T19 = U19, 0, 1) )) ) -> 8 | Z19: =IF( OR(ISBLANK(U19), ISBLANK(V19)), "", MAX(1, IF( NETWORKDAYS(U19, V19) <= 0, 1, NETWORKDAYS(U19, V19) - IF(U19 = V19, 0, 1) )) ) | AA19: =IF( OR(IF(V19<>"", V19, U19)="", W19=""), "", MAX(1, IF( NETWORKDAYS(IF(V19<>"", V19, U19), W19) <= 0, 1, NETWORKDAYS(IF(V19<>"", V19, U19), W19) - IF(IF(V19<>"", V19, U19)=W19, 0, 1) ) ) ) -> 1 | AB19: =IF( OR(ISBLANK(W19), ISBLANK(X19)), "", MAX(1, IF( NETWORKDAYS(W19, X19) <= 0, 1, NETWORKDAYS(W19, X19) - IF(W19 = X19, 0, 1) )) ) -> 3 | AC19: Received by Planning | AD19: 0.36 | AE19: 12, 582.71 kg/day | AF19: 92.12 | AG19: LGU owned SLF | AH19: =IF(AND(AI19 = "YES", AJ19 = "YES", AK19 = "YES", AL19 = "YES", AN19 = "YES"), "Compliant", "Not Compliant") -> Compliant | AI19: YES | AJ19: YES | AK19: YES | AL19: YES | AM19: YES | AN19: YES | AR19: 15928.22 | AT19: 10257.77 | AV19: 2564.44 | AX19: 1850.86 | AZ19: 1035.33 | BB19: 219.81 | BD19: =SUM(BF19,BH19,BJ19,BL19,BN19) -> 0 | BP19: =SUM(BF19,BH19,BJ19)/BD19*100 -> #DIV/0! | BQ19: =SUM(BL19,BN19)/BD19*100 -> #DIV/0!
A20: BULACAN | B20: SAN MIGUEL | C20: BULACAN, SAN MIGUEL | D20: MBA | E20: 3rd | F20: 15.140474 | G20: 120.97742 | H20: =CONCATENATE(F20,",",G20) -> 15.140474,120.977422 | I20: Municipal / City Plan | J20: NSWMC RESO NO. 179A S 2015 | K20: 2015 - 2025 | L20: 2015 | M20: 2025 | N20: For Renewal | O20: 11.November | P20: Ronaldo P. Roque, Jr. | Q20: Maria Cecilia Pascual | R20: Diozelle A. Lazatin | S20: R3-2025-037390 | T20: 45965 | U20: 45969 | V20: 45979 | W20: 45980 | X20: 45980 | Y20: =IF( OR(ISBLANK(T20), ISBLANK(U20)), "", MAX(1, IF( NETWORKDAYS(T20, U20) <= 0, 1, NETWORKDAYS(T20, U20) - IF(T20 = U20, 0, 1) )) ) -> 3 | Z20: =IF( OR(ISBLANK(U20), ISBLANK(V20)), "", MAX(1, IF( NETWORKDAYS(U20, V20) <= 0, 1, NETWORKDAYS(U20, V20) - IF(U20 = V20, 0, 1) )) ) -> 6 | AA20: =IF( OR(IF(V20<>"", V20, U20)="", W20=""), "", MAX(1, IF( NETWORKDAYS(IF(V20<>"", V20, U20), W20) <= 0, 1, NETWORKDAYS(IF(V20<>"", V20, U20), W20) - IF(IF(V20<>"", V20, U20)=W20, 0, 1) ) ) ) -> 1 | AB20: =IF( OR(ISBLANK(W20), ISBLANK(X20)), "", MAX(1, IF( NETWORKDAYS(W20, X20) <= 0, 1, NETWORKDAYS(W20, X20) - IF(W20 = X20, 0, 1) )) ) -> 1 | AC20: Received by Planning | AD20: 0.3394 | AE20: 71811.45 | AF20: 95.16 | AH20: =IF(AND(AI20 = "YES", AJ20 = "YES", AK20 = "YES", AL20 = "YES", AN20 = "YES"), "Compliant", "Not Compliant") -> Not Compliant | AR20: 67480.78 | AT20: 44017.71 | AV20: 13232.98 | AX20: 6964.02 | AZ20: 3023.14 | BB20: 242.93 | BD20: =SUM(BF20,BH20,BJ20,BL20,BN20) -> 0 | BP20: =SUM(BF20,BH20,BJ20)/BD20*100 -> #DIV/0! | BQ20: =SUM(BL20,BN20)/BD20*100 -> #DIV/0!
A21: NUEVA ECIJA | B21: CABANATUAN | C21: NUEVA ECIJA, CABANATUAN | D21: MBA | E21: 3rd | F21: 15.470778 | G21: 120.9521 | H21: =CONCATENATE(F21,",",G21) -> 15.470778,120.952099 | I21: Municipal / City Plan | J21: NSWMC RESO NO. 1513 SERIES OF 2022 | K21: 2020 - 2029 | L21: 2022 | M21: 2029 | O21: 11.November | P21: Christian Jem L. Buluran | Q21: Jaypee Ordoñez | R21: Zosimo P. Suyat | S21: R3-2025-037837 | T21: 45968 | U21: 45972 | V21: 45980 | W21: 45980 | X21: 45980 | Y21: =IF( OR(ISBLANK(T21), ISBLANK(U21)), "", MAX(1, IF( NETWORKDAYS(T21, U21) <= 0, 1, NETWORKDAYS(T21, U21) - IF(T21 = U21, 0, 1) )) ) -> 2 | Z21: =IF( OR(ISBLANK(U21), ISBLANK(V21)), "", MAX(1, IF( NETWORKDAYS(U21, V21) <= 0, 1, NETWORKDAYS(U21, V21) - IF(U21 = V21, 0, 1) )) ) -> 6 | AA21: =IF( OR(IF(V21<>"", V21, U21)="", W21=""), "", MAX(1, IF( NETWORKDAYS(IF(V21<>"", V21, U21), W21) <= 0, 1, NETWORKDAYS(IF(V21<>"", V21, U21), W21) - IF(IF(V21<>"", V21, U21)=W21, 0, 1) ) ) ) -> 1 | AB21: =IF( OR(ISBLANK(W21), ISBLANK(X21)), "", MAX(1, IF( NETWORKDAYS(W21, X21) <= 0, 1, NETWORKDAYS(W21, X21) - IF(W21 = X21, 0, 1) )) ) -> 1 | AC21: Received by Planning | AD21: 0.363 | AG21: Prime Waste Solutions Inc. | AH21: =IF(AND(AI21 = "YES", AJ21 = "YES", AK21 = "YES", AL21 = "YES", AN21 = "YES"), "Compliant", "Not Compliant") -> Compliant | AI21: YES | AJ21: YES | AK21: YES | AL21: YES | AM21: YES | AN21: YES | AR21: 140635.62 | AT21: 74705.64 | AV21: 34104.14 | AX21: 10111.7 | AZ21: 21348.49 | BB21: 365.65 | BD21: =SUM(BF21,BH21,BJ21,BL21,BN21) -> 0 | BP21: =SUM(BF21,BH21,BJ21)/BD21*100 -> #DIV/0! | BQ21: =SUM(BL21,BN21)/BD21*100 -> #DIV/0!
A22: NUEVA ECIJA | B22: LUPAO | C22: NUEVA ECIJA, LUPAO | D22: MBA | E22: 2nd | F22: 15.877262 | G22: 120.8989 | H22: =CONCATENATE(F22,",",G22) -> 15.877262,120.898901 | I22: Municipal / City Plan | J22: 1065 Series of 2018 | K22: 2017 - 2026 | L22: 2018 | M22: 2026 | O22: 11.November | P22: Aser A. Inocencio, Jr. | Q22: Jaypee Ordoñez | R22: Zosimo P. Suyat | S22: R3-2025-037805 | T22: 45972 | U22: 45972 | V22: 45980 | W22: 45980 | X22: 45980 | Y22: =IF( OR(ISBLANK(T22), ISBLANK(U22)), "", MAX(1, IF( NETWORKDAYS(T22, U22) <= 0, 1, NETWORKDAYS(T22, U22) - IF(T22 = U22, 0, 1) )) ) -> 1 | Z22: =IF( OR(ISBLANK(U22), ISBLANK(V22)), "", MAX(1, IF( NETWORKDAYS(U22, V22) <= 0, 1, NETWORKDAYS(U22, V22) - IF(U22 = V22, 0, 1) )) ) -> 6 | AA22: =IF( OR(IF(V22<>"", V22, U22)="", W22=""), "", MAX(1, IF( NETWORKDAYS(IF(V22<>"", V22, U22), W22) <= 0, 1, NETWORKDAYS(IF(V22<>"", V22, U22), W22) - IF(IF(V22<>"", V22, U22)=W22, 0, 1) ) ) ) -> 1 | AB22: =IF( OR(ISBLANK(W22), ISBLANK(X22)), "", MAX(1, IF( NETWORKDAYS(W22, X22) <= 0, 1, NETWORKDAYS(W22, X22) - IF(W22 = X22, 0, 1) )) ) -> 1 | AC22: Received by Planning | AD22: 0.607 | AE22: 31609.92 | AF22: 92.47 | AG22: Metro Waste | AH22: =IF(AND(AI22 = "YES", AJ22 = "YES", AK22 = "YES", AL22 = "YES", AN22 = "YES"), "Compliant", "Not Compliant") -> Compliant | AI22: YES | AJ22: YES | AK22: YES | AL22: YES | AM22: YES | AN22: YES | AR22: 31609.92 | AT22: 19591.83 | AV22: 5680.3 | AX22: 3957.56 | AZ22: 1760.67 | BB22: 619.55 | BD22: =SUM(BF22,BH22,BJ22,BL22,BN22) -> 0 | BP22: =SUM(BF22,BH22,BJ22)/BD22*100 -> #DIV/0! | BQ22: =SUM(BL22,BN22)/BD22*100 -> #DIV/0!
A23: NUEVA ECIJA | B23: RIZAL | C23: NUEVA ECIJA, RIZAL | D23: MBA | E23: 2nd | F23: 15.707877 | G23: 121.10188 | H23: =CONCATENATE(F23,",",G23) -> 15.707877,121.101882 | I23: Municipal / City Plan | J23: 1288 SERIES 2019 | K23: 2017 - 2027 | L23: 2019 | M23: 2027 | O23: 11.November | P23: Hosannah R. Sabio | Q23: Jaypee Ordoñez | R23: Zosimo P. Suyat | S23: R3-2025-038732 | T23: 45972 | U23: 45980 | V23: 45980 | W23: 45980 | X23: 45980 | Y23: =IF( OR(ISBLANK(T23), ISBLANK(U23)), "", MAX(1, IF( NETWORKDAYS(T23, U23) <= 0, 1, NETWORKDAYS(T23, U23) - IF(T23 = U23, 0, 1) )) ) -> 6 | Z23: =IF( OR(ISBLANK(U23), ISBLANK(V23)), "", MAX(1, IF( NETWORKDAYS(U23, V23) <= 0, 1, NETWORKDAYS(U23, V23) - IF(U23 = V23, 0, 1) )) ) -> 1 | AA23: =IF( OR(IF(V23<>"", V23, U23)="", W23=""), "", MAX(1, IF( NETWORKDAYS(IF(V23<>"", V23, U23), W23) <= 0, 1, NETWORKDAYS(IF(V23<>"", V23, U23), W23) - IF(IF(V23<>"", V23, U23)=W23, 0, 1) ) ) ) -> 1 | AB23: =IF( OR(ISBLANK(W23), ISBLANK(X23)), "", MAX(1, IF( NETWORKDAYS(W23, X23) <= 0, 1, NETWORKDAYS(W23, X23) - IF(W23 = X23, 0, 1) )) ) -> 1 | AC23: Received by Planning | AD23: 0.461 | AH23: =IF(AND(AI23 = "YES", AJ23 = "YES", AK23 = "YES", AL23 = "YES", AN23 = "YES"), "Compliant", "Not Compliant") -> Not Compliant | AR23: 38680.41 | AT23: 23595.05 | AV23: 6567.93 | AX23: 3465.76 | AZ23: 4591.36 | BB23: 460.3 | BD23: =SUM(BF23,BH23,BJ23,BL23,BN23) -> 0 | BP23: =SUM(BF23,BH23,BJ23)/BD23*100 -> #DIV/0! | BQ23: =SUM(BL23,BN23)/BD23*100 -> #DIV/0!
A24: NUEVA ECIJA | B24: SAN ANTONIO | C24: NUEVA ECIJA, SAN ANTONIO | D24: MBA | E24: 4th | F24: 15.306809 | G24: 120.85671 | H24: =CONCATENATE(F24,",",G24) -> 15.306809,120.856712 | I24: Municipal / City Plan | J24: NSWMC RESO NO. 1490 SERIES OF 2021 | K24: 2020 - 2029 | L24: 2021 | M24: 2029 | O24: 11.November | P24: Christine Ann V. Ramos | Q24: Jaypee Ordoñez | R24: Zosimo P. Suyat | S24: R3-2025-036611 | T24: 45959 | U24: 45963 | V24: 45966 | W24: 45968 | X24: 45978 | Y24: =IF( OR(ISBLANK(T24), ISBLANK(U24)), "", MAX(1, IF( NETWORKDAYS(T24, U24) <= 0, 1, NETWORKDAYS(T24, U24) - IF(T24 = U24, 0, 1) )) ) -> 2 | Z24: =IF( OR(ISBLANK(U24), ISBLANK(V24)), "", MAX(1, IF( NETWORKDAYS(U24, V24) <= 0, 1, NETWORKDAYS(U24, V24) - IF(U24 = V24, 0, 1) )) ) -> 2 | AA24: =IF( OR(IF(V24<>"", V24, U24)="", W24=""), "", MAX(1, IF( NETWORKDAYS(IF(V24<>"", V24, U24), W24) <= 0, 1, NETWORKDAYS(IF(V24<>"", V24, U24), W24) - IF(IF(V24<>"", V24, U24)=W24, 0, 1) ) ) ) -> 2 | AB24: =IF( OR(ISBLANK(W24), ISBLANK(X24)), "", MAX(1, IF( NETWORKDAYS(W24, X24) <= 0, 1, NETWORKDAYS(W24, X24) - IF(W24 = X24, 0, 1) )) ) -> 6 | AC24: Received by Planning | AD24: 0.63 | AE24: 59542.48 | AF24: 84.18 | AG24: Urdaneta Waste Management | AH24: =IF(AND(AI24 = "YES", AJ24 = "YES", AK24 = "YES", AL24 = "YES", AN24 = "YES"), "Compliant", "Not Compliant") -> Compliant | AI24: YES | AJ24: YES | AK24: YES | AL24: YES | AM24: YES | AN24: YES | AR24: 59542.48 | AT24: 33689.14 | AV24: 13426.83 | AX24: 3006.9 | AZ24: 9276.72 | BB24: 142.9 | BD24: =SUM(BF24,BH24,BJ24,BL24,BN24) -> 0 | BP24: =SUM(BF24,BH24,BJ24)/BD24*100 -> #DIV/0! | BQ24: =SUM(BL24,BN24)/BD24*100 -> #DIV/0!
A25: NUEVA ECIJA | B25: TALUGTUG | C25: NUEVA ECIJA, TALUGTUG | D25: MBA | E25: 2nd | F25: 15.777162 | G25: 120.80776 | H25: =CONCATENATE(F25,",",G25) -> 15.777162,120.807756 | I25: Municipal / City Plan | J25: NSWMC RESO NO. 1078 SERIES OF 2018 | K25: 2017 - 2027 | L25: 2018 | M25: 2027 | O25: 11.November | P25: Aser A. Inocencio, Jr. | Q25: Jaypee Ordoñez | R25: Zosimo P. Suyat | S25: R3-2025-036959 | T25: 45959 | U25: 45965 | V25: 45972 | W25: 45972 | X25: 45978 | Y25: =IF( OR(ISBLANK(T25), ISBLANK(U25)), "", MAX(1, IF( NETWORKDAYS(T25, U25) <= 0, 1, NETWORKDAYS(T25, U25) - IF(T25 = U25, 0, 1) )) ) -> 4 | Z25: =IF( OR(ISBLANK(U25), ISBLANK(V25)), "", MAX(1, IF( NETWORKDAYS(U25, V25) <= 0, 1, NETWORKDAYS(U25, V25) - IF(U25 = V25, 0, 1) )) ) -> 5 | AA25: =IF( OR(IF(V25<>"", V25, U25)="", W25=""), "", MAX(1, IF( NETWORKDAYS(IF(V25<>"", V25, U25), W25) <= 0, 1, NETWORKDAYS(IF(V25<>"", V25, U25), W25) - IF(IF(V25<>"", V25, U25)=W25, 0, 1) ) ) ) -> 1 | AB25: =IF( OR(ISBLANK(W25), ISBLANK(X25)), "", MAX(1, IF( NETWORKDAYS(W25, X25) <= 0, 1, NETWORKDAYS(W25, X25) - IF(W25 = X25, 0, 1) )) ) -> 4 | AC25: Received by Planning | AD25: 0.205 | AE25: 5828.8 | AG25: Metro Waste Solid Waste Management Corporation | AH25: =IF(AND(AI25 = "YES", AJ25 = "YES", AK25 = "YES", AL25 = "YES", AN25 = "YES"), "Compliant", "Not Compliant") -> Not Compliant | AI25: NO | AJ25: YES | AK25: NO | AL25: NO | AM25: NO | AN25: YES | AO25: NO | AR25: 5828.8 | AT25: 3262.38 | AV25: 908.71 | AX25: 259.38 | AZ25: 1362.77 | BB25: 35.56 | BD25: =SUM(BF25,BH25,BJ25,BL25,BN25) -> 0 | BP25: =SUM(BF25,BH25,BJ25)/BD25*100 -> #DIV/0! | BQ25: =SUM(BL25,BN25)/BD25*100 -> #DIV/0!
A26: PAMPANGA | B26: ANGELES | C26: PAMPANGA, ANGELES | D26: MBA | E26: 1st | F26: 15.1653 | G26: 120.6084 | H26: =CONCATENATE(F26,",",G26) -> 15.1653,120.6084 | I26: Municipal / City Plan | J26: NSWMC RESO NO. 196 SERIES OF 2015 | K26: 2015 - 2024 | L26: 2015 | M26: 2024 | N26: For Renewal | O26: 11.November | P26: Elyza A. Evilla | R26: Yves Yshmael M. Balagtas | S26: R3-2025-037819 | T26: 45972 | U26: 45972 | W26: 45978 | X26: 45979 | Y26: =IF( OR(ISBLANK(T26), ISBLANK(U26)), "", MAX(1, IF( NETWORKDAYS(T26, U26) <= 0, 1, NETWORKDAYS(T26, U26) - IF(T26 = U26, 0, 1) )) ) -> 1 | Z26: =IF( OR(ISBLANK(U26), ISBLANK(V26)), "", MAX(1, IF( NETWORKDAYS(U26, V26) <= 0, 1, NETWORKDAYS(U26, V26) - IF(U26 = V26, 0, 1) )) ) | AA26: =IF( OR(IF(V26<>"", V26, U26)="", W26=""), "", MAX(1, IF( NETWORKDAYS(IF(V26<>"", V26, U26), W26) <= 0, 1, NETWORKDAYS(IF(V26<>"", V26, U26), W26) - IF(IF(V26<>"", V26, U26)=W26, 0, 1) ) ) ) -> 4 | AB26: =IF( OR(ISBLANK(W26), ISBLANK(X26)), "", MAX(1, IF( NETWORKDAYS(W26, X26) <= 0, 1, NETWORKDAYS(W26, X26) - IF(W26 = X26, 0, 1) )) ) -> 1 | AC26: Received by Planning | AD26: 0.5 | AE26: 79314 | AF26: 0.6 | AG26: Eco Protect Management Corp. | AH26: =IF(AND(AI26 = "YES", AJ26 = "YES", AK26 = "YES", AL26 = "YES", AN26 = "YES"), "Compliant", "Not Compliant") -> Not Compliant | AI26: YES | AJ26: YES | AK26: YES | AL26: NO | AM26: YES | AN26: YES | AR26: 293415.48 | AT26: 153925.76 | AV26: 56071.7 | AX26: 37967.96 | AZ26: 43865.61 | BB26: 1584.44 | BD26: =SUM(BF26,BH26,BJ26,BL26,BN26) -> 0 | BP26: =SUM(BF26,BH26,BJ26)/BD26*100 -> #DIV/0! | BQ26: =SUM(BL26,BN26)/BD26*100 -> #DIV/0!
A27: PAMPANGA | B27: ARAYAT | C27: PAMPANGA, ARAYAT | D27: MBA | E27: 3rd | F27: 15.154167 | G27: 120.7716 | H27: =CONCATENATE(F27,",",G27) -> 15.154167,120.771598 | I27: Municipal / City Plan | J27: 1038-A Series of 2019 | K27: 2017 -2028 | L27: 2019 | M27: 2028 | O27: 11.November | P27: Roger T. Encarnacion II | R27: Yves Yshmael M. Balagtas | S27: R3-2025-037414 | T27: 45967 | U27: 45970 | W27: 45978 | X27: 45979 | Y27: =IF( OR(ISBLANK(T27), ISBLANK(U27)), "", MAX(1, IF( NETWORKDAYS(T27, U27) <= 0, 1, NETWORKDAYS(T27, U27) - IF(T27 = U27, 0, 1) )) ) -> 1 | Z27: =IF( OR(ISBLANK(U27), ISBLANK(V27)), "", MAX(1, IF( NETWORKDAYS(U27, V27) <= 0, 1, NETWORKDAYS(U27, V27) - IF(U27 = V27, 0, 1) )) ) | AA27: =IF( OR(IF(V27<>"", V27, U27)="", W27=""), "", MAX(1, IF( NETWORKDAYS(IF(V27<>"", V27, U27), W27) <= 0, 1, NETWORKDAYS(IF(V27<>"", V27, U27), W27) - IF(IF(V27<>"", V27, U27)=W27, 0, 1) ) ) ) -> 5 | AB27: =IF( OR(ISBLANK(W27), ISBLANK(X27)), "", MAX(1, IF( NETWORKDAYS(W27, X27) <= 0, 1, NETWORKDAYS(W27, X27) - IF(W27 = X27, 0, 1) )) ) -> 1 | AC27: Received by Planning | AD27: 0.151 | AE27: 22221.68 | AF27: 94.44! | AG27: Floridablanca Enviro Corporation | AH27: =IF(AND(AI27 = "YES", AJ27 = "YES", AK27 = "YES", AL27 = "YES", AN27 = "YES"), "Compliant", "Not Compliant") -> Not Compliant | AI27: YES | AJ27: YES | AK27: YES | AL27: NO | AM27: YES | AN27: YES | AR27: 7030.51 | AT27: 3489.95 | AV27: 2057.83 | AX27: 338.17 | AZ27: 1096.76 | BB27: 47.81 | BD27: =SUM(BF27,BH27,BJ27,BL27,BN27) -> 0 | BP27: =SUM(BF27,BH27,BJ27)/BD27*100 -> #DIV/0! | BQ27: =SUM(BL27,BN27)/BD27*100 -> #DIV/0!
A28: TARLAC | B28: BAMBAN | C28: TARLAC, BAMBAN | D28: MBA | E28: 3rd | F28: 15.289574 | G28: 120.57066 | H28: =CONCATENATE(F28,",",G28) -> 15.289574,120.570662 | I28: Municipal / City Plan | J28: 1248 | K28: 2016 - 2027 | L28: 2019 | M28: 2027 | O28: 11.November | P28: Gretzhen M. Apolonio | Q28: Sherwin John Loquellano | R28: Jan Emerson C. Gonzales | S28: R3-2025-036979 | T28: 45965 | U28: 45968 | V28: 45978 | W28: 45978 | X28: 45978 | Y28: =IF( OR(ISBLANK(T28), ISBLANK(U28)), "", MAX(1, IF( NETWORKDAYS(T28, U28) <= 0, 1, NETWORKDAYS(T28, U28) - IF(T28 = U28, 0, 1) )) ) -> 3 | Z28: =IF( OR(ISBLANK(U28), ISBLANK(V28)), "", MAX(1, IF( NETWORKDAYS(U28, V28) <= 0, 1, NETWORKDAYS(U28, V28) - IF(U28 = V28, 0, 1) )) ) -> 6 | AA28: =IF( OR(IF(V28<>"", V28, U28)="", W28=""), "", MAX(1, IF( NETWORKDAYS(IF(V28<>"", V28, U28), W28) <= 0, 1, NETWORKDAYS(IF(V28<>"", V28, U28), W28) - IF(IF(V28<>"", V28, U28)=W28, 0, 1) ) ) ) -> 1 | AB28: =IF( OR(ISBLANK(W28), ISBLANK(X28)), "", MAX(1, IF( NETWORKDAYS(W28, X28) <= 0, 1, NETWORKDAYS(W28, X28) - IF(W28 = X28, 0, 1) )) ) -> 1 | AC28: Received by Planning | AD28: 0.368 | AE28: 26685.52 | AF28: 0.6852 | AG28: M.A.A Waste Integrated Solution Corporation | AH28: =IF(AND(AI28 = "YES", AJ28 = "YES", AK28 = "YES", AL28 = "YES", AN28 = "YES"), "Compliant", "Not Compliant") -> Compliant | AI28: YES | AJ28: YES | AK28: YES | AL28: YES | AM28: NO | AN28: YES | AR28: 36507.93 | AT28: 13697.78 | AV28: 11321.11 | AX28: 7243.17 | AZ28: 3720.16 | BB28: 525.71 | BD28: =SUM(BF28,BH28,BJ28,BL28,BN28) -> 0 | BP28: =SUM(BF28,BH28,BJ28)/BD28*100 -> #DIV/0! | BQ28: =SUM(BL28,BN28)/BD28*100 -> #DIV/0!
A29: TARLAC | B29: STA IGNACIA | C29: TARLAC, STA IGNACIA | D29: OUTSIDE MBA | E29: 1st | F29: 15.616387 | G29: 120.43469 | H29: =CONCATENATE(F29,",",G29) -> 15.616387,120.434693 | I29: Municipal / City Plan | J29: 1334 series of 2019 | K29: 2018 - 2027 | L29: 2019 | M29: 2027 | O29: 11.November | P29: Joshua A. Capones | Q29: Sherwin John Loquellano | R29: Jan Emerson C. Gonzales | S29: R3-2025-036967 | T29: 45965 | U29: 45965 | V29: 45967 | W29: 45967 | X29: 45978 | Y29: =IF( OR(ISBLANK(T29), ISBLANK(U29)), "", MAX(1, IF( NETWORKDAYS(T29, U29) <= 0, 1, NETWORKDAYS(T29, U29) - IF(T29 = U29, 0, 1) )) ) -> 1 | Z29: =IF( OR(ISBLANK(U29), ISBLANK(V29)), "", MAX(1, IF( NETWORKDAYS(U29, V29) <= 0, 1, NETWORKDAYS(U29, V29) - IF(U29 = V29, 0, 1) )) ) -> 2 | AA29: =IF( OR(ISBLANK(U29), ISBLANK(W29)), "", MAX(1, IF( NETWORKDAYS(U29, W29) <= 0, 1, NETWORKDAYS(U29, W29) - IF(U29 = W29, 0, 1) )) ) -> 2 | AB29: =IF( OR(ISBLANK(W29), ISBLANK(X29)), "", MAX(1, IF( NETWORKDAYS(W29, X29) <= 0, 1, NETWORKDAYS(W29, X29) - IF(W29 = X29, 0, 1) )) ) -> 7 | AC29: Received by Planning | AD29: 0.18 | AE29: 4576.11 | AG29: INTERNATIONAL SOLID WASTE INTEGRATED MNGT. SPECIALIST INC. (ISWIMS) | AH29: =IF(AND(AI29 = "YES", AJ29 = "YES", AK29 = "YES", AL29 = "YES", AN29 = "YES"), "Compliant", "Not Compliant") -> Compliant | AI29: YES | AJ29: YES | AK29: YES | AL29: YES | AM29: YES | AN29: YES | AO29: NO | AR29: 10998.93 | AT29: 4069.6 | AV29: 3629.65 | AX29: 1429.86 | AZ29: 1099.89 | BB29: 769.93 | BD29: =SUM(BF29,BH29,BJ29,BL29,BN29) -> 0 | BP29: =SUM(BF29,BH29,BJ29)/BD29*100 -> #DIV/0! | BQ29: =SUM(BL29,BN29)/BD29*100 -> #DIV/0!
A30: AURORA | B30: MARIA AURORA | C30: AURORA, MARIA AURORA | D30: OUTSIDE MBA | E30: Lone | F30: 15.798717 | G30: 121.47355 | H30: =CONCATENATE(F30,",",G30) -> 15.798717,121.47355 | I30: Municipal / City Plan | J30: NSWMC Resolution No. 139, Series of 2015 | K30: 2015 - 2024 | L30: 2025 | M30: 2034 | N30: Approved | O30: 2.February | P30: Nikko Jay M. Valenzuela | R30: Ryan Christian R. Nunag | S30: R3-2025-004099 | T30: 45692 | U30: 45694 | W30: 45695 | X30: 45695 | Y30: =IF( OR(ISBLANK(T30), ISBLANK(U30)), "", MAX(1, IF( NETWORKDAYS(T30, U30) <= 0, 1, NETWORKDAYS(T30, U30) - IF(T30 = U30, 0, 1) )) ) -> 2 | Z30: =IF( OR(ISBLANK(U30), ISBLANK(V30)), "", MAX(1, IF( NETWORKDAYS(U30, V30) <= 0, 1, NETWORKDAYS(U30, V30) - IF(U30 = V30, 0, 1) )) ) | AA30: =IF( OR(IF(V30<>"", V30, U30)="", W30=""), "", MAX(1, IF( NETWORKDAYS(IF(V30<>"", V30, U30), W30) <= 0, 1, NETWORKDAYS(IF(V30<>"", V30, U30), W30) - IF(IF(V30<>"", V30, U30)=W30, 0, 1) ) ) ) -> 1 | AB30: =IF( OR(ISBLANK(W30), ISBLANK(X30)), "", MAX(1, IF( NETWORKDAYS(W30, X30) <= 0, 1, NETWORKDAYS(W30, X30) - IF(W30 = X30, 0, 1) )) ) -> 1 | AC30: Received by Planning | AD30: 0.24 | AE30: 1825.36 | AF30: 5.24 | AG30: LGU owned SLF | AH30: Compliant | AI30: YES | AJ30: YES | AK30: YES | AL30: YES | AM30: N/A | AN30: YES | AQ30: On going review of the sumitted PLan | AR30: 12056.78 | AT30: 6789.17 | AV30: 1844.69 | AX30: 2629.58 | AZ30: 778.87 | BB30: 14.47 | BD30: =SUM(BF30,BH30,BJ30,BL30,BN30) -> 0 | BP30: =SUM(BF30,BH30,BJ30)/BD30*100 -> #DIV/0! | BQ30: =SUM(BL30,BN30)/BD30*100 -> #DIV/0!
A31: BATAAN | B31: DINALUPIHAN | C31: BATAAN, DINALUPIHAN | D31: MBA | E31: 3rd | F31: 14.866933 | G31: 120.4611 | H31: =CONCATENATE(F31,",",G31) -> 14.866933,120.461103 | I31: Municipal / City Plan | J31: 149 Series of 2015 | K31: 2015 - 2025 | L31: 2015 | M31: 2025 | N31: For Renewal | O31: 2.February | P31: John-lester Signio | R31: Christle D. David | S31: R3-2025-005077 | T31: 45699 | U31: 45700 | W31: 45701 | X31: 45701 | Y31: =IF( OR(ISBLANK(T31), ISBLANK(U31)), "", MAX(1, IF( NETWORKDAYS(T31, U31) <= 0, 1, NETWORKDAYS(T31, U31) - IF(T31 = U31, 0, 1) )) ) -> 1 | Z31: =IF( OR(ISBLANK(U31), ISBLANK(V31)), "", MAX(1, IF( NETWORKDAYS(U31, V31) <= 0, 1, NETWORKDAYS(U31, V31) - IF(U31 = V31, 0, 1) )) ) | AA31: =IF( OR(IF(V31<>"", V31, U31)="", W31=""), "", MAX(1, IF( NETWORKDAYS(IF(V31<>"", V31, U31), W31) <= 0, 1, NETWORKDAYS(IF(V31<>"", V31, U31), W31) - IF(IF(V31<>"", V31, U31)=W31, 0, 1) ) ) ) -> 1 | AB31: =IF( OR(ISBLANK(W31), ISBLANK(X31)), "", MAX(1, IF( NETWORKDAYS(W31, X31) <= 0, 1, NETWORKDAYS(W31, X31) - IF(W31 = X31, 0, 1) )) ) -> 1 | AC31: Received by Planning | AD31: 0.321 | AE31: 38095.24 | AF31: 90 | AG31: Floridablanca Enviro Corporation | AH31: Compliant | AI31: YES | AJ31: YES | AK31: YES | AL31: YES | AM31: YES | AN31: YES | AR31: 29103.01 | AT31: 12805.33 | AV31: 11641.21 | AX31: 1746.18 | AZ31: 1746.18 | BB31: 1164.12 | BD31: =SUM(BF31,BH31,BJ31,BL31,BN31) -> 0 | BP31: =SUM(BF31,BH31,BJ31)/BD31*100 -> #DIV/0! | BQ31: =SUM(BL31,BN31)/BD31*100 -> #DIV/0!
A32: BATAAN | B32: HERMOSA | C32: BATAAN, HERMOSA | D32: MBA | E32: 1st | F32: 14.830649 | G32: 120.50857 | H32: =CONCATENATE(F32,",",G32) -> 14.830649,120.508569 | I32: Municipal / City Plan | J32: NSWMC Resolution No. 1173 | K32: 2017 - 2027 | L32: 2018 | M32: 2027 | O32: 2.February | P32: John-lester Signio | R32: Christle D. David | S32: R3-2025-005565 | T32: 45701 | U32: 45704 | W32: 45705 | X32: 45705 | Y32: =IF( OR(ISBLANK(T32), ISBLANK(U32)), "", MAX(1, IF( NETWORKDAYS(T32, U32) <= 0, 1, NETWORKDAYS(T32, U32) - IF(T32 = U32, 0, 1) )) ) -> 1 | Z32: =IF( OR(ISBLANK(U32), ISBLANK(V32)), "", MAX(1, IF( NETWORKDAYS(U32, V32) <= 0, 1, NETWORKDAYS(U32, V32) - IF(U32 = V32, 0, 1) )) ) | AA32: =IF( OR(IF(V32<>"", V32, U32)="", W32=""), "", MAX(1, IF( NETWORKDAYS(IF(V32<>"", V32, U32), W32) <= 0, 1, NETWORKDAYS(IF(V32<>"", V32, U32), W32) - IF(IF(V32<>"", V32, U32)=W32, 0, 1) ) ) ) -> 1 | AB32: =IF( OR(ISBLANK(W32), ISBLANK(X32)), "", MAX(1, IF( NETWORKDAYS(W32, X32) <= 0, 1, NETWORKDAYS(W32, X32) - IF(W32 = X32, 0, 1) )) ) -> 1 | AC32: Received by Planning | AD32: 0.47 | AE32: 34698.22 | AF32: 85.4 | AG32: Hauler = 5-1 Construction Corporation | AH32: Compliant | AI32: YES | AJ32: YES | AK32: YES | AL32: YES | AM32: YES | AN32: YES | AR32: 50359.71 | AT32: 24555.4 | AV32: 14171.22 | AX32: 4280.58 | AZ32: 6712.95 | BB32: 639.57 | BD32: =SUM(BF32,BH32,BJ32,BL32,BN32) -> 0 | BP32: =SUM(BF32,BH32,BJ32)/BD32*100 -> #DIV/0! | BQ32: =SUM(BL32,BN32)/BD32*100 -> #DIV/0!
A33: BULACAN | B33: CALUMPIT | C33: BULACAN, CALUMPIT | D33: MBA | E33: 1st | F33: 14.91396 | G33: 120.76478 | H33: =CONCATENATE(F33,",",G33) -> 14.91396,120.764777 | I33: Municipal / City Plan | J33: 1082 series of 2018 | K33: 2017 - 2028 | L33: 2018 | M33: 2028 | O33: 2.February | P33: Ronaldo P. Roque, Jr. | Q33: Rod Ross S. De Jesus | R33: Diozelle A. Lazatin | S33: R3-2025-005555 | T33: 45702 | U33: 45704 | V33: 45705 | W33: 45705 | X33: 45706 | Y33: =IF( OR(ISBLANK(T33), ISBLANK(U33)), "", MAX(1, IF( NETWORKDAYS(T33, U33) <= 0, 1, NETWORKDAYS(T33, U33) - IF(T33 = U33, 0, 1) )) ) -> 1 | Z33: =IF( OR(ISBLANK(U33), ISBLANK(V33)), "", MAX(1, IF( NETWORKDAYS(U33, V33) <= 0, 1, NETWORKDAYS(U33, V33) - IF(U33 = V33, 0, 1) )) ) -> 1 | AA33: =IF( OR(IF(V33<>"", V33, U33)="", W33=""), "", MAX(1, IF( NETWORKDAYS(IF(V33<>"", V33, U33), W33) <= 0, 1, NETWORKDAYS(IF(V33<>"", V33, U33), W33) - IF(IF(V33<>"", V33, U33)=W33, 0, 1) ) ) ) -> 1 | AB33: =IF( OR(ISBLANK(W33), ISBLANK(X33)), "", MAX(1, IF( NETWORKDAYS(W33, X33) <= 0, 1, NETWORKDAYS(W33, X33) - IF(W33 = X33, 0, 1) )) ) -> 1 | AC33: Received by Planning | AD33: 0.368 | AE33: 43597.328 | AG33: Eco Protect Management Corporation | AH33: Compliant | AI33: YES | AJ33: NO | AK33: YES | AL33: YES | AN33: YES | AR33: 51602.34 | AT33: 23566.79 | AV33: 12694.18 | AX33: 11280.27 | AZ33: 2827.81 | BB33: 1233.3 | BD33: =SUM(BF33,BH33,BJ33,BL33,BN33) -> 0 | BP33: =SUM(BF33,BH33,BJ33)/BD33*100 -> #DIV/0! | BQ33: =SUM(BL33,BN33)/BD33*100 -> #DIV/0!
A34: BULACAN | B34: MALOLOS | C34: BULACAN, MALOLOS | D34: MBA | E34: 1st | F34: 14.843702 | G34: 120.81114 | H34: =CONCATENATE(F34,",",G34) -> 14.843702,120.811145 | I34: Municipal / City Plan | J34: NSWMC RESO NO. 503-A SERIES OF 2019 | K34: 2018-2028 | L34: 2019 | M34: 2028 | O34: 2.February | P34: Ronaldo P. Roque, Jr. | Q34: Rod Ross S. De Jesus | R34: Diozelle A. Lazatin | S34: R3-2025-004155 | T34: 45692 | U34: 45694 | V34: 45694 | W34: 45698 | X34: 45701 | Y34: =IF( OR(ISBLANK(T34), ISBLANK(U34)), "", MAX(1, IF( NETWORKDAYS(T34, U34) <= 0, 1, NETWORKDAYS(T34, U34) - IF(T34 = U34, 0, 1) )) ) -> 2 | Z34: =IF( OR(ISBLANK(U34), ISBLANK(V34)), "", MAX(1, IF( NETWORKDAYS(U34, V34) <= 0, 1, NETWORKDAYS(U34, V34) - IF(U34 = V34, 0, 1) )) ) -> 1 | AA34: =IF( OR(IF(V34<>"", V34, U34)="", W34=""), "", MAX(1, IF( NETWORKDAYS(IF(V34<>"", V34, U34), W34) <= 0, 1, NETWORKDAYS(IF(V34<>"", V34, U34), W34) - IF(IF(V34<>"", V34, U34)=W34, 0, 1) ) ) ) -> 2 | AB34: =IF( OR(ISBLANK(W34), ISBLANK(X34)), "", MAX(1, IF( NETWORKDAYS(W34, X34) <= 0, 1, NETWORKDAYS(W34, X34) - IF(W34 = X34, 0, 1) )) ) -> 3 | AC34: Received by Planning | AD34: 0.238 | AE34: 69116.39 | AF34: 100 | AG34: Eco Protect Management Corporation | AH34: Compliant | AI34: YES | AJ34: YES | AK34: YES | AL34: YES | AM34: YES | AN34: YES | AR34: 66654.05 | AT34: 37939.49 | AV34: 14490.59 | AX34: 8685.02 | AZ34: 3412.69 | BB34: 2126.26 | BD34: =SUM(BF34,BH34,BJ34,BL34,BN34) -> 0 | BP34: =SUM(BF34,BH34,BJ34)/BD34*100 -> #DIV/0! | BQ34: =SUM(BL34,BN34)/BD34*100 -> #DIV/0!
A35: NUEVA ECIJA | B35: CABIAO | C35: NUEVA ECIJA, CABIAO | D35: MBA | E35: 4th | F35: 15.252382 | G35: 120.86015 | H35: =CONCATENATE(F35,",",G35) -> 15.252382,120.860145 | I35: Municipal / City Plan | J35: 1365 series of 2019 | K35: 2017 - 2027 | L35: 2019 | M35: 2027 | O35: 2.February | P35: Christine Ann V. Ramos | Q35: Jaypee Ordoñez | R35: Zosimo P. Suyat | S35: R3-2025-003758 | T35: 45692 | U35: 45693 | V35: 45694 | W35: 45698 | X35: 45705 | Y35: =IF( OR(ISBLANK(T35), ISBLANK(U35)), "", MAX(1, IF( NETWORKDAYS(T35, U35) <= 0, 1, NETWORKDAYS(T35, U35) - IF(T35 = U35, 0, 1) )) ) -> 1 | Z35: =IF( OR(ISBLANK(U35), ISBLANK(V35)), "", MAX(1, IF( NETWORKDAYS(U35, V35) <= 0, 1, NETWORKDAYS(U35, V35) - IF(U35 = V35, 0, 1) )) ) -> 1 | AA35: =IF( OR(IF(V35<>"", V35, U35)="", W35=""), "", MAX(1, IF( NETWORKDAYS(IF(V35<>"", V35, U35), W35) <= 0, 1, NETWORKDAYS(IF(V35<>"", V35, U35), W35) - IF(IF(V35<>"", V35, U35)=W35, 0, 1) ) ) ) -> 2 | AB35: =IF( OR(ISBLANK(W35), ISBLANK(X35)), "", MAX(1, IF( NETWORKDAYS(W35, X35) <= 0, 1, NETWORKDAYS(W35, X35) - IF(W35 = X35, 0, 1) )) ) -> 5 | AC35: Received by Planning | AD35: 0.723 | AE35: 45349.47 | AH35: Compliant | AI35: YES | AJ35: YES | AK35: YES | AL35: YES | AM35: YES | AN35: YES | AR35: 65905.11 | AT35: 34000.45 | AV35: 8119.51 | AX35: 10564.59 | AZ35: 12805.36 | BB35: 415.2 | BD35: =SUM(BF35,BH35,BJ35,BL35,BN35) -> 0 | BP35: =SUM(BF35,BH35,BJ35)/BD35*100 -> #DIV/0! | BQ35: =SUM(BL35,BN35)/BD35*100 -> #DIV/0!
A36: NUEVA ECIJA | B36: GAPAN CITY | C36: NUEVA ECIJA, GAPAN | D36: MBA | E36: 4th | F36: 15.293716 | G36: 120.9486 | H36: =CONCATENATE(F36,",",G36) -> 15.293716,120.948601 | I36: Municipal / City Plan | J36: 1064 S. 2018 | K36: 2017 - 2026 | L36: 2018 | M36: 2026 | O36: 2.February | P36: Christine Ann V. Ramos | Q36: Jaypee Ordoñez | R36: Zosimo P. Suyat | S36: R3-2025-004165 | T36: 45693 | U36: 45695 | V36: 45695 | W36: 45698 | X36: 45701 | Y36: =IF( OR(ISBLANK(T36), ISBLANK(U36)), "", MAX(1, IF( NETWORKDAYS(T36, U36) <= 0, 1, NETWORKDAYS(T36, U36) - IF(T36 = U36, 0, 1) )) ) -> 2 | Z36: =IF( OR(ISBLANK(U36), ISBLANK(V36)), "", MAX(1, IF( NETWORKDAYS(U36, V36) <= 0, 1, NETWORKDAYS(U36, V36) - IF(U36 = V36, 0, 1) )) ) -> 1 | AA36: =IF( OR(IF(V36<>"", V36, U36)="", W36=""), "", MAX(1, IF( NETWORKDAYS(IF(V36<>"", V36, U36), W36) <= 0, 1, NETWORKDAYS(IF(V36<>"", V36, U36), W36) - IF(IF(V36<>"", V36, U36)=W36, 0, 1) ) ) ) -> 1 | AB36: =IF( OR(ISBLANK(W36), ISBLANK(X36)), "", MAX(1, IF( NETWORKDAYS(W36, X36) <= 0, 1, NETWORKDAYS(W36, X36) - IF(W36 = X36, 0, 1) )) ) -> 3 | AC36: Received by Planning | AD36: 0.376 | AE36: 50252.07 | AF36: 92.68 | AG36: Floridablanca Enviro Corporation | AH36: =IF(AND(AI36 = "YES", AJ36 = "YES", AK36 = "YES", AL36 = "YES", AN36 = "YES"), "Compliant", "Not Compliant") -> Not Compliant | AI36: YES | AJ36: YES | AK36: YES | AL36: YES | AM36: NO | AN36: NO | AO36: NO | AR36: 50704.34 | AT36: 24510.48 | AV36: 15753.84 | AX36: 6728.47 | AZ36: 3427.61 | BB36: 283.94 | BD36: =SUM(BF36,BH36,BJ36,BL36,BN36) -> 0 | BP36: =SUM(BF36,BH36,BJ36)/BD36*100 -> #DIV/0! | BQ36: =SUM(BL36,BN36)/BD36*100 -> #DIV/0!
A37: NUEVA ECIJA | B37: SAN ISIDRO | C37: NUEVA ECIJA, SAN ISIDRO | D37: MBA | E37: 4th | F37: 15.309493 | G37: 120.90685 | H37: =CONCATENATE(F37,",",G37) -> 15.309493,120.906855 | I37: Municipal / City Plan | J37: NSWMC RESO NO. 1444SERIES OF 2021 | K37: 2020 - 2029 | L37: 2021 | M37: 2029 | O37: 2.February | P37: Christine Ann V. Ramos | Q37: Jaypee Ordoñez | R37: Zosimo P. Suyat | S37: R3-2025-004470 | T37: 45693 | U37: 45697 | V37: 45698 | W37: 45698 | X37: 45701 | Y37: =IF( OR(ISBLANK(T37), ISBLANK(U37)), "", MAX(1, IF( NETWORKDAYS(T37, U37) <= 0, 1, NETWORKDAYS(T37, U37) - IF(T37 = U37, 0, 1) )) ) -> 2 | Z37: =IF( OR(ISBLANK(U37), ISBLANK(V37)), "", MAX(1, IF( NETWORKDAYS(U37, V37) <= 0, 1, NETWORKDAYS(U37, V37) - IF(U37 = V37, 0, 1) )) ) -> 1 | AA37: =IF( OR(IF(V37<>"", V37, U37)="", W37=""), "", MAX(1, IF( NETWORKDAYS(IF(V37<>"", V37, U37), W37) <= 0, 1, NETWORKDAYS(IF(V37<>"", V37, U37), W37) - IF(IF(V37<>"", V37, U37)=W37, 0, 1) ) ) ) -> 1 | AB37: =IF( OR(ISBLANK(W37), ISBLANK(X37)), "", MAX(1, IF( NETWORKDAYS(W37, X37) <= 0, 1, NETWORKDAYS(W37, X37) - IF(W37 = X37, 0, 1) )) ) -> 3 | AC37: Received by Planning | AD37: 0.306 | AE37: 18196.55 | AG37: Primwaste Solutions Inc | AH37: Compliant | AI37: YES | AJ37: YES | AK37: YES | AL37: YES | AM37: YES | AN37: YES | AR37: 18378.52 | AT37: 9501.69 | AV37: 4543.17 | AX37: 1723.9 | AZ37: 2017.96 | BB37: 591.79 | BD37: =SUM(BF37,BH37,BJ37,BL37,BN37) -> 0 | BP37: =SUM(BF37,BH37,BJ37)/BD37*100 -> #DIV/0! | BQ37: =SUM(BL37,BN37)/BD37*100 -> #DIV/0!
A38: NUEVA ECIJA | B38: NAMPICUAN | C38: NUEVA ECIJA, NAMPICUAN | D38: OUTSIDE MBA | E38: 1st | F38: 15.733889 | G38: 120.63528 | H38: =CONCATENATE(F38,",",G38) -> 15.733889,120.635278 | I38: Municipal / City Plan | J38: No. 1406 Series of 2020 | K38: 2018 - 2027 | L38: 2020 | M38: 2027 | O38: 2.February | P38: Aser A. Inocencio, Jr. | Q38: Jaypee Ordoñez | R38: Zosimo P. Suyat | S38: R3-2025-005766 | T38: 45699 | U38: 45705 | V38: 45706 | W38: 45706 | X38: 45706 | Y38: =IF( OR(ISBLANK(T38), ISBLANK(U38)), "", MAX(1, IF( NETWORKDAYS(T38, U38) <= 0, 1, NETWORKDAYS(T38, U38) - IF(T38 = U38, 0, 1) )) ) -> 4 | Z38: =IF( OR(ISBLANK(U38), ISBLANK(V38)), "", MAX(1, IF( NETWORKDAYS(U38, V38) <= 0, 1, NETWORKDAYS(U38, V38) - IF(U38 = V38, 0, 1) )) ) -> 1 | AA38: =IF( OR(ISBLANK(U38), ISBLANK(W38)), "", MAX(1, IF( NETWORKDAYS(U38, W38) <= 0, 1, NETWORKDAYS(U38, W38) - IF(U38 = W38, 0, 1) )) ) -> 1 | AB38: =IF( OR(ISBLANK(W38), ISBLANK(X38)), "", MAX(1, IF( NETWORKDAYS(W38, X38) <= 0, 1, NETWORKDAYS(W38, X38) - IF(W38 = X38, 0, 1) )) ) -> 1 | AC38: Received by Planning | AD38: 0.398 | AE38: 6299.03 | AG38: Metro Waste Solid Waste Management Corporation | AH38: =IF(AND(AI38 = "YES", AJ38 = "YES", AK38 = "YES", AL38 = "YES", AN38 = "YES"), "Compliant", "Not Compliant") -> Not Compliant | AI38: NO | AJ38: YES | AK38: NO | AL38: YES | AM38: NO | AN38: YES | AO38: NO | AR38: 6362.02 | AT38: 2442.38 | AV38: 2742.67 | AX38: 650.84 | AZ38: 437.07 | BB38: 89.07 | BD38: =SUM(BF38,BH38,BJ38,BL38,BN38) -> 0 | BP38: =SUM(BF38,BH38,BJ38)/BD38*100 -> #DIV/0! | BQ38: =SUM(BL38,BN38)/BD38*100 -> #DIV/0!
A39: PAMPANGA | B39: MINALIN | C39: PAMPANGA, MINALIN | D39: MBA | E39: 4th | F39: 14.9704 | G39: 120.6861 | H39: =CONCATENATE(F39,",",G39) -> 14.9704,120.6861 | I39: Municipal / City Plan | J39: 763 s. 2016 | K39: 2015 - 2024 | L39: 2016 | M39: 2024 | N39: For Renewal | O39: 2.February | P39: Glaiza S.Gaza | Q39: Maria Cecilia Pascual | R39: Yves Yshmael M. Balagtas | S39: R3-2025-005288 | T39: 45699 | U39: 45701 | V39: 45701 | W39: 45705 | X39: 45705 | Y39: =IF( OR(ISBLANK(T39), ISBLANK(U39)), "", MAX(1, IF( NETWORKDAYS(T39, U39) <= 0, 1, NETWORKDAYS(T39, U39) - IF(T39 = U39, 0, 1) )) ) -> 2 | Z39: =IF( OR(ISBLANK(U39), ISBLANK(V39)), "", MAX(1, IF( NETWORKDAYS(U39, V39) <= 0, 1, NETWORKDAYS(U39, V39) - IF(U39 = V39, 0, 1) )) ) -> 1 | AA39: =IF( OR(IF(V39<>"", V39, U39)="", W39=""), "", MAX(1, IF( NETWORKDAYS(IF(V39<>"", V39, U39), W39) <= 0, 1, NETWORKDAYS(IF(V39<>"", V39, U39), W39) - IF(IF(V39<>"", V39, U39)=W39, 0, 1) ) ) ) -> 2 | AB39: =IF( OR(ISBLANK(W39), ISBLANK(X39)), "", MAX(1, IF( NETWORKDAYS(W39, X39) <= 0, 1, NETWORKDAYS(W39, X39) - IF(W39 = X39, 0, 1) )) ) -> 1 | AC39: Received by Planning | AD39: 0.391 | AE39: 14116 | AF39: 72.04 | AG39: Floridablanca Enviro Corporation | AH39: Compliant | AI39: YES | AJ39: YES | AK39: YES | AL39: YES | AM39: YES | AN39: YES | AR39: 19491.8 | AT39: 9966.16 | AV39: 3939.29 | AX39: 2387.75 | AZ39: 2820.46 | BB39: 378.14 | BD39: =SUM(BF39,BH39,BJ39,BL39,BN39) -> 0 | BP39: =SUM(BF39,BH39,BJ39)/BD39*100 -> #DIV/0! | BQ39: =SUM(BL39,BN39)/BD39*100 -> #DIV/0!
A40: PAMPANGA | B40: STO TOMAS | C40: PAMPANGA, STO TOMAS | D40: MBA | E40: 4th | F40: 14.996704 | G40: 120.70418 | H40: =CONCATENATE(F40,",",G40) -> 14.996704,120.704181 | I40: Municipal / City Plan | J40: 1243 | K40: 2017 - 2027 | L40: 2019 | M40: 2027 | O40: 2.February | P40: Elyza A. Evilla | Q40: Maria Cecilia Pascual | R40: Yves Yshmael M. Balagtas | S40: R3-2025-004396 | T40: 45695 | U40: 45697 | V40: 45699 | W40: 45699 | X40: 45701 | Y40: =IF( OR(ISBLANK(T40), ISBLANK(U40)), "", MAX(1, IF( NETWORKDAYS(T40, U40) <= 0, 1, NETWORKDAYS(T40, U40) - IF(T40 = U40, 0, 1) )) ) -> 1 | Z40: =IF( OR(ISBLANK(U40), ISBLANK(V40)), "", MAX(1, IF( NETWORKDAYS(U40, V40) <= 0, 1, NETWORKDAYS(U40, V40) - IF(U40 = V40, 0, 1) )) ) -> 1 | AA40: =IF( OR(IF(V40<>"", V40, U40)="", W40=""), "", MAX(1, IF( NETWORKDAYS(IF(V40<>"", V40, U40), W40) <= 0, 1, NETWORKDAYS(IF(V40<>"", V40, U40), W40) - IF(IF(V40<>"", V40, U40)=W40, 0, 1) ) ) ) -> 1 | AB40: =IF( OR(ISBLANK(W40), ISBLANK(X40)), "", MAX(1, IF( NETWORKDAYS(W40, X40) <= 0, 1, NETWORKDAYS(W40, X40) - IF(W40 = X40, 0, 1) )) ) -> 2 | AC40: Received by Planning | AD40: 0.232 | AE40: 9,658.52 kg | AF40: 100 | AG40: Floridablanca Enviro Corp | AH40: =IF(AND(AI40 = "YES", AJ40 = "YES", AK40 = "YES", AL40 = "YES", AN40 = "YES"), "Compliant", "Not Compliant") -> Not Compliant | AI40: NO | AJ40: NO | AK40: NO | AL40: YES | AM40: NO | AN40: YES | AO40: NO | AR40: 11089.45 | AT40: 2937.59 | AV40: 3911.25 | AX40: 1286.38 | AZ40: 2214.56 | BB40: 739.67 | BD40: =SUM(BF40,BH40,BJ40,BL40,BN40) -> 0 | BP40: =SUM(BF40,BH40,BJ40)/BD40*100 -> #DIV/0! | BQ40: =SUM(BL40,BN40)/BD40*100 -> #DIV/0!
A41: TARLAC | B41: CAMILING | C41: TARLAC, CAMILING | D41: OUTSIDE MBA | E41: 1st | F41: 15.686329 | G41: 120.41465 | H41: =CONCATENATE(F41,",",G41) -> 15.6863285,120.4146513 | I41: Municipal / City Plan | J41: 1090 series of 2018 | K41: 2018 - 2027 | L41: 2018 | M41: 2027 | O41: 2.February | P41: Jasper Kieht B. Pili | Q41: Ryan Christian R. Nunag | R41: Rod Ross S. De Jesus | S41: R3-2025-005939 | T41: 45706 | U41: 45706 | V41: 45707 | W41: 45707 | X41: 45707 | Y41: =IF( OR(ISBLANK(T41), ISBLANK(U41)), "", MAX(1, IF( NETWORKDAYS(T41, U41) <= 0, 1, NETWORKDAYS(T41, U41) - IF(T41 = U41, 0, 1) )) ) -> 1 | Z41: =IF( OR(ISBLANK(U41), ISBLANK(V41)), "", MAX(1, IF( NETWORKDAYS(U41, V41) <= 0, 1, NETWORKDAYS(U41, V41) - IF(U41 = V41, 0, 1) )) ) -> 1 | AA41: =IF( OR(IF(V41<>"", V41, U41)="", W41=""), "", MAX(1, IF( NETWORKDAYS(IF(V41<>"", V41, U41), W41) <= 0, 1, NETWORKDAYS(IF(V41<>"", V41, U41), W41) - IF(IF(V41<>"", V41, U41)=W41, 0, 1) ) ) ) -> 1 | AB41: =IF( OR(ISBLANK(W41), ISBLANK(X41)), "", MAX(1, IF( NETWORKDAYS(W41, X41) <= 0, 1, NETWORKDAYS(W41, X41) - IF(W41 = X41, 0, 1) )) ) -> 1 | AC41: Received by Planning | AD41: 0.45 | AE41: 14257.31 | AF41: 100 | AG41: MetroWaste Solid Waste Management Corporation | AH41: Not Compliant | AI41: YES | AJ41: NO | AK41: YES | AL41: YES | AM41: N/A | AN41: YES | AO41: NO | AR41: 43404.52 | AT41: 19540.72 | AV41: 8854.52 | AX41: 6862.26 | AZ41: 6892.64 | BB41: 1254.39 | BD41: =SUM(BF41,BH41,BJ41,BL41,BN41) -> 0 | BP41: =SUM(BF41,BH41,BJ41)/BD41*100 -> #DIV/0! | BQ41: =SUM(BL41,BN41)/BD41*100 -> #DIV/0!
A42: TARLAC | B42: CAPAS | C42: TARLAC, CAPAS | D42: MBA | E42: 3rd | F42: 15.346305 | G42: 120.59294 | H42: =CONCATENATE(F42,",",G42) -> 15.346305,120.592937 | I42: Municipal / City Plan | J42: 1250 series of 2019 | K42: 2018 - 2027 | L42: 2019 | M42: 2027 | O42: 2.February | Q42: Ryan Christian R. Nunag | R42: Rod Ross S. De Jesus | S42: R3-2025-004609 | T42: 45694 | U42: 45698 | W42: 45700 | X42: 45701 | Y42: =IF( OR(ISBLANK(T42), ISBLANK(U42)), "", MAX(1, IF( NETWORKDAYS(T42, U42) <= 0, 1, NETWORKDAYS(T42, U42) - IF(T42 = U42, 0, 1) )) ) -> 2 | Z42: =IF( OR(ISBLANK(U42), ISBLANK(V42)), "", MAX(1, IF( NETWORKDAYS(U42, V42) <= 0, 1, NETWORKDAYS(U42, V42) - IF(U42 = V42, 0, 1) )) ) | AA42: =IF( OR(IF(V42<>"", V42, U42)="", W42=""), "", MAX(1, IF( NETWORKDAYS(IF(V42<>"", V42, U42), W42) <= 0, 1, NETWORKDAYS(IF(V42<>"", V42, U42), W42) - IF(IF(V42<>"", V42, U42)=W42, 0, 1) ) ) ) -> 2 | AB42: =IF( OR(ISBLANK(W42), ISBLANK(X42)), "", MAX(1, IF( NETWORKDAYS(W42, X42) <= 0, 1, NETWORKDAYS(W42, X42) - IF(W42 = X42, 0, 1) )) ) -> 1 | AC42: Received by Planning | AD42: 0.44 | AE42: 68974.13 | AF42: 100 | AG42: International Solid Waste Integrated Management Specialist Inc (ISWIMS)/ GREEN LEAF | AH42: Compliant | AI42: YES | AJ42: YES | AK42: YES | AL42: YES | AM42: NO | AN42: YES | AR42: 85357.58 | AT42: 42789.76 | AV42: 15125.36 | AX42: 16653.26 | AZ42: 9867.34 | BB42: 921.86 | BD42: =SUM(BF42,BH42,BJ42,BL42,BN42) -> 0 | BP42: =SUM(BF42,BH42,BJ42)/BD42*100 -> #DIV/0! | BQ42: =SUM(BL42,BN42)/BD42*100 -> #DIV/0!
A43: ZAMBALES | B43: SAN MARCELINO | C43: ZAMBALES, SAN MARCELINO | D43: OUTSIDE MBA | E43: 1st | F43: 14.974092 | G43: 120.15555 | H43: =CONCATENATE(F43,",",G43) -> 14.974092,120.155547 | I43: Municipal / City Plan | J43: 1253 | K43: 2017 - 2027 | L43: 2019 | M43: 2027 | O43: 2.February | P43: Larizze A. Santos | Q43: Ryan Christian R. Nunag | R43: Jun D. Guillermo | S43: R3-2025-004763 | T43: 45693 | U43: 45698 | V43: 45699 | W43: 45701 | X43: 45702 | Y43: =IF( OR(ISBLANK(T43), ISBLANK(U43)), "", MAX(1, IF( NETWORKDAYS(T43, U43) <= 0, 1, NETWORKDAYS(T43, U43) - IF(T43 = U43, 0, 1) )) ) -> 3 | Z43: =IF( OR(ISBLANK(U43), ISBLANK(V43)), "", MAX(1, IF( NETWORKDAYS(U43, V43) <= 0, 1, NETWORKDAYS(U43, V43) - IF(U43 = V43, 0, 1) )) ) -> 1 | AA43: =IF( OR(ISBLANK(U43), ISBLANK(W43)), "", MAX(1, IF( NETWORKDAYS(U43, W43) <= 0, 1, NETWORKDAYS(U43, W43) - IF(U43 = W43, 0, 1) )) ) -> 3 | AB43: =IF( OR(ISBLANK(W43), ISBLANK(X43)), "", MAX(1, IF( NETWORKDAYS(W43, X43) <= 0, 1, NETWORKDAYS(W43, X43) - IF(W43 = X43, 0, 1) )) ) -> 1 | AC43: Received by Planning | AD43: 0.236 | AE43: 9352.68 | AF43: 5246.85 | AG43: Prime Waste Solutions - Pampanga | AH43: Compliant | AI43: YES | AJ43: YES | AK43: YES | AL43: YES | AM43: YES | AN43: YES | AR43: 11174.51 | AT43: 2417.05 | AV43: 3851.85 | AX43: 3499.86 | AZ43: 1063.81 | BB43: 341.94 | BD43: =SUM(BF43,BH43,BJ43,BL43,BN43) -> 0 | BP43: =SUM(BF43,BH43,BJ43)/BD43*100 -> #DIV/0! | BQ43: =SUM(BL43,BN43)/BD43*100 -> #DIV/0!
A44: BATAAN | B44: BALANGA CITY | C44: BATAAN, BALANGA CITY | D44: MBA | E44: 2nd | F44: 14.679914 | G44: 120.5407 | H44: =CONCATENATE(F44,",",G44) -> 14.679914,120.540698 | I44: Municipal / City Plan | J44: 482 series of 2016 | K44: 2016 - 2025 | L44: 2016 | M44: 2025 | N44: For Renewal | O44: 3.March | P44: Dennis Tolentino | R44: Christle D. David | S44: R3-2025-007105 | T44: 45716 | U44: 45718 | W44: 45719 | X44: 45719 | Y44: =IF( OR(ISBLANK(T44), ISBLANK(U44)), "", MAX(1, IF( NETWORKDAYS(T44, U44) <= 0, 1, NETWORKDAYS(T44, U44) - IF(T44 = U44, 0, 1) )) ) -> 1 | Z44: =IF( OR(ISBLANK(U44), ISBLANK(V44)), "", MAX(1, IF( NETWORKDAYS(U44, V44) <= 0, 1, NETWORKDAYS(U44, V44) - IF(U44 = V44, 0, 1) )) ) | AA44: =IF( OR(IF(V44<>"", V44, U44)="", W44=""), "", MAX(1, IF( NETWORKDAYS(IF(V44<>"", V44, U44), W44) <= 0, 1, NETWORKDAYS(IF(V44<>"", V44, U44), W44) - IF(IF(V44<>"", V44, U44)=W44, 0, 1) ) ) ) -> 1 | AB44: =IF( OR(ISBLANK(W44), ISBLANK(X44)), "", MAX(1, IF( NETWORKDAYS(W44, X44) <= 0, 1, NETWORKDAYS(W44, X44) - IF(W44 = X44, 0, 1) )) ) -> 1 | AC44: Received by Planning | AD44: 0.235 | AE44: 24547.38 | AF44: 48.48 | AG44: Bataan Integrated Waste Management Facility | AH44: Compliant | AI44: YES | AJ44: YES | AK44: YES | AL44: YES | AM44: NO | AN44: YES | AR44: 70203.72 | AT44: 35277.37 | AV44: 14974.45 | AX44: 10811.37 | AZ44: 8684.2 | BB44: 456.32 | BD44: =SUM(BF44,BH44,BJ44,BL44,BN44) -> 0 | BP44: =SUM(BF44,BH44,BJ44)/BD44*100 -> #DIV/0! | BQ44: =SUM(BL44,BN44)/BD44*100 -> #DIV/0!
A45: BATAAN | B45: PILAR | C45: BATAAN, PILAR | D45: MBA | E45: 2nd | F45: 14.66851 | G45: 120.55284 | H45: =CONCATENATE(F45,",",G45) -> 14.66851,120.552837 | I45: Municipal / City Plan | J45: NSWMC Res. No. 138 s. 2015 | K45: 2015 - 2024 | L45: 2015 | M45: 2024 | N45: For Renewal | O45: 3.March | P45: Dennis Tolentino | R45: Christle D. David | S45: R3-2025-008931 | T45: 45729 | U45: 45733 | W45: 45733 | X45: 45733 | Y45: =IF( OR(ISBLANK(T45), ISBLANK(U45)), "", MAX(1, IF( NETWORKDAYS(T45, U45) <= 0, 1, NETWORKDAYS(T45, U45) - IF(T45 = U45, 0, 1) )) ) -> 2 | Z45: =IF( OR(ISBLANK(U45), ISBLANK(V45)), "", MAX(1, IF( NETWORKDAYS(U45, V45) <= 0, 1, NETWORKDAYS(U45, V45) - IF(U45 = V45, 0, 1) )) ) | AA45: =IF( OR(IF(V45<>"", V45, U45)="", W45=""), "", MAX(1, IF( NETWORKDAYS(IF(V45<>"", V45, U45), W45) <= 0, 1, NETWORKDAYS(IF(V45<>"", V45, U45), W45) - IF(IF(V45<>"", V45, U45)=W45, 0, 1) ) ) ) -> 1 | AB45: =IF( OR(ISBLANK(W45), ISBLANK(X45)), "", MAX(1, IF( NETWORKDAYS(W45, X45) <= 0, 1, NETWORKDAYS(W45, X45) - IF(W45 = X45, 0, 1) )) ) -> 1 | AC45: Received by Planning | AD45: 0.51 | AE45: 23600.1 | AF45: 0.55 | AG45: Bataan Integrated Waste Management Facility | AH45: Compliant | AI45: YES | AJ45: YES | AK45: YES | AL45: YES | AM45: N/A | AN45: YES | AR45: 21587.83 | AT45: 8229.28 | AV45: 7156.36 | AX45: 3078.42 | AZ45: 3033.09 | BB45: 90.67 | BD45: =SUM(BF45,BH45,BJ45,BL45,BN45) -> 0 | BP45: =SUM(BF45,BH45,BJ45)/BD45*100 -> #DIV/0! | BQ45: =SUM(BL45,BN45)/BD45*100 -> #DIV/0!
A46: BULACAN | B46: BULAKAN | C46: BULACAN, BULAKAN | D46: MBA | E46: 1st | F46: 14.794464 | G46: 120.87892 | H46: =CONCATENATE(F46,",",G46) -> 14.79446412,120.8789154 | I46: Municipal / City Plan | J46: 1180 | K46: 2017 - 2027 | L46: 2018 | M46: 2027 | O46: 3.March | P46: Jasmin Marie N. Siapco | Q46: Rod Ross S. De Jesus | R46: Diozelle A. Lazatin | S46: R3-2025-008783 | T46: 45729 | U46: 45732 | V46: 45735 | W46: 45735 | X46: 45735 | Y46: =IF( OR(ISBLANK(T46), ISBLANK(U46)), "", MAX(1, IF( NETWORKDAYS(T46, U46) <= 0, 1, NETWORKDAYS(T46, U46) - IF(T46 = U46, 0, 1) )) ) -> 1 | Z46: =IF( OR(ISBLANK(U46), ISBLANK(V46)), "", MAX(1, IF( NETWORKDAYS(U46, V46) <= 0, 1, NETWORKDAYS(U46, V46) - IF(U46 = V46, 0, 1) )) ) -> 2 | AA46: =IF( OR(IF(V46<>"", V46, U46)="", W46=""), "", MAX(1, IF( NETWORKDAYS(IF(V46<>"", V46, U46), W46) <= 0, 1, NETWORKDAYS(IF(V46<>"", V46, U46), W46) - IF(IF(V46<>"", V46, U46)=W46, 0, 1) ) ) ) -> 1 | AB46: =IF( OR(ISBLANK(W46), ISBLANK(X46)), "", MAX(1, IF( NETWORKDAYS(W46, X46) <= 0, 1, NETWORKDAYS(W46, X46) - IF(W46 = X46, 0, 1) )) ) -> 1 | AC46: Received by Planning | AD46: 0.127 | AE46: 213800 | AF46: 100 | AG46: ISWIMS SLF, Montalban, Rizal | AH46: Compliant | AI46: YES | AJ46: YES | AK46: YES | AL46: YES | AM46: NO | AN46: YES | AR46: 11623.48 | AT46: 3647.45 | AV46: 1982.96 | AX46: 3133.69 | AZ46: 2850.08 | BB46: 9.3 | BD46: =SUM(BF46,BH46,BJ46,BL46,BN46) -> 0 | BP46: =SUM(BF46,BH46,BJ46)/BD46*100 -> #DIV/0! | BQ46: =SUM(BL46,BN46)/BD46*100 -> #DIV/0!
A47: BULACAN | B47: HAGONOY | C47: BULACAN, HAGONOY | D47: MBA | E47: 1st | F47: 14.836099 | G47: 120.7341 | H47: =CONCATENATE(F47,",",G47) -> 14.836099,120.734098 | I47: Municipal / City Plan | J47: 499A | K47: 2016 - 2025 | L47: 2018 | M47: 2025 | N47: For Renewal | O47: 3.March | P47: Ronaldo P. Roque, Jr. | Q47: Rod Ross S. De Jesus | R47: Diozelle A. Lazatin | S47: R3-2025-007937 | T47: 45722 | U47: 45724 | V47: 45727 | W47: 45727 | X47: 45730 | Y47: =IF( OR(ISBLANK(T47), ISBLANK(U47)), "", MAX(1, IF( NETWORKDAYS(T47, U47) <= 0, 1, NETWORKDAYS(T47, U47) - IF(T47 = U47, 0, 1) )) ) -> 1 | Z47: =IF( OR(ISBLANK(U47), ISBLANK(V47)), "", MAX(1, IF( NETWORKDAYS(U47, V47) <= 0, 1, NETWORKDAYS(U47, V47) - IF(U47 = V47, 0, 1) )) ) -> 1 | AA47: =IF( OR(IF(V47<>"", V47, U47)="", W47=""), "", MAX(1, IF( NETWORKDAYS(IF(V47<>"", V47, U47), W47) <= 0, 1, NETWORKDAYS(IF(V47<>"", V47, U47), W47) - IF(IF(V47<>"", V47, U47)=W47, 0, 1) ) ) ) -> 1 | AB47: =IF( OR(ISBLANK(W47), ISBLANK(X47)), "", MAX(1, IF( NETWORKDAYS(W47, X47) <= 0, 1, NETWORKDAYS(W47, X47) - IF(W47 = X47, 0, 1) )) ) -> 3 | AC47: Received by Planning | AD47: 0.424 | AE47: 45657.37 | AF47: 100 | AG47: ISWIMS SLF, Montalban, Rizal | AH47: Compliant | AI47: YES | AJ47: YES | AK47: YES | AL47: YES | AM47: YES | AN47: YES | AR47: 19692.76 | AT47: 8940.51 | AV47: 4844.42 | AX47: 2745.17 | AZ47: 2607.32 | BB47: 555.34 | BD47: =SUM(BF47,BH47,BJ47,BL47,BN47) -> 0 | BP47: =SUM(BF47,BH47,BJ47)/BD47*100 -> #DIV/0! | BQ47: =SUM(BL47,BN47)/BD47*100 -> #DIV/0!
A48: BULACAN | B48: PAOMBONG | C48: BULACAN, PAOMBONG | D48: MBA | E48: 1st | F48: 14.836511 | G48: 120.78777 | H48: =CONCATENATE(F48,",",G48) -> 14.83651081,120.7877692 | I48: Municipal / City Plan | J48: 664-A series of 2019 | K48: 2017 - 2026 | L48: 2019 | M48: 2026 | O48: 3.March | P48: Ronaldo P. Roque, Jr. | Q48: Rod Ross S. De Jesus | R48: Diozelle A. Lazatin | S48: R3-2025-008383 | T48: 45727 | U48: 45733 | V48: 45733 | W48: 45733 | X48: 45735 | Y48: =IF( OR(ISBLANK(T48), ISBLANK(U48)), "", MAX(1, IF( NETWORKDAYS(T48, U48) <= 0, 1, NETWORKDAYS(T48, U48) - IF(T48 = U48, 0, 1) )) ) -> 4 | Z48: =IF( OR(ISBLANK(U48), ISBLANK(V48)), "", MAX(1, IF( NETWORKDAYS(U48, V48) <= 0, 1, NETWORKDAYS(U48, V48) - IF(U48 = V48, 0, 1) )) ) -> 1 | AA48: =IF( OR(IF(V48<>"", V48, U48)="", W48=""), "", MAX(1, IF( NETWORKDAYS(IF(V48<>"", V48, U48), W48) <= 0, 1, NETWORKDAYS(IF(V48<>"", V48, U48), W48) - IF(IF(V48<>"", V48, U48)=W48, 0, 1) ) ) ) -> 1 | AB48: =IF( OR(ISBLANK(W48), ISBLANK(X48)), "", MAX(1, IF( NETWORKDAYS(W48, X48) <= 0, 1, NETWORKDAYS(W48, X48) - IF(W48 = X48, 0, 1) )) ) -> 2 | AC48: Received by Planning | AD48: 0.45 | AE48: 25564.46 | AF48: 100 | AG48: Eco Protect Management Corporation | AH48: Compliant | AI48: YES | AJ48: YES | AK48: YES | AL48: YES | AM48: YES | AN48: YES | AR48: 27960.72 | AT48: 9478.68 | AV48: 11603.7 | AX48: 2485.71 | AZ48: 3769.11 | BB48: 623.52 | BD48: =SUM(BF48,BH48,BJ48,BL48,BN48) -> 0 | BP48: =SUM(BF48,BH48,BJ48)/BD48*100 -> #DIV/0! | BQ48: =SUM(BL48,BN48)/BD48*100 -> #DIV/0!
A49: NUEVA ECIJA | B49: SAN LEONARDO | C49: NUEVA ECIJA, SAN LEONARDO | D49: MBA | E49: 4th | F49: 15.362293 | G49: 120.94051 | H49: =CONCATENATE(F49,",",G49) -> 15.362293,120.940508 | I49: Municipal / City Plan | J49: 1087 series of 2018 | K49: 2017 - 2026 | L49: 2018 | M49: 2026 | O49: 3.March | P49: Jan Emerson C. Gonzales | Q49: Jaypee Ordoñez | R49: Zosimo P. Suyat | S49: R3-2025-009219 | T49: 45730 | U49: 45734 | V49: 45734 | W49: 45734 | X49: 45735 | Y49: =IF( OR(ISBLANK(T49), ISBLANK(U49)), "", MAX(1, IF( NETWORKDAYS(T49, U49) <= 0, 1, NETWORKDAYS(T49, U49) - IF(T49 = U49, 0, 1) )) ) -> 2 | Z49: =IF( OR(ISBLANK(U49), ISBLANK(V49)), "", MAX(1, IF( NETWORKDAYS(U49, V49) <= 0, 1, NETWORKDAYS(U49, V49) - IF(U49 = V49, 0, 1) )) ) -> 1 | AA49: =IF( OR(IF(V49<>"", V49, U49)="", W49=""), "", MAX(1, IF( NETWORKDAYS(IF(V49<>"", V49, U49), W49) <= 0, 1, NETWORKDAYS(IF(V49<>"", V49, U49), W49) - IF(IF(V49<>"", V49, U49)=W49, 0, 1) ) ) ) -> 1 | AB49: =IF( OR(ISBLANK(W49), ISBLANK(X49)), "", MAX(1, IF( NETWORKDAYS(W49, X49) <= 0, 1, NETWORKDAYS(W49, X49) - IF(W49 = X49, 0, 1) )) ) -> 1 | AC49: Received by Planning | AD49: 0.48 | AE49: 51, 565.92 | AF49: 86.98 | AG49: Prime Waste Solutions | AH49: Compliant | AI49: YES | AJ49: YES | AK49: YES | AL49: YES | AM49: YES | AN49: YES | AR49: 36339.06 | AT49: 15066.18 | AV49: 16454.33 | AX49: 846.7 | AZ49: 3292.32 | BB49: 679.54 | BD49: =SUM(BF49,BH49,BJ49,BL49,BN49) -> 0 | BP49: =SUM(BF49,BH49,BJ49)/BD49*100 -> #DIV/0! | BQ49: =SUM(BL49,BN49)/BD49*100 -> #DIV/0!
A50: NUEVA ECIJA | B50: SANTA ROSA | C50: NUEVA ECIJA, SANTA ROSA | D50: MBA | E50: 3rd | F50: 15.424259 | G50: 120.93948 | H50: =CONCATENATE(F50,",",G50) -> 15.424259,120.939475 | I50: Municipal / City Plan | J50: No. 1412 Series of 2020 | K50: 2017 - 2026 | L50: 2020 | M50: 2026 | O50: 3.March | P50: Jan Emerson C. Gonzales | Q50: Jaypee Ordoñez | R50: Zosimo P. Suyat | S50: R3-2025-009273 | T50: 45730 | U50: 45734 | V50: 45735 | W50: 45735 | X50: 45735 | Y50: =IF( OR(ISBLANK(T50), ISBLANK(U50)), "", MAX(1, IF( NETWORKDAYS(T50, U50) <= 0, 1, NETWORKDAYS(T50, U50) - IF(T50 = U50, 0, 1) )) ) -> 2 | Z50: =IF( OR(ISBLANK(U50), ISBLANK(V50)), "", MAX(1, IF( NETWORKDAYS(U50, V50) <= 0, 1, NETWORKDAYS(U50, V50) - IF(U50 = V50, 0, 1) )) ) -> 1 | AA50: =IF( OR(IF(V50<>"", V50, U50)="", W50=""), "", MAX(1, IF( NETWORKDAYS(IF(V50<>"", V50, U50), W50) <= 0, 1, NETWORKDAYS(IF(V50<>"", V50, U50), W50) - IF(IF(V50<>"", V50, U50)=W50, 0, 1) ) ) ) -> 1 | AB50: =IF( OR(ISBLANK(W50), ISBLANK(X50)), "", MAX(1, IF( NETWORKDAYS(W50, X50) <= 0, 1, NETWORKDAYS(W50, X50) - IF(W50 = X50, 0, 1) )) ) -> 1 | AC50: Received by Planning | AD50: 0.248 | AE50: 19836.56 | AF50: 76.87 | AG50: Local Government Unit - Santa Rosa, Nueva Ecija | AH50: =IF(AND(AI50 = "YES", AJ50 = "YES", AK50 = "YES", AL50 = "YES", AN50 = "YES"), "Compliant", "Not Compliant") -> Compliant | AI50: YES | AJ50: YES | AK50: YES | AL50: YES | AM50: YES | AN50: YES | AO50: NO | AR50: 20929.87 | AT50: 12503.5 | AV50: 3066.23 | AX50: 1810.43 | AZ50: 3478.54 | BB50: 71.16 | BD50: =SUM(BF50,BH50,BJ50,BL50,BN50) -> 0 | BP50: =SUM(BF50,BH50,BJ50)/BD50*100 -> #DIV/0! | BQ50: =SUM(BL50,BN50)/BD50*100 -> #DIV/0!
A51: NUEVA ECIJA | B51: BONGABON | C51: NUEVA ECIJA, BONGABON | D51: MBA | E51: 3rd | F51: 15.627503 | G51: 121.14521 | H51: =CONCATENATE(F51,",",G51) -> 15.627503,121.145207 | I51: Municipal / City Plan | J51: 1075 series 2018 | K51: 2017 - 2026 | L51: 2018 | M51: 2026 | O51: 3.March | P51: Jan Emerson C. Gonzales | Q51: Jaypee Ordoñez | R51: Zosimo P. Suyat | S51: R3-2025-008214 | T51: 45723 | U51: 45726 | V51: 45729 | W51: 45734 | X51: 45735 | Y51: =IF( OR(ISBLANK(T51), ISBLANK(U51)), "", MAX(1, IF( NETWORKDAYS(T51, U51) <= 0, 1, NETWORKDAYS(T51, U51) - IF(T51 = U51, 0, 1) )) ) -> 1 | Z51: =IF( OR(ISBLANK(U51), ISBLANK(V51)), "", MAX(1, IF( NETWORKDAYS(U51, V51) <= 0, 1, NETWORKDAYS(U51, V51) - IF(U51 = V51, 0, 1) )) ) -> 3 | AA51: =IF( OR(IF(V51<>"", V51, U51)="", W51=""), "", MAX(1, IF( NETWORKDAYS(IF(V51<>"", V51, U51), W51) <= 0, 1, NETWORKDAYS(IF(V51<>"", V51, U51), W51) - IF(IF(V51<>"", V51, U51)=W51, 0, 1) ) ) ) -> 3 | AB51: =IF( OR(ISBLANK(W51), ISBLANK(X51)), "", MAX(1, IF( NETWORKDAYS(W51, X51) <= 0, 1, NETWORKDAYS(W51, X51) - IF(W51 = X51, 0, 1) )) ) -> 1 | AC51: Received by Planning | AD51: 0.727 | AE51: 53609.71 | AF51: 87.99 | AG51: Urdaneta Engineered Sanitary Landfill | AH51: Compliant | AI51: YES | AJ51: YES | AK51: YES | AL51: YES | AM51: YES | AN51: YES | AR51: 52622.28 | AT51: 24900.86 | AV51: 16865.44 | AX51: 5493.77 | AZ51: 3920.36 | BB51: 1441.85 | BD51: =SUM(BF51,BH51,BJ51,BL51,BN51) -> 0 | BP51: =SUM(BF51,BH51,BJ51)/BD51*100 -> #DIV/0! | BQ51: =SUM(BL51,BN51)/BD51*100 -> #DIV/0!
A52: PAMPANGA | B52: GUAGUA | C52: PAMPANGA, GUAGUA | D52: MBA | E52: 2nd | F52: 14.965207 | G52: 120.63334 | H52: =CONCATENATE(F52,",",G52) -> 14.965207,120.633338 | I52: Municipal / City Plan | J52: 158 | K52: 2015 - 2024 | L52: 2015 | M52: 2024 | N52: For Renewal | O52: 3.March | P52: Ivy M. Castro | R52: Yves Yshmael M. Balagtas | S52: R3-2025-008781 | T52: 45729 | U52: 45732 | W52: 45733 | X52: 45734 | Y52: =IF( OR(ISBLANK(T52), ISBLANK(U52)), "", MAX(1, IF( NETWORKDAYS(T52, U52) <= 0, 1, NETWORKDAYS(T52, U52) - IF(T52 = U52, 0, 1) )) ) -> 1 | Z52: =IF( OR(ISBLANK(U52), ISBLANK(V52)), "", MAX(1, IF( NETWORKDAYS(U52, V52) <= 0, 1, NETWORKDAYS(U52, V52) - IF(U52 = V52, 0, 1) )) ) | AA52: =IF( OR(IF(V52<>"", V52, U52)="", W52=""), "", MAX(1, IF( NETWORKDAYS(IF(V52<>"", V52, U52), W52) <= 0, 1, NETWORKDAYS(IF(V52<>"", V52, U52), W52) - IF(IF(V52<>"", V52, U52)=W52, 0, 1) ) ) ) -> 1 | AB52: =IF( OR(ISBLANK(W52), ISBLANK(X52)), "", MAX(1, IF( NETWORKDAYS(W52, X52) <= 0, 1, NETWORKDAYS(W52, X52) - IF(W52 = X52, 0, 1) )) ) -> 1 | AC52: Received by Planning | AH52: =IF(AND(AI52 = "YES", AJ52 = "YES", AK52 = "YES", AL52 = "YES", AN52 = "YES"), "Compliant", "Not Compliant") -> Not Compliant | AO52: NO | AR52: 54610.77 | AT52: 26671.9 | AV52: 15471.23 | AX52: 2042.44 | AZ52: 10097.53 | BB52: 327.66 | BD52: =SUM(BF52,BH52,BJ52,BL52,BN52) -> 0 | BP52: =SUM(BF52,BH52,BJ52)/BD52*100 -> #DIV/0! | BQ52: =SUM(BL52,BN52)/BD52*100 -> #DIV/0!
A53: PAMPANGA | B53: SASMUAN | C53: PAMPANGA, SASMUAN | D53: MBA | E53: 2nd | F53: 14.9363 | G53: 120.6223 | H53: =CONCATENATE(F53,",",G53) -> 14.9363,120.6223 | I53: Municipal / City Plan | J53: NSWMC RESO NO. 1332 SERIES OF 2019 | K53: 2017 - 2028 | L53: 2019 | M53: 2028 | O53: 3.March | P53: Ivy M. Castro | R53: Yves Yshmael M. Balagtas | S53: R3-2025-008780 | T53: 45730 | U53: 45732 | W53: 45733 | X53: 45734 | Y53: =IF( OR(ISBLANK(T53), ISBLANK(U53)), "", MAX(1, IF( NETWORKDAYS(T53, U53) <= 0, 1, NETWORKDAYS(T53, U53) - IF(T53 = U53, 0, 1) )) ) -> 1 | Z53: =IF( OR(ISBLANK(U53), ISBLANK(V53)), "", MAX(1, IF( NETWORKDAYS(U53, V53) <= 0, 1, NETWORKDAYS(U53, V53) - IF(U53 = V53, 0, 1) )) ) | AA53: =IF( OR(IF(V53<>"", V53, U53)="", W53=""), "", MAX(1, IF( NETWORKDAYS(IF(V53<>"", V53, U53), W53) <= 0, 1, NETWORKDAYS(IF(V53<>"", V53, U53), W53) - IF(IF(V53<>"", V53, U53)=W53, 0, 1) ) ) ) -> 1 | AB53: =IF( OR(ISBLANK(W53), ISBLANK(X53)), "", MAX(1, IF( NETWORKDAYS(W53, X53) <= 0, 1, NETWORKDAYS(W53, X53) - IF(W53 = X53, 0, 1) )) ) -> 1 | AC53: Received by Planning | AH53: Compliant | AR53: 11020.67 | AT53: 6051.45 | AV53: 2298.91 | AX53: 1351.13 | AZ53: 1167.09 | BB53: 152.09 | BD53: =SUM(BF53,BH53,BJ53,BL53,BN53) -> 0 | BP53: =SUM(BF53,BH53,BJ53)/BD53*100 -> #DIV/0! | BQ53: =SUM(BL53,BN53)/BD53*100 -> #DIV/0!
A54: TARLAC | B54: CONCEPCION | C54: TARLAC, CONCEPCION | D54: MBA | E54: 3rd | F54: 15.323352 | G54: 120.65551 | H54: =CONCATENATE(F54,",",G54) -> 15.323352,120.655511 | I54: Municipal / City Plan | J54: NSWMC RESO NO. 1404SERIES OF 2020 | K54: 2018 - 2027 | L54: 2020 | M54: 2027 | O54: 3.March | Q54: Ryan Christian R. Nunag | R54: Rod Ross S. De Jesus | S54: R3-2025-007778 | T54: 45720 | U54: 45723 | V54: 45723 | W54: 45726 | X54: 45728 | Y54: =IF( OR(ISBLANK(T54), ISBLANK(U54)), "", MAX(1, IF( NETWORKDAYS(T54, U54) <= 0, 1, NETWORKDAYS(T54, U54) - IF(T54 = U54, 0, 1) )) ) -> 3 | Z54: =IF( OR(ISBLANK(U54), ISBLANK(V54)), "", MAX(1, IF( NETWORKDAYS(U54, V54) <= 0, 1, NETWORKDAYS(U54, V54) - IF(U54 = V54, 0, 1) )) ) -> 1 | AA54: =IF( OR(IF(V54<>"", V54, U54)="", W54=""), "", MAX(1, IF( NETWORKDAYS(IF(V54<>"", V54, U54), W54) <= 0, 1, NETWORKDAYS(IF(V54<>"", V54, U54), W54) - IF(IF(V54<>"", V54, U54)=W54, 0, 1) ) ) ) -> 1 | AB54: =IF( OR(ISBLANK(W54), ISBLANK(X54)), "", MAX(1, IF( NETWORKDAYS(W54, X54) <= 0, 1, NETWORKDAYS(W54, X54) - IF(W54 = X54, 0, 1) )) ) -> 2 | AC54: Received by Planning | AD54: 0.55 | AE54: 93474.15 | AF54: 94.03 | AG54: Green Leaf International | AH54: Compliant | AI54: YES | AJ54: YES | AK54: YES | AL54: YES | AM54: YES | AN54: YES | AR54: 113944.47 | AT54: 73186.53 | AV54: 24281.57 | AX54: 9673.89 | AZ54: 6745.51 | BB54: 56.97 | BD54: =SUM(BF54,BH54,BJ54,BL54,BN54) -> 0 | BP54: =SUM(BF54,BH54,BJ54)/BD54*100 -> #DIV/0! | BQ54: =SUM(BL54,BN54)/BD54*100 -> #DIV/0!
A55: TARLAC | B55: MONCADA | C55: TARLAC, MONCADA | D55: OUTSIDE MBA | E55: 1st | F55: 15.733045 | G55: 120.5727 | H55: =CONCATENATE(F55,",",G55) -> 15.7330446,120.5727025 | I55: Municipal / City Plan | J55: No.237,series of 2015 | K55: 2015 - 2024 | L55: 2015 | M55: 2024 | N55: For Renewal | O55: 3.March | P55: Joshua A. Capones | R55: Rod Ross S. De Jesus | S55: R3-2025-008901 | T55: 45730 | U55: 45733 | W55: 45734 | X55: 45734 | Y55: =IF( OR(ISBLANK(T55), ISBLANK(U55)), "", MAX(1, IF( NETWORKDAYS(T55, U55) <= 0, 1, NETWORKDAYS(T55, U55) - IF(T55 = U55, 0, 1) )) ) -> 1 | Z55: =IF( OR(ISBLANK(U55), ISBLANK(V55)), "", MAX(1, IF( NETWORKDAYS(U55, V55) <= 0, 1, NETWORKDAYS(U55, V55) - IF(U55 = V55, 0, 1) )) ) | AA55: =IF( OR(ISBLANK(U55), ISBLANK(W55)), "", MAX(1, IF( NETWORKDAYS(U55, W55) <= 0, 1, NETWORKDAYS(U55, W55) - IF(U55 = W55, 0, 1) )) ) -> 1 | AB55: =IF( OR(ISBLANK(W55), ISBLANK(X55)), "", MAX(1, IF( NETWORKDAYS(W55, X55) <= 0, 1, NETWORKDAYS(W55, X55) - IF(W55 = X55, 0, 1) )) ) -> 1 | AC55: Received by Planning | AD55: 0.35 | AE55: 25 588.67 | AF55: 100 | AG55: Metro Waste Management Corporation | AH55: Compliant | AI55: YES | AJ55: YES | AK55: YES | AL55: YES | AM55: YES | AN55: YES | AR55: 26023.67 | AT55: 17258.9 | AV55: 5131.87 | AX55: 861.38 | AZ55: 2022.04 | BB55: 749.48 | BD55: =SUM(BF55,BH55,BJ55,BL55,BN55) -> 0 | BP55: =SUM(BF55,BH55,BJ55)/BD55*100 -> #DIV/0! | BQ55: =SUM(BL55,BN55)/BD55*100 -> #DIV/0!
A56: TARLAC | B56: SAN MANUEL | C56: TARLAC, SAN MANUEL | D56: OUTSIDE MBA | E56: 1st | F56: 15.799371 | G56: 120.60732 | H56: =CONCATENATE(F56,",",G56) -> 15.7993705,120.6073187 | I56: Municipal / City Plan | J56: Resolution No. 1604, Series of 2023 | K56: 2022 - 2031 | L56: 2023 | M56: 2031 | O56: 3.March | P56: Jasper Kieht B. Pili | R56: Rod Ross S. De Jesus | S56: R3-2025-008830 | T56: 45730 | U56: 45732 | W56: 45735 | X56: 45735 | Y56: =IF( OR(ISBLANK(T56), ISBLANK(U56)), "", MAX(1, IF( NETWORKDAYS(T56, U56) <= 0, 1, NETWORKDAYS(T56, U56) - IF(T56 = U56, 0, 1) )) ) -> 1 | Z56: =IF( OR(ISBLANK(U56), ISBLANK(V56)), "", MAX(1, IF( NETWORKDAYS(U56, V56) <= 0, 1, NETWORKDAYS(U56, V56) - IF(U56 = V56, 0, 1) )) ) | AA56: =IF( OR(ISBLANK(U56), ISBLANK(W56)), "", MAX(1, IF( NETWORKDAYS(U56, W56) <= 0, 1, NETWORKDAYS(U56, W56) - IF(U56 = W56, 0, 1) )) ) -> 2 | AB56: =IF( OR(ISBLANK(W56), ISBLANK(X56)), "", MAX(1, IF( NETWORKDAYS(W56, X56) <= 0, 1, NETWORKDAYS(W56, X56) - IF(W56 = X56, 0, 1) )) ) -> 1 | AC56: Received by Planning | AD56: 0.2 | AE56: 6, 176.8 | AF56: 100 | AG56: Urdaneta Engineered Sanitary Landfill | AH56: =IF(AND(AI56 = "YES", AJ56 = "YES", AK56 = "YES", AL56 = "YES", AN56 = "YES"), "Compliant", "Not Compliant") -> Not Compliant | AI56: NO | AJ56: NO | AK56: NO | AL56: NO | AM56: NO | AN56: YES | AO56: NO | AR56: 6246 | AT56: 4188.57 | AV56: 1029.34 | AX56: 405.37 | AZ56: 527.79 | BB56: 94.94 | BD56: =SUM(BF56,BH56,BJ56,BL56,BN56) -> 0 | BP56: =SUM(BF56,BH56,BJ56)/BD56*100 -> #DIV/0! | BQ56: =SUM(BL56,BN56)/BD56*100 -> #DIV/0!
A57: ZAMBALES | B57: SAN FELIPE | C57: ZAMBALES, SAN FELIPE | D57: OUTSIDE MBA | E57: 2nd | F57: 15.060178 | G57: 120.07053 | H57: =CONCATENATE(F57,",",G57) -> 15.060178,120.070525 | I57: Municipal / City Plan | J57: Resolution No. 772-A, Series of 2023 | K57: 2022 - 2031 | L57: 2023 | M57: 2031 | O57: 3.March | P57: Larizze A. Santos | Q57: Ryan Christian R. Nunag | R57: Jun D. Guillermo | S57: R3-2025-009159 | T57: 45730 | U57: 45734 | V57: 45734 | W57: 45734 | X57: 45734 | Y57: =IF( OR(ISBLANK(T57), ISBLANK(U57)), "", MAX(1, IF( NETWORKDAYS(T57, U57) <= 0, 1, NETWORKDAYS(T57, U57) - IF(T57 = U57, 0, 1) )) ) -> 2 | Z57: =IF( OR(ISBLANK(U57), ISBLANK(V57)), "", MAX(1, IF( NETWORKDAYS(U57, V57) <= 0, 1, NETWORKDAYS(U57, V57) - IF(U57 = V57, 0, 1) )) ) -> 1 | AA57: =IF( OR(ISBLANK(U57), ISBLANK(W57)), "", MAX(1, IF( NETWORKDAYS(U57, W57) <= 0, 1, NETWORKDAYS(U57, W57) - IF(U57 = W57, 0, 1) )) ) -> 1 | AB57: =IF( OR(ISBLANK(W57), ISBLANK(X57)), "", MAX(1, IF( NETWORKDAYS(W57, X57) <= 0, 1, NETWORKDAYS(W57, X57) - IF(W57 = X57, 0, 1) )) ) -> 1 | AC57: Received by Planning | AD57: 0.235 | AE57: 5882.76 | AF57: 90.32 | AG57: Prime Waste Solutions | AH57: Compliant | AI57: YES | AJ57: YES | AK57: YES | AL57: YES | AN57: YES | AR57: 7873.04 | AT57: 5510.34 | AV57: 1433.68 | AX57: 167.7 | AZ57: 473.96 | BB57: 287.37 | BD57: =SUM(BF57,BH57,BJ57,BL57,BN57) -> 0 | BP57: =SUM(BF57,BH57,BJ57)/BD57*100 -> #DIV/0! | BQ57: =SUM(BL57,BN57)/BD57*100 -> #DIV/0!
A58: ZAMBALES | B58: SAN NARCISO | C58: ZAMBALES, SAN NARCISO | D58: OUTSIDE MBA | E58: 2nd | F58: 15.015553 | G58: 120.07906 | H58: =CONCATENATE(F58,",",G58) -> 15.015553,120.079056 | I58: Municipal / City Plan | J58: 1349 s2019 | K58: 2017 - 2027 | L58: 2019 | M58: 2027 | O58: 3.March | P58: Larizze A. Santos | Q58: Ryan Christian R. Nunag | R58: Jun D. Guillermo | S58: R3-2025-009161 | T58: 45730 | U58: 45734 | V58: 45734 | W58: 45734 | X58: 45734 | Y58: =IF( OR(ISBLANK(T58), ISBLANK(U58)), "", MAX(1, IF( NETWORKDAYS(T58, U58) <= 0, 1, NETWORKDAYS(T58, U58) - IF(T58 = U58, 0, 1) )) ) -> 2 | Z58: =IF( OR(ISBLANK(U58), ISBLANK(V58)), "", MAX(1, IF( NETWORKDAYS(U58, V58) <= 0, 1, NETWORKDAYS(U58, V58) - IF(U58 = V58, 0, 1) )) ) -> 1 | AA58: =IF( OR(ISBLANK(U58), ISBLANK(W58)), "", MAX(1, IF( NETWORKDAYS(U58, W58) <= 0, 1, NETWORKDAYS(U58, W58) - IF(U58 = W58, 0, 1) )) ) -> 1 | AB58: =IF( OR(ISBLANK(W58), ISBLANK(X58)), "", MAX(1, IF( NETWORKDAYS(W58, X58) <= 0, 1, NETWORKDAYS(W58, X58) - IF(W58 = X58, 0, 1) )) ) -> 1 | AC58: Received by Planning | AD58: 0.267 | AE58: 8212.65 | AF58: 0.9009 | AG58: Eco Protect Management Corporation | AH58: Compliant | AI58: YES | AJ58: YES | AK58: YES | AL58: YES | AM58: YES | AN58: YES | AR58: 9625.44 | AT58: 6840.8 | AV58: 1595.9 | AX58: 234.86 | AZ58: 642.98 | BB58: 310.9 | BD58: =SUM(BF58,BH58,BJ58,BL58,BN58) -> 0 | BP58: =SUM(BF58,BH58,BJ58)/BD58*100 -> #DIV/0! | BQ58: =SUM(BL58,BN58)/BD58*100 -> #DIV/0!
A59: AURORA | B59: BALER | C59: AURORA, BALER | D59: OUTSIDE MBA | E59: Lone | F59: 15.759064 | G59: 121.56307 | H59: =CONCATENATE(F59,",",G59) -> 15.759064,121.563075 | I59: Municipal / City Plan | J59: 859 series of 2018 | K59: 2017 - 2027 | L59: 2018 | M59: 2027 | O59: 4.April | P59: Zaila Mae Leander | R59: Ryan Christian R. Nunag | S59: R3-2025-012391 | T59: 45757 | U59: 45758 | W59: 45761 | X59: 45761 | Y59: =IF( OR(ISBLANK(T59), ISBLANK(U59)), "", MAX(1, IF( NETWORKDAYS(T59, U59) <= 0, 1, NETWORKDAYS(T59, U59) - IF(T59 = U59, 0, 1) )) ) -> 1 | Z59: =IF( OR(ISBLANK(U59), ISBLANK(V59)), "", MAX(1, IF( NETWORKDAYS(U59, V59) <= 0, 1, NETWORKDAYS(U59, V59) - IF(U59 = V59, 0, 1) )) ) | AA59: =IF( OR(IF(V59<>"", V59, U59)="", W59=""), "", MAX(1, IF( NETWORKDAYS(IF(V59<>"", V59, U59), W59) <= 0, 1, NETWORKDAYS(IF(V59<>"", V59, U59), W59) - IF(IF(V59<>"", V59, U59)=W59, 0, 1) ) ) ) -> 1 | AB59: =IF( OR(ISBLANK(W59), ISBLANK(X59)), "", MAX(1, IF( NETWORKDAYS(W59, X59) <= 0, 1, NETWORKDAYS(W59, X59) - IF(W59 = X59, 0, 1) )) ) -> 1 | AC59: Received by Planning | AD59: 0.42 | AE59: 18389.7 | AF59: 0.8891 | AG59: Prime Waste Solutions | AH59: =IF(AND(AI59 = "YES", AJ59 = "YES", AK59 = "YES", AL59 = "YES", AN59 = "YES"), "Compliant", "Not Compliant") -> Compliant | AI59: YES | AJ59: YES | AK59: YES | AL59: YES | AN59: YES | AR59: 22416.94 | AT59: 9206.64 | AV59: 6794.58 | AX59: 3929.69 | AZ59: 1818.01 | BB59: 668.02 | BD59: =SUM(BF59,BH59,BJ59,BL59,BN59) -> 232 | BF59: 32 | BH59: 56 | BJ59: 76 | BL59: 45 | BN59: 23 | BP59: =SUM(BF59,BH59,BJ59)/BD59*100 -> 70.689655 | BQ59: =SUM(BL59,BN59)/BD59*100 -> 29.310345
A60: BATAAN | B60: ABUCAY | C60: BATAAN, ABUCAY | D60: MBA | E60: 1st | F60: 14.722283 | G60: 120.53544 | H60: =CONCATENATE(F60,",",G60) -> 14.722283,120.535442 | I60: Municipal / City Plan | J60: 1252 Series of 2019 | K60: 2017 -2027 | L60: 2019 | M60: 2027 | O60: 4.April | P60: Dennis Tolentino | R60: Christle D. David | S60: R3-2025-010093 | T60: 45736 | U60: 45740 | W60: 45742 | X60: 45743 | Y60: =IF( OR(ISBLANK(T60), ISBLANK(U60)), "", MAX(1, IF( NETWORKDAYS(T60, U60) <= 0, 1, NETWORKDAYS(T60, U60) - IF(T60 = U60, 0, 1) )) ) -> 2 | Z60: =IF( OR(ISBLANK(U60), ISBLANK(V60)), "", MAX(1, IF( NETWORKDAYS(U60, V60) <= 0, 1, NETWORKDAYS(U60, V60) - IF(U60 = V60, 0, 1) )) ) | AA60: =IF( OR(IF(V60<>"", V60, U60)="", W60=""), "", MAX(1, IF( NETWORKDAYS(IF(V60<>"", V60, U60), W60) <= 0, 1, NETWORKDAYS(IF(V60<>"", V60, U60), W60) - IF(IF(V60<>"", V60, U60)=W60, 0, 1) ) ) ) -> 2 | AB60: =IF( OR(ISBLANK(W60), ISBLANK(X60)), "", MAX(1, IF( NETWORKDAYS(W60, X60) <= 0, 1, NETWORKDAYS(W60, X60) - IF(W60 = X60, 0, 1) )) ) -> 1 | AC60: Received by Planning | AD60: 0.232 | AE60: 11155.55 | AF60: 92.01 | AG60: LGU owned SLF | AH60: Compliant | AI60: YES | AJ60: YES | AK60: YES | AL60: YES | AM60: YES | AN60: YES | AR60: 11423.59 | AT60: 5415.93 | AV60: 2722.24 | AX60: 2568.02 | AZ60: 169.07 | BB60: 548.33 | BD60: =SUM(BF60,BH60,BJ60,BL60,BN60) -> 0 | BP60: =SUM(BF60,BH60,BJ60)/BD60*100 -> #DIV/0! | BQ60: =SUM(BL60,BN60)/BD60*100 -> #DIV/0!
A61: BATAAN | B61: SAMAL | C61: BATAAN, SAMAL | D61: MBA | E61: 1st | F61: 14.768971 | G61: 120.54241 | H61: =CONCATENATE(F61,",",G61) -> 14.768971,120.542407 | I61: Municipal / City Plan | J61: 975 Series of 2017 | K61: 2015 - 2024 | L61: 2017 | M61: 2024 | N61: For Renewal | O61: 4.April | P61: John-lester Signio | R61: Christle D. David | S61: R3-2025-012168 | T61: 45755 | U61: 45757 | W61: 45758 | X61: 45758 | Y61: =IF( OR(ISBLANK(T61), ISBLANK(U61)), "", MAX(1, IF( NETWORKDAYS(T61, U61) <= 0, 1, NETWORKDAYS(T61, U61) - IF(T61 = U61, 0, 1) )) ) -> 2 | Z61: =IF( OR(ISBLANK(U61), ISBLANK(V61)), "", MAX(1, IF( NETWORKDAYS(U61, V61) <= 0, 1, NETWORKDAYS(U61, V61) - IF(U61 = V61, 0, 1) )) ) | AA61: =IF( OR(IF(V61<>"", V61, U61)="", W61=""), "", MAX(1, IF( NETWORKDAYS(IF(V61<>"", V61, U61), W61) <= 0, 1, NETWORKDAYS(IF(V61<>"", V61, U61), W61) - IF(IF(V61<>"", V61, U61)=W61, 0, 1) ) ) ) -> 1 | AB61: =IF( OR(ISBLANK(W61), ISBLANK(X61)), "", MAX(1, IF( NETWORKDAYS(W61, X61) <= 0, 1, NETWORKDAYS(W61, X61) - IF(W61 = X61, 0, 1) )) ) -> 1 | AC61: Received by Planning | AH61: Compliant | AR61: 14858.9 | AT61: 6918.3 | AV61: 2976.24 | AX61: 2316.5 | AZ61: 2511.15 | BB61: 136.7 | BD61: =SUM(BF61,BH61,BJ61,BL61,BN61) -> 0 | BP61: =SUM(BF61,BH61,BJ61)/BD61*100 -> #DIV/0! | BQ61: =SUM(BL61,BN61)/BD61*100 -> #DIV/0!
A62: BULACAN | B62: BALIWAG | C62: BULACAN, BALIWAG | D62: MBA | E62: 2nd | F62: 14.959281 | G62: 120.89952 | H62: =CONCATENATE(F62,",",G62) -> 14.959281,120.899518 | I62: Municipal / City Plan | J62: 653 A Series of 2018 | K62: 2017 - 2027 | L62: 2018 | M62: 2027 | O62: 4.April | P62: Ronaldo P. Roque, Jr. | R62: Diozelle A. Lazatin | S62: R3-2025-013045 | T62: 45762 | U62: 45762 | W62: 45763 | X62: 45768 | Y62: =IF( OR(ISBLANK(T62), ISBLANK(U62)), "", MAX(1, IF( NETWORKDAYS(T62, U62) <= 0, 1, NETWORKDAYS(T62, U62) - IF(T62 = U62, 0, 1) )) ) -> 1 | Z62: =IF( OR(ISBLANK(U62), ISBLANK(V62)), "", MAX(1, IF( NETWORKDAYS(U62, V62) <= 0, 1, NETWORKDAYS(U62, V62) - IF(U62 = V62, 0, 1) )) ) | AA62: =IF( OR(IF(V62<>"", V62, U62)="", W62=""), "", MAX(1, IF( NETWORKDAYS(IF(V62<>"", V62, U62), W62) <= 0, 1, NETWORKDAYS(IF(V62<>"", V62, U62), W62) - IF(IF(V62<>"", V62, U62)=W62, 0, 1) ) ) ) -> 1 | AB62: =IF( OR(ISBLANK(W62), ISBLANK(X62)), "", MAX(1, IF( NETWORKDAYS(W62, X62) <= 0, 1, NETWORKDAYS(W62, X62) - IF(W62 = X62, 0, 1) )) ) -> 3 | AC62: Received by Planning | AD62: 0.307 | AE62: 53804.82 | AF62: 100 | AG62: ISSWIMS SLF, Montalban, Rizal | AH62: Compliant | AI62: YES | AJ62: YES | AK62: YES | AL62: YES | AM62: YES | AN62: YES | AQ62: Hauler - JD 218 Trading and construction | AR62: 65563.26 | AT62: 32178.45 | AV62: 20475.41 | AX62: 7487.32 | AZ62: 5048.37 | BB62: 373.71 | BD62: =SUM(BF62,BH62,BJ62,BL62,BN62) -> 0 | BP62: =SUM(BF62,BH62,BJ62)/BD62*100 -> #DIV/0! | BQ62: =SUM(BL62,BN62)/BD62*100 -> #DIV/0!
A63: BULACAN | B63: BUSTOS | C63: BULACAN, BUSTOS | D63: MBA | E63: 2nd | F63: 14.953785 | G63: 120.91889 | H63: =CONCATENATE(F63,",",G63) -> 14.95378487,120.9188855 | I63: Municipal / City Plan | J63: 1325 s.2019 | K63: 2017 - 2027 | L63: 2019 | M63: 2027 | O63: 4.April | P63: Ronaldo P. Roque, Jr. | R63: Diozelle A. Lazatin | S63: R3-2025-013044 | T63: 45762 | U63: 45762 | W63: 45763 | X63: 45768 | Y63: =IF( OR(ISBLANK(T63), ISBLANK(U63)), "", MAX(1, IF( NETWORKDAYS(T63, U63) <= 0, 1, NETWORKDAYS(T63, U63) - IF(T63 = U63, 0, 1) )) ) -> 1 | Z63: =IF( OR(ISBLANK(U63), ISBLANK(V63)), "", MAX(1, IF( NETWORKDAYS(U63, V63) <= 0, 1, NETWORKDAYS(U63, V63) - IF(U63 = V63, 0, 1) )) ) | AA63: =IF( OR(IF(V63<>"", V63, U63)="", W63=""), "", MAX(1, IF( NETWORKDAYS(IF(V63<>"", V63, U63), W63) <= 0, 1, NETWORKDAYS(IF(V63<>"", V63, U63), W63) - IF(IF(V63<>"", V63, U63)=W63, 0, 1) ) ) ) -> 1 | AB63: =IF( OR(ISBLANK(W63), ISBLANK(X63)), "", MAX(1, IF( NETWORKDAYS(W63, X63) <= 0, 1, NETWORKDAYS(W63, X63) - IF(W63 = X63, 0, 1) )) ) -> 3 | AC63: Received by Planning | AD63: 0.097 | AE63: 7836.15 | AF63: 100 | AG63: ISWIMS SLF, Montalban, Rizal | AH63: Compliant | AI63: YES | AJ63: YES | AK63: YES | AL63: YES | AM63: NO | AN63: YES | AR63: 4520.83 | AT63: 1161.85 | AV63: 924.51 | AX63: 2013.13 | AZ63: 110.31 | BB63: 311.03 | BD63: =SUM(BF63,BH63,BJ63,BL63,BN63) -> 0 | BP63: =SUM(BF63,BH63,BJ63)/BD63*100 -> #DIV/0! | BQ63: =SUM(BL63,BN63)/BD63*100 -> #DIV/0!
A64: NUEVA ECIJA | B64: GEN. TINIO | C64: NUEVA ECIJA, GEN. TINIO | D64: MBA | E64: 4th | F64: 15.3499 | G64: 121.04583 | H64: =CONCATENATE(F64,",",G64) -> 15.3499,121.045834 | I64: Municipal / City Plan | J64: no.1247 series of 2019 | K64: 2016 - 2027 | L64: 2019 | M64: 2027 | O64: 4.April | P64: Christian Jem L. Buluran | Q64: Jan Emerson C. Gonzales | R64: Zosimo P. Suyat | S64: R3-2025-013062 | T64: 45758 | U64: 45763 | V64: 45768 | W64: 45768 | X64: 45769 | Y64: =IF( OR(ISBLANK(T64), ISBLANK(U64)), "", MAX(1, IF( NETWORKDAYS(T64, U64) <= 0, 1, NETWORKDAYS(T64, U64) - IF(T64 = U64, 0, 1) )) ) -> 3 | Z64: =IF( OR(ISBLANK(U64), ISBLANK(V64)), "", MAX(1, IF( NETWORKDAYS(U64, V64) <= 0, 1, NETWORKDAYS(U64, V64) - IF(U64 = V64, 0, 1) )) ) -> 3 | AA64: =IF( OR(IF(V64<>"", V64, U64)="", W64=""), "", MAX(1, IF( NETWORKDAYS(IF(V64<>"", V64, U64), W64) <= 0, 1, NETWORKDAYS(IF(V64<>"", V64, U64), W64) - IF(IF(V64<>"", V64, U64)=W64, 0, 1) ) ) ) -> 1 | AB64: =IF( OR(ISBLANK(W64), ISBLANK(X64)), "", MAX(1, IF( NETWORKDAYS(W64, X64) <= 0, 1, NETWORKDAYS(W64, X64) - IF(W64 = X64, 0, 1) )) ) -> 1 | AC64: Received by Planning | AD64: 0.318 | AE64: 18763.27 | AF64: 0.155 | AG64: LGU owned SLF | AH64: Compliant | AI64: YES | AJ64: YES | AK64: YES | AL64: YES | AM64: YES | AN64: YES | AR64: 19344.14 | AT64: 6383.57 | AV64: 5634.95 | AX64: 2487.66 | AZ64: 2586.31 | BB64: 2251.66 | BD64: =SUM(BF64,BH64,BJ64,BL64,BN64) -> 0 | BP64: =SUM(BF64,BH64,BJ64)/BD64*100 -> #DIV/0! | BQ64: =SUM(BL64,BN64)/BD64*100 -> #DIV/0!
A65: NUEVA ECIJA | B65: PEñARANDA | C65: NUEVA ECIJA, PEñARANDA | D65: MBA | E65: 4th | F65: 15.36518 | G65: 121.01418 | H65: =CONCATENATE(F65,",",G65) -> 15.36518,121.014179 | I65: Municipal / City Plan | J65: 1357, Series of 2019 | K65: 2017 - 2027 | L65: 2019 | M65: 2027 | O65: 4.April | P65: Christine Ann V. Ramos | Q65: Jan Emerson C. Gonzales | R65: Zosimo P. Suyat | S65: R3-2025-012451 | T65: 45757 | U65: 45759 | V65: 45762 | W65: 45762 | X65: 45768 | Y65: =IF( OR(ISBLANK(T65), ISBLANK(U65)), "", MAX(1, IF( NETWORKDAYS(T65, U65) <= 0, 1, NETWORKDAYS(T65, U65) - IF(T65 = U65, 0, 1) )) ) -> 1 | Z65: =IF( OR(ISBLANK(U65), ISBLANK(V65)), "", MAX(1, IF( NETWORKDAYS(U65, V65) <= 0, 1, NETWORKDAYS(U65, V65) - IF(U65 = V65, 0, 1) )) ) -> 1 | AA65: =IF( OR(IF(V65<>"", V65, U65)="", W65=""), "", MAX(1, IF( NETWORKDAYS(IF(V65<>"", V65, U65), W65) <= 0, 1, NETWORKDAYS(IF(V65<>"", V65, U65), W65) - IF(IF(V65<>"", V65, U65)=W65, 0, 1) ) ) ) -> 1 | AB65: =IF( OR(ISBLANK(W65), ISBLANK(X65)), "", MAX(1, IF( NETWORKDAYS(W65, X65) <= 0, 1, NETWORKDAYS(W65, X65) - IF(W65 = X65, 0, 1) )) ) -> 4 | AC65: Received by Planning | AD65: 0.34 | AE65: 12359.49 | AF65: 0.83 | AG65: Floridablanca Enviro Corp | AH65: Not Compliant | AI65: YES | AJ65: YES | AK65: YES | AL65: YES | AM65: NO | AN65: YES | AO65: NO | AR65: 12732.83 | AT65: 7339.2 | AV65: 1880.64 | AX65: 2317.37 | AZ65: 1129.4 | BB65: 66.21 | BD65: =SUM(BF65,BH65,BJ65,BL65,BN65) -> 0 | BP65: =SUM(BF65,BH65,BJ65)/BD65*100 -> #DIV/0! | BQ65: =SUM(BL65,BN65)/BD65*100 -> #DIV/0!
A66: PAMPANGA | B66: FLORIDABLANCA | C66: PAMPANGA, FLORIDABLANCA | D66: MBA | E66: 2nd | F66: 14.9745 | G66: 120.5281 | H66: =CONCATENATE(F66,",",G66) -> 14.9745,120.5281 | I66: Municipal / City Plan | J66: NSWMC NO. 684 A S 2018 | K66: 2018 - 2027 | L66: 2018 | M66: 2027 | O66: 4.April | P66: Elyza A. Evilla | R66: Yves Yshmael M. Balagtas | S66: R3-2025-013110 | T66: 45762 | U66: 45763 | W66: 45768 | X66: 45768 | Y66: =IF( OR(ISBLANK(T66), ISBLANK(U66)), "", MAX(1, IF( NETWORKDAYS(T66, U66) <= 0, 1, NETWORKDAYS(T66, U66) - IF(T66 = U66, 0, 1) )) ) -> 1 | Z66: =IF( OR(ISBLANK(U66), ISBLANK(V66)), "", MAX(1, IF( NETWORKDAYS(U66, V66) <= 0, 1, NETWORKDAYS(U66, V66) - IF(U66 = V66, 0, 1) )) ) | AA66: =IF( OR(IF(V66<>"", V66, U66)="", W66=""), "", MAX(1, IF( NETWORKDAYS(IF(V66<>"", V66, U66), W66) <= 0, 1, NETWORKDAYS(IF(V66<>"", V66, U66), W66) - IF(IF(V66<>"", V66, U66)=W66, 0, 1) ) ) ) -> 3 | AB66: =IF( OR(ISBLANK(W66), ISBLANK(X66)), "", MAX(1, IF( NETWORKDAYS(W66, X66) <= 0, 1, NETWORKDAYS(W66, X66) - IF(W66 = X66, 0, 1) )) ) -> 1 | AC66: Received by Planning | AD66: 0.387 | AE66: 56310.822 | AF66: 0.63 | AG66: Floridablanca Enviro Corp | AH66: Compliant | AI66: YES | AJ66: YES | AK66: YES | AL66: YES | AM66: YES | AN66: YES | AR66: 61478.31 | AT66: 21886.28 | AV66: 14631.84 | AX66: 14742.5 | AZ66: 8994.28 | BB66: 1223.42 | BD66: =SUM(BF66,BH66,BJ66,BL66,BN66) -> 0 | BP66: =SUM(BF66,BH66,BJ66)/BD66*100 -> #DIV/0! | BQ66: =SUM(BL66,BN66)/BD66*100 -> #DIV/0!
A67: PAMPANGA | B67: PORAC | C67: PAMPANGA, PORAC | D67: MBA | E67: 2nd | F67: 15.0732 | G67: 120.5406 | H67: =CONCATENATE(F67,",",G67) -> 15.0732,120.5406 | I67: Municipal / City Plan | J67: 787 A series of 2018 | K67: 2018 - 2027 | L67: 2018 | M67: 2027 | O67: 4.April | P67: Elyza A. Evilla | R67: Yves Yshmael M. Balagtas | S67: R3-2025-012410 | T67: 45758 | U67: 45758 | W67: 45768 | X67: 45768 | Y67: =IF( OR(ISBLANK(T67), ISBLANK(U67)), "", MAX(1, IF( NETWORKDAYS(T67, U67) <= 0, 1, NETWORKDAYS(T67, U67) - IF(T67 = U67, 0, 1) )) ) -> 1 | Z67: =IF( OR(ISBLANK(U67), ISBLANK(V67)), "", MAX(1, IF( NETWORKDAYS(U67, V67) <= 0, 1, NETWORKDAYS(U67, V67) - IF(U67 = V67, 0, 1) )) ) | AA67: =IF( OR(IF(V67<>"", V67, U67)="", W67=""), "", MAX(1, IF( NETWORKDAYS(IF(V67<>"", V67, U67), W67) <= 0, 1, NETWORKDAYS(IF(V67<>"", V67, U67), W67) - IF(IF(V67<>"", V67, U67)=W67, 0, 1) ) ) ) -> 6 | AB67: =IF( OR(ISBLANK(W67), ISBLANK(X67)), "", MAX(1, IF( NETWORKDAYS(W67, X67) <= 0, 1, NETWORKDAYS(W67, X67) - IF(W67 = X67, 0, 1) )) ) -> 1 | AC67: Received by Planning | AD67: 0.66 | AE67: 92895.66 | AF67: 100 | AG67: Eco Protect Management Corp. | AH67: =IF(AND(AI67 = "YES", AJ67 = "YES", AK67 = "YES", AL67 = "YES", AN67 = "YES"), "Compliant", "Not Compliant") -> Not Compliant | AI67: NO | AJ67: NO | AK67: NO | AL67: YES | AM67: N/A | AN67: YES | AO67: NO | AR67: 118734.13 | AT67: 59462.05 | AV67: 16622.78 | AX67: 15803.51 | AZ67: 26406.47 | BB67: 439.32 | BD67: =SUM(BF67,BH67,BJ67,BL67,BN67) -> 0 | BP67: =SUM(BF67,BH67,BJ67)/BD67*100 -> #DIV/0! | BQ67: =SUM(BL67,BN67)/BD67*100 -> #DIV/0!
A68: TARLAC | B68: RAMOS | C68: TARLAC, RAMOS | D68: OUTSIDE MBA | E68: 1st | F68: 15.665793 | G68: 120.63928 | H68: =CONCATENATE(F68,",",G68) -> 15.665793,120.6392786 | I68: Municipal / City Plan | J68: NSWMC RESO NO. 1419 SERIES OF 2021 | K68: 2020 - 2029 | L68: 2021 | M68: 2029 | O68: 4.April | P68: Jasper Kieht B. Pili | R68: Rod Ross S. De Jesus | S68: R3-2025-011429 | T68: 45750 | U68: 45753 | W68: 45754 | X68: 45757 | Y68: =IF( OR(ISBLANK(T68), ISBLANK(U68)), "", MAX(1, IF( NETWORKDAYS(T68, U68) <= 0, 1, NETWORKDAYS(T68, U68) - IF(T68 = U68, 0, 1) )) ) -> 1 | Z68: =IF( OR(ISBLANK(U68), ISBLANK(V68)), "", MAX(1, IF( NETWORKDAYS(U68, V68) <= 0, 1, NETWORKDAYS(U68, V68) - IF(U68 = V68, 0, 1) )) ) | AA68: =IF( OR(ISBLANK(U68), ISBLANK(W68)), "", MAX(1, IF( NETWORKDAYS(U68, W68) <= 0, 1, NETWORKDAYS(U68, W68) - IF(U68 = W68, 0, 1) )) ) -> 1 | AB68: =IF( OR(ISBLANK(W68), ISBLANK(X68)), "", MAX(1, IF( NETWORKDAYS(W68, X68) <= 0, 1, NETWORKDAYS(W68, X68) - IF(W68 = X68, 0, 1) )) ) -> 3 | AC68: Received by Planning | AD68: 0.23 | AE68: 5164.88 | AF68: 1 | AG68: Metro Waste Solid Waste Management | AH68: Compliant | AI68: YES | AJ68: YES | AK68: YES | AL68: YES | AN68: YES | AR68: 6047.06 | AT68: 1911.48 | AV68: 1700.43 | AX68: 1700.43 | AZ68: 143.92 | BB68: 590.8 | BD68: =SUM(BF68,BH68,BJ68,BL68,BN68) -> 0 | BP68: =SUM(BF68,BH68,BJ68)/BD68*100 -> #DIV/0! | BQ68: =SUM(BL68,BN68)/BD68*100 -> #DIV/0!
A69: ZAMBALES | B69: IBA | C69: ZAMBALES, IBA | D69: OUTSIDE MBA | E69: 2nd | F69: 15.327714 | G69: 119.97639 | H69: =CONCATENATE(F69,",",G69) -> 15.327714,119.976389 | I69: Municipal / City Plan | J69: NSWMC RESO NO. 1445 SERIES OF 2021 | K69: 2020 - 2029 | L69: 2021 | M69: 2029 | O69: 4.April | Q69: Ryan Christian R. Nunag | R69: Jun D. Guillermo | S69: R3-2025-010780 | T69: 45737 | U69: 45737 | V69: 45747 | W69: 45747 | X69: 45749 | Y69: =IF( OR(ISBLANK(T69), ISBLANK(U69)), "", MAX(1, IF( NETWORKDAYS(T69, U69) <= 0, 1, NETWORKDAYS(T69, U69) - IF(T69 = U69, 0, 1) )) ) -> 1 | Z69: =IF( OR(ISBLANK(U69), ISBLANK(V69)), "", MAX(1, IF( NETWORKDAYS(U69, V69) <= 0, 1, NETWORKDAYS(U69, V69) - IF(U69 = V69, 0, 1) )) ) -> 6 | AA69: =IF( OR(ISBLANK(U69), ISBLANK(W69)), "", MAX(1, IF( NETWORKDAYS(U69, W69) <= 0, 1, NETWORKDAYS(U69, W69) - IF(U69 = W69, 0, 1) )) ) -> 6 | AB69: =IF( OR(ISBLANK(W69), ISBLANK(X69)), "", MAX(1, IF( NETWORKDAYS(W69, X69) <= 0, 1, NETWORKDAYS(W69, X69) - IF(W69 = X69, 0, 1) )) ) -> 2 | AC69: Received by Planning | AD69: 0.501 | AE69: 27846.08 | AF69: 0.7498 | AG69: LGU SLF | AH69: Compliant | AI69: YES | AJ69: YES | AK69: YES | AL69: YES | AN69: YES | AR69: 27172.1 | AT69: 12298.09 | AV69: 6018.62 | AX69: 2059.65 | AZ69: 6303.93 | BB69: 491.82 | BD69: =SUM(BF69,BH69,BJ69,BL69,BN69) -> 0 | BP69: =SUM(BF69,BH69,BJ69)/BD69*100 -> #DIV/0! | BQ69: =SUM(BL69,BN69)/BD69*100 -> #DIV/0!
A70: BATAAN | B70: BAGAC | C70: BATAAN, BAGAC | D70: MBA | E70: 3rd | F70: 14.607148 | G70: 120.402 | H70: =CONCATENATE(F70,",",G70) -> 14.607148,120.401997 | I70: Municipal / City Plan | J70: 975 SERIES OF 2017 | K70: 2015 - 2024 | L70: 2017 | M70: 2024 | N70: For Renewal | O70: 5.May | P70: Laurence Radasa | R70: Christle D. David | S70: R3-2025-016785 | T70: 45790 | U70: 45796 | W70: 45796 | X70: 45797 | Y70: 4 | AA70: =IF( OR(IF(V70<>"", V70, U70)="", W70=""), "", MAX(1, IF( NETWORKDAYS(IF(V70<>"", V70, U70), W70) <= 0, 1, NETWORKDAYS(IF(V70<>"", V70, U70), W70) - IF(IF(V70<>"", V70, U70)=W70, 0, 1) ) ) ) -> 1 | AB70: =IF( OR(ISBLANK(W70), ISBLANK(X70)), "", MAX(1, IF( NETWORKDAYS(W70, X70) <= 0, 1, NETWORKDAYS(W70, X70) - IF(W70 = X70, 0, 1) )) ) -> 1 | AC70: Received by Planning | AD70: 0.752 | AE70: 26749.09 | AF70: 58.24 | AG70: Eco Protect Management Corporation and Floridablanca Enviro Corporation | AH70: =IF(AND(AI70 = "YES", AJ70 = "YES", AK70 = "YES", AL70 = "YES", AN70 = "YES"), "Compliant", "Not Compliant") -> Compliant | AI70: YES | AJ70: YES | AK70: YES | AL70: YES | AM70: YES | AN70: YES | AR70: 17195.44 | AT70: 9500.48 | AV70: 4553.35 | AX70: 1621.53 | AZ70: 1501.16 | BB70: 18.91 | BD70: =SUM(BF70,BH70,BJ70,BL70,BN70) -> 0 | BP70: =SUM(BF70,BH70,BJ70)/BD70*100 -> #DIV/0! | BQ70: =SUM(BL70,BN70)/BD70*100 -> #DIV/0!
A71: BATAAN | B71: MORONG | C71: BATAAN, MORONG | D71: MBA | E71: 3rd | F71: 14.678464 | G71: 120.2652 | H71: =CONCATENATE(F71,",",G71) -> 14.678464,120.265204 | I71: Municipal / City Plan | J71: NSWMC Res. No. 1083 Series 2017 | K71: 2017 - 2027 | L71: 2018 | M71: 2027 | O71: 5.May | P71: Laurence Radasa | R71: Christle D. David | S71: R3-2025-016823 | T71: 45793 | U71: 45796 | W71: 45796 | X71: 45797 | Y71: =IF( OR(ISBLANK(T71), ISBLANK(U71)), "", MAX(1, IF( NETWORKDAYS(T71, U71) <= 0, 1, NETWORKDAYS(T71, U71) - IF(T71 = U71, 0, 1) )) ) -> 1 | Z71: =IF( OR(ISBLANK(U71), ISBLANK(V71)), "", MAX(1, IF( NETWORKDAYS(U71, V71) <= 0, 1, NETWORKDAYS(U71, V71) - IF(U71 = V71, 0, 1) )) ) | AA71: =IF( OR(IF(V71<>"", V71, U71)="", W71=""), "", MAX(1, IF( NETWORKDAYS(IF(V71<>"", V71, U71), W71) <= 0, 1, NETWORKDAYS(IF(V71<>"", V71, U71), W71) - IF(IF(V71<>"", V71, U71)=W71, 0, 1) ) ) ) -> 1 | AB71: =IF( OR(ISBLANK(W71), ISBLANK(X71)), "", MAX(1, IF( NETWORKDAYS(W71, X71) <= 0, 1, NETWORKDAYS(W71, X71) - IF(W71 = X71, 0, 1) )) ) -> 1 | AC71: Received by Planning | AD71: 0.359 | AE71: 12879.79 | AF71: 81 | AG71: Eco Protect Management Corporation | AH71: Compliant | AI71: YES | AJ71: YES | AK71: YES | AM71: YES | AN71: YES | AR71: 17751.27 | AT71: 9949.59 | AV71: 2476.3 | AX71: 2119.5 | AZ71: 3149.08 | BB71: 56.8 | BD71: =SUM(BF71,BH71,BJ71,BL71,BN71) -> 0 | BP71: =SUM(BF71,BH71,BJ71)/BD71*100 -> #DIV/0! | BQ71: =SUM(BL71,BN71)/BD71*100 -> #DIV/0!
A72: BULACAN | B72: MARILAO | C72: BULACAN, MARILAO | D72: MBA | E72: 4th | F72: 14.774122 | G72: 120.95918 | H72: =CONCATENATE(F72,",",G72) -> 14.774122,120.959182 | I72: Municipal / City Plan | J72: No.1427 Series of 2020 | K72: 2019 - 2029 | L72: 2020 | M72: 2029 | N72: For Renewal | O72: 5.May | P72: James Wilson T. Pena | R72: Diozelle A. Lazatin | S72: R3-2025-016682 | T72: 45793 | U72: 45796 | W72: 45797 | X72: 45797 | Y72: =IF( OR(ISBLANK(T72), ISBLANK(U72)), "", MAX(1, IF( NETWORKDAYS(T72, U72) <= 0, 1, NETWORKDAYS(T72, U72) - IF(T72 = U72, 0, 1) )) ) -> 1 | Z72: =IF( OR(ISBLANK(U72), ISBLANK(V72)), "", MAX(1, IF( NETWORKDAYS(U72, V72) <= 0, 1, NETWORKDAYS(U72, V72) - IF(U72 = V72, 0, 1) )) ) | AA72: =IF( OR(IF(V72<>"", V72, U72)="", W72=""), "", MAX(1, IF( NETWORKDAYS(IF(V72<>"", V72, U72), W72) <= 0, 1, NETWORKDAYS(IF(V72<>"", V72, U72), W72) - IF(IF(V72<>"", V72, U72)=W72, 0, 1) ) ) ) -> 1 | AB72: =IF( OR(ISBLANK(W72), ISBLANK(X72)), "", MAX(1, IF( NETWORKDAYS(W72, X72) <= 0, 1, NETWORKDAYS(W72, X72) - IF(W72 = X72, 0, 1) )) ) -> 1 | AC72: Received by Planning | AD72: 0.3557 | AE72: 91843.79 | AF72: 77.44 | AG72: Eco Protect Management Corporation | AH72: Compliant | AI72: YES | AJ72: YES | AK72: YES | AL72: YES | AM72: YES | AN72: YES | AR72: 119060.33 | AT72: 52112.71 | AV72: 27991.08 | AX72: 26586.17 | AZ72: 12013.19 | BB72: 357.18 | BD72: =SUM(BF72,BH72,BJ72,BL72,BN72) -> 0 | BP72: =SUM(BF72,BH72,BJ72)/BD72*100 -> #DIV/0! | BQ72: =SUM(BL72,BN72)/BD72*100 -> #DIV/0!
A73: BULACAN | B73: MEYCAUAYAN | C73: BULACAN, MEYCAUAYAN | D73: MBA | E73: 4th | F73: 14.774921 | G73: 120.99868 | H73: =CONCATENATE(F73,",",G73) -> 14.774921,120.998685 | I73: Municipal / City Plan | J73: NSWMC RESO NO. 1326 SERIES OF 2019 | K73: 2018 -2028 | L73: 2019 | M73: 2028 | N73: For Renewal | O73: 5.May | P73: Ronaldo P. Roque, Jr. | R73: Diozelle A. Lazatin | S73: R3-2025-016522 | T73: 45793 | U73: 45796 | W73: 45797 | X73: 45797 | Y73: =IF( OR(ISBLANK(T73), ISBLANK(U73)), "", MAX(1, IF( NETWORKDAYS(T73, U73) <= 0, 1, NETWORKDAYS(T73, U73) - IF(T73 = U73, 0, 1) )) ) -> 1 | Z73: =IF( OR(ISBLANK(U73), ISBLANK(V73)), "", MAX(1, IF( NETWORKDAYS(U73, V73) <= 0, 1, NETWORKDAYS(U73, V73) - IF(U73 = V73, 0, 1) )) ) | AA73: =IF( OR(IF(V73<>"", V73, U73)="", W73=""), "", MAX(1, IF( NETWORKDAYS(IF(V73<>"", V73, U73), W73) <= 0, 1, NETWORKDAYS(IF(V73<>"", V73, U73), W73) - IF(IF(V73<>"", V73, U73)=W73, 0, 1) ) ) ) -> 1 | AB73: =IF( OR(ISBLANK(W73), ISBLANK(X73)), "", MAX(1, IF( NETWORKDAYS(W73, X73) <= 0, 1, NETWORKDAYS(W73, X73) - IF(W73 = X73, 0, 1) )) ) -> 1 | AC73: Received by Planning | AD73: 0.599 | AE73: 135178.13 | AF73: 70.77 | AG73: ISWIMS SLF, Montalban, Rizal | AH73: Compliant | AI73: YES | AJ73: YES | AK73: YES | AL73: YES | AM73: NO | AN73: YES | AO73: NO | AR73: 156879.74 | AT73: 54907.91 | AV73: 51817.38 | AX73: 4188.69 | AZ73: 43549.81 | BB73: 2415.95 | BD73: =SUM(BF73,BH73,BJ73,BL73,BN73) -> 0 | BP73: =SUM(BF73,BH73,BJ73)/BD73*100 -> #DIV/0! | BQ73: =SUM(BL73,BN73)/BD73*100 -> #DIV/0!
A74: NUEVA ECIJA | B74: PALAYAN CITY | C74: NUEVA ECIJA, PALAYAN CITY | D74: MBA | E74: 3rd | F74: 15.563497 | G74: 121.10041 | H74: =CONCATENATE(F74,",",G74) -> 15.563497,121.10041 | I74: Municipal / City Plan | J74: 1330 series of 2019 | K74: 2017 - 2027 | L74: 2019 | M74: 2027 | O74: 5.May | P74: Hosannah R. Sabio | Q74: Jaypee Ordoñez | R74: Zosimo P. Suyat | S74: R3-2025-016842 | T74: 45790 | U74: 45796 | V74: 45796 | W74: 45796 | X74: 45797 | Y74: =IF( OR(ISBLANK(T74), ISBLANK(U74)), "", MAX(1, IF( NETWORKDAYS(T74, U74) <= 0, 1, NETWORKDAYS(T74, U74) - IF(T74 = U74, 0, 1) )) ) -> 4 | Z74: =IF( OR(ISBLANK(U74), ISBLANK(V74)), "", MAX(1, IF( NETWORKDAYS(U74, V74) <= 0, 1, NETWORKDAYS(U74, V74) - IF(U74 = V74, 0, 1) )) ) -> 1 | AA74: =IF( OR(IF(V74<>"", V74, U74)="", W74=""), "", MAX(1, IF( NETWORKDAYS(IF(V74<>"", V74, U74), W74) <= 0, 1, NETWORKDAYS(IF(V74<>"", V74, U74), W74) - IF(IF(V74<>"", V74, U74)=W74, 0, 1) ) ) ) -> 1 | AB74: =IF( OR(ISBLANK(W74), ISBLANK(X74)), "", MAX(1, IF( NETWORKDAYS(W74, X74) <= 0, 1, NETWORKDAYS(W74, X74) - IF(W74 = X74, 0, 1) )) ) -> 1 | AC74: Received by Planning | AD74: 0.24 | AE74: 10661.52 | AF74: 67.82 | AG74: Metro Waste Solid Waste Management Sanitary Landfill | AH74: =IF(AND(AI74 = "YES", AJ74 = "YES", AK74 = "YES", AL74 = "YES", AN74 = "YES"), "Compliant", "Not Compliant") -> Compliant | AI74: YES | AJ74: YES | AK74: YES | AL74: YES | AM74: YES | AN74: YES | AR74: 10153.06 | AT74: 4497.81 | AV74: 2388 | AX74: 1728.05 | AZ74: 1224.46 | BB74: 314.74 | BD74: =SUM(BF74,BH74,BJ74,BL74,BN74) -> 0 | BP74: =SUM(BF74,BH74,BJ74)/BD74*100 -> #DIV/0! | BQ74: =SUM(BL74,BN74)/BD74*100 -> #DIV/0!
A75: NUEVA ECIJA | B75: CUYAPO | C75: NUEVA ECIJA, CUYAPO | D75: OUTSIDE MBA | E75: 1st | F75: 15.778768 | G75: 120.66395 | H75: =CONCATENATE(F75,",",G75) -> 15.778768,120.663947 | I75: Municipal / City Plan | J75: 500-A series of 2019 | K75: 2017 - 2027 | L75: 2019 | M75: 2027 | O75: 5.May | P75: Aser A. Inocencio, Jr. | Q75: Jaypee Ordoñez | R75: Zosimo P. Suyat | S75: R3-2025-016760 | T75: 45786 | U75: 45796 | V75: 45796 | W75: 45796 | X75: 45796 | Y75: =IF( OR(ISBLANK(T75), ISBLANK(U75)), "", MAX(1, IF( NETWORKDAYS(T75, U75) <= 0, 1, NETWORKDAYS(T75, U75) - IF(T75 = U75, 0, 1) )) ) -> 6 | Z75: =IF( OR(ISBLANK(U75), ISBLANK(V75)), "", MAX(1, IF( NETWORKDAYS(U75, V75) <= 0, 1, NETWORKDAYS(U75, V75) - IF(U75 = V75, 0, 1) )) ) -> 1 | AA75: =IF( OR(ISBLANK(U75), ISBLANK(W75)), "", MAX(1, IF( NETWORKDAYS(U75, W75) <= 0, 1, NETWORKDAYS(U75, W75) - IF(U75 = W75, 0, 1) )) ) -> 1 | AB75: =IF( OR(ISBLANK(W75), ISBLANK(X75)), "", MAX(1, IF( NETWORKDAYS(W75, X75) <= 0, 1, NETWORKDAYS(W75, X75) - IF(W75 = X75, 0, 1) )) ) -> 1 | AC75: Received by Planning | AD75: 0.24 | AE75: 47696.28 | AF75: 79.55 | AG75: Urdaneta Engineered Sanitary Landfill | AH75: =IF(AND(AI75 = "YES", AJ75 = "YES", AK75 = "YES", AL75 = "YES", AN75 = "YES"), "Compliant", "Not Compliant") -> Compliant | AI75: YES | AJ75: YES | AK75: YES | AL75: YES | AM75: YES | AN75: YES | AR75: 35283.79 | AT75: 18019.43 | AV75: 10048.82 | AX75: 3228.47 | AZ75: 3306.09 | BB75: 680.98 | BD75: =SUM(BF75,BH75,BJ75,BL75,BN75) -> 0 | BP75: =SUM(BF75,BH75,BJ75)/BD75*100 -> #DIV/0! | BQ75: =SUM(BL75,BN75)/BD75*100 -> #DIV/0!
A76: PAMPANGA | B76: MABALACAT | C76: PAMPANGA, MABALACAT | D76: MBA | E76: 1st | F76: 15.244213 | G76: 120.56472 | H76: =CONCATENATE(F76,",",G76) -> 15.244213,120.564715 | I76: Municipal / City Plan | J76: 147 | K76: 2014 - 2023 | L76: 2015 | M76: 2023 | N76: Approved | O76: 5.May | P76: Roger T. Encarnacion II | R76: Yves Yshmael M. Balagtas | S76: R3-2025-016981 | T76: 45793 | U76: 45797 | W76: 45797 | X76: 45797 | Y76: =IF( OR(ISBLANK(T76), ISBLANK(U76)), "", MAX(1, IF( NETWORKDAYS(T76, U76) <= 0, 1, NETWORKDAYS(T76, U76) - IF(T76 = U76, 0, 1) )) ) -> 2 | Z76: =IF( OR(ISBLANK(U76), ISBLANK(V76)), "", MAX(1, IF( NETWORKDAYS(U76, V76) <= 0, 1, NETWORKDAYS(U76, V76) - IF(U76 = V76, 0, 1) )) ) | AA76: =IF( OR(IF(V76<>"", V76, U76)="", W76=""), "", MAX(1, IF( NETWORKDAYS(IF(V76<>"", V76, U76), W76) <= 0, 1, NETWORKDAYS(IF(V76<>"", V76, U76), W76) - IF(IF(V76<>"", V76, U76)=W76, 0, 1) ) ) ) -> 1 | AB76: =IF( OR(ISBLANK(W76), ISBLANK(X76)), "", MAX(1, IF( NETWORKDAYS(W76, X76) <= 0, 1, NETWORKDAYS(W76, X76) - IF(W76 = X76, 0, 1) )) ) -> 1 | AC76: Received by Planning | AE76: 110165 | AF76: 0.7772 | AH76: =IF(AND(AI76 = "YES", AJ76 = "YES", AK76 = "YES", AL76 = "YES", AN76 = "YES"), "Compliant", "Not Compliant") -> Compliant | AI76: YES | AJ76: YES | AK76: YES | AL76: YES | AM76: YES | AN76: YES | AR76: 134608.01 | AT76: 85651.08 | AV76: 18966.27 | AX76: 15345.31 | AZ76: 14066.54 | BB76: 578.81 | BD76: =SUM(BF76,BH76,BJ76,BL76,BN76) -> 0 | BP76: =SUM(BF76,BH76,BJ76)/BD76*100 -> #DIV/0! | BQ76: =SUM(BL76,BN76)/BD76*100 -> #DIV/0!
A77: PAMPANGA | B77: MAGALANG | C77: PAMPANGA, MAGALANG | D77: MBA | E77: 1st | F77: 15.214281 | G77: 120.66215 | H77: =CONCATENATE(F77,",",G77) -> 15.214281,120.66215 | I77: Municipal / City Plan | J77: 1114s.2018 | K77: 2017 - 2026 | L77: 2018 | M77: 2026 | O77: 5.May | P77: Roger T. Encarnacion II | R77: Yves Yshmael M. Balagtas | S77: R3-2025-016741 | T77: 45793 | U77: 45796 | W77: 45796 | X77: 45797 | Y77: =IF( OR(ISBLANK(T77), ISBLANK(U77)), "", MAX(1, IF( NETWORKDAYS(T77, U77) <= 0, 1, NETWORKDAYS(T77, U77) - IF(T77 = U77, 0, 1) )) ) -> 1 | Z77: =IF( OR(ISBLANK(U77), ISBLANK(V77)), "", MAX(1, IF( NETWORKDAYS(U77, V77) <= 0, 1, NETWORKDAYS(U77, V77) - IF(U77 = V77, 0, 1) )) ) | AA77: =IF( OR(IF(V77<>"", V77, U77)="", W77=""), "", MAX(1, IF( NETWORKDAYS(IF(V77<>"", V77, U77), W77) <= 0, 1, NETWORKDAYS(IF(V77<>"", V77, U77), W77) - IF(IF(V77<>"", V77, U77)=W77, 0, 1) ) ) ) -> 1 | AB77: =IF( OR(ISBLANK(W77), ISBLANK(X77)), "", MAX(1, IF( NETWORKDAYS(W77, X77) <= 0, 1, NETWORKDAYS(W77, X77) - IF(W77 = X77, 0, 1) )) ) -> 1 | AC77: Received by Planning | AD77: 0.432 | AE77: 47321.74 | AF77: 100 | AG77: Floridablanca Enviro Corp. | AH77: =IF(AND(AI77 = "YES", AJ77 = "YES", AK77 = "YES", AL77 = "YES", AN77 = "YES"), "Compliant", "Not Compliant") -> Compliant | AI77: YES | AJ77: YES | AK77: YES | AL77: YES | AM77: YES | AN77: YES | AR77: 64759.76 | AT77: 40623.8 | AV77: 12097.12 | AX77: 7842.41 | AZ77: 3756.07 | BB77: 440.37 | BD77: =SUM(BF77,BH77,BJ77,BL77,BN77) -> 0 | BP77: =SUM(BF77,BH77,BJ77)/BD77*100 -> #DIV/0! | BQ77: =SUM(BL77,BN77)/BD77*100 -> #DIV/0!
A78: TARLAC | B78: SAN JOSE | C78: TARLAC, SAN JOSE | D78: OUTSIDE MBA | E78: 2nd | F78: 15.477382 | G78: 120.46389 | H78: =CONCATENATE(F78,",",G78) -> 15.477382,120.463888 | I78: Municipal / City Plan | J78: NSWMC RESO NO. 1299 SERIES OF 2019 | K78: 2018 -2027 | L78: 2019 | M78: 2027 | O78: 5.May | P78: Gretzhen M. Apolonio | R78: Rod Ross S. De Jesus | S78: R3-2025-016714 | T78: 45785 | U78: 45796 | W78: 45796 | X78: 45796 | Y78: =IF( OR(ISBLANK(T78), ISBLANK(U78)), "", MAX(1, IF( NETWORKDAYS(T78, U78) <= 0, 1, NETWORKDAYS(T78, U78) - IF(T78 = U78, 0, 1) )) ) -> 7 | Z78: =IF( OR(ISBLANK(U78), ISBLANK(V78)), "", MAX(1, IF( NETWORKDAYS(U78, V78) <= 0, 1, NETWORKDAYS(U78, V78) - IF(U78 = V78, 0, 1) )) ) | AA78: =IF( OR(ISBLANK(U78), ISBLANK(W78)), "", MAX(1, IF( NETWORKDAYS(U78, W78) <= 0, 1, NETWORKDAYS(U78, W78) - IF(U78 = W78, 0, 1) )) ) -> 1 | AB78: =IF( OR(ISBLANK(W78), ISBLANK(X78)), "", MAX(1, IF( NETWORKDAYS(W78, X78) <= 0, 1, NETWORKDAYS(W78, X78) - IF(W78 = X78, 0, 1) )) ) -> 1 | AC78: Received by Planning | AD78: 0.3 | AE78: 11575.2 | AF78: 100 | AG78: International Solid Waste Integrated Management Specialist Inc. (ISWIMS INC.) | AH78: =IF(AND(AI78 = "YES", AJ78 = "YES", AK78 = "YES", AL78 = "YES", AN78 = "YES"), "Compliant", "Not Compliant") -> Compliant | AI78: YES | AJ78: YES | AK78: YES | AL78: YES | AM78: YES | AN78: YES | AR78: 15969.9 | AT78: 13315.71 | AV78: 1062 | AX78: 715.45 | AZ78: 745.79 | BB78: 130.95 | BD78: =SUM(BF78,BH78,BJ78,BL78,BN78) -> 0 | BP78: =SUM(BF78,BH78,BJ78)/BD78*100 -> #DIV/0! | BQ78: =SUM(BL78,BN78)/BD78*100 -> #DIV/0!
A79: ZAMBALES | B79: STA CRUZ | C79: ZAMBALES, STA CRUZ | D79: OUTSIDE MBA | E79: 2nd | F79: 15.762053 | G79: 119.90908 | H79: =CONCATENATE(F79,",",G79) -> 15.762053,119.909081 | I79: Municipal / City Plan | J79: NSWMC Resolution No. 1596, Series of 2023 | K79: 2022 - 2031 | L79: 2023 | M79: 2031 | O79: 5.May | P79: Ryan Ace R. Angel | Q79: Ryan Christian R. Nunag | R79: Jun D. Guillermo | S79: R3-2025-016953 | T79: 45793 | U79: 45797 | V79: 45797 | W79: 45797 | X79: 45797 | Y79: =IF( OR(ISBLANK(T79), ISBLANK(U79)), "", MAX(1, IF( NETWORKDAYS(T79, U79) <= 0, 1, NETWORKDAYS(T79, U79) - IF(T79 = U79, 0, 1) )) ) -> 2 | Z79: =IF( OR(ISBLANK(U79), ISBLANK(V79)), "", MAX(1, IF( NETWORKDAYS(U79, V79) <= 0, 1, NETWORKDAYS(U79, V79) - IF(U79 = V79, 0, 1) )) ) -> 1 | AA79: =IF( OR(ISBLANK(U79), ISBLANK(W79)), "", MAX(1, IF( NETWORKDAYS(U79, W79) <= 0, 1, NETWORKDAYS(U79, W79) - IF(U79 = W79, 0, 1) )) ) -> 1 | AB79: =IF( OR(ISBLANK(W79), ISBLANK(X79)), "", MAX(1, IF( NETWORKDAYS(W79, X79) <= 0, 1, NETWORKDAYS(W79, X79) - IF(W79 = X79, 0, 1) )) ) -> 1 | AC79: Received by Planning | AD79: 0.561 | AE79: 35813.68 | AF79: 89.78 | AG79: Greentech Total Environmental Solutions Incorporated | AH79: =IF(AND(AI79 = "YES", AJ79 = "YES", AK79 = "YES", AL79 = "YES", AN79 = "YES"), "Compliant", "Not Compliant") -> Compliant | AI79: YES | AJ79: YES | AK79: YES | AL79: YES | AN79: YES | AR79: 43230.55 | AT79: 14374.16 | AV79: 17668.33 | AX79: 6769.9 | AZ79: 4011.8 | BB79: 406.37 | BD79: =SUM(BF79,BH79,BJ79,BL79,BN79) -> 0 | BP79: =SUM(BF79,BH79,BJ79)/BD79*100 -> #DIV/0! | BQ79: =SUM(BL79,BN79)/BD79*100 -> #DIV/0!
A80: AURORA | B80: CASIGURAN | C80: AURORA, CASIGURAN | D80: OUTSIDE MBA | E80: Lone | F80: 16.277169 | G80: 122.12314 | H80: =CONCATENATE(F80,",",G80) -> 16.277169,122.123139 | I80: Municipal / City Plan | J80: 1289 | K80: 2017 - 2027 | L80: 2019 | M80: 2027 | O80: 6.June | P80: Queenyvel Laguisma | R80: Ryan Christian R. Nunag | S80: R3-2025-020337 | T80: 45819 | U80: 45827 | W80: 45827 | X80: 45827 | Y80: =IF( OR(ISBLANK(T80), ISBLANK(U80)), "", MAX(1, IF( NETWORKDAYS(T80, U80) <= 0, 1, NETWORKDAYS(T80, U80) - IF(T80 = U80, 0, 1) )) ) -> 6 | Z80: =IF( OR(ISBLANK(U80), ISBLANK(V80)), "", MAX(1, IF( NETWORKDAYS(U80, V80) <= 0, 1, NETWORKDAYS(U80, V80) - IF(U80 = V80, 0, 1) )) ) | AA80: =IF( OR(IF(V80<>"", V80, U80)="", W80=""), "", MAX(1, IF( NETWORKDAYS(IF(V80<>"", V80, U80), W80) <= 0, 1, NETWORKDAYS(IF(V80<>"", V80, U80), W80) - IF(IF(V80<>"", V80, U80)=W80, 0, 1) ) ) ) -> 1 | AB80: =IF( OR(ISBLANK(W80), ISBLANK(X80)), "", MAX(1, IF( NETWORKDAYS(W80, X80) <= 0, 1, NETWORKDAYS(W80, X80) - IF(W80 = X80, 0, 1) )) ) -> 1 | AC80: Received by Planning | AD80: 0.266 | AE80: 7721.714 | AF80: 0.9413 | AG80: Floridablanca Enviro Corporation | AH80: =IF(AND(AI80 = "YES", AJ80 = "YES", AK80 = "YES", AL80 = "YES", AN80 = "YES"), "Compliant", "Not Compliant") -> Compliant | AI80: YES | AJ80: YES | AK80: YES | AL80: YES | AM80: N/A | AN80: YES | AR80: 9229.78 | AT80: 4773.64 | AV80: 2514.19 | AX80: 1400.16 | AZ80: 467.95 | BB80: 73.84 | BD80: =SUM(BF80,BH80,BJ80,BL80,BN80) -> 0 | BP80: =SUM(BF80,BH80,BJ80)/BD80*100 -> #DIV/0! | BQ80: =SUM(BL80,BN80)/BD80*100 -> #DIV/0!
A81: BATAAN | B81: MARIVELES | C81: BATAAN, MARIVELES | D81: MBA | E81: 3rd | F81: 14.435804 | G81: 120.49021 | H81: =CONCATENATE(F81,",",G81) -> 14.435804,120.490214 | I81: Municipal / City Plan | J81: 483 SERIES 2016 | K81: 2016 - 2025 | L81: 2016 | M81: 2025 | N81: For Renewal | O81: 6.June | P81: Laurence Radasa | R81: Christle D. David | S81: R3-2025-019721 | T81: 45821 | U81: 45824 | W81: 45824 | X81: 45825 | Y81: =IF( OR(ISBLANK(T81), ISBLANK(U81)), "", MAX(1, IF( NETWORKDAYS(T81, U81) <= 0, 1, NETWORKDAYS(T81, U81) - IF(T81 = U81, 0, 1) )) ) -> 1 | Z81: =IF( OR(ISBLANK(U81), ISBLANK(V81)), "", MAX(1, IF( NETWORKDAYS(U81, V81) <= 0, 1, NETWORKDAYS(U81, V81) - IF(U81 = V81, 0, 1) )) ) | AA81: =IF( OR(IF(V81<>"", V81, U81)="", W81=""), "", MAX(1, IF( NETWORKDAYS(IF(V81<>"", V81, U81), W81) <= 0, 1, NETWORKDAYS(IF(V81<>"", V81, U81), W81) - IF(IF(V81<>"", V81, U81)=W81, 0, 1) ) ) ) -> 1 | AB81: =IF( OR(ISBLANK(W81), ISBLANK(X81)), "", MAX(1, IF( NETWORKDAYS(W81, X81) <= 0, 1, NETWORKDAYS(W81, X81) - IF(W81 = X81, 0, 1) )) ) -> 1 | AC81: Received by Planning | AD81: 0.201 | AE81: 37352.96 | AF81: 0.9147 | AG81: Floridablanca Enviro Corporation | AH81: =IF(AND(AI81 = "YES", AJ81 = "YES", AK81 = "YES", AL81 = "YES", AN81 = "YES"), "Compliant", "Not Compliant") -> Compliant | AI81: YES | AJ81: YES | AK81: YES | AL81: YES | AM81: YES | AN81: YES | AR81: 41681.19 | AT81: 8982.3 | AV81: 6260.51 | AX81: 22882.97 | AZ81: 2075.72 | BB81: 1479.68 | BD81: =SUM(BF81,BH81,BJ81,BL81,BN81) -> 0 | BP81: =SUM(BF81,BH81,BJ81)/BD81*100 -> #DIV/0! | BQ81: =SUM(BL81,BN81)/BD81*100 -> #DIV/0!
A82: BULACAN | B82: GUIGUINTO | C82: BULACAN, GUIGUINTO | D82: MBA | E82: 5th | F82: 14.827419 | G82: 120.87897 | H82: =CONCATENATE(F82,",",G82) -> 14.8274194,120.87897 | I82: Municipal / City Plan | J82: 1080 series of 2018 | K82: 2017 - 2027 | L82: 2018 | M82: 2027 | O82: 6.June | P82: Jasmin Marie N. Siapco | R82: Diozelle A. Lazatin | S82: R3-2025-019680 | T82: 45821 | U82: 45824 | W82: 45827 | X82: 45827 | Y82: =IF( OR(ISBLANK(T82), ISBLANK(U82)), "", MAX(1, IF( NETWORKDAYS(T82, U82) <= 0, 1, NETWORKDAYS(T82, U82) - IF(T82 = U82, 0, 1) )) ) -> 1 | Z82: =IF( OR(ISBLANK(U82), ISBLANK(V82)), "", MAX(1, IF( NETWORKDAYS(U82, V82) <= 0, 1, NETWORKDAYS(U82, V82) - IF(U82 = V82, 0, 1) )) ) | AA82: =IF( OR(IF(V82<>"", V82, U82)="", W82=""), "", MAX(1, IF( NETWORKDAYS(IF(V82<>"", V82, U82), W82) <= 0, 1, NETWORKDAYS(IF(V82<>"", V82, U82), W82) - IF(IF(V82<>"", V82, U82)=W82, 0, 1) ) ) ) -> 3 | AB82: =IF( OR(ISBLANK(W82), ISBLANK(X82)), "", MAX(1, IF( NETWORKDAYS(W82, X82) <= 0, 1, NETWORKDAYS(W82, X82) - IF(W82 = X82, 0, 1) )) ) -> 1 | AC82: Received by Planning | AD82: 0.277 | AE82: 27524.99 | AG82: ISWIMS SLF, Montalban, Rizal | AH82: Compliant | AI82: YES | AJ82: YES | AK82: YES | AL82: YES | AM82: NO | AN82: YES | AR82: 122054.12 | AT82: 52666.35 | AV82: 35346.87 | AX82: 20248.78 | AZ82: 11460.88 | BB82: 2331.23 | BD82: =SUM(BF82,BH82,BJ82,BL82,BN82) -> 0 | BP82: =SUM(BF82,BH82,BJ82)/BD82*100 -> #DIV/0! | BQ82: =SUM(BL82,BN82)/BD82*100 -> #DIV/0!
A83: BULACAN | B83: PLARIDEL | C83: BULACAN, PLARIDEL | D83: MBA | E83: 2nd | F83: 14.886807 | G83: 120.85987 | H83: =CONCATENATE(F83,",",G83) -> 14.88680651,120.8598685 | I83: Municipal / City Plan | J83: 157 Series of 2015 | K83: 2015 - 2024 | L83: 2015 | M83: 2024 | N83: For Renewal | O83: 6.June | P83: Jasmin Marie N. Siapco | R83: Diozelle A. Lazatin | S83: R3-2025-020040 | T83: 45825 | U83: 45825 | W83: 45827 | X83: 45827 | Y83: =IF( OR(ISBLANK(T83), ISBLANK(U83)), "", MAX(1, IF( NETWORKDAYS(T83, U83) <= 0, 1, NETWORKDAYS(T83, U83) - IF(T83 = U83, 0, 1) )) ) -> 1 | Z83: =IF( OR(ISBLANK(U83), ISBLANK(V83)), "", MAX(1, IF( NETWORKDAYS(U83, V83) <= 0, 1, NETWORKDAYS(U83, V83) - IF(U83 = V83, 0, 1) )) ) | AA83: =IF( OR(IF(V83<>"", V83, U83)="", W83=""), "", MAX(1, IF( NETWORKDAYS(IF(V83<>"", V83, U83), W83) <= 0, 1, NETWORKDAYS(IF(V83<>"", V83, U83), W83) - IF(IF(V83<>"", V83, U83)=W83, 0, 1) ) ) ) -> 2 | AB83: =IF( OR(ISBLANK(W83), ISBLANK(X83)), "", MAX(1, IF( NETWORKDAYS(W83, X83) <= 0, 1, NETWORKDAYS(W83, X83) - IF(W83 = X83, 0, 1) )) ) -> 1 | AC83: Received by Planning | AD83: 0.315 | AE83: 42534.59 | AG83: Eco Protect Management Corporation | AH83: Compliant | AI83: YES | AJ83: YES | AK83: YES | AL83: YES | AM83: NO | AN83: YES | AR83: 114747.34 | AT83: 61894.71 | AV83: 27275.44 | AX83: 5243.95 | AZ83: 15835.13 | BB83: 4498.1 | BD83: =SUM(BF83,BH83,BJ83,BL83,BN83) -> 0 | BP83: =SUM(BF83,BH83,BJ83)/BD83*100 -> #DIV/0! | BQ83: =SUM(BL83,BN83)/BD83*100 -> #DIV/0!
A84: BULACAN | B84: PULILAN | C84: BULACAN, PULILAN | D84: MBA | E84: 1st | F84: 14.901106 | G84: 120.84865 | H84: =CONCATENATE(F84,",",G84) -> 14.90110634,120.8486538 | I84: Municipal / City Plan | J84: 1142 Series of 2018 | K84: 2017 - 2027 | L84: 2018 | M84: 2027 | O84: 6.June | P84: Jasmin Marie N. Siapco | R84: Diozelle A. Lazatin | S84: R3-2025-019679 | T84: 45818 | U84: 45823 | W84: 45827 | X84: 45827 | Y84: =IF( OR(ISBLANK(T84), ISBLANK(U84)), "", MAX(1, IF( NETWORKDAYS(T84, U84) <= 0, 1, NETWORKDAYS(T84, U84) - IF(T84 = U84, 0, 1) )) ) -> 3 | Z84: =IF( OR(ISBLANK(U84), ISBLANK(V84)), "", MAX(1, IF( NETWORKDAYS(U84, V84) <= 0, 1, NETWORKDAYS(U84, V84) - IF(U84 = V84, 0, 1) )) ) | AA84: =IF( OR(IF(V84<>"", V84, U84)="", W84=""), "", MAX(1, IF( NETWORKDAYS(IF(V84<>"", V84, U84), W84) <= 0, 1, NETWORKDAYS(IF(V84<>"", V84, U84), W84) - IF(IF(V84<>"", V84, U84)=W84, 0, 1) ) ) ) -> 3 | AB84: =IF( OR(ISBLANK(W84), ISBLANK(X84)), "", MAX(1, IF( NETWORKDAYS(W84, X84) <= 0, 1, NETWORKDAYS(W84, X84) - IF(W84 = X84, 0, 1) )) ) -> 1 | AC84: Received by Planning | AD84: 0.67 | AE84: 18503.84 | AG84: Eco Protect Management Corporation | AH84: Compliant | AI84: YES | AJ84: YES | AK84: YES | AL84: YES | AM84: YES | AN84: YES | AR84: 22816.31 | AT84: 9957.04 | AV84: 7721.04 | AX84: 1651.9 | AZ84: 3290.11 | BB84: 196.22 | BD84: =SUM(BF84,BH84,BJ84,BL84,BN84) -> 0 | BP84: =SUM(BF84,BH84,BJ84)/BD84*100 -> #DIV/0! | BQ84: =SUM(BL84,BN84)/BD84*100 -> #DIV/0!
A85: NUEVA ECIJA | B85: LLANERA | C85: NUEVA ECIJA, LLANERA | D85: MBA | E85: 2nd | F85: 15.662212 | G85: 121.01904 | H85: =CONCATENATE(F85,",",G85) -> 15.662212,121.01904 | I85: Municipal / City Plan | J85: No. 1411 Series of 2020 | K85: 2017 - 2026 | L85: 2020 | M85: 2026 | O85: 6.June | P85: Hosannah R. Sabio | R85: Zosimo P. Suyat | S85: R3-2025-020168 | T85: 45825 | U85: 45826 | W85: 45826 | X85: 45826 | Y85: =IF( OR(ISBLANK(T85), ISBLANK(U85)), "", MAX(1, IF( NETWORKDAYS(T85, U85) <= 0, 1, NETWORKDAYS(T85, U85) - IF(T85 = U85, 0, 1) )) ) -> 1 | Z85: =IF( OR(ISBLANK(U85), ISBLANK(V85)), "", MAX(1, IF( NETWORKDAYS(U85, V85) <= 0, 1, NETWORKDAYS(U85, V85) - IF(U85 = V85, 0, 1) )) ) | AA85: =IF( OR(IF(V85<>"", V85, U85)="", W85=""), "", MAX(1, IF( NETWORKDAYS(IF(V85<>"", V85, U85), W85) <= 0, 1, NETWORKDAYS(IF(V85<>"", V85, U85), W85) - IF(IF(V85<>"", V85, U85)=W85, 0, 1) ) ) ) -> 1 | AB85: =IF( OR(ISBLANK(W85), ISBLANK(X85)), "", MAX(1, IF( NETWORKDAYS(W85, X85) <= 0, 1, NETWORKDAYS(W85, X85) - IF(W85 = X85, 0, 1) )) ) -> 1 | AC85: Received by Planning | AD85: 0.472 | AE85: 10785.54 | AF85: 85.91 | AG85: Prime Waste Solutions | AH85: =IF(AND(AI85 = "YES", AJ85 = "YES", AK85 = "YES", AL85 = "YES", AN85 = "YES"), "Compliant", "Not Compliant") -> Compliant | AI85: YES | AJ85: YES | AK85: YES | AL85: YES | AM85: YES | AN85: YES | AR85: 21398.43 | AT85: 11786.26 | AV85: 3945.87 | AX85: 2651.27 | AZ85: 2914.47 | BB85: 100.57 | BD85: =SUM(BF85,BH85,BJ85,BL85,BN85) -> 0 | BP85: =SUM(BF85,BH85,BJ85)/BD85*100 -> #DIV/0! | BQ85: =SUM(BL85,BN85)/BD85*100 -> #DIV/0!
A86: NUEVA ECIJA | B86: PANTABANGAN | C86: NUEVA ECIJA, PANTABANGAN | D86: MBA | E86: 2nd | F86: 15.808002 | G86: 121.14324 | H86: =CONCATENATE(F86,",",G86) -> 15.808002,121.143238 | I86: Municipal / City Plan | J86: 1331 Series of 2019 | K86: 2018 -2028 | L86: 2019 | M86: 2028 | O86: 6.June | P86: Hosannah R. Sabio | Q86: Jaypee Ordoñez | R86: Zosimo P. Suyat | S86: R3-2025-020211 | T86: 45807 | U86: 45826 | V86: 45826 | W86: 45826 | X86: 45827 | Y86: =IF( OR(ISBLANK(T86), ISBLANK(U86)), "", MAX(1, IF( NETWORKDAYS(T86, U86) <= 0, 1, NETWORKDAYS(T86, U86) - IF(T86 = U86, 0, 1) )) ) -> 13 | Z86: =IF( OR(ISBLANK(U86), ISBLANK(V86)), "", MAX(1, IF( NETWORKDAYS(U86, V86) <= 0, 1, NETWORKDAYS(U86, V86) - IF(U86 = V86, 0, 1) )) ) -> 1 | AA86: =IF( OR(IF(V86<>"", V86, U86)="", W86=""), "", MAX(1, IF( NETWORKDAYS(IF(V86<>"", V86, U86), W86) <= 0, 1, NETWORKDAYS(IF(V86<>"", V86, U86), W86) - IF(IF(V86<>"", V86, U86)=W86, 0, 1) ) ) ) -> 1 | AB86: =IF( OR(ISBLANK(W86), ISBLANK(X86)), "", MAX(1, IF( NETWORKDAYS(W86, X86) <= 0, 1, NETWORKDAYS(W86, X86) - IF(W86 = X86, 0, 1) )) ) -> 1 | AC86: Received by Planning | AD86: 0.26 | AE86: 8258.38 | AF86: 87.05 | AG86: Urdaneta Engineered Sanitary Landfill/Metro Waste Solid Waste Management | AH86: =IF(AND(AI86 = "YES", AJ86 = "YES", AK86 = "YES", AL86 = "YES", AN86 = "YES"), "Compliant", "Not Compliant") -> Compliant | AI86: YES | AJ86: YES | AK86: YES | AL86: YES | AM86: YES | AN86: YES | AR86: 9304.65 | AT86: 5220.84 | AV86: 2110.29 | AX86: 768.56 | AZ86: 1199.37 | BB86: 5.58 | BD86: =SUM(BF86,BH86,BJ86,BL86,BN86) -> 0 | BP86: =SUM(BF86,BH86,BJ86)/BD86*100 -> #DIV/0! | BQ86: =SUM(BL86,BN86)/BD86*100 -> #DIV/0!
A87: NUEVA ECIJA | B87: SAN JOSE CITY | C87: NUEVA ECIJA, SAN JOSE CITY | D87: MBA | E87: 2nd | F87: 15.792271 | G87: 120.98886 | H87: =CONCATENATE(F87,",",G87) -> 15.792271,120.988859 | I87: Municipal / City Plan | J87: 129 | K87: 2014 - 2023 | L87: 2015 | M87: 2023 | N87: For Renewal | O87: 6.June | P87: Hosannah R. Sabio | Q87: Jaypee Ordoñez | R87: Zosimo P. Suyat | S87: R3-2025-020239 | T87: 45826 | U87: 45826 | V87: 45826 | W87: 45826 | X87: 45827 | Y87: =IF( OR(ISBLANK(T87), ISBLANK(U87)), "", MAX(1, IF( NETWORKDAYS(T87, U87) <= 0, 1, NETWORKDAYS(T87, U87) - IF(T87 = U87, 0, 1) )) ) -> 1 | Z87: =IF( OR(ISBLANK(U87), ISBLANK(V87)), "", MAX(1, IF( NETWORKDAYS(U87, V87) <= 0, 1, NETWORKDAYS(U87, V87) - IF(U87 = V87, 0, 1) )) ) -> 1 | AA87: =IF( OR(IF(V87<>"", V87, U87)="", W87=""), "", MAX(1, IF( NETWORKDAYS(IF(V87<>"", V87, U87), W87) <= 0, 1, NETWORKDAYS(IF(V87<>"", V87, U87), W87) - IF(IF(V87<>"", V87, U87)=W87, 0, 1) ) ) ) -> 1 | AB87: =IF( OR(ISBLANK(W87), ISBLANK(X87)), "", MAX(1, IF( NETWORKDAYS(W87, X87) <= 0, 1, NETWORKDAYS(W87, X87) - IF(W87 = X87, 0, 1) )) ) -> 1 | AC87: Received by Planning | AD87: 0.367 | AE87: 55, 325.98 | AF87: 91.3 | AG87: Metro Waste Solid Waste Management Corporation | AH87: =IF(AND(AI87 = "YES", AJ87 = "YES", AK87 = "YES", AL87 = "YES", AN87 = "YES"), "Compliant", "Not Compliant") -> Compliant | AI87: YES | AJ87: YES | AK87: YES | AL87: YES | AM87: YES | AN87: YES | AR87: 64914.44 | AT87: 37780.2 | AV87: 12658.32 | AX87: 8828.36 | AZ87: 4855.6 | BB87: 791.96 | BD87: =SUM(BF87,BH87,BJ87,BL87,BN87) -> 0 | BP87: =SUM(BF87,BH87,BJ87)/BD87*100 -> #DIV/0! | BQ87: =SUM(BL87,BN87)/BD87*100 -> #DIV/0!
A88: PAMPANGA | B88: APALIT | C88: PAMPANGA, APALIT | D88: MBA | E88: 4th | F88: 14.9536 | G88: 120.7685 | H88: =CONCATENATE(F88,",",G88) -> 14.9536,120.7685 | I88: Municipal / City Plan | J88: 1241 | K88: 2017 - 2027 | L88: 2019 | M88: 2027 | O88: 6.June | P88: Glaiza S.Gaza | Q88: Jan Emerson C. Gonzales | R88: Yves Yshmael M. Balagtas | S88: R3-2025-019924 | T88: 45821 | U88: 45824 | V88: 45827 | W88: 45827 | X88: 45827 | Y88: =IF( OR(ISBLANK(T88), ISBLANK(U88)), "", MAX(1, IF( NETWORKDAYS(T88, U88) <= 0, 1, NETWORKDAYS(T88, U88) - IF(T88 = U88, 0, 1) )) ) -> 1 | Z88: =IF( OR(ISBLANK(U88), ISBLANK(V88)), "", MAX(1, IF( NETWORKDAYS(U88, V88) <= 0, 1, NETWORKDAYS(U88, V88) - IF(U88 = V88, 0, 1) )) ) -> 3 | AA88: =IF( OR(IF(V88<>"", V88, U88)="", W88=""), "", MAX(1, IF( NETWORKDAYS(IF(V88<>"", V88, U88), W88) <= 0, 1, NETWORKDAYS(IF(V88<>"", V88, U88), W88) - IF(IF(V88<>"", V88, U88)=W88, 0, 1) ) ) ) -> 1 | AB88: =IF( OR(ISBLANK(W88), ISBLANK(X88)), "", MAX(1, IF( NETWORKDAYS(W88, X88) <= 0, 1, NETWORKDAYS(W88, X88) - IF(W88 = X88, 0, 1) )) ) -> 1 | AC88: Received by Planning | AD88: 0.201 | AE88: 23549 | AF88: 79.45 | AG88: Prime Waste Solutions | AH88: =IF(AND(AI88 = "YES", AJ88 = "YES", AK88 = "YES", AL88 = "YES", AN88 = "YES"), "Compliant", "Not Compliant") -> Not Compliant | AI88: NO | AJ88: NO | AK88: NO | AL88: YES | AM88: YES | AN88: NO | AO88: NO | AR88: 27600.22 | AT88: 16524.25 | AV88: 5404.12 | AX88: 2318.42 | AZ88: 2735.18 | BB88: 618.24 | BD88: =SUM(BF88,BH88,BJ88,BL88,BN88) -> 0 | BP88: =SUM(BF88,BH88,BJ88)/BD88*100 -> #DIV/0! | BQ88: =SUM(BL88,BN88)/BD88*100 -> #DIV/0!
A89: PAMPANGA | B89: MASANTOL | C89: PAMPANGA, MASANTOL | D89: MBA | E89: 4th | F89: 14.8925 | G89: 120.7053 | H89: =CONCATENATE(F89,",",G89) -> 14.8925,120.7053 | I89: Municipal / City Plan | J89: 1028-A series of 2019 | K89: 2014 - 2024 | L89: 2019 | M89: 2024 | N89: For Renewal | O89: 6.June | P89: Glaiza S.Gaza | Q89: Jan Emerson C. Gonzales | R89: Yves Yshmael M. Balagtas | S89: R3-2025-019923 | T89: 45818 | U89: 45824 | V89: 45826 | W89: 45827 | X89: 45827 | Y89: =IF( OR(ISBLANK(T89), ISBLANK(U89)), "", MAX(1, IF( NETWORKDAYS(T89, U89) <= 0, 1, NETWORKDAYS(T89, U89) - IF(T89 = U89, 0, 1) )) ) -> 4 | Z89: =IF( OR(ISBLANK(U89), ISBLANK(V89)), "", MAX(1, IF( NETWORKDAYS(U89, V89) <= 0, 1, NETWORKDAYS(U89, V89) - IF(U89 = V89, 0, 1) )) ) -> 2 | AA89: =IF( OR(IF(V89<>"", V89, U89)="", W89=""), "", MAX(1, IF( NETWORKDAYS(IF(V89<>"", V89, U89), W89) <= 0, 1, NETWORKDAYS(IF(V89<>"", V89, U89), W89) - IF(IF(V89<>"", V89, U89)=W89, 0, 1) ) ) ) -> 1 | AB89: =IF( OR(ISBLANK(W89), ISBLANK(X89)), "", MAX(1, IF( NETWORKDAYS(W89, X89) <= 0, 1, NETWORKDAYS(W89, X89) - IF(W89 = X89, 0, 1) )) ) -> 1 | AC89: Received by Planning | AD89: 0.524 | AE89: 30966.67 | AF89: 69.05 | AG89: Floridablanca Enviro Corp | AH89: =IF(AND(AI89 = "YES", AJ89 = "YES", AK89 = "YES", AL89 = "YES", AN89 = "YES"), "Compliant", "Not Compliant") -> Not Compliant | AI89: YES | AJ89: NO | AK89: NO | AL89: YES | AM89: YES | AN89: YES | AO89: NO | AR89: 31310.77 | AT89: 10846.05 | AV89: 10774.04 | AX89: 2877.46 | AZ89: 6058.63 | BB89: 754.59 | BD89: =SUM(BF89,BH89,BJ89,BL89,BN89) -> 0 | BP89: =SUM(BF89,BH89,BJ89)/BD89*100 -> #DIV/0! | BQ89: =SUM(BL89,BN89)/BD89*100 -> #DIV/0!
A90: TARLAC | B90: PROVINCIAL GOV. OF TARLAC | C90: TARLAC, PROVINCIAL GOV. OF TARLAC | D90: OUTSIDE MBA | F90: 15.480299 | G90: 120.58801 | H90: =CONCATENATE(F90,",",G90) -> 15.480299,120.588006 | I90: Provincial Plan | J90: NSWMC RESO NO. 793 SERIES OF 2016 | K90: 2014 - 2023 | L90: 2016 | M90: 2023 | N90: For Renewal | O90: 6.June | P90: Joshua A. Capones | R90: Rod Ross S. De Jesus | S90: R3-2025-020365 | T90: 45827 | U90: 45827 | W90: 45827 | X90: 45827 | Y90: =IF( OR(ISBLANK(T90), ISBLANK(U90)), "", MAX(1, IF( NETWORKDAYS(T90, U90) <= 0, 1, NETWORKDAYS(T90, U90) - IF(T90 = U90, 0, 1) )) ) -> 1 | Z90: =IF( OR(ISBLANK(U90), ISBLANK(V90)), "", MAX(1, IF( NETWORKDAYS(U90, V90) <= 0, 1, NETWORKDAYS(U90, V90) - IF(U90 = V90, 0, 1) )) ) | AA90: =IF( OR(ISBLANK(U90), ISBLANK(W90)), "", MAX(1, IF( NETWORKDAYS(U90, W90) <= 0, 1, NETWORKDAYS(U90, W90) - IF(U90 = W90, 0, 1) )) ) -> 1 | AB90: =IF( OR(ISBLANK(W90), ISBLANK(X90)), "", MAX(1, IF( NETWORKDAYS(W90, X90) <= 0, 1, NETWORKDAYS(W90, X90) - IF(W90 = X90, 0, 1) )) ) -> 1 | AC90: Received by Planning | AG90: MAA Integrated Solid Waste Solution Corporation, Urdaneta, Pangasinan | AH90: =IF(AND(AI90 = "YES", AJ90 = "YES", AK90 = "YES", AL90 = "YES", AN90 = "YES"), "Compliant", "Not Compliant") -> Compliant | AI90: YES | AJ90: YES | AK90: YES | AL90: YES | AM90: N/A | AN90: YES | AQ90: 18 Municipalities Province of Tarlac (Consolidated Data) | BD90: =SUM(BF90,BH90,BJ90,BL90,BN90) -> 0 | BP90: =SUM(BF90,BH90,BJ90)/BD90*100 -> #DIV/0! | BQ90: =SUM(BL90,BN90)/BD90*100 -> #DIV/0!
A91: ZAMBALES | B91: CASTILLEJOS | C91: ZAMBALES, CASTILLEJOS | D91: OUTSIDE MBA | E91: 1st | F91: 14.93211 | G91: 120.19998 | H91: =CONCATENATE(F91,",",G91) -> 14.93211,120.199976 | I91: Municipal / City Plan | J91: No.1414 Series of 2020 | K91: 2017 - 2027 | L91: 2020 | M91: 2027 | O91: 6.June | Q91: Ryan Christian R. Nunag | R91: Jun D. Guillermo | S91: R3-2025-018038 | T91: 45804 | U91: 45807 | V91: 45807 | W91: 45807 | X91: 45807 | Y91: =IF( OR(ISBLANK(T91), ISBLANK(U91)), "", MAX(1, IF( NETWORKDAYS(T91, U91) <= 0, 1, NETWORKDAYS(T91, U91) - IF(T91 = U91, 0, 1) )) ) -> 3 | Z91: =IF( OR(ISBLANK(U91), ISBLANK(V91)), "", MAX(1, IF( NETWORKDAYS(U91, V91) <= 0, 1, NETWORKDAYS(U91, V91) - IF(U91 = V91, 0, 1) )) ) -> 1 | AA91: =IF( OR(ISBLANK(U91), ISBLANK(W91)), "", MAX(1, IF( NETWORKDAYS(U91, W91) <= 0, 1, NETWORKDAYS(U91, W91) - IF(U91 = W91, 0, 1) )) ) -> 1 | AB91: =IF( OR(ISBLANK(W91), ISBLANK(X91)), "", MAX(1, IF( NETWORKDAYS(W91, X91) <= 0, 1, NETWORKDAYS(W91, X91) - IF(W91 = X91, 0, 1) )) ) -> 1 | AC91: Received by Planning | AD91: 0.234 | AE91: 15886.03 | AF91: 0.6604 | AG91: Greentech Total Environmental Solutions Incorporated | AH91: =IF(AND(AI91 = "YES", AJ91 = "YES", AK91 = "YES", AL91 = "YES", AN91 = "YES"), "Compliant", "Not Compliant") -> Compliant | AI91: YES | AJ91: YES | AK91: YES | AL91: YES | AM91: YES | AN91: YES | AR91: 17375.08 | AT91: 3740.86 | AV91: 5996.14 | AX91: 1737.51 | AZ91: 5368.9 | BB91: 531.68 | BD91: =SUM(BF91,BH91,BJ91,BL91,BN91) -> 0 | BP91: =SUM(BF91,BH91,BJ91)/BD91*100 -> #DIV/0! | BQ91: =SUM(BL91,BN91)/BD91*100 -> #DIV/0!
A92: BULACAN | B92: ANGAT | C92: BULACAN, ANGAT | D92: MBA | E92: 6th | F92: 14.928065 | G92: 121.02828 | H92: =CONCATENATE(F92,",",G92) -> 14.92806531,121.0282841 | I92: Municipal / City Plan | J92: 1079 Series of 2018 | K92: 2017 - 2027 | L92: 2018 | M92: 2027 | O92: 7.July | P92: Ronaldo P. Roque, Jr. | R92: Diozelle A. Lazatin | S92: R3-2025-023821 | T92: 45853 | U92: 45853 | W92: 45855 | X92: 45856 | Y92: =IF( OR(ISBLANK(T92), ISBLANK(U92)), "", MAX(1, IF( NETWORKDAYS(T92, U92) <= 0, 1, NETWORKDAYS(T92, U92) - IF(T92 = U92, 0, 1) )) ) -> 1 | Z92: =IF( OR(ISBLANK(U92), ISBLANK(V92)), "", MAX(1, IF( NETWORKDAYS(U92, V92) <= 0, 1, NETWORKDAYS(U92, V92) - IF(U92 = V92, 0, 1) )) ) | AA92: =IF( OR(IF(V92<>"", V92, U92)="", W92=""), "", MAX(1, IF( NETWORKDAYS(IF(V92<>"", V92, U92), W92) <= 0, 1, NETWORKDAYS(IF(V92<>"", V92, U92), W92) - IF(IF(V92<>"", V92, U92)=W92, 0, 1) ) ) ) -> 2 | AB92: =IF( OR(ISBLANK(W92), ISBLANK(X92)), "", MAX(1, IF( NETWORKDAYS(W92, X92) <= 0, 1, NETWORKDAYS(W92, X92) - IF(W92 = X92, 0, 1) )) ) -> 1 | AC92: Received by Planning | AD92: 0.268 | AE92: 21646.9 | AG92: MOA with GENAR 22 | AH92: Compliant | AR92: 21647.54 | AT92: 10535.86 | AV92: 5266.85 | AX92: 2374.74 | AZ92: 3195.18 | BB92: 274.92 | BD92: =SUM(BF92,BH92,BJ92,BL92,BN92) -> 0 | BP92: =SUM(BF92,BH92,BJ92)/BD92*100 -> #DIV/0! | BQ92: =SUM(BL92,BN92)/BD92*100 -> #DIV/0!
A93: BULACAN | B93: PANDI | C93: BULACAN, PANDI | D93: MBA | E93: 5th | F93: 14.865724 | G93: 120.95814 | H93: =CONCATENATE(F93,",",G93) -> 14.86572366,120.9581422 | I93: Municipal / City Plan | J93: No. 1403 Series of 2020 | K93: 2019 - 2028 | L93: 2020 | M93: 2028 | O93: 7.July | P93: Ronaldo P. Roque, Jr. | R93: Diozelle A. Lazatin | S93: R3-2025-022969 | T93: 45847 | U93: 45849 | W93: 45855 | X93: 45856 | Y93: =IF( OR(ISBLANK(T93), ISBLANK(U93)), "", MAX(1, IF( NETWORKDAYS(T93, U93) <= 0, 1, NETWORKDAYS(T93, U93) - IF(T93 = U93, 0, 1) )) ) -> 2 | Z93: =IF( OR(ISBLANK(U93), ISBLANK(V93)), "", MAX(1, IF( NETWORKDAYS(U93, V93) <= 0, 1, NETWORKDAYS(U93, V93) - IF(U93 = V93, 0, 1) )) ) | AA93: =IF( OR(IF(V93<>"", V93, U93)="", W93=""), "", MAX(1, IF( NETWORKDAYS(IF(V93<>"", V93, U93), W93) <= 0, 1, NETWORKDAYS(IF(V93<>"", V93, U93), W93) - IF(IF(V93<>"", V93, U93)=W93, 0, 1) ) ) ) -> 4 | AB93: =IF( OR(ISBLANK(W93), ISBLANK(X93)), "", MAX(1, IF( NETWORKDAYS(W93, X93) <= 0, 1, NETWORKDAYS(W93, X93) - IF(W93 = X93, 0, 1) )) ) -> 1 | AC93: Received by Planning | AD93: 0.62 | AE93: 0.62 | AG93: Eco Protect Management Corporation | AR93: 289381.45 | AT93: 158812.54 | AV93: 71477.22 | AX93: 17825.9 | AZ93: 30761.25 | BB93: 10504.55 | BD93: =SUM(BF93,BH93,BJ93,BL93,BN93) -> 0 | BP93: =SUM(BF93,BH93,BJ93)/BD93*100 -> #DIV/0! | BQ93: =SUM(BL93,BN93)/BD93*100 -> #DIV/0!
A94: BULACAN | B94: STA. MARIA | C94: BULACAN, STA. MARIA | D94: MBA | E94: 6th | F94: 14.819555 | G94: 120.9601 | H94: =CONCATENATE(F94,",",G94) -> 14.81955522,120.9601016 | I94: Municipal / City Plan | J94: 201 s.2015 | K94: 2015 - 2024 | L94: 2015 | M94: 2024 | N94: For Renewal | O94: 7.July | P94: James Wilson T. Pena | R94: Diozelle A. Lazatin | S94: R3-2025-024025 | T94: 45846 | U94: 45855 | W94: 45856 | X94: 45856 | Y94: =IF( OR(ISBLANK(T94), ISBLANK(U94)), "", MAX(1, IF( NETWORKDAYS(T94, U94) <= 0, 1, NETWORKDAYS(T94, U94) - IF(T94 = U94, 0, 1) )) ) -> 7 | Z94: =IF( OR(ISBLANK(U94), ISBLANK(V94)), "", MAX(1, IF( NETWORKDAYS(U94, V94) <= 0, 1, NETWORKDAYS(U94, V94) - IF(U94 = V94, 0, 1) )) ) | AA94: =IF( OR(IF(V94<>"", V94, U94)="", W94=""), "", MAX(1, IF( NETWORKDAYS(IF(V94<>"", V94, U94), W94) <= 0, 1, NETWORKDAYS(IF(V94<>"", V94, U94), W94) - IF(IF(V94<>"", V94, U94)=W94, 0, 1) ) ) ) -> 1 | AB94: =IF( OR(ISBLANK(W94), ISBLANK(X94)), "", MAX(1, IF( NETWORKDAYS(W94, X94) <= 0, 1, NETWORKDAYS(W94, X94) - IF(W94 = X94, 0, 1) )) ) -> 1 | AC94: Received by Planning | AD94: 0.44 | AE94: 106491 | AG94: Prime Waste Solution | AH94: Compliant | AI94: YES | AJ94: YES | AK94: yES | AL94: YES | AM94: YES | AN94: YES | AR94: 163237.41 | AT94: 55941.46 | AV94: 46408.39 | AX94: 25856.8 | AZ94: 25840.48 | BB94: 9190.27 | BD94: =SUM(BF94,BH94,BJ94,BL94,BN94) -> 0 | BP94: =SUM(BF94,BH94,BJ94)/BD94*100 -> #DIV/0! | BQ94: =SUM(BL94,BN94)/BD94*100 -> #DIV/0!
A95: NUEVA ECIJA | B95: GABALDON | C95: NUEVA ECIJA, GABALDON | D95: MBA | E95: 3rd | F95: 15.455567 | G95: 121.33825 | H95: =CONCATENATE(F95,",",G95) -> 15.455567,121.33825 | I95: Municipal / City Plan | J95: 1246 series of 2019 | K95: 2016 - 2027 | L95: 2019 | M95: 2027 | O95: 7.July | P95: Christian Jem L. Buluran | Q95: Jan Emerson C. Gonzales | R95: Zosimo P. Suyat | S95: R3-2025-024196 | T95: 45848 | U95: 45856 | V95: 45856 | W95: 45859 | X95: 45859 | Y95: =IF( OR(ISBLANK(T95), ISBLANK(U95)), "", MAX(1, IF( NETWORKDAYS(T95, U95) <= 0, 1, NETWORKDAYS(T95, U95) - IF(T95 = U95, 0, 1) )) ) -> 6 | Z95: =IF( OR(ISBLANK(U95), ISBLANK(V95)), "", MAX(1, IF( NETWORKDAYS(U95, V95) <= 0, 1, NETWORKDAYS(U95, V95) - IF(U95 = V95, 0, 1) )) ) -> 1 | AA95: =IF( OR(IF(V95<>"", V95, U95)="", W95=""), "", MAX(1, IF( NETWORKDAYS(IF(V95<>"", V95, U95), W95) <= 0, 1, NETWORKDAYS(IF(V95<>"", V95, U95), W95) - IF(IF(V95<>"", V95, U95)=W95, 0, 1) ) ) ) -> 1 | AB95: =IF( OR(ISBLANK(W95), ISBLANK(X95)), "", MAX(1, IF( NETWORKDAYS(W95, X95) <= 0, 1, NETWORKDAYS(W95, X95) - IF(W95 = X95, 0, 1) )) ) -> 1 | AC95: Received by Planning | AD95: 0.355 | AE95: 16528.24 | AF95: 75.65 | AG95: Prime Waste Solutions Inc. | AH95: =IF(AND(AI95 = "YES", AJ95 = "YES", AK95 = "YES", AL95 = "YES", AN95 = "YES"), "Compliant", "Not Compliant") -> Compliant | AI95: YES | AJ95: YES | AK95: YES | AL95: YES | AM95: YES | AN95: YES | AR95: 16858.8 | AT95: 9334.72 | AV95: 3418.97 | AX95: 2764.84 | AZ95: 1229.01 | BB95: 111.27 | BD95: =SUM(BF95,BH95,BJ95,BL95,BN95) -> 0 | BP95: =SUM(BF95,BH95,BJ95)/BD95*100 -> #DIV/0! | BQ95: =SUM(BL95,BN95)/BD95*100 -> #DIV/0!
A96: NUEVA ECIJA | B96: GEN. NATIVIDAD | C96: NUEVA ECIJA, GEN. NATIVIDAD | D96: MBA | E96: 3rd | F96: 15.602761 | G96: 121.04995 | H96: =CONCATENATE(F96,",",G96) -> 15.602761,121.049951 | I96: Municipal / City Plan | J96: 1076 series 2018 | K96: 2017 - 2027 | L96: 2018 | M96: 2027 | O96: 7.July | P96: Hosannah R. Sabio | Q96: Jaypee Ordoñez | R96: Zosimo P. Suyat | S96: R3-2025-023505 | T96: 45849 | U96: 45852 | V96: 45853 | W96: 45854 | X96: 45855 | Y96: =IF( OR(ISBLANK(T96), ISBLANK(U96)), "", MAX(1, IF( NETWORKDAYS(T96, U96) <= 0, 1, NETWORKDAYS(T96, U96) - IF(T96 = U96, 0, 1) )) ) -> 1 | Z96: =IF( OR(ISBLANK(U96), ISBLANK(V96)), "", MAX(1, IF( NETWORKDAYS(U96, V96) <= 0, 1, NETWORKDAYS(U96, V96) - IF(U96 = V96, 0, 1) )) ) -> 1 | AA96: =IF( OR(IF(V96<>"", V96, U96)="", W96=""), "", MAX(1, IF( NETWORKDAYS(IF(V96<>"", V96, U96), W96) <= 0, 1, NETWORKDAYS(IF(V96<>"", V96, U96), W96) - IF(IF(V96<>"", V96, U96)=W96, 0, 1) ) ) ) -> 1 | AB96: =IF( OR(ISBLANK(W96), ISBLANK(X96)), "", MAX(1, IF( NETWORKDAYS(W96, X96) <= 0, 1, NETWORKDAYS(W96, X96) - IF(W96 = X96, 0, 1) )) ) -> 1 | AC96: Received by Planning | AD96: 0.25 | AF96: 91.25 | AG96: Prime Waste Solutions | AH96: =IF(AND(AI96 = "YES", AJ96 = "YES", AK96 = "YES", AL96 = "YES", AN96 = "YES"), "Compliant", "Not Compliant") -> Compliant | AI96: YES | AJ96: YES | AK96: YES | AL96: YES | AM96: YES | AN96: YES | AR96: 10690 | AS96: 0.25 | AT96: 6812.11 | AU96: 60.95 | AV96: 3386.05 | AW96: 30 | AX96: - | AZ96: 527.12 | BA96: 4.72 | BB96: 450.85 | BC96: 4.03 | BD96: =SUM(BF96,BH96,BJ96,BL96,BN96) -> 0 | BP96: =SUM(BF96,BH96,BJ96)/BD96*100 -> #DIV/0! | BQ96: =SUM(BL96,BN96)/BD96*100 -> #DIV/0!
A97: NUEVA ECIJA | B97: LAUR | C97: NUEVA ECIJA, LAUR | D97: MBA | E97: 3rd | F97: 15.571914 | G97: 121.16846 | H97: =CONCATENATE(F97,",",G97) -> 15.571914,121.168456 | I97: Municipal / City Plan | J97: 195 | K97: 2016 - 2025 | L97: 2015 | M97: 2025 | N97: For Renewal | O97: 7.July | P97: Christian Jem L. Buluran | Q97: Jan Emerson C. Gonzales | R97: Zosimo P. Suyat | S97: R3-2025-024264 | T97: 45848 | U97: 45856 | V97: 45856 | W97: 45859 | X97: 45859 | Y97: =IF( OR(ISBLANK(T97), ISBLANK(U97)), "", MAX(1, IF( NETWORKDAYS(T97, U97) <= 0, 1, NETWORKDAYS(T97, U97) - IF(T97 = U97, 0, 1) )) ) -> 6 | Z97: =IF( OR(ISBLANK(U97), ISBLANK(V97)), "", MAX(1, IF( NETWORKDAYS(U97, V97) <= 0, 1, NETWORKDAYS(U97, V97) - IF(U97 = V97, 0, 1) )) ) -> 1 | AA97: =IF( OR(IF(V97<>"", V97, U97)="", W97=""), "", MAX(1, IF( NETWORKDAYS(IF(V97<>"", V97, U97), W97) <= 0, 1, NETWORKDAYS(IF(V97<>"", V97, U97), W97) - IF(IF(V97<>"", V97, U97)=W97, 0, 1) ) ) ) -> 1 | AB97: =IF( OR(ISBLANK(W97), ISBLANK(X97)), "", MAX(1, IF( NETWORKDAYS(W97, X97) <= 0, 1, NETWORKDAYS(W97, X97) - IF(W97 = X97, 0, 1) )) ) -> 1 | AC97: Received by Planning | AD97: 0.273 | AE97: 11, 600.86 | AF97: 76.53 | AG97: Prime Waste Solutions | AH97: =IF(AND(AI97 = "YES", AJ97 = "YES", AK97 = "YES", AL97 = "YES", AN97 = "YES"), "Compliant", "Not Compliant") -> Not Compliant | AI97: YES | AJ97: YES | AK97: YES | AL97: YES | AM97: YES | AN97: NO | AR97: 11883.98 | AT97: 7514.24 | AV97: 1580.57 | AX97: 937.65 | AZ97: 1741 | BB97: 110.52 | BD97: =SUM(BF97,BH97,BJ97,BL97,BN97) -> 0 | BP97: =SUM(BF97,BH97,BJ97)/BD97*100 -> #DIV/0! | BQ97: =SUM(BL97,BN97)/BD97*100 -> #DIV/0!
A98: PAMPANGA | B98: SAN LUIS | C98: PAMPANGA, SAN LUIS | D98: MBA | E98: 4th | F98: 15.038968 | G98: 120.78928 | H98: =CONCATENATE(F98,",",G98) -> 15.038968,120.789279 | I98: Municipal / City Plan | J98: NSWMC RESO NO. 1113 SERIES OF 2018 | K98: 2018 - 2027 | L98: 2018 | M98: 2027 | O98: 7.July | P98: Glaiza S.Gaza | Q98: Jan Emerson C. Gonzales | R98: Yves Yshmael M. Balagtas | S98: R3-2025-024267 | T98: 45853 | U98: 45856 | V98: 45856 | W98: 45856 | X98: 45859 | Y98: =IF( OR(ISBLANK(T98), ISBLANK(U98)), "", MAX(1, IF( NETWORKDAYS(T98, U98) <= 0, 1, NETWORKDAYS(T98, U98) - IF(T98 = U98, 0, 1) )) ) -> 3 | Z98: =IF( OR(ISBLANK(U98), ISBLANK(V98)), "", MAX(1, IF( NETWORKDAYS(U98, V98) <= 0, 1, NETWORKDAYS(U98, V98) - IF(U98 = V98, 0, 1) )) ) -> 1 | AA98: =IF( OR(IF(V98<>"", V98, U98)="", W98=""), "", MAX(1, IF( NETWORKDAYS(IF(V98<>"", V98, U98), W98) <= 0, 1, NETWORKDAYS(IF(V98<>"", V98, U98), W98) - IF(IF(V98<>"", V98, U98)=W98, 0, 1) ) ) ) -> 1 | AB98: =IF( OR(ISBLANK(W98), ISBLANK(X98)), "", MAX(1, IF( NETWORKDAYS(W98, X98) <= 0, 1, NETWORKDAYS(W98, X98) - IF(W98 = X98, 0, 1) )) ) -> 1 | AC98: Received by Planning | AD98: 0.228 | AE98: 13713.74 | AF98: 64.77 | AG98: Eco Protect Management Corporation | AH98: =IF(AND(AI98 = "YES", AJ98 = "YES", AK98 = "YES", AL98 = "YES", AN98 = "YES"), "Compliant", "Not Compliant") -> Not Compliant | AI98: NO | AJ98: YES | AK98: NO | AL98: YES | AM98: YES | AN98: NO | AO98: NO | AR98: 15646.11 | AT98: 6203.68 | AV98: 1619.37 | AX98: 797.95 | AZ98: 6729.39 | BB98: 295.71 | BD98: =SUM(BF98,BH98,BJ98,BL98,BN98) -> 0 | BP98: =SUM(BF98,BH98,BJ98)/BD98*100 -> #DIV/0! | BQ98: =SUM(BL98,BN98)/BD98*100 -> #DIV/0!
A99: PAMPANGA | B99: STA ANA | C99: PAMPANGA, STA ANA | D99: MBA | E99: 3rd | F99: 15.0839 | G99: 120.7631 | H99: =CONCATENATE(F99,",",G99) -> 15.0839,120.7631 | I99: Municipal / City Plan | J99: 1244 of 2019 | K99: 2016 - 2027 | L99: 2019 | M99: 2027 | O99: 7.July | P99: Roger T. Encarnacion II | Q99: Jan Emerson C. Gonzales | R99: Yves Yshmael M. Balagtas | S99: R3-2025-023735 | T99: 45848 | U99: 45854 | V99: 45856 | W99: 45856 | X99: 45856 | Y99: =IF( OR(ISBLANK(T99), ISBLANK(U99)), "", MAX(1, IF( NETWORKDAYS(T99, U99) <= 0, 1, NETWORKDAYS(T99, U99) - IF(T99 = U99, 0, 1) )) ) -> 4 | Z99: =IF( OR(ISBLANK(U99), ISBLANK(V99)), "", MAX(1, IF( NETWORKDAYS(U99, V99) <= 0, 1, NETWORKDAYS(U99, V99) - IF(U99 = V99, 0, 1) )) ) -> 2 | AA99: =IF( OR(IF(V99<>"", V99, U99)="", W99=""), "", MAX(1, IF( NETWORKDAYS(IF(V99<>"", V99, U99), W99) <= 0, 1, NETWORKDAYS(IF(V99<>"", V99, U99), W99) - IF(IF(V99<>"", V99, U99)=W99, 0, 1) ) ) ) -> 1 | AB99: =IF( OR(ISBLANK(W99), ISBLANK(X99)), "", MAX(1, IF( NETWORKDAYS(W99, X99) <= 0, 1, NETWORKDAYS(W99, X99) - IF(W99 = X99, 0, 1) )) ) -> 1 | AC99: Received by Planning | AD99: 0.201 | AE99: 23549.16 | AF99: 79.45 | AG99: Florida Enviro Corp | AH99: =IF(AND(AI99 = "YES", AJ99 = "YES", AK99 = "YES", AL99 = "YES", AN99 = "YES"), "Compliant", "Not Compliant") -> Not Compliant | AR99: 27079.99 | AT99: 8124 | AV99: 4332.8 | AX99: 10019.6 | AZ99: 4062 | BB99: 541.6 | BD99: =SUM(BF99,BH99,BJ99,BL99,BN99) -> 0 | BP99: =SUM(BF99,BH99,BJ99)/BD99*100 -> #DIV/0! | BQ99: =SUM(BL99,BN99)/BD99*100 -> #DIV/0!
A100: TARLAC | B100: ANAO | C100: TARLAC, ANAO | D100: OUTSIDE MBA | E100: 1st | F100: 15.730196 | G100: 120.6266 | H100: =CONCATENATE(F100,",",G100) -> 15.730196,120.6265988 | I100: Municipal / City Plan | J100: 1089 s.2018 | K100: 2018 - 2027 | L100: 2018 | M100: 2027 | O100: 7.July | P100: Jasper Kieht B. Pili | R100: Rod Ross S. De Jesus | S100: R3-2025-024271 | T100: 45856 | U100: 45856 | W100: 45856 | X100: 45856 | Y100: =IF( OR(ISBLANK(T100), ISBLANK(U100)), "", MAX(1, IF( NETWORKDAYS(T100, U100) <= 0, 1, NETWORKDAYS(T100, U100) - IF(T100 = U100, 0, 1) )) ) -> 1 | Z100: =IF( OR(ISBLANK(U100), ISBLANK(V100)), "", MAX(1, IF( NETWORKDAYS(U100, V100) <= 0, 1, NETWORKDAYS(U100, V100) - IF(U100 = V100, 0, 1) )) ) | AA100: =IF( OR(IF(V100<>"", V100, U100)="", W100=""), "", MAX(1, IF( NETWORKDAYS(IF(V100<>"", V100, U100), W100) <= 0, 1, NETWORKDAYS(IF(V100<>"", V100, U100), W100) - IF(IF(V100<>"", V100, U100)=W100, 0, 1) ) ) ) -> 1 | AB100: =IF( OR(ISBLANK(W100), ISBLANK(X100)), "", MAX(1, IF( NETWORKDAYS(W100, X100) <= 0, 1, NETWORKDAYS(W100, X100) - IF(W100 = X100, 0, 1) )) ) -> 1 | AC100: Received by Planning | AD100: 0.23 | AE100: 2790.92 | AF100: 99.9 | AG100: MAA Integrated Waste Solutions Incorporated | AH100: =IF(AND(AI100 = "YES", AJ100 = "YES", AK100 = "YES", AL100 = "YES", AN100 = "YES"), "Compliant", "Not Compliant") -> Compliant | AI100: YES | AJ100: YES | AK100: YES | AL100: YES | AN100: YES | AR100: 3163.57 | AT100: 1522.94 | AV100: 919.97 | AX100: 3.16 | AZ100: 597.6 | BB100: 119.9 | BD100: =SUM(BF100,BH100,BJ100,BL100,BN100) -> 0 | BP100: =SUM(BF100,BH100,BJ100)/BD100*100 -> #DIV/0! | BQ100: =SUM(BL100,BN100)/BD100*100 -> #DIV/0!
...

Sheet MRF
A1: Province | B1: Municipality | C1: Barangay | D1: Manila Bay Area (MBA) | E1: Congressional District | F1: Lat | G1: Long | H1: Coordinates | I1: Type of MRF | J1: No Funding Support | K1: Year Granted | L1: Amount Granted | M1: Target Month | N1: ENMO Assigned | O1: ESWM Staff | P1: Focal Person | Q1: IIS NUMBER | R1: Date of Monitoring | S1: Date Report Prepared (Submitted to IIS by ENMO) | T1: Date Report Reviewed (by ESWM Staff) | U1: Date Report Reviewed (by Focal Person) | V1: Date Report Approved | W1: Total No. of Days (Report prepared) | X1: Total No. of Days (Report Reviewed by ESWM Staff) | Y1: Total No. of Days (Report Reviewed by Focal) | Z1: Total No. of Days (Report Approved by C, ESWM) | AA1: Tracking of Reports (To be Filled out by Planning Section) | AB1: No. of Brgy. Served | AC1: Equipment used in the Operation of the MRF | AD1: Type of wastes received | AE1: Quantity of waste diverted (kg) | AF1: Total Waste Generation (kg/day) | AG1: Waste Diversion Rate (%) | AH1: Status of MRF | AI1: Remarks (If Not Operational) | AJ1: Remarks and Recommendation (Compliant/ Non-Compliant) | AK1: Findings (If not compliant) | AL1: Advise Letter/Notice Date Issued | AM1: Compliance of LGU to Issued Advise/ Letter | AN1: Docket No. / NOV | AO1: Violation (Sec. ___ ) | AP1: Date of Issuance of NOV | AQ1: Date of Technical Conference | AR1: Commitment/s
A2: Aurora | B2: Baler | C2: 5 | D2: OUTSIDE MBA | E2: Lone | F2: 15.759167 | G2: 121.56285 | H2: =CONCATENATE(F2,",",G2) -> 15.759167,121.562848 | I2: EMB FUNDED BRGY MRF | J2: 1 | K2: 2018 | L2: 427500 | M2: 3.March | N2: Zaila Mae R. Leander | P2: Ryan Christian R. Nunag | Q2: R3-2025-007935 | R2: 45720 | S2: 45724 | T2: 45724 | U2: 45727 | V2: 45728 | W2: =IF( OR(ISBLANK(R2), ISBLANK(S2)), "", MAX(1, IF( NETWORKDAYS(R2, S2) <= 0, 1, NETWORKDAYS(R2, S2) - IF(R2 = S2, 0, 1) )) ) -> 3 | X2: =IF( OR(ISBLANK(S2), ISBLANK(T2)), "", MAX(1, IF( NETWORKDAYS(S2, T2) <= 0, 1, NETWORKDAYS(S2, T2) - IF(S2 = T2, 0, 1) )) ) -> 1 | Y2: =IF( OR(IF(T2<>"", T2, S2)="", U2=""), "", MAX(1, IF( NETWORKDAYS(IF(T2<>"", T2, S2), U2) <= 0, 1, NETWORKDAYS(IF(T2<>"", T2, S2), U2) - IF(IF(T2<>"", T2, S2)=U2, 0, 1) ) ) ) -> 1 | Z2: =IF( OR(ISBLANK(U2), ISBLANK(V2)), "", MAX(1, IF( NETWORKDAYS(U2, V2) <= 0, 1, NETWORKDAYS(U2, V2) - IF(U2 = V2, 0, 1) )) ) -> 1 | AA2: Received by Planning | AB2: 1 | AC2: Plastic shredder | AD2: No Data | AE2: No Data | AF2: No Data | AG2: =(AE2/AF2) -> #VALUE! | AH2: NON-OPERATIONAL | AJ2: Non-Compliant | AL2: NO | AS2: No proper recording/ filing Personnel does not wear PPEs
A3: Aurora | B3: Baler | C3: Buhangin | D3: OUTSIDE MBA | E3: Lone | F3: 15.768186 | G3: 121.55754 | H3: =CONCATENATE(F3,",",G3) -> 15.768186,121.557544 | I3: EMB FUNDED BRGY MRF | J3: 1 | K3: 2018 | L3: 427500 | M3: 3.March | N3: Zaila Mae R. Leander | P3: Ryan Christian R. Nunag | Q3: R3-2025-007933 | R3: 45720 | S3: 45724 | T3: 45724 | U3: 45727 | V3: 45728 | W3: =IF( OR(ISBLANK(R3), ISBLANK(S3)), "", MAX(1, IF( NETWORKDAYS(R3, S3) <= 0, 1, NETWORKDAYS(R3, S3) - IF(R3 = S3, 0, 1) )) ) -> 3 | X3: =IF( OR(ISBLANK(S3), ISBLANK(T3)), "", MAX(1, IF( NETWORKDAYS(S3, T3) <= 0, 1, NETWORKDAYS(S3, T3) - IF(S3 = T3, 0, 1) )) ) -> 1 | Y3: =IF( OR(IF(T3<>"", T3, S3)="", U3=""), "", MAX(1, IF( NETWORKDAYS(IF(T3<>"", T3, S3), U3) <= 0, 1, NETWORKDAYS(IF(T3<>"", T3, S3), U3) - IF(IF(T3<>"", T3, S3)=U3, 0, 1) ) ) ) -> 1 | Z3: =IF( OR(ISBLANK(U3), ISBLANK(V3)), "", MAX(1, IF( NETWORKDAYS(U3, V3) <= 0, 1, NETWORKDAYS(U3, V3) - IF(U3 = V3, 0, 1) )) ) -> 1 | AA3: Received by Planning | AB3: 1 | AC3: No Data | AE3: No Data | AF3: No Data | AG3: =(AE3/AF3) -> #VALUE! | AH3: OPERATIONAL | AJ3: Non-Compliant | AL3: NO | AS3: No proper recording/ filing Personnel does not wear PPEs
A4: Aurora | B4: Baler | C4: Obligasyon | D4: OUTSIDE MBA | E4: Lone | F4: 15.779536 | G4: 121.52657 | H4: =CONCATENATE(F4,",",G4) -> 15.779536,121.526573 | I4: EMB FUNDED BRGY MRF | J4: 1 | K4: 2018 | L4: 427500 | M4: 7.July | N4: Zaila Mae R. Leander | P4: Ryan Christian R. Nunag | Q4: R3-2025-021989 | R4: 45839 | S4: 45841 | U4: 45845 | V4: 45847 | W4: =IF( OR(ISBLANK(R4), ISBLANK(S4)), "", MAX(1, IF( NETWORKDAYS(R4, S4) <= 0, 1, NETWORKDAYS(R4, S4) - IF(R4 = S4, 0, 1) )) ) -> 2 | X4: =IF( OR(ISBLANK(S4), ISBLANK(T4)), "", MAX(1, IF( NETWORKDAYS(S4, T4) <= 0, 1, NETWORKDAYS(S4, T4) - IF(S4 = T4, 0, 1) )) ) | Y4: =IF( OR(IF(T4<>"", T4, S4)="", U4=""), "", MAX(1, IF( NETWORKDAYS(IF(T4<>"", T4, S4), U4) <= 0, 1, NETWORKDAYS(IF(T4<>"", T4, S4), U4) - IF(IF(T4<>"", T4, S4)=U4, 0, 1) ) ) ) -> 2 | Z4: =IF( OR(ISBLANK(U4), ISBLANK(V4)), "", MAX(1, IF( NETWORKDAYS(U4, V4) <= 0, 1, NETWORKDAYS(U4, V4) - IF(U4 = V4, 0, 1) )) ) -> 2 | AA4: Received by Planning | AB4: 0 | AC4: None | AD4: N/A | AE4: N/A | AF4: N/A | AG4: =(AE4/AF4) -> #VALUE! | AH4: NON-OPERATIONAL | AI4: Used as storage of equipment by the barangay
A5: Aurora | B5: Baler | C5: Pingit | D5: OUTSIDE MBA | E5: Lone | F5: 15.735852 | G5: 121.56293 | H5: =CONCATENATE(F5,",",G5) -> 15.7358523,121.5629275 | I5: EMB FUNDED BRGY MRF | J5: 1 | K5: 2018 | L5: 427500 | M5: 8.August | N5: Zaila Mae R. Leander | P5: Ryan Christian R. Nunag | Q5: R3-2025-026688 | R5: 45877 | S5: 45880 | U5: 45882 | V5: 45882 | W5: =IF( OR(ISBLANK(R5), ISBLANK(S5)), "", MAX(1, IF( NETWORKDAYS(R5, S5) <= 0, 1, NETWORKDAYS(R5, S5) - IF(R5 = S5, 0, 1) )) ) -> 1 | X5: =IF( OR(ISBLANK(S5), ISBLANK(T5)), "", MAX(1, IF( NETWORKDAYS(S5, T5) <= 0, 1, NETWORKDAYS(S5, T5) - IF(S5 = T5, 0, 1) )) ) | Y5: =IF( OR(IF(T5<>"", T5, S5)="", U5=""), "", MAX(1, IF( NETWORKDAYS(IF(T5<>"", T5, S5), U5) <= 0, 1, NETWORKDAYS(IF(T5<>"", T5, S5), U5) - IF(IF(T5<>"", T5, S5)=U5, 0, 1) ) ) ) -> 2 | Z5: =IF( OR(ISBLANK(U5), ISBLANK(V5)), "", MAX(1, IF( NETWORKDAYS(U5, V5) <= 0, 1, NETWORKDAYS(U5, V5) - IF(U5 = V5, 0, 1) )) ) -> 1 | AA5: Received by Planning | AB5: 1 | AC5: None | AD5: Biodegradable waste,Recyclables,Residual Wastes | AE5: 0 | AF5: 91.44 | AG5: =(AE5/AF5) -> 0 | AH5: OPERATIONAL | AJ5: Non-Compliant | AK5: No Records | AL5: NO
A6: Aurora | B6: Baler | C6: Zabali | D6: OUTSIDE MBA | E6: Lone | F6: 15.751451 | G6: 121.56715 | H6: =CONCATENATE(F6,",",G6) -> 15.751451,121.5671508 | I6: EMB FUNDED BRGY MRF | J6: 1 | K6: 2018 | L6: 427500 | M6: 8.August | N6: Zaila Mae R. Leander | P6: Ryan Christian R. Nunag | Q6: R3-2025-026694 | R6: 45877 | S6: 45880 | U6: 45883 | V6: 45887 | W6: =IF( OR(ISBLANK(R6), ISBLANK(S6)), "", MAX(1, IF( NETWORKDAYS(R6, S6) <= 0, 1, NETWORKDAYS(R6, S6) - IF(R6 = S6, 0, 1) )) ) -> 1 | X6: =IF( OR(ISBLANK(S6), ISBLANK(T6)), "", MAX(1, IF( NETWORKDAYS(S6, T6) <= 0, 1, NETWORKDAYS(S6, T6) - IF(S6 = T6, 0, 1) )) ) | Y6: =IF( OR(IF(T6<>"", T6, S6)="", U6=""), "", MAX(1, IF( NETWORKDAYS(IF(T6<>"", T6, S6), U6) <= 0, 1, NETWORKDAYS(IF(T6<>"", T6, S6), U6) - IF(IF(T6<>"", T6, S6)=U6, 0, 1) ) ) ) -> 3 | Z6: =IF( OR(ISBLANK(U6), ISBLANK(V6)), "", MAX(1, IF( NETWORKDAYS(U6, V6) <= 0, 1, NETWORKDAYS(U6, V6) - IF(U6 = V6, 0, 1) )) ) -> 2 | AA6: Received by Planning | AB6: 0 | AC6: N/A | AD6: N/A | AE6: N/A | AF6: N/A | AG6: =(AE6/AF6) -> #VALUE! | AH6: NON-OPERATIONAL | AI6: The Facility has been domolished and replaced by constructing the Senior Citizen Building of the LGU | AL6: 45896 | AM6: The LGU submitted an explanation letter regarding the removal of the EMB Funded MRF and according to the letter the LGU was constructed a new MRF besides the newly constructed Senior Citizen Building.
A7: Aurora | B7: Dingalan | C7: Umiray | D7: OUTSIDE MBA | E7: Lone | F7: 15.223196 | G7: 121.40795 | H7: =CONCATENATE(F7,",",G7) -> 15.223196,121.40795 | I7: EMB FUNDED BRGY MRF | J7: 1 | K7: 2018 | L7: 427500 | M7: 9.September | N7: Nikko Jay M. Valenzuela | P7: Ryan Christian R. Nunag | Q7: R3-2025-031098 | R7: 45911 | S7: 45916 | U7: 45916 | V7: 45917 | W7: =IF( OR(ISBLANK(R7), ISBLANK(S7)), "", MAX(1, IF( NETWORKDAYS(R7, S7) <= 0, 1, NETWORKDAYS(R7, S7) - IF(R7 = S7, 0, 1) )) ) -> 3 | X7: =IF( OR(ISBLANK(S7), ISBLANK(T7)), "", MAX(1, IF( NETWORKDAYS(S7, T7) <= 0, 1, NETWORKDAYS(S7, T7) - IF(S7 = T7, 0, 1) )) ) | Y7: =IF( OR(IF(T7<>"", T7, S7)="", U7=""), "", MAX(1, IF( NETWORKDAYS(IF(T7<>"", T7, S7), U7) <= 0, 1, NETWORKDAYS(IF(T7<>"", T7, S7), U7) - IF(IF(T7<>"", T7, S7)=U7, 0, 1) ) ) ) -> 1 | Z7: =IF( OR(ISBLANK(U7), ISBLANK(V7)), "", MAX(1, IF( NETWORKDAYS(U7, V7) <= 0, 1, NETWORKDAYS(U7, V7) - IF(U7 = V7, 0, 1) )) ) -> 1 | AA7: Received by Planning | AB7: 1 | AC7: None | AD7: Recyclables | AE7: 6.66 | AF7: 123.33 | AG7: =(AE7/AF7) -> 0.054001459 | AH7: OPERATIONAL | AJ7: Compliant
A8: Aurora | B8: Dipaculao | C8: Dibutonan | D8: OUTSIDE MBA | E8: Lone | F8: 15.942102 | G8: 121.60366 | H8: =CONCATENATE(F8,",",G8) -> 15.9421021,121.603663 | I8: EMB FUNDED BRGY MRF | J8: 1 | K8: 2018 | L8: 427500 | M8: 10.October | N8: Zaila Mae R. Leander | P8: Ryan Christian R. Nunag | Q8: R3-2025-034214 | R8: 45939 | S8: 45940 | U8: 45944 | V8: 45945 | W8: =IF( OR(ISBLANK(R8), ISBLANK(S8)), "", MAX(1, IF( NETWORKDAYS(R8, S8) <= 0, 1, NETWORKDAYS(R8, S8) - IF(R8 = S8, 0, 1) )) ) -> 1 | X8: =IF( OR(ISBLANK(S8), ISBLANK(T8)), "", MAX(1, IF( NETWORKDAYS(S8, T8) <= 0, 1, NETWORKDAYS(S8, T8) - IF(S8 = T8, 0, 1) )) ) | Y8: =IF( OR(IF(T8<>"", T8, S8)="", U8=""), "", MAX(1, IF( NETWORKDAYS(IF(T8<>"", T8, S8), U8) <= 0, 1, NETWORKDAYS(IF(T8<>"", T8, S8), U8) - IF(IF(T8<>"", T8, S8)=U8, 0, 1) ) ) ) -> 2 | Z8: =IF( OR(ISBLANK(U8), ISBLANK(V8)), "", MAX(1, IF( NETWORKDAYS(U8, V8) <= 0, 1, NETWORKDAYS(U8, V8) - IF(U8 = V8, 0, 1) )) ) -> 1 | AA8: Received by Planning | AB8: 1 | AC8: None | AD8: NO Data | AE8: No Data | AF8: No Data | AG8: =(AE8/AF8) -> #VALUE! | AH8: OPERATIONAL
A9: Aurora | B9: Dipaculao | C9: Dinadiawan | D9: OUTSIDE MBA | E9: Lone | F9: 16.076998 | G9: 121.76936 | H9: =CONCATENATE(F9,",",G9) -> 16.076998,121.769361 | I9: EMB FUNDED BRGY MRF | J9: 1 | K9: 2018 | L9: 427500 | M9: 10.October | N9: Zaila Mae R. Leander | P9: Ryan Christian R. Nunag | Q9: R3-2025-034968 | R9: 45944 | S9: 45945 | U9: 45946 | V9: 45946 | W9: =IF( OR(ISBLANK(R9), ISBLANK(S9)), "", MAX(1, IF( NETWORKDAYS(R9, S9) <= 0, 1, NETWORKDAYS(R9, S9) - IF(R9 = S9, 0, 1) )) ) -> 1 | X9: =IF( OR(ISBLANK(S9), ISBLANK(T9)), "", MAX(1, IF( NETWORKDAYS(S9, T9) <= 0, 1, NETWORKDAYS(S9, T9) - IF(S9 = T9, 0, 1) )) ) | Y9: =IF( OR(IF(T9<>"", T9, S9)="", U9=""), "", MAX(1, IF( NETWORKDAYS(IF(T9<>"", T9, S9), U9) <= 0, 1, NETWORKDAYS(IF(T9<>"", T9, S9), U9) - IF(IF(T9<>"", T9, S9)=U9, 0, 1) ) ) ) -> 1 | Z9: =IF( OR(ISBLANK(U9), ISBLANK(V9)), "", MAX(1, IF( NETWORKDAYS(U9, V9) <= 0, 1, NETWORKDAYS(U9, V9) - IF(U9 = V9, 0, 1) )) ) -> 1 | AA9: Received by Planning | AB9: 1 | AC9: None | AD9: No Data | AE9: No Data | AF9: No Data | AG9: =(AE9/AF9) -> #VALUE! | AH9: OPERATIONAL
A10: Aurora | B10: Dipaculao | C10: Gupa | D10: OUTSIDE MBA | E10: Lone | F10: 15.887986 | G10: 121.55079 | H10: =CONCATENATE(F10,",",G10) -> 15.887986,121.550789 | I10: EMB FUNDED BRGY MRF | J10: 1 | K10: 2018 | L10: 427500 | M10: 11.November | N10: Zaila Mae R. Leander | P10: Ryan Christian R. Nunag | Q10: R3-2025-036844 | R10: 45960 | S10: 45965 | U10: 45966 | V10: 45968 | W10: =IF( OR(ISBLANK(R10), ISBLANK(S10)), "", MAX(1, IF( NETWORKDAYS(R10, S10) <= 0, 1, NETWORKDAYS(R10, S10) - IF(R10 = S10, 0, 1) )) ) -> 3 | X10: =IF( OR(ISBLANK(S10), ISBLANK(T10)), "", MAX(1, IF( NETWORKDAYS(S10, T10) <= 0, 1, NETWORKDAYS(S10, T10) - IF(S10 = T10, 0, 1) )) ) | Y10: =IF( OR(IF(T10<>"", T10, S10)="", U10=""), "", MAX(1, IF( NETWORKDAYS(IF(T10<>"", T10, S10), U10) <= 0, 1, NETWORKDAYS(IF(T10<>"", T10, S10), U10) - IF(IF(T10<>"", T10, S10)=U10, 0, 1) ) ) ) -> 1 | Z10: =IF( OR(ISBLANK(U10), ISBLANK(V10)), "", MAX(1, IF( NETWORKDAYS(U10, V10) <= 0, 1, NETWORKDAYS(U10, V10) - IF(U10 = V10, 0, 1) )) ) -> 2 | AA10: Received by Planning | AB10: 1 | AC10: Weighing Scale | AD10: Biodegradable, Recyclable, Residual | AE10: 0 | AF10: 0 | AG10: =(AE10/AF10) -> #DIV/0! | AH10: OPERATIONAL
A11: Aurora | B11: Dipaculao | C11: Majires | D11: OUTSIDE MBA | E11: Lone | F11: 15.874659 | G11: 121.54438 | H11: =CONCATENATE(F11,",",G11) -> 15.874659,121.544376 | I11: EMB FUNDED BRGY MRF | J11: 1 | K11: 2018 | L11: 427500 | M11: 11.November | N11: Zaila Mae R. Leander | P11: Ryan Christian R. Nunag | Q11: R3-2025-036843 | R11: 45960 | S11: 45965 | U11: 45966 | V11: 45968 | W11: =IF( OR(ISBLANK(R11), ISBLANK(S11)), "", MAX(1, IF( NETWORKDAYS(R11, S11) <= 0, 1, NETWORKDAYS(R11, S11) - IF(R11 = S11, 0, 1) )) ) -> 3 | X11: =IF( OR(ISBLANK(S11), ISBLANK(T11)), "", MAX(1, IF( NETWORKDAYS(S11, T11) <= 0, 1, NETWORKDAYS(S11, T11) - IF(S11 = T11, 0, 1) )) ) | Y11: =IF( OR(IF(T11<>"", T11, S11)="", U11=""), "", MAX(1, IF( NETWORKDAYS(IF(T11<>"", T11, S11), U11) <= 0, 1, NETWORKDAYS(IF(T11<>"", T11, S11), U11) - IF(IF(T11<>"", T11, S11)=U11, 0, 1) ) ) ) -> 1 | Z11: =IF( OR(ISBLANK(U11), ISBLANK(V11)), "", MAX(1, IF( NETWORKDAYS(U11, V11) <= 0, 1, NETWORKDAYS(U11, V11) - IF(U11 = V11, 0, 1) )) ) -> 2 | AA11: Received by Planning | AB11: 1 | AC11: Weighing Scale | AD11: Biodegradable, Recyclable, Residual | AE11: N/A | AF11: N/A | AG11: =(AE11/AF11) -> #VALUE! | AH11: OPERATIONAL | AK11: • The barangay still has no MRF record book, resulting in the absence of documented data on waste collection, segregation, and hauling activities.
A12: Bataan | B12: Abucay | C12: Capitangan | D12: MBA | E12: 1st | F12: 14.7035 | G12: 120.488 | H12: =CONCATENATE(F12,",",G12) -> 14.7035,120.488 | I12: LGU FUNDED MRF | K12: N/A | L12: N/A | M12: 7.July | N12: Dennis Tolentino | P12: Christle D. David | Q12: R3-2025-023327 | R12: 45847 | S12: 45852 | U12: 45853 | V12: 45855 | W12: =IF( OR(ISBLANK(R12), ISBLANK(S12)), "", MAX(1, IF( NETWORKDAYS(R12, S12) <= 0, 1, NETWORKDAYS(R12, S12) - IF(R12 = S12, 0, 1) )) ) -> 3 | X12: =IF( OR(ISBLANK(S12), ISBLANK(T12)), "", MAX(1, IF( NETWORKDAYS(S12, T12) <= 0, 1, NETWORKDAYS(S12, T12) - IF(S12 = T12, 0, 1) )) ) | Y12: =IF( OR(IF(T12<>"", T12, S12)="", U12=""), "", MAX(1, IF( NETWORKDAYS(IF(T12<>"", T12, S12), U12) <= 0, 1, NETWORKDAYS(IF(T12<>"", T12, S12), U12) - IF(IF(T12<>"", T12, S12)=U12, 0, 1) ) ) ) -> 1 | Z12: =IF( OR(ISBLANK(U12), ISBLANK(V12)), "", MAX(1, IF( NETWORKDAYS(U12, V12) <= 0, 1, NETWORKDAYS(U12, V12) - IF(U12 = V12, 0, 1) )) ) -> 2 | AA12: Received by Planning | AB12: 9 | AC12: Conveyor, Wheel Loader, Biowaste Shredder, Plastic Shredder, Rotary Composter, Plastic Chair Factory, Charcoal Briquetting Machine/ Carbonizer, Electric Power | AD12: Biodegradable, Recyclables, Special, Residual | AE12: 3448.02 | AF12: 9800.35 | AG12: =(AE12/AF12) -> 0.35182621 | AH12: Operational | AJ12: Compliant
A13: Bataan | B13: Bagac | C13: Banawang | D13: MBA | E13: 3rd | F13: 14.619694 | G13: 120.38603 | H13: =CONCATENATE(F13,",",G13) -> 14.619694,120.386025 | I13: EMB FUNDED BRGY MRF | J13: 1 | K13: 2018 | L13: 285000 | M13: 5.May | N13: Laurence Radasa | P13: Christle D. David | Q13: R3-2025-016419 | R13: 45792 | S13: 45794 | T13: 45794 | U13: 45796 | V13: 45797 | W13: =IF( OR(ISBLANK(R13), ISBLANK(S13)), "", MAX(1, IF( NETWORKDAYS(R13, S13) <= 0, 1, NETWORKDAYS(R13, S13) - IF(R13 = S13, 0, 1) )) ) -> 1 | X13: =IF( OR(ISBLANK(S13), ISBLANK(T13)), "", MAX(1, IF( NETWORKDAYS(S13, T13) <= 0, 1, NETWORKDAYS(S13, T13) - IF(S13 = T13, 0, 1) )) ) -> 1 | Y13: =IF( OR(IF(T13<>"", T13, S13)="", U13=""), "", MAX(1, IF( NETWORKDAYS(IF(T13<>"", T13, S13), U13) <= 0, 1, NETWORKDAYS(IF(T13<>"", T13, S13), U13) - IF(IF(T13<>"", T13, S13)=U13, 0, 1) ) ) ) -> 1 | Z13: =IF( OR(ISBLANK(U13), ISBLANK(V13)), "", MAX(1, IF( NETWORKDAYS(U13, V13) <= 0, 1, NETWORKDAYS(U13, V13) - IF(U13 = V13, 0, 1) )) ) -> 1 | AA13: Received by Planning | AB13: 1 | AC13: None | AD13: Bio, Rcyclable,Residual | AE13: 14.5 | AF13: 124.56 | AG13: =(AE13/AF13) -> 0.11640976 | AH13: OPERATIONAL | AI13: Used as MRS
A14: Bataan | B14: Balanga City | C14: Puerto Rivas Lote | D14: MBA | E14: 2nd | F14: 14.687931 | G14: 120.55046 | H14: =CONCATENATE(F14,",",G14) -> 14.687931,120.550458 | I14: EMB FUNDED BRGY MRF | J14: 1 | K14: 2018 | L14: 427500 | M14: 8.August | N14: Dennis Tolentino | P14: Christle D. David | Q14: R3-2025-027730 | R14: 45881 | S14: 45887 | T14: 45887 | U14: 45887 | V14: 45887 | W14: =IF( OR(ISBLANK(R14), ISBLANK(S14)), "", MAX(1, IF( NETWORKDAYS(R14, S14) <= 0, 1, NETWORKDAYS(R14, S14) - IF(R14 = S14, 0, 1) )) ) -> 4 | X14: =IF( OR(ISBLANK(S14), ISBLANK(T14)), "", MAX(1, IF( NETWORKDAYS(S14, T14) <= 0, 1, NETWORKDAYS(S14, T14) - IF(S14 = T14, 0, 1) )) ) -> 1 | Y14: =IF( OR(IF(T14<>"", T14, S14)="", U14=""), "", MAX(1, IF( NETWORKDAYS(IF(T14<>"", T14, S14), U14) <= 0, 1, NETWORKDAYS(IF(T14<>"", T14, S14), U14) - IF(IF(T14<>"", T14, S14)=U14, 0, 1) ) ) ) -> 1 | Z14: =IF( OR(ISBLANK(U14), ISBLANK(V14)), "", MAX(1, IF( NETWORKDAYS(U14, V14) <= 0, 1, NETWORKDAYS(U14, V14) - IF(U14 = V14, 0, 1) )) ) -> 1 | AA14: Received by Planning | AB14: 1 | AC14: Boiwaste Shredder, Rotary Composter | AD14: Biodegrdable, Recyclable, | AE14: 73.36 | AF14: 586.09 | AG14: =(AE14/AF14) -> 0.12516849 | AH14: OPERATIONAL
A15: Bataan | B15: Balanga City | C15: San Jose | D15: MBA | E15: 2nd | F15: 14.671465 | G15: 120.53447 | H15: =CONCATENATE(F15,",",G15) -> 14.671465,120.534471 | I15: EMB FUNDED BRGY MRF | J15: 1 | K15: 2018 | L15: 285000 | M15: 8.August | N15: Dennis Tolentino | P15: Christle D. David | Q15: R3-2025-027729 | R15: 45881 | S15: 45887 | U15: 45887 | V15: 45887 | W15: =IF( OR(ISBLANK(R15), ISBLANK(S15)), "", MAX(1, IF( NETWORKDAYS(R15, S15) <= 0, 1, NETWORKDAYS(R15, S15) - IF(R15 = S15, 0, 1) )) ) -> 4 | X15: =IF( OR(ISBLANK(S15), ISBLANK(T15)), "", MAX(1, IF( NETWORKDAYS(S15, T15) <= 0, 1, NETWORKDAYS(S15, T15) - IF(S15 = T15, 0, 1) )) ) | Y15: =IF( OR(IF(T15<>"", T15, S15)="", U15=""), "", MAX(1, IF( NETWORKDAYS(IF(T15<>"", T15, S15), U15) <= 0, 1, NETWORKDAYS(IF(T15<>"", T15, S15), U15) - IF(IF(T15<>"", T15, S15)=U15, 0, 1) ) ) ) -> 1 | Z15: =IF( OR(ISBLANK(U15), ISBLANK(V15)), "", MAX(1, IF( NETWORKDAYS(U15, V15) <= 0, 1, NETWORKDAYS(U15, V15) - IF(U15 = V15, 0, 1) )) ) -> 1 | AA15: Received by Planning | AB15: 1 | AC15: None | AD15: Reyclable | AE15: 448 | AF15: 1578.73 | AG15: =(AE15/AF15) -> 0.2837724 | AH15: OPERATIONAL | AJ15: Compliant
A16: Bataan | B16: Orion | C16: General Lim | D16: MBA | E16: 2nd | F16: 14.5871 | G16: 120.527 | H16: =CONCATENATE(F16,",",G16) -> 14.5871,120.527 | I16: LGU FUNDED MRF | K16: N/A | L16: N/A | M16: 9.September | N16: Dennis Tolentino | P16: Christle D. David | Q16: R3-2025-031520 | R16: 45916 | S16: 45917 | U16: 45917 | V16: 45918 | W16: =IF( OR(ISBLANK(R16), ISBLANK(S16)), "", MAX(1, IF( NETWORKDAYS(R16, S16) <= 0, 1, NETWORKDAYS(R16, S16) - IF(R16 = S16, 0, 1) )) ) -> 1 | X16: =IF( OR(ISBLANK(S16), ISBLANK(T16)), "", MAX(1, IF( NETWORKDAYS(S16, T16) <= 0, 1, NETWORKDAYS(S16, T16) - IF(S16 = T16, 0, 1) )) ) | Y16: =IF( OR(IF(T16<>"", T16, S16)="", U16=""), "", MAX(1, IF( NETWORKDAYS(IF(T16<>"", T16, S16), U16) <= 0, 1, NETWORKDAYS(IF(T16<>"", T16, S16), U16) - IF(IF(T16<>"", T16, S16)=U16, 0, 1) ) ) ) -> 1 | Z16: =IF( OR(ISBLANK(U16), ISBLANK(V16)), "", MAX(1, IF( NETWORKDAYS(U16, V16) <= 0, 1, NETWORKDAYS(U16, V16) - IF(U16 = V16, 0, 1) )) ) -> 1 | AA16: Received by Planning | AB16: 23 | AC16: Conveyor, Bottle Crusher, Bricks Mixer Machine, Biowaste Shredder, Plastic Shredder, Rotary Composter, Bricks maker/molder | AD16: Biodegradable, Recyclable, Residual | AE16: 21370 | AF16: 28866.23 | AG16: =(AE16/AF16) -> 0.74031143 | AH16: OPERATIONAL
A17: Bataan | B17: Limay | C17: San Franciso De Asis | D17: MBA | E17: 2nd | F17: 14.569686 | G17: 120.55153 | H17: =CONCATENATE(F17,",",G17) -> 14.569686,120.551528 | I17: EMB FUNDED MRF | J17: 1 | K17: 2019 | L17: 502714.29 | M17: 9.September | N17: Dennis Tolentino | P17: Christle D. David | Q17: R3-2025-031511 | R17: 45917 | S17: 45917 | U17: 45917 | V17: 45918 | W17: =IF( OR(ISBLANK(R17), ISBLANK(S17)), "", MAX(1, IF( NETWORKDAYS(R17, S17) <= 0, 1, NETWORKDAYS(R17, S17) - IF(R17 = S17, 0, 1) )) ) -> 1 | X17: =IF( OR(ISBLANK(S17), ISBLANK(T17)), "", MAX(1, IF( NETWORKDAYS(S17, T17) <= 0, 1, NETWORKDAYS(S17, T17) - IF(S17 = T17, 0, 1) )) ) | Y17: =IF( OR(IF(T17<>"", T17, S17)="", U17=""), "", MAX(1, IF( NETWORKDAYS(IF(T17<>"", T17, S17), U17) <= 0, 1, NETWORKDAYS(IF(T17<>"", T17, S17), U17) - IF(IF(T17<>"", T17, S17)=U17, 0, 1) ) ) ) -> 1 | Z17: =IF( OR(ISBLANK(U17), ISBLANK(V17)), "", MAX(1, IF( NETWORKDAYS(U17, V17) <= 0, 1, NETWORKDAYS(U17, V17) - IF(U17 = V17, 0, 1) )) ) -> 1 | AA17: Received by Planning | AB17: 0 | AC17: None | AD17: None | AE17: No Data | AF17: No Data | AG17: =(AE17/AF17) -> #VALUE! | AH17: NON-OPERATIONAL | AI17: The LGU is yet to operate the Materials Recovery Facility this 2025 due to the availability of equipment within the facility.
A18: Bataan | B18: Balanga City | C18: Cabog Cabog | D18: MBA | E18: 2nd | F18: 14.671575 | G18: 120.53445 | H18: =CONCATENATE(F18,",",G18) -> 14.671575,120.534451 | I18: EMB FUNDED BRGY MRF | J18: 1 | K18: 2018 | L18: 285000 | M18: 4.April | N18: Dennis Tolentino | P18: Christle D. David | Q18: R3-2025-010730 | R18: 45744 | S18: 45746 | T18: 45746 | U18: 45747 | V18: 45747 | W18: =IF( OR(ISBLANK(R18), ISBLANK(S18)), "", MAX(1, IF( NETWORKDAYS(R18, S18) <= 0, 1, NETWORKDAYS(R18, S18) - IF(R18 = S18, 0, 1) )) ) -> 1 | X18: =IF( OR(ISBLANK(S18), ISBLANK(T18)), "", MAX(1, IF( NETWORKDAYS(S18, T18) <= 0, 1, NETWORKDAYS(S18, T18) - IF(S18 = T18, 0, 1) )) ) -> 1 | Y18: =IF( OR(IF(T18<>"", T18, S18)="", U18=""), "", MAX(1, IF( NETWORKDAYS(IF(T18<>"", T18, S18), U18) <= 0, 1, NETWORKDAYS(IF(T18<>"", T18, S18), U18) - IF(IF(T18<>"", T18, S18)=U18, 0, 1) ) ) ) -> 1 | Z18: =IF( OR(ISBLANK(U18), ISBLANK(V18)), "", MAX(1, IF( NETWORKDAYS(U18, V18) <= 0, 1, NETWORKDAYS(U18, V18) - IF(U18 = V18, 0, 1) )) ) -> 1 | AA18: Received by Planning | AB18: 1 | AC18: Biowaste Shredder | AD18: Biodegradable, Recyclables | AE18: 100 | AF18: 1089.6 | AG18: =(AE18/AF18) -> 0.091776799 | AH18: OPERATIONAL | AJ18: Compliant
A19: Bataan | B19: Balanga City | C19: Munting Batangas | D19: MBA | E19: 2nd | F19: 14.6781 | G19: 120.477 | H19: =CONCATENATE(F19,",",G19) -> 14.6781,120.477 | I19: LGU FUNDED MRF | K19: N/A | L19: N/A | M19: 3.March | N19: Dennis Tolentino | P19: Christle D. David | Q19: R3-2025-007106 | R19: 45715 | S19: 45718 | U19: 45719 | V19: 45719 | W19: =IF( OR(ISBLANK(R19), ISBLANK(S19)), "", MAX(1, IF( NETWORKDAYS(R19, S19) <= 0, 1, NETWORKDAYS(R19, S19) - IF(R19 = S19, 0, 1) )) ) -> 1 | X19: =IF( OR(ISBLANK(S19), ISBLANK(T19)), "", MAX(1, IF( NETWORKDAYS(S19, T19) <= 0, 1, NETWORKDAYS(S19, T19) - IF(S19 = T19, 0, 1) )) ) | Y19: =IF( OR(IF(T19<>"", T19, S19)="", U19=""), "", MAX(1, IF( NETWORKDAYS(IF(T19<>"", T19, S19), U19) <= 0, 1, NETWORKDAYS(IF(T19<>"", T19, S19), U19) - IF(IF(T19<>"", T19, S19)=U19, 0, 1) ) ) ) -> 1 | Z19: =IF( OR(ISBLANK(U19), ISBLANK(V19)), "", MAX(1, IF( NETWORKDAYS(U19, V19) <= 0, 1, NETWORKDAYS(U19, V19) - IF(U19 = V19, 0, 1) )) ) -> 1 | AA19: Received by Planning | AB19: 25 | AC19: Conveyor, Bricks Mixer Machine, Biowaste Shredder, Plastic Shredder, Rotary Composter, Bricks Maker/Molder | AD19: Bidegradable, Recyclable, Residual | AE19: 10721.89 | AF19: 24547.38 | AG19: =(AE19/AF19) -> 0.43678348 | AH19: OPERATIONAL | AJ19: Compliant
A20: Bataan | B20: Pilar | C20: Alauli | D20: MBA | E20: 2nd | F20: 14.66066 | G20: 120.5436 | H20: =CONCATENATE(F20,",",G20) -> 14.66066,120.543603 | I20: EMB FUNDED MRF | J20: 1 | K20: 2019 | L20: 502714.29 | M20: 10.October | N20: Dennis Tolentino | P20: Christle D. David | Q20: R3-2025-034952 | R20: 45945 | S20: 45945 | U20: 45950 | V20: 45950 | W20: =IF( OR(ISBLANK(R20), ISBLANK(S20)), "", MAX(1, IF( NETWORKDAYS(R20, S20) <= 0, 1, NETWORKDAYS(R20, S20) - IF(R20 = S20, 0, 1) )) ) -> 1 | X20: =IF( OR(ISBLANK(S20), ISBLANK(T20)), "", MAX(1, IF( NETWORKDAYS(S20, T20) <= 0, 1, NETWORKDAYS(S20, T20) - IF(S20 = T20, 0, 1) )) ) | Y20: =IF( OR(IF(T20<>"", T20, S20)="", U20=""), "", MAX(1, IF( NETWORKDAYS(IF(T20<>"", T20, S20), U20) <= 0, 1, NETWORKDAYS(IF(T20<>"", T20, S20), U20) - IF(IF(T20<>"", T20, S20)=U20, 0, 1) ) ) ) -> 3 | Z20: =IF( OR(ISBLANK(U20), ISBLANK(V20)), "", MAX(1, IF( NETWORKDAYS(U20, V20) <= 0, 1, NETWORKDAYS(U20, V20) - IF(U20 = V20, 0, 1) )) ) -> 1 | AA20: Received by Planning | AB20: 19 | AC20: Biowaste Granulating Machine, Bottle Crusher, Plastic Granulating Machine, Bricks Mixer Machine, Glass shredder/ pulverizer, Rotary composter, Bricks maker/molder | AD20: Biodegradable, Recyclable, Residual, Special | AE20: 0 | AF20: 26397.56 | AG20: =(AE20/AF20) -> 0 | AH20: OPERATIONAL | AJ20: Non-Compliant | AL20: 45958
A21: Bataan | B21: Balanga City | C21: San Jose | D21: MBA | E21: 2nd | F21: 14.628389 | G21: 120.46927 | H21: =CONCATENATE(F21,",",G21) -> 14.628389,120.469267 | I21: EMB FUNDED BRGY MRF | J21: 1 | K21: 2018 | L21: 285000 | M21: 3.March | N21: Dennis Tolentino | P21: Christle D. David | Q21: R3-2025-008825 | R21: 45730 | S21: 45732 | T21: 45732 | U21: 45732 | V21: 45733 | W21: =IF( OR(ISBLANK(R21), ISBLANK(S21)), "", MAX(1, IF( NETWORKDAYS(R21, S21) <= 0, 1, NETWORKDAYS(R21, S21) - IF(R21 = S21, 0, 1) )) ) -> 1 | X21: =IF( OR(ISBLANK(S21), ISBLANK(T21)), "", MAX(1, IF( NETWORKDAYS(S21, T21) <= 0, 1, NETWORKDAYS(S21, T21) - IF(S21 = T21, 0, 1) )) ) -> 1 | Y21: =IF( OR(IF(T21<>"", T21, S21)="", U21=""), "", MAX(1, IF( NETWORKDAYS(IF(T21<>"", T21, S21), U21) <= 0, 1, NETWORKDAYS(IF(T21<>"", T21, S21), U21) - IF(IF(T21<>"", T21, S21)=U21, 0, 1) ) ) ) -> 1 | Z21: =IF( OR(ISBLANK(U21), ISBLANK(V21)), "", MAX(1, IF( NETWORKDAYS(U21, V21) <= 0, 1, NETWORKDAYS(U21, V21) - IF(U21 = V21, 0, 1) )) ) -> 1 | AA21: Received by Planning | AB21: 1 | AC21: None | AD21: Bidegradable, Recyclable | AE21: 448 | AF21: 3359 | AG21: =(AE21/AF21) -> 0.13337303 | AH21: OPERATIONAL | AJ21: Compliant
A22: Bataan | B22: Hermosa | C22: Mambog | D22: MBA | E22: 1st | F22: 14.8145 | G22: 120.479 | H22: =CONCATENATE(F22,",",G22) -> 14.8145,120.479 | I22: LGU FUNDED MRF | K22: N/A | L22: N/A | M22: 8.August | N22: John-lester Signio | P22: Christle D. David | Q22: R3-2025-027711 | R22: 45881 | S22: 45887 | U22: 45887 | V22: 45887 | W22: =IF( OR(ISBLANK(R22), ISBLANK(S22)), "", MAX(1, IF( NETWORKDAYS(R22, S22) <= 0, 1, NETWORKDAYS(R22, S22) - IF(R22 = S22, 0, 1) )) ) -> 4 | X22: =IF( OR(ISBLANK(S22), ISBLANK(T22)), "", MAX(1, IF( NETWORKDAYS(S22, T22) <= 0, 1, NETWORKDAYS(S22, T22) - IF(S22 = T22, 0, 1) )) ) | Y22: =IF( OR(IF(T22<>"", T22, S22)="", U22=""), "", MAX(1, IF( NETWORKDAYS(IF(T22<>"", T22, S22), U22) <= 0, 1, NETWORKDAYS(IF(T22<>"", T22, S22), U22) - IF(IF(T22<>"", T22, S22)=U22, 0, 1) ) ) ) -> 1 | Z22: =IF( OR(ISBLANK(U22), ISBLANK(V22)), "", MAX(1, IF( NETWORKDAYS(U22, V22) <= 0, 1, NETWORKDAYS(U22, V22) - IF(U22 = V22, 0, 1) )) ) -> 1 | AA22: Received by Planning | AB22: 23 | AC22: Boiwaste Shredder, Rotary Composter | AD22: Biodegrdable, Recyclable, Residual | AE22: 30.09 | AF22: 38088.69 | AG22: =(AE22/AF22) -> 0.00078999829 | AH22: OPERATIONAL | AJ22: Compliant
A23: Bataan | B23: Balanga City | C23: San Jose Proper (Market) | D23: MBA | E23: 2nd | F23: 14.673789 | G23: 120.53288 | H23: =CONCATENATE(F23,",",G23) -> 14.673789,120.532878 | I23: EMB FUNDED BRGY MRF | J23: 1 | K23: 2018 | L23: 285000 | M23: 3.March | N23: Dennis Tolentino | P23: Christle D. David | Q23: R3-2025-008826 | R23: 45730 | S23: 45732 | T23: 45732 | U23: 45732 | V23: 45732 | W23: =IF( OR(ISBLANK(R23), ISBLANK(S23)), "", MAX(1, IF( NETWORKDAYS(R23, S23) <= 0, 1, NETWORKDAYS(R23, S23) - IF(R23 = S23, 0, 1) )) ) -> 1 | X23: =IF( OR(ISBLANK(S23), ISBLANK(T23)), "", MAX(1, IF( NETWORKDAYS(S23, T23) <= 0, 1, NETWORKDAYS(S23, T23) - IF(S23 = T23, 0, 1) )) ) -> 1 | Y23: =IF( OR(IF(T23<>"", T23, S23)="", U23=""), "", MAX(1, IF( NETWORKDAYS(IF(T23<>"", T23, S23), U23) <= 0, 1, NETWORKDAYS(IF(T23<>"", T23, S23), U23) - IF(IF(T23<>"", T23, S23)=U23, 0, 1) ) ) ) -> 1 | Z23: =IF( OR(ISBLANK(U23), ISBLANK(V23)), "", MAX(1, IF( NETWORKDAYS(U23, V23) <= 0, 1, NETWORKDAYS(U23, V23) - IF(U23 = V23, 0, 1) )) ) -> 1 | AA23: Received by Planning | AB23: 1 | AC23: Biowaste shredder | AD23: None | AE23: 0 | AF23: 0 | AG23: =(AE23/AF23) -> #DIV/0! | AH23: NON-OPERATIONAL | AJ23: Compliant
A24: Bataan | B24: Orani | C24: Pag-asa | D24: MBA | E24: 1st | F24: 14.7852 | G24: 120.476 | H24: =CONCATENATE(F24,",",G24) -> 14.7852,120.476 | I24: LGU FUNDED MRF | K24: N/A | L24: N/A | M24: 9.September | N24: John-lester Signio | P24: Christle D. David | Q24: R3-2025-030937 | R24: 45911 | S24: 45915 | U24: 45917 | V24: 45917 | W24: =IF( OR(ISBLANK(R24), ISBLANK(S24)), "", MAX(1, IF( NETWORKDAYS(R24, S24) <= 0, 1, NETWORKDAYS(R24, S24) - IF(R24 = S24, 0, 1) )) ) -> 2 | X24: =IF( OR(ISBLANK(S24), ISBLANK(T24)), "", MAX(1, IF( NETWORKDAYS(S24, T24) <= 0, 1, NETWORKDAYS(S24, T24) - IF(S24 = T24, 0, 1) )) ) | Y24: =IF( OR(IF(T24<>"", T24, S24)="", U24=""), "", MAX(1, IF( NETWORKDAYS(IF(T24<>"", T24, S24), U24) <= 0, 1, NETWORKDAYS(IF(T24<>"", T24, S24), U24) - IF(IF(T24<>"", T24, S24)=U24, 0, 1) ) ) ) -> 2 | Z24: =IF( OR(ISBLANK(U24), ISBLANK(V24)), "", MAX(1, IF( NETWORKDAYS(U24, V24) <= 0, 1, NETWORKDAYS(U24, V24) - IF(U24 = V24, 0, 1) )) ) -> 1 | AA24: Received by Planning | AB24: 29 | AC24: Weighing Scale, Conveyor, Bottle Crusher, Bricks Mixer Machine, Biowaste shredder, Plastic shredder, Glass shredder/ pulverizer, Rotary composter, Bricks maker/molder, Electric power | AD24: Biodegradable, Recyclable, Residual | AE24: 5138.99 | AF24: 41180.11 | AG24: =(AE24/AF24) -> 0.12479301 | AH24: OPERATIONAL | AJ24: Compliant
A25: Bataan | B25: Mariveles | C25: Alas-Asin | D25: MBA | E25: 3rd | F25: 14.459136 | G25: 120.52663 | H25: =CONCATENATE(F25,",",G25) -> 14.4591363,120.5266262 | I25: EMB FUNDED BRGY MRF | J25: 1 | K25: 2018 | L25: 285000 | M25: 6.June | N25: Laurence Radasa | P25: Christle D. David | Q25: R3-2025-018260 | R25: 45806 | S25: 45810 | T25: 45810 | U25: 45810 | V25: 45812 | W25: =IF( OR(ISBLANK(R25), ISBLANK(S25)), "", MAX(1, IF( NETWORKDAYS(R25, S25) <= 0, 1, NETWORKDAYS(R25, S25) - IF(R25 = S25, 0, 1) )) ) -> 2 | X25: =IF( OR(ISBLANK(S25), ISBLANK(T25)), "", MAX(1, IF( NETWORKDAYS(S25, T25) <= 0, 1, NETWORKDAYS(S25, T25) - IF(S25 = T25, 0, 1) )) ) -> 1 | Y25: =IF( OR(IF(T25<>"", T25, S25)="", U25=""), "", MAX(1, IF( NETWORKDAYS(IF(T25<>"", T25, S25), U25) <= 0, 1, NETWORKDAYS(IF(T25<>"", T25, S25), U25) - IF(IF(T25<>"", T25, S25)=U25, 0, 1) ) ) ) -> 1 | Z25: =IF( OR(ISBLANK(U25), ISBLANK(V25)), "", MAX(1, IF( NETWORKDAYS(U25, V25) <= 0, 1, NETWORKDAYS(U25, V25) - IF(U25 = V25, 0, 1) )) ) -> 2 | AA25: Received by Planning | AB25: 1 | AC25: Biowaste shredder | AD25: Biodegradable, Recyclable, Residual | AE25: 1232 | AF25: 2973.65 | AG25: =(AE25/AF25) -> 0.41430565 | AH25: OPERATIONAL | AJ25: Compliant
A26: Bataan | B26: Mariveles | C26: Alion | D26: MBA | E26: 3rd | F26: 14.490862 | G26: 120.58112 | H26: =CONCATENATE(F26,",",G26) -> 14.4908616,120.5811223 | I26: EMB FUNDED BRGY MRF | J26: 1 | K26: 2018 | L26: 285000 | M26: 6.June | N26: Laurence Radasa | P26: Christle D. David | Q26: R3-2025-017932 | R26: 45804 | S26: 45805 | T26: 45805 | U26: 45806 | V26: 45807 | W26: =IF( OR(ISBLANK(R26), ISBLANK(S26)), "", MAX(1, IF( NETWORKDAYS(R26, S26) <= 0, 1, NETWORKDAYS(R26, S26) - IF(R26 = S26, 0, 1) )) ) -> 1 | X26: =IF( OR(ISBLANK(S26), ISBLANK(T26)), "", MAX(1, IF( NETWORKDAYS(S26, T26) <= 0, 1, NETWORKDAYS(S26, T26) - IF(S26 = T26, 0, 1) )) ) -> 1 | Y26: =IF( OR(IF(T26<>"", T26, S26)="", U26=""), "", MAX(1, IF( NETWORKDAYS(IF(T26<>"", T26, S26), U26) <= 0, 1, NETWORKDAYS(IF(T26<>"", T26, S26), U26) - IF(IF(T26<>"", T26, S26)=U26, 0, 1) ) ) ) -> 1 | Z26: =IF( OR(ISBLANK(U26), ISBLANK(V26)), "", MAX(1, IF( NETWORKDAYS(U26, V26) <= 0, 1, NETWORKDAYS(U26, V26) - IF(U26 = V26, 0, 1) )) ) -> 1 | AA26: Received by Planning | AB26: 1 | AC26: Biowaste shredder | AD26: Biodegradable, Recyclable, Residual | AE26: 152 | AF26: 624.13 | AG26: =(AE26/AF26) -> 0.24353901 | AH26: OPERATIONAL | AJ26: Compliant
A27: Bataan | B27: Mariveles | C27: Balon-Anito | D27: MBA | E27: 3rd | F27: 14.442139 | G27: 120.46041 | H27: =CONCATENATE(F27,",",G27) -> 14.4421395,120.4604072 | I27: EMB FUNDED BRGY MRF | J27: 1 | K27: 2018 | L27: 285000 | M27: 6.June | N27: Laurence Radasa | P27: Christle D. David | Q27: R3-2025-018261 | R27: 45806 | S27: 45810 | T27: 45810 | U27: 45810 | V27: 45812 | W27: =IF( OR(ISBLANK(R27), ISBLANK(S27)), "", MAX(1, IF( NETWORKDAYS(R27, S27) <= 0, 1, NETWORKDAYS(R27, S27) - IF(R27 = S27, 0, 1) )) ) -> 2 | X27: =IF( OR(ISBLANK(S27), ISBLANK(T27)), "", MAX(1, IF( NETWORKDAYS(S27, T27) <= 0, 1, NETWORKDAYS(S27, T27) - IF(S27 = T27, 0, 1) )) ) -> 1 | Y27: =IF( OR(IF(T27<>"", T27, S27)="", U27=""), "", MAX(1, IF( NETWORKDAYS(IF(T27<>"", T27, S27), U27) <= 0, 1, NETWORKDAYS(IF(T27<>"", T27, S27), U27) - IF(IF(T27<>"", T27, S27)=U27, 0, 1) ) ) ) -> 1 | Z27: =IF( OR(ISBLANK(U27), ISBLANK(V27)), "", MAX(1, IF( NETWORKDAYS(U27, V27) <= 0, 1, NETWORKDAYS(U27, V27) - IF(U27 = V27, 0, 1) )) ) -> 2 | AA27: Received by Planning | AB27: 1 | AC27: Biowaste shredder | AD27: Biodegradable, Recyclable, Residual | AE27: 21 | AF27: 3955 | AG27: =(AE27/AF27) -> 0.0053097345 | AH27: OPERATIONAL | AJ27: Compliant
A28: Bataan | B28: Bagac | C28: Binuangan | D28: MBA | E28: 3rd | F28: 14.516517 | G28: 120.38641 | H28: =CONCATENATE(F28,",",G28) -> 14.516517,120.386411 | I28: EMB FUNDED BRGY MRF | J28: 1 | K28: 2018 | L28: 285000 | M28: 7.July | N28: Laurence Radasa | P28: Christle D. David | Q28: R3-2025-022317 | R28: 45841 | S28: 45845 | U28: 45845 | V28: 45847 | W28: =IF( OR(ISBLANK(R28), ISBLANK(S28)), "", MAX(1, IF( NETWORKDAYS(R28, S28) <= 0, 1, NETWORKDAYS(R28, S28) - IF(R28 = S28, 0, 1) )) ) -> 2 | X28: =IF( OR(ISBLANK(S28), ISBLANK(T28)), "", MAX(1, IF( NETWORKDAYS(S28, T28) <= 0, 1, NETWORKDAYS(S28, T28) - IF(S28 = T28, 0, 1) )) ) | Y28: =IF( OR(IF(T28<>"", T28, S28)="", U28=""), "", MAX(1, IF( NETWORKDAYS(IF(T28<>"", T28, S28), U28) <= 0, 1, NETWORKDAYS(IF(T28<>"", T28, S28), U28) - IF(IF(T28<>"", T28, S28)=U28, 0, 1) ) ) ) -> 1 | Z28: =IF( OR(ISBLANK(U28), ISBLANK(V28)), "", MAX(1, IF( NETWORKDAYS(U28, V28) <= 0, 1, NETWORKDAYS(U28, V28) - IF(U28 = V28, 0, 1) )) ) -> 2 | AA28: Received by Planning | AB28: 1 | AC28: None | AD28: Recyclable, Residual | AE28: 10 | AF28: 61.78 | AG28: =(AE28/AF28) -> 0.16186468 | AH28: Operational
A29: Bataan | B29: Mariveles | C29: Ipag | D29: MBA | E29: 3rd | F29: 14.424604 | G29: 120.48033 | H29: 14.42460374,120.48033257 | I29: LGU FUNDED MRF | M29: 6.June | N29: Laurence Radasa | P29: Christle D. David | Q29: R3-2025-018264 | R29: 45807 | S29: 45810 | T29: 45810 | U29: 45810 | V29: 45812 | W29: =IF( OR(ISBLANK(R29), ISBLANK(S29)), "", MAX(1, IF( NETWORKDAYS(R29, S29) <= 0, 1, NETWORKDAYS(R29, S29) - IF(R29 = S29, 0, 1) )) ) -> 1 | X29: =IF( OR(ISBLANK(S29), ISBLANK(T29)), "", MAX(1, IF( NETWORKDAYS(S29, T29) <= 0, 1, NETWORKDAYS(S29, T29) - IF(S29 = T29, 0, 1) )) ) -> 1 | Y29: =IF( OR(IF(T29<>"", T29, S29)="", U29=""), "", MAX(1, IF( NETWORKDAYS(IF(T29<>"", T29, S29), U29) <= 0, 1, NETWORKDAYS(IF(T29<>"", T29, S29), U29) - IF(IF(T29<>"", T29, S29)=U29, 0, 1) ) ) ) -> 1 | Z29: =IF( OR(ISBLANK(U29), ISBLANK(V29)), "", MAX(1, IF( NETWORKDAYS(U29, V29) <= 0, 1, NETWORKDAYS(U29, V29) - IF(U29 = V29, 0, 1) )) ) -> 2 | AA29: Received by Planning | AB29: 14 | AC29: Conveyor, Bottle Crusher, Bricks Maker Machine, Biowaste Shredder, Plastic Shredder, Glass shredder/ pulverizer, | AD29: Biodegradable, Recyclable, Residual | AE29: 183 | AF29: 26853.84 | AG29: =(AE29/AF29) -> 0.0068146678 | AH29: OPERATIONAL | AJ29: Compliant
A30: Bataan | B30: Bagac | C30: Pasyawan | D30: MBA | E30: 3rd | F30: 14.535556 | G30: 120.39278 | H30: =CONCATENATE(F30,",",G30) -> 14.535556,120.392778 | I30: EMB FUNDED BRGY MRF | J30: 1 | K30: 2018 | L30: 285000 | M30: 7.July | N30: Laurence Radasa | P30: Christle D. David | Q30: R3-2025-022318 | R30: 45841 | S30: 45845 | U30: 45845 | V30: 45847 | W30: =IF( OR(ISBLANK(R30), ISBLANK(S30)), "", MAX(1, IF( NETWORKDAYS(R30, S30) <= 0, 1, NETWORKDAYS(R30, S30) - IF(R30 = S30, 0, 1) )) ) -> 2 | X30: =IF( OR(ISBLANK(S30), ISBLANK(T30)), "", MAX(1, IF( NETWORKDAYS(S30, T30) <= 0, 1, NETWORKDAYS(S30, T30) - IF(S30 = T30, 0, 1) )) ) | Y30: =IF( OR(IF(T30<>"", T30, S30)="", U30=""), "", MAX(1, IF( NETWORKDAYS(IF(T30<>"", T30, S30), U30) <= 0, 1, NETWORKDAYS(IF(T30<>"", T30, S30), U30) - IF(IF(T30<>"", T30, S30)=U30, 0, 1) ) ) ) -> 1 | Z30: =IF( OR(ISBLANK(U30), ISBLANK(V30)), "", MAX(1, IF( NETWORKDAYS(U30, V30) <= 0, 1, NETWORKDAYS(U30, V30) - IF(U30 = V30, 0, 1) )) ) -> 2 | AA30: Received by Planning | AB30: 1 | AC30: Biowaste shredder | AD30: Recyclable, Residual | AE30: 20 | AF30: 87.26 | AG30: =(AE30/AF30) -> 0.22920009 | AH30: Operational | AJ30: Non-Compliant | AL30: NO
A31: Bataan | B31: Bagac | C31: Quinawan | D31: MBA | E31: 3rd | F31: 14.481149 | G31: 120.39035 | H31: =CONCATENATE(F31,",",G31) -> 14.481149,120.390354 | I31: EMB FUNDED BRGY MRF | J31: 1 | K31: 2018 | L31: 427500 | M31: 11.November | N31: Laurence Radasa | P31: Christle D. David | Q31: R3-2025-036661 | R31: 45958 | S31: 45964 | U31: 45964 | V31: 45964 | W31: =IF( OR(ISBLANK(R31), ISBLANK(S31)), "", MAX(1, IF( NETWORKDAYS(R31, S31) <= 0, 1, NETWORKDAYS(R31, S31) - IF(R31 = S31, 0, 1) )) ) -> 4 | X31: =IF( OR(ISBLANK(S31), ISBLANK(T31)), "", MAX(1, IF( NETWORKDAYS(S31, T31) <= 0, 1, NETWORKDAYS(S31, T31) - IF(S31 = T31, 0, 1) )) ) | Y31: =IF( OR(IF(T31<>"", T31, S31)="", U31=""), "", MAX(1, IF( NETWORKDAYS(IF(T31<>"", T31, S31), U31) <= 0, 1, NETWORKDAYS(IF(T31<>"", T31, S31), U31) - IF(IF(T31<>"", T31, S31)=U31, 0, 1) ) ) ) -> 1 | Z31: =IF( OR(ISBLANK(U31), ISBLANK(V31)), "", MAX(1, IF( NETWORKDAYS(U31, V31) <= 0, 1, NETWORKDAYS(U31, V31) - IF(U31 = V31, 0, 1) )) ) -> 1 | AA31: Received by Planning | AB31: 1 | AC31: Weighing Scale | AD31: Biodegradable, Recyclable, Residual | AE31: 18 | AF31: 691.83 | AG31: =(AE31/AF31) -> 0.026017952 | AH31: OPERATIONAL | AJ31: Compliant | AL31: NO
A32: Bataan | B32: Bagac | C32: San Antonio | D32: MBA | E32: 3rd | F32: 14.628317 | G32: 120.43926 | H32: =CONCATENATE(F32,",",G32) -> 14.628317,120.439263 | I32: EMB FUNDED BRGY MRF | J32: 1 | K32: 2018 | L32: 427500 | M32: 9.September | N32: Laurence Radasa | P32: Christle D. David | Q32: R3-2025-030071 | R32: 45902 | S32: 45908 | U32: 45909 | V32: 45909 | W32: =IF( OR(ISBLANK(R32), ISBLANK(S32)), "", MAX(1, IF( NETWORKDAYS(R32, S32) <= 0, 1, NETWORKDAYS(R32, S32) - IF(R32 = S32, 0, 1) )) ) -> 4 | X32: =IF( OR(ISBLANK(S32), ISBLANK(T32)), "", MAX(1, IF( NETWORKDAYS(S32, T32) <= 0, 1, NETWORKDAYS(S32, T32) - IF(S32 = T32, 0, 1) )) ) | Y32: =IF( OR(IF(T32<>"", T32, S32)="", U32=""), "", MAX(1, IF( NETWORKDAYS(IF(T32<>"", T32, S32), U32) <= 0, 1, NETWORKDAYS(IF(T32<>"", T32, S32), U32) - IF(IF(T32<>"", T32, S32)=U32, 0, 1) ) ) ) -> 1 | Z32: =IF( OR(ISBLANK(U32), ISBLANK(V32)), "", MAX(1, IF( NETWORKDAYS(U32, V32) <= 0, 1, NETWORKDAYS(U32, V32) - IF(U32 = V32, 0, 1) )) ) -> 1 | AA32: Received by Planning | AB32: 1 | AC32: Biowaste Shredder | AD32: Biodegradable, Recyclables, Residual | AE32: 129 | AF32: 179.45 | AG32: =(AE32/AF32) -> 0.71886319 | AH32: OPERATIONAL
A33: Bataan | B33: Samal | C33: San Juan | D33: MBA | E33: 1st | F33: 14.772728 | G33: 120.51735 | H33: =CONCATENATE(F33,",",G33) -> 14.772728,120.517353 | I33: EMB FUNDED MRF | J33: 2 | K33: 2016 & 2021 | L33: 449444& 179444.44 | M33: 2.February | N33: John-lester Signio | P33: Christle D. David | Q33: R3-2025-004158 | R33: 45692 | S33: 45694 | U33: 45697 | V33: 45697 | W33: =IF( OR(ISBLANK(R33), ISBLANK(S33)), "", MAX(1, IF( NETWORKDAYS(R33, S33) <= 0, 1, NETWORKDAYS(R33, S33) - IF(R33 = S33, 0, 1) )) ) -> 2 | X33: =IF( OR(ISBLANK(S33), ISBLANK(T33)), "", MAX(1, IF( NETWORKDAYS(S33, T33) <= 0, 1, NETWORKDAYS(S33, T33) - IF(S33 = T33, 0, 1) )) ) | Y33: =IF( OR(IF(T33<>"", T33, S33)="", U33=""), "", MAX(1, IF( NETWORKDAYS(IF(T33<>"", T33, S33), U33) <= 0, 1, NETWORKDAYS(IF(T33<>"", T33, S33), U33) - IF(IF(T33<>"", T33, S33)=U33, 0, 1) ) ) ) -> 1 | Z33: =IF( OR(ISBLANK(U33), ISBLANK(V33)), "", MAX(1, IF( NETWORKDAYS(U33, V33) <= 0, 1, NETWORKDAYS(U33, V33) - IF(U33 = V33, 0, 1) )) ) -> 1 | AA33: Received by Planning | AB33: 14 | AC33: Weighing Scale, Conveyor, Bottle Crusher, Bricks Mixer Machine, Biowaste Shredder, Plastic Shredder, Glass Shredder/Pulverizer, Rotary Composter, Bricks maker/molder, Charcoal briquetting machine/ Carbonizer | AD33: Biodegradable, Recyclables, Residual | AE33: 255.19 | AF33: 12065.46 | AG33: =(AE33/AF33) -> 0.021150458 | AH33: OPERATIONAL | AJ33: Compliant
